Workbook
Name AuthorityFY1819: #REF!
Name AuthorityFY1920: #REF!
Name AuthorityFY2021: #REF!
Name AuthorityFY2122: #REF!
Name AuthorityFY2324: #REF!
Name AuthorityPhase0: #REF!
Name AuthorityPhaseA: #REF!
Name AuthorityPhaseBC: #REF!
Name AuthorityPhaseD: #REF!
Name AuthorityPhaseE: #REF!
Name Autorités2: #REF!
Name basis: #REF!
Name bbbbbbbbbbbbbbbbbbbb: #REF!
Name BI_4: #REF!
Name BudgetPhaseA: #REF!
Name BudgetPhaseBC: #REF!
Name BudgetPhaseD: #REF!
Name BudgetPhaseE: #REF!
Name bushmen_admin: #REF!
Name bushmen_easy: #REF!
Name bushmen_far: #REF!
Name bushmen_rate: #REF!
Name bushmen_travelrate: #REF!
Name CATEGORIES: #REF!
Name CCG: #REF!
Name CEGNAME: #REF!
Name CENAME: #REF!
Name CI_GL_Description: #REF!
Name Classifications: #REF!
Name CONT: #REF!
Name ContRates: #REF!
Name Conversion: #REF!
Name Cost_per_Pass_CCMEO: #REF!
Name Cost_per_Pass_MDA: #REF!
Name Cost_per_Pass_NGT: #REF!
Name Costing_Phases: '6 - Phase Name'!$F$13:$F$25
Name Costing_Phases: #REF!
Name Costing_Phases_PM: '6 - Phase Name'!$I$13:$I$25
Name Costing_Phases_PM: #REF!
Name CoT_admin: #REF!
Name CR: #REF!
Name dad: #REF!
Name Delay_list: #REF!
Name Department: #REF!
Name Depth: #REF!
Name Depth2: #REF!
Name Description_SST_Eng_Dev: #REF!
Name Destinations: #REF!
Name dfdsf: #REF!
Name DFED: #REF!
Name dfg: #REF!
Name DFGED: #REF!
Name dfgsd: #REF!
Name dfsd: #REF!
Name dfsdf: #REF!
Name dfsgdf: #REF!
Name DIR: #REF!
Name direction: #REF!
Name duree_campagne: #REF!
Name EBP: #REF!

Sheet Cover Page
B3: CSA-FIN-RD-0589
B4: Version Draft 1.0
B5: 46286
B8: Cost Analysis Data Requirement (CADRe)
D9: CADRe Part D - Additional Programmatic Inputs
D10: ORCA at SIR
C16: Prepared by ORCA Project Team
C17: Reviewed by [TBD]

Sheet Table of contents
A3: Table of Contents
C6: Version control | D6: 1 | E6: Change History | F6: Used to track the evolution of the baseline overtime
D7: 2 | E7: CM List | F7: List of documents (title, version, date, number) used in the costing exercise
B8: ✔️ | C8: Decompositions | D8: 3 | E8: Context : Taxon, Phylum and Design Reference Missions | F8: Provides context of this CADRe in relation to other associated CADRe. A given mission has alternate analysis scenarios (DRMs) and nearest neighbors in the same Taxon
B9: 🕒 | D9: 4 | E9: CBS x WBS = mapping to alternate taxonomy | F9: The CBS is a decomposition used by the costing team. The WBS is a decomposition used by the project team. this tab is used to ma the two for reporting purposes
B10: 🕒 | D10: 5 | E10: Organizational Breakdown Structure (OBS) | F10: The organizational breakdown structure identifies vendors, scientific teams, international partners, OGD clients and suppliers. It help specify their roles and hierarchy
B11: ✔️ | C11: Phasing and Scheduling | D11: 6 | E11: Phasing Nomenclature | F11: The costing team has prescribed names for engineering phases, and these may differ from the nameing convention of the project team. this tab help us identify what the project team uses as their naming convention
B12: ✔️ | D12: 7 | E12: Phasing durations | F12: This specifies the phase durations for each segment of time, accordnig to the costing definitions
B13: ✔️ | D13: 8 | E13: Milestone Register | F13: List of milestones (governance gates, technical reviews, contract start and end dates, and some interim dates)
B14: 🕒 | D14: 9 | E14: Gantt chart | F14: utility function that draws a gantt chart
D15: 10 | E15: Schedule Constraints and Dependencies
C16: Strategies | D16: 11 | E16: Strategy Narratives | F16: Narratives including: Procurement strategy, IP strategy, Open Data Strategy, Cyber strategy, staffing strategy, etc
D17: 12 | E17: DDDD - Dispose, Divest, Descope, Delay | F17: Phase F disposal plan, Divestment Plan (After nominal operations), mitigation plans for cost overruns and extended delays (descope and delay)
D18: 13 | E18: Procurement Plan | F18: Procurement plan is a list which includes past investments (Sunk Costs), anticipated R&D activities as well as future contracts, MOUs, grants and contributions, and other sources of cunding
D19: 14 | E19: Overhead Costs
B20: 🕒 | C20: Constants | D20: 15 | E20: Economic factors (rates, fees, etc) | F20: This is a default tab, pre-populated with economic constants, labour rates, and other commonly used rates like EBP
B21: 🕒 | D21: 16 | E21: Inflation Model | F21: The inflation model help actualize historic data into the current base year, and helps add inflation on future years. It is specific to the CBS segments, and includes a most likely value as well as a pessimistic value to sensitivity analysis
C22: Math Models | D22: 17 | E22: CERs used and compensation algorithms | F22: List of tools used, their versions and any compensation algorithms aplpied to results
D23: 18 | E23: Nearest Neighbors | F23: Description of Legacy or Similar Systems for comparison by analogy
D24: 19 | E24: Phasing Curves (Cost distribution functions)
D25: 20 | E25: Value Chain | F25: Economic model for job impact analysis
C26: Process Improvement | D26: 21 | E26: Lessons Learned | F26: Past Lessons learned considered, new lessons generated associated with Cost & Schedule Estimation

Sheet 1 - Change history
A1: ` Table of Contents
A3: 1. Version Control - Baseline Tracker
A4: Purpose: | B4: To track the baseline across time
B5: hold the major and minor releases of the baseline
B9: Change history and associated files that contain the relevant data | G9: Reserved
B10: File Number | C10: Date | D10: File Version | E10: Author | F10: Changes | G10: Parent Baseline Name | H10: Baseline ID
G11: ORCA @ PREP1 | H11: 1
G12: ORCA @ KDP-0 | H12: 2
G13: ORCA @ MDR#2 | H13: 3
G14: ORCA @ PREP2 | H14: 4
G15: ORCA @ KDP-A | H15: 5
G16: ORCA @ KDP-B | H16: 6
G17: ORCA @ PDR | H17: 7
G18: ORCA @ CDR | H18: 8
B19: CSA-FIN-RD-0591 | C19: 46286 | D19: Draft 1 | E19: MB | F19: Initial CADRe Part D baseline: schedule scenarios, dependencies, strategies and procurement plan, aligned to the CADRe Part C SIR baseline. | G19: ORCA @ SIR | H19: 9 | I19: <<--- We are here now
G20: ORCA @ KDP-E | H20: 10
G21: ORCA @ Launch (as flown) | H21: 11
G22: ORCA @ CR | H22: 12
G23: ORCA @ KDP-X | H23: 13
G24: ORCA @ end of life | H24: 14

Sheet 2 - CM 
A1: ` Table of Contents
A3: 2. Version Control - CM List - Document Tracker
A4: Purpose: | B4: this is a list of useful documents used in costing
A5: Why we are asking for this:
B6: It helps document the source of inputs used in calculations
R8: Reserved
B9: Internal ID | C9: Category | D9: Document Title | E9: Org | F9: Doc Number | G9: Doc version | H9: Doc date | I9: Phase | J9: Milestone | K9: CDRL | L9: Source | M9: Contract No | N9: LL Data ID | O9: hyperlink | P9: Comments | Q9: Used in this CADRe ? | R9: Parent Baseline
B10: 1.01 | C10: Costing Exercise | D10: ORCA CADRe Part A - Mission Description | E10: CSA | F10: ORC-CAD-A-001 | G10: Rev 1.0 | H10: 46490 | I10: Phase D | J10: Start of Nominal Operations | K10: A | L10: ORCA CM Repository | M10: ORC-CSA-001 | N10: LL-ORC-001 | O10: https://cm.orca.fake/ORC-CAD-A-001 | P10: Baseline mission description | Q10: Yes | R10: ORC-BASE-001
B11: 1.02 | C11: Costing Exercise | D11: ORCA CADRe Part B - Engineering Parameters | E11: CSA | F11: ORC-CAD-B-001 | G11: Rev 1.0 | H11: 46490 | I11: Phase D | J11: Start of Nominal Operations | K11: B | L11: ORCA CM Repository | M11: ORC-CSA-001 | N11: LL-ORC-002 | O11: https://cm.orca.fake/ORC-CAD-B-001 | P11: Engineering parameter baseline | Q11: Yes | R11: ORC-BASE-001
B12: 1.03 | C12: Costing Exercise | D12: ORCA CADRe Part C - Essential Programmatics | E12: CSA | F12: ORC-CAD-C-001 | G12: Rev 1.0 | H12: 46490 | I12: Phase D | J12: Start of Nominal Operations | K12: C | L12: ORCA CM Repository | M12: ORC-CSA-001 | N12: LL-ORC-003 | O12: https://cm.orca.fake/ORC-CAD-C-001 | P12: Programmatic baseline | Q12: Yes | R12: ORC-BASE-001
B13: 1.04 | C13: Costing Exercise | D13: ORCA CADRe Part D - More Programmatics | E13: CSA | F13: ORC-CAD-D-001 | G13: Rev 1.0 | H13: 46490 | I13: Phase D | J13: Start of Nominal Operations | K13: D | L13: ORCA CM Repository | M13: ORC-CSA-001 | N13: LL-ORC-004 | O13: https://cm.orca.fake/ORC-CAD-D-001 | P13: Current CADRe Part D baseline | Q13: Yes | R13: ORC-BASE-001
B14: 1.05 | C14: Costing Exercise | D14: ORCA PM Cost Report | E14: CSA | F14: ORC-PM-COST-001 | G14: Rev 1.0 | H14: 46490 | I14: Phase D | J14: Start of Nominal Operations | K14: - | L14: ORCA PMO | M14: ORC-CSA-001 | N14: LL-ORC-005 | O14: https://cm.orca.fake/ORC-PM-COST-001 | P14: Current cost baseline | Q14: Yes | R14: ORC-BASE-001
B15: 1.06 | C15: Costing Exercise | D15: ORCA Cost Model Verification Checklist | E15: CSA | F15: ORC-CM-VER-001 | G15: Rev 1.0 | H15: 46490 | I15: Phase D | J15: Start of Nominal Operations | K15: - | L15: ORCA PMO | M15: ORC-CSA-001 | N15: LL-ORC-006 | O15: https://cm.orca.fake/ORC-CM-VER-001 | P15: Cost model verification | Q15: Yes | R15: ORC-BASE-001
B16: 1.07 | C16: Costing Exercise | D16: ORCA Risk Cost Adjustment Memo | E16: CSA | F16: ORC-RISK-COST-001 | G16: Rev 1.0 | H16: 46490 | I16: Phase D | J16: Start of Nominal Operations | K16: - | L16: ORCA PMO | M16: ORC-CSA-001 | N16: LL-ORC-007 | O16: https://cm.orca.fake/ORC-RISK-COST-001 | P16: Risk-adjusted cost inputs | Q16: Yes | R16: ORC-BASE-001
B17: 2.01 | C17: Governance | D17: ORCA Project Charter | E17: CSA | F17: ORC-GOV-001 | G17: Rev 2.0 | H17: 45638 | I17: Phase C | J17: Critical Design Review | K17: - | L17: ORCA PMO | M17: ORC-CSA-001 | N17: LL-ORC-008 | O17: https://cm.orca.fake/ORC-GOV-001 | P17: Approved project governance baseline | Q17: Yes | R17: ORC-BASE-001
B18: 2.02 | C18: Governance | D18: ORCA KDP-E Decision Package | E18: CSA | F18: ORC-GOV-002 | G18: Rev 1.0 | H18: 46490 | I18: Phase D | J18: Start of Nominal Operations | K18: - | L18: ORCA PMO | M18: ORC-CSA-001 | N18: LL-ORC-009 | O18: https://cm.orca.fake/ORC-GOV-002 | P18: KDP-E program decision baseline | Q18: Yes | R18: ORC-KDPE-001
B19: 2.03 | C19: Governance | D19: ORCA Phase E Gate Data Package | E19: CSA | F19: ORC-GOV-003 | G19: Rev 1.0 | H19: 46490 | I19: Phase D | J19: Start of Nominal Operations | K19: - | L19: ORCA PMO | M19: ORC-CSA-001 | N19: LL-ORC-010 | O19: https://cm.orca.fake/ORC-GOV-003 | P19: Phase E evidence package | Q19: Yes | R19: ORC-KDPE-001
B20: 2.04 | C20: Governance | D20: ORCA Configuration Control Board Charter | E20: CSA | F20: ORC-GOV-004 | G20: Rev 1.0 | H20: 46289 | I20: Phase D | J20: Acceptance Review | K20: - | L20: ORCA PMO | M20: ORC-CSA-001 | N20: LL-ORC-011 | O20: https://cm.orca.fake/ORC-GOV-004 | P20: CM authority and change control | Q20: Yes | R20: ORC-BASE-001
B21: 2.05 | C21: Governance | D21: ORCA KDP-E Baseline Approval Memo | E21: CSA | F21: ORC-GOV-005 | G21: Rev 1.0 | H21: 46490 | I21: Phase D | J21: Start of Nominal Operations | K21: - | L21: ORCA PMO | M21: ORC-CSA-001 | N21: LL-ORC-012 | O21: https://cm.orca.fake/ORC-GOV-005 | P21: Configuration baseline approval | Q21: Yes | R21: ORC-KDPE-001
... B45: 9.04 | C45: Vendor Quotes | D45: Flight Computer and Avionics Procurement Estimate | E45: CSA | F45: ORC-VQ-004 | G45: Rev 1.0 | H45: 45611 | I45: Phase C | J45: Critical Design Review | K45: - | L45: ORCA Procurement | M45: ORC-CSA-001 | N45: LL-ORC-036 | O45: https://quotes.orca.fake/ORC-VQ-004 | P45: Fictional supplier estimate | Q45: Yes | R45: ORC-BASE-001

Sheet 3 - Taxon
A1: ` Table of Contents
A3: 3. Context (TAXON, Phylum , DRM)
A4: Purpose: | B4: Provides context of this CADRe in relation to other associated CADRe. A given mission has alternate analysis scenarios (DRMs) and nearest neighbors in the same Taxon
B5: The DRM is used to express different mission concepts, or different analysis options like AIS (on-off), mission class (B-C)
A8: The taxon is used to classify missions into similar neighborhoods.
A9: TAXON 1 | B9: TAXON 2 | C9: PHYLUM | D9: Generation | E9: Missions | F9: Mission Description | G9: Analysis Scenarios | H9: Analysis Scenarios desc | I9: DRM
A10: Space Mission | B10: Orbital Sustainability Missions | C10: On-Orbit Debris Removal | D10: 1 | E10: DELTARA | F10: Single-target mission that captures an inactive satellite and lowers its orbit for atmospheric re-entry. | G10: Single-Pass Sampling Scenario | I10: DRM-VAN-001
D11: 2 | E11: NEXORA | F11: Multi-target debris-removal mission using autonomous orbital transfers between inactive LEO satellites. | G11: Multi-Pass Sampling Scenario | I11: DRM-NEX-001
D12: 3 | E12: SENTRA | F12: Active debris-removal mission using a robotic capture arm to rendezvous with and deorbit inactive LEO satellites. | G12: SENTRA Baseline Mission | I12: DRM-SEN-001: Multi-target rendezvous, robotic capture, and deorbit of inactive LEO satellites
F13: Space situational awareness mission | G13: Option 1 | H13: MDA concept at Phase 0
G14: Option 2 | H14: Airbus concept at Phase 0
G15: Option 3 | H15: Boeing Mission Concept at Phase 0
G16: Option 4 | H16: PPP option by Company X
G17: Baseline at KDP-B | H17: Comdev is the mission baseline starting at Phase B
C18: On_orbit Servicing | D18: 1 | E18: VANTERA | F18: Robotic inspection of inactive LEO spacecraft. | G18: Inspection Scenario
D19: 2 | E19: ORVEX | F19: Robotic capture and servicing of cooperative spacecraft. | G19: Servicing Scenario
H20: Remote sensing of the Enceladus plume and surface. | I20: Inspection Scenario
H21: In-situ sampling and analysis of plume ejecta. | I21: Servicing Scenario
A22: Space Mission | B22: Deep Space Science Missions | C22: Outer-Planet In-Situ Instrument Missions | D22: 1 | E22: LUMEN | F22: CSA-led space telescope instrument contribution to a partner-agency observatory mission. | G22: LUMEN Baseline Mission | I22: DRM-LUM-001
D23: 2 | E23: BOREALIS | F23: CSA-led remote-sensing instrument contribution to a partner-agency deep-space mission. | G23: Borealis Baseline Mission | I23: DRM-BOR-001
D24: 3 | E24: ORCA | F24: CSA-led instrument suite (ice-penetrating radar, mass spectrometer and sampling arm) hosted on the NEREID orbiter (NASA-led, ESA-contributed platform) to transit Enceladus's plume and characterize its composition and sub-surface ocean chemistry. | G24: ORCA Baseline Mission | I24: DRM-ORC-001: Enceladus plume transit, in-situ sampling, and sub-surface ocean chemistry characterization
C33: On-Orbit Servicing | D33: 1 | E33: VANTERA | F33: Robotic inspection of inactive LEO spacecraft. | G33: Inspection Scenario | I33: DRM-VAN-001
D34: 2 | E34: ORVEX | F34: Robotic capture and servicing of cooperative spacecraft. | G34: Servicing Scenario | I34: DRM-ORV-001

Sheet 4- WBS Mapping
A1: 4. CBS to WBS Traceability Table — ORCA
A2: Purpose: | B2: The ORCA WBS translates the project CBS into the mission team's planning and reporting structure, covering the NEREID Orbiter, instrument accommodation payload, launch, ground segment, integration, and mission operations.
A4: WBS | B4: WBS Element | C4: Phase A | D4: Phase B/C | E4: MAIT | F4: SAIT | G4: LEOP | H4: Phase E/X
A5: 1 | B5: ORCA Mission Program | C5: 1.1, 1.2 | D5: 1.1, 1.2, 1.3 | E5: 1.1 | F5: 1.1 | G5: 1.1 | H5: 1.1
A6: 1.1 | B6: Project Management & Mission Control | C6: 1.1 | D6: 1.1 | E6: 1.1 | F6: 1.1 | G6: 1.1 | H6: 1.1
A7: 1.1.1 | B7: Project Management & Controls | C7: 1.1.1 | D7: 1.1.1 | E7: 1.1.1 | F7: 1.1.1 | G7: 1.1.1 | H7: 1.1.1
A8: 1.1.2 | B8: Cost, Schedule & Configuration Management | C8: 1.1.2 | D8: 1.1.2 | E8: 1.1.2 | F8: 1.1.2 | G8: 1.1.2 | H8: 1.1.2
A9: 1.1.3 | B9: Reviews, Governance & Mission Reporting | C9: 1.1.3 | D9: 1.1.3 | E9: 1.1.3 | F9: 1.1.3 | G9: 1.1.3 | H9: 1.1.3
A10: 1.2 | B10: Safety & Mission Assurance | C10: 1.2 | D10: 1.2 | E10: 1.2 | F10: 1.2 | G10: 1.2 | H10: 1.2
A11: 1.3 | B11: Host Orbiter Interface & Accommodation (Partner-Provided Platform) | C11: 1.3 | D11: 1.3 | E11: 1.3 | F11: 1.3 | G11: 1.3 | H11: 1.3
A12: 1.3.1 | B12: Power Interface & Energy Budget Coordination | C12: 1.3.1 | D12: 1.3.1 | E12: 1.3.1 | F12: 1.3.1 | G12: 1.3.1 | H12: 1.3.1
A13: 1.3.2 | B13: Pointing & Accommodation Requirements | C13: 1.3.2 | D13: 1.3.2 | E13: 1.3.2 | F13: 1.3.2 | G13: 1.3.2 | H13: 1.3.2
A14: 1.3.3 | B14: Command & Data Handling Interface | C14: 1.3.3 | D14: 1.3.3 | E14: 1.3.3 | F14: 1.3.3 | G14: 1.3.3 | H14: 1.3.3
A15: 1.3.4 | B15: Communications Relay Interface | C15: 1.3.4 | D15: 1.3.4 | E15: 1.3.4 | F15: 1.3.4 | G15: 1.3.4 | H15: 1.3.4
... A21: 1.4.3 | B21: Mass Spectrometer & Instrument Electronics | C21: 1.4.3 | D21: 1.4.3 | E21: 1.4.3 | F21: 1.4.3 | G21: 1.4.3 | H21: 1.4.3
A22: 1.5 | B22: Launch Support (Partner-Procured) | C22: 1.5 | D22: 1.5 | E22: 1.5 | F22: 1.5
A23: 1.5.1 | B23: Instrument Suite Launch Readiness | D23: 1.5.1 | E23: 1.5.1 | F23: 1.5.1
A24: 1.5.2 | B24: Launch Campaign Support | E24: 1.5.2 | F24: 1.5.2 | G24: 1.5.2
A25: 1.6 | B25: Ground Segment | C25: 1.6 | D25: 1.6 | E25: 1.6 | F25: 1.6 | G25: 1.6 | H25: 1.6
A26: 1.6.1 | B26: Mission Control & Telemetry | C26: 1.6.1 | D26: 1.6.1 | E26: 1.6.1 | F26: 1.6.1 | G26: 1.6.1 | H26: 1.6.1
A27: 1.6.2 | B27: Mission Planning & Science Data Database | C27: 1.6.2 | D27: 1.6.2 | E27: 1.6.2 | F27: 1.6.2 | G27: 1.6.2 | H27: 1.6.2
A28: 1.7 | B28: Mission Operations | C28: 1.7 | D28: 1.7 | E28: 1.7 | F28: 1.7 | G28: 1.7 | H28: 1.7
A29: 1.7.1 | B29: Plume Transit & Sampling Operations | D29: 1.7.1 | E29: 1.7.1 | F29: 1.7.1 | G29: 1.7.1 | H29: 1.7.1
A30: 1.7.2 | B30: Sample Acquisition & Science Data Operations | E30: 1.7.2 | F30: 1.7.2 | G30: 1.7.2 | H30: 1.7.2
A31: 1.8 | B31: System Integration, Assembly, Test & Verification | D31: 1.8 | E31: 1.8 | F31: 1.8 | G31: 1.8
A32: 1.8.1 | B32: Engineering Model Integration & Test | D32: 1.8.1 | E32: 1.8.1
A33: 1.8.2 | B33: Qualification & Environmental Testing | D33: 1.8.2 | E33: 1.8.2 | F33: 1.8.2
A34: 1.8.3 | B34: Flight Acceptance & End-to-End Testing | F34: 1.8.3 | G34: 1.8.3
A35: 1.9 | B35: Commissioning | G35: 1.9 | H35: 1.9
A36: 1.9.1 | B36: Host Orbiter Interface Commissioning | G36: 1.9.1 | H36: 1.9.1
A37: 1.9.2 | B37: Instrument Suite Commissioning | G37: 1.9.2 | H37: 1.9.2

Sheet 4d - CBS in JS format
A1: ` Table of Contents
A3: 4d. CBS (as self referencing list) for use as a javascript array
A4: Why we we asking:
B5: this page is auto-generated and used for drawing it out
E6: Self referencing list for dtree
A8: UID | B8: Parent ID | C8: Level | D8: Node Name | E8: CBS Code | F8: Depth | G8: Icon | H8: Notes | J8: Javascript Code | N8: Depth
A9: 1 | B9: -1 | C9: 1 | D9: Space Missions | F9: Taxon 1 | G9: Box.png | J9: ="datatable["&A9-1&"] = new Array(""" & A9 &""",""" & B9 &""",""" & D9 & """,""" & C9&""","""&""&G9&""");" -> datatable[0] = new Array("1","-1","Space Missions","1","Box.png"); | N9: Taxon 1
A10: 2 | B10: =A9 -> 1 | C10: 2 | D10: EO SAR Missions | F10: Taxon 2 | G10: EO.png | J10: ="datatable["&A10-1&"] = new Array(""" & A10 &""",""" & B10 &""",""" & D10 & """,""" & C10&""","""&""&G10&""");" -> datatable[1] = new Array("2","1","EO SAR Missions","2","EO.png"); | N10: Taxon 2
A11: =A10+1 -> 3 | B11: =A10 -> 2 | C11: 3 | D11: Radarsat Portfolio | F11: Phylum | G11: Pouch.png | J11: ="datatable["&A11-1&"] = new Array(""" & A11 &""",""" & B11 &""",""" & D11 & """,""" & C11&""","""&""&G11&""");" -> datatable[2] = new Array("3","2","Radarsat Portfolio","3","Pouch.png"); | N11: Phylum
A12: =A11+1 -> 4 | B12: =A$6 -> 0 | C12: 4 | D12: Radarsat 1 | F12: Mission | G12: Satellite.png | J12: ="datatable["&A12-1&"] = new Array(""" & A12 &""",""" & B12 &""",""" & D12 & """,""" & C12&""","""&""&G12&""");" -> datatable[3] = new Array("4","0","Radarsat 1","4","Satellite.png"); | N12: Mission
A13: =A12+1 -> 5 | B13: =A$6 -> 0 | C13: 4 | D13: Radarsat 2 | F13: Mission | G13: Satellite.png | J13: ="datatable["&A13-1&"] = new Array(""" & A13 &""",""" & B13 &""",""" & D13 & """,""" & C13&""","""&""&G13&""");" -> datatable[4] = new Array("5","0","Radarsat 2","4","Satellite.png"); | N13: Design Reference Mission
A14: =A13+1 -> 6 | B14: =A$6 -> 0 | C14: 4 | D14: Radarsat Constellation Mission | F14: Mission | G14: Satellite.png | J14: ="datatable["&A14-1&"] = new Array(""" & A14 &""",""" & B14 &""",""" & D14 & """,""" & C14&""","""&""&G14&""");" -> datatable[5] = new Array("6","0","Radarsat Constellation Mission","4","Satellite.png"); | N14: Segment
A15: =A14+1 -> 7 | B15: =A$6 -> 0 | C15: 4 | D15: Radarsat+ Replenishment | E15: 1 | F15: Mission | G15: Satellite.png | J15: ="datatable["&A15-1&"] = new Array(""" & A15 &""",""" & B15 &""",""" & D15 & """,""" & C15&""","""&""&G15&""");" -> datatable[6] = new Array("7","0","Radarsat+ Replenishment","4","Satellite.png"); | N15: System of Systems
A16: =A15+1 -> 8 | B16: =A$6 -> 0 | C16: 4 | D16: Radarsat+ Next Generation | F16: Mission | G16: Satellite.png | J16: ="datatable["&A16-1&"] = new Array(""" & A16 &""",""" & B16 &""",""" & D16 & """,""" & C16&""","""&""&G16&""");" -> datatable[7] = new Array("8","0","Radarsat+ Next Generation","4","Satellite.png"); | N16: System
A17: =A16+1 -> 9 | B17: =A$10 -> 2 | C17: 5 | D17: Analysis Scenario 1: RCM Proxy | F17: Design Reference Mission | G17: Scenario.png | J17: ="datatable["&A17-1&"] = new Array(""" & A17 &""",""" & B17 &""",""" & D17 & """,""" & C17&""","""&""&G17&""");" -> datatable[8] = new Array("9","2","Analysis Scenario 1: RCM Proxy","5","Scenario.png"); | N17: Subsystem
A18: =A17+1 -> 10 | B18: =A$10 -> 2 | C18: 5 | D18: Analysis Scenario 2: RCM+ | F18: Design Reference Mission | G18: Scenario.png | J18: ="datatable["&A18-1&"] = new Array(""" & A18 &""",""" & B18 &""",""" & D18 & """,""" & C18&""","""&""&G18&""");" -> datatable[9] = new Array("10","2","Analysis Scenario 2: RCM+","5","Scenario.png"); | N18: Assembly
A19: =A18+1 -> 11 | B19: =A$10 -> 2 | C19: 5 | D19: Analysis Scenario 3: Airbus concept | F19: Design Reference Mission | G19: Scenario.png | J19: ="datatable["&A19-1&"] = new Array(""" & A19 &""",""" & B19 &""",""" & D19 & """,""" & C19&""","""&""&G19&""");" -> datatable[10] = new Array("11","2","Analysis Scenario 3: Airbus concept","5","Scenario.png"); | N19: Component
A20: =A19+1 -> 12 | B20: =A$10 -> 2 | C20: 5 | D20: Analysis Scenario 4: MDA Chorus Data Buy | F20: Design Reference Mission | G20: Scenario.png | J20: ="datatable["&A20-1&"] = new Array(""" & A20 &""",""" & B20 &""",""" & D20 & """,""" & C20&""","""&""&G20&""");" -> datatable[11] = new Array("12","2","Analysis Scenario 4: MDA Chorus Data Buy","5","Scenario.png");
A21: =A20+1 -> 13 | B21: =A$10 -> 2 | C21: 5 | D21: Analysis Scenario 5: MDA Chorus+ | F21: Design Reference Mission | G21: Scenario.png | J21: ="datatable["&A21-1&"] = new Array(""" & A21 &""",""" & B21 &""",""" & D21 & """,""" & C21&""","""&""&G21&""");" -> datatable[12] = new Array("13","2","Analysis Scenario 5: MDA Chorus+","5","Scenario.png");
A22: =A21+1 -> 14 | B22: =A$10 -> 2 | C22: 5 | D22: Analysis Scenario 6: Airbus Sentinel 2 | F22: Design Reference Mission | G22: Scenario.png | J22: ="datatable["&A22-1&"] = new Array(""" & A22 &""",""" & B22 &""",""" & D22 & """,""" & C22&""","""&""&G22&""");" -> datatable[13] = new Array("14","2","Analysis Scenario 6: Airbus Sentinel 2","5","Scenario.png");
A23: =A22+1 -> 15 | B23: =A$16 -> 8 | C23: 6 | D23: Government Overhead and Oversight | E23: 1.1 | F23: Segment | G23: Government.png | H23: This WBS includes all CSA Oversight, OGD salaries, and basic overhead for the care and maintenance of CSA staff | J23: ="datatable["&A23-1&"] = new Array(""" & A23 &""",""" & B23 &""",""" & D23 & """,""" & C23&""","""&""&G23&""");" -> datatable[14] = new Array("15","8","Government Overhead and Oversight","6","Government.png");
A24: =A23+1 -> 16 | B24: =A$16 -> 8 | C24: 6 | D24: Space Segment | E24: 1.2 | F24: Segment | G24: Satellite.png | H24: The Space Segment includes things we launch into space | J24: ="datatable["&A24-1&"] = new Array(""" & A24 &""",""" & B24 &""",""" & D24 & """,""" & C24&""","""&""&G24&""");" -> datatable[15] = new Array("16","8","Space Segment","6","Satellite.png");
A25: =A24+1 -> 17 | B25: =A$16 -> 8 | C25: 6 | D25: Launch Segment | E25: 1.3 | F25: Segment | G25: Rocket.png | H25: The launch segment includes the launch vehicle and seom support services | J25: ="datatable["&A25-1&"] = new Array(""" & A25 &""",""" & B25 &""",""" & D25 & """,""" & C25&""","""&""&G25&""");" -> datatable[16] = new Array("17","8","Launch Segment","6","Rocket.png");
A26: =A25+1 -> 18 | B26: =A$16 -> 8 | C26: 6 | D26: Ground Segment | E26: 1.4 | F26: Segment | G26: Facility.png | H26: The ground segment includes the planning desgin and development of the GS, but not the Ops | J26: ="datatable["&A26-1&"] = new Array(""" & A26 &""",""" & B26 &""",""" & D26 & """,""" & C26&""","""&""&G26&""");" -> datatable[17] = new Array("18","8","Ground Segment","6","Facility.png");
A27: =A26+1 -> 19 | B27: =A$16 -> 8 | C27: 6 | D27: Ops Segment | E27: 1.5 | F27: Segment | G27: Ops.png | H27: Ops includes SatOps, Mission Ops, Science Ops - typically contracts | J27: ="datatable["&A27-1&"] = new Array(""" & A27 &""",""" & B27 &""",""" & D27 & """,""" & C27&""","""&""&G27&""");" -> datatable[18] = new Array("19","8","Ops Segment","6","Ops.png");
A28: =A27+1 -> 20 | B28: =A$16 -> 8 | C28: 6 | D28: Science Segment | E28: 1.6 | F28: Segment | G28: Science.png | H28: Typically G&C | J28: ="datatable["&A28-1&"] = new Array(""" & A28 &""",""" & B28 &""",""" & D28 & """,""" & C28&""","""&""&G28&""");" -> datatable[19] = new Array("20","8","Science Segment","6","Science.png");
A29: =A28+1 -> 21 | B29: =A$18 -> 10 | C29: 7 | D29: Gov't Oversight (Salaries and EBP) | E29: 1.1.1 | F29: System of Systems | G29: Government.png | J29: ="datatable["&A29-1&"] = new Array(""" & A29 &""",""" & B29 &""",""" & D29 & """,""" & C29&""","""&""&G29&""");" -> datatable[20] = new Array("21","10","Gov't Oversight (Salaries and EBP)","7","Government.png");
A30: =A29+1 -> 22 | B30: =A$18 -> 10 | C30: 7 | D30: Government Overhead | E30: 1.1.2 | F30: System of Systems | G30: Government.png | J30: ="datatable["&A30-1&"] = new Array(""" & A30 &""",""" & B30 &""",""" & D30 & """,""" & C30&""","""&""&G30&""");" -> datatable[21] = new Array("22","10","Government Overhead","7","Government.png");
A31: =A30+1 -> 23 | B31: =A29 -> 21 | C31: 8 | D31: CSA Oversight | E31: 1.1.1.1 | F31: System | G31: Government.png | J31: ="datatable["&A31-1&"] = new Array(""" & A31 &""",""" & B31 &""",""" & D31 & """,""" & C31&""","""&""&G31&""");" -> datatable[22] = new Array("23","21","CSA Oversight","8","Government.png");
A32: =A31+1 -> 24 | B32: =A29 -> 21 | C32: 8 | D32: OGD Oversight | E32: 1.1.1.2 | F32: System | G32: Government.png | J32: ="datatable["&A32-1&"] = new Array(""" & A32 &""",""" & B32 &""",""" & D32 & """,""" & C32&""","""&""&G32&""");" -> datatable[23] = new Array("24","21","OGD Oversight","8","Government.png");
A33: =A32+1 -> 25 | B33: =A31 -> 23 | C33: 9 | D33: CSA Project Team | E33: 1.1.1.1.1 | F33: Subsystem | G33: Government.png | H33: This CBS contains all salaries associated with the RAM of the Project team | J33: ="datatable["&A33-1&"] = new Array(""" & A33 &""",""" & B33 &""",""" & D33 & """,""" & C33&""","""&""&G33&""");" -> datatable[24] = new Array("25","23","CSA Project Team","9","Government.png");
A34: =A33+1 -> 26 | B34: =A31 -> 23 | C34: 9 | D34: CSA Internal Services | E34: 1.1.1.1.2 | F34: Subsystem | G34: Government.png | H34: This CBS contains all salaries associated with CSA internal services (finance, HR, audit, eval, policy, Executives, IM, IT, contracts, shipping, etc) | J34: ="datatable["&A34-1&"] = new Array(""" & A34 &""",""" & B34 &""",""" & D34 & """,""" & C34&""","""&""&G34&""");" -> datatable[25] = new Array("26","23","CSA Internal Services","9","Government.png");
A35: =A34+1 -> 27 | B35: =A32 -> 24 | C35: 9 | D35: OGD Internal Services by MOU | E35: 1.1.1.2.1 | F35: Subsystem | G35: Government.png | J35: ="datatable["&A35-1&"] = new Array(""" & A35 &""",""" & B35 &""",""" & D35 & """,""" & C35&""","""&""&G35&""");" -> datatable[26] = new Array("27","24","OGD Internal Services by MOU","9","Government.png");
A36: =A35+1 -> 28 | B36: =A32 -> 24 | C36: 9 | D36: OGD User Departments by MOU (RAM portion) | E36: 1.1.1.2.2 | F36: Subsystem | G36: Government.png | J36: ="datatable["&A36-1&"] = new Array(""" & A36 &""",""" & B36 &""",""" & D36 & """,""" & C36&""","""&""&G36&""");" -> datatable[27] = new Array("28","24","OGD User Departments by MOU (RAM portion)","9","Government.png");
A37: =A36+1 -> 29 | B37: =A$29 -> 21 | C37: 10 | D37: Shared Services | E37: 1.1.1.2.1.1 | F37: Assembly | G37: Government.png | J37: ="datatable["&A37-1&"] = new Array(""" & A37 &""",""" & B37 &""",""" & D37 & """,""" & C37&""","""&""&G37&""");" -> datatable[28] = new Array("29","21","Shared Services","10","Government.png");
A38: =A37+1 -> 30 | B38: =A$29 -> 21 | C38: 10 | D38: SPAC | E38: 1.1.1.2.1.2 | F38: Assembly | G38: Government.png | J38: ="datatable["&A38-1&"] = new Array(""" & A38 &""",""" & B38 &""",""" & D38 & """,""" & C38&""","""&""&G38&""");" -> datatable[29] = new Array("30","21","SPAC","10","Government.png");
A39: =A38+1 -> 31 | B39: =A$29 -> 21 | C39: 10 | D39: Justice Canada | E39: 1.1.1.2.1.3 | F39: Assembly | G39: Government.png | J39: ="datatable["&A39-1&"] = new Array(""" & A39 &""",""" & B39 &""",""" & D39 & """,""" & C39&""","""&""&G39&""");" -> datatable[30] = new Array("31","21","Justice Canada","10","Government.png");
A40: =A39+1 -> 32 | B40: =A$31 -> 23 | C40: 10 | D40: ECCC | E40: 1.1.1.2.2.1 | F40: Assembly | G40: Government.png | J40: ="datatable["&A40-1&"] = new Array(""" & A40 &""",""" & B40 &""",""" & D40 & """,""" & C40&""","""&""&G40&""");" -> datatable[31] = new Array("32","23","ECCC","10","Government.png");
A41: =A40+1 -> 33 | B41: =A$31 -> 23 | C41: 10 | D41: NRCAN | E41: 1.1.1.2.2.2 | F41: Assembly | G41: Government.png | J41: ="datatable["&A41-1&"] = new Array(""" & A41 &""",""" & B41 &""",""" & D41 & """,""" & C41&""","""&""&G41&""");" -> datatable[32] = new Array("33","23","NRCAN","10","Government.png");
A42: =A41+1 -> 34 | B42: =A$31 -> 23 | C42: 10 | D42: DND | E42: 1.1.1.2.2.3 | F42: Assembly | G42: Government.png | J42: ="datatable["&A42-1&"] = new Array(""" & A42 &""",""" & B42 &""",""" & D42 & """,""" & C42&""","""&""&G42&""");" -> datatable[33] = new Array("34","23","DND","10","Government.png");
A43: =A42+1 -> 35 | B43: =A33 -> 25 | C43: 11 | D43: RAM per Person per FY and Phase | E43: 1.1.1.1.1.1 | F43: Component | G43: Government.png | J43: ="datatable["&A43-1&"] = new Array(""" & A43 &""",""" & B43 &""",""" & D43 & """,""" & C43&""","""&""&G43&""");" -> datatable[34] = new Array("35","25","RAM per Person per FY and Phase","11","Government.png");
A44: =A43+1 -> 36 | B44: =A$33 -> 25 | C44: 11 | D44: PSPC Procurement Services | E44: 1.1.1.2.1.2.1 | F44: Component | G44: Government.png | J44: ="datatable["&A44-1&"] = new Array(""" & A44 &""",""" & B44 &""",""" & D44 & """,""" & C44&""","""&""&G44&""");" -> datatable[35] = new Array("36","25","PSPC Procurement Services","11","Government.png");
A45: =A44+1 -> 37 | B45: =A$33 -> 25 | C45: 11 | D45: PSPC Fairness Monitor | E45: 1.1.1.2.1.2.2 | F45: Component | G45: Government.png | J45: ="datatable["&A45-1&"] = new Array(""" & A45 &""",""" & B45 &""",""" & D45 & """,""" & C45&""","""&""&G45&""");" -> datatable[36] = new Array("37","25","PSPC Fairness Monitor","11","Government.png");
A46: =A45+1 -> 38 | B46: =A39 -> 31 | C46: 11 | D46: Legal Services | E46: 1.1.1.2.1.3.1 | F46: Component | G46: Government.png | J46: ="datatable["&A46-1&"] = new Array(""" & A46 &""",""" & B46 &""",""" & D46 & """,""" & C46&""","""&""&G46&""");" -> datatable[37] = new Array("38","31","Legal Services","11","Government.png");
A47: =A46+1 -> 39 | B47: =A30 -> 22 | C47: 8 | D47: CSA Overhead | E47: 1.1.2.1 | F47: System | G47: Government.png | J47: ="datatable["&A47-1&"] = new Array(""" & A47 &""",""" & B47 &""",""" & D47 & """,""" & C47&""","""&""&G47&""");" -> datatable[38] = new Array("39","22","CSA Overhead","8","Government.png");
A48: =A47+1 -> 40 | B48: =A$42 -> 34 | C48: 9 | D48: IS Management Overhead | E48: 1.1.2.1.1 | F48: Subsystem | G48: Government.png | J48: ="datatable["&A48-1&"] = new Array(""" & A48 &""",""" & B48 &""",""" & D48 & """,""" & C48&""","""&""&G48&""");" -> datatable[39] = new Array("40","34","IS Management Overhead ","9","Government.png");
A49: =A48+1 -> 41 | B49: =A$42 -> 34 | C49: 9 | D49: Management Consulting Services | E49: 1.1.2.1.2 | F49: Subsystem | G49: Government.png | J49: ="datatable["&A49-1&"] = new Array(""" & A49 &""",""" & B49 &""",""" & D49 & """,""" & C49&""","""&""&G49&""");" -> datatable[40] = new Array("41","34","Management Consulting Services","9","Government.png");
A50: =A49+1 -> 42 | B50: =A$42 -> 34 | C50: 9 | D50: Temporary Help | E50: 1.1.2.1.3 | F50: Subsystem | G50: Government.png | J50: ="datatable["&A50-1&"] = new Array(""" & A50 &""",""" & B50 &""",""" & D50 & """,""" & C50&""","""&""&G50&""");" -> datatable[41] = new Array("42","34","Temporary Help","9","Government.png");
A51: =A50+1 -> 43 | B51: =A$42 -> 34 | C51: 9 | D51: Students | E51: 1.1.2.1.4 | F51: Subsystem | G51: Government.png | H51: This CBS includes any students, FSWEP or PDF assisint Csa project team | J51: ="datatable["&A51-1&"] = new Array(""" & A51 &""",""" & B51 &""",""" & D51 & """,""" & C51&""","""&""&G51&""");" -> datatable[42] = new Array("43","34","Students","9","Government.png");
A52: =A51+1 -> 44 | B52: =A$42 -> 34 | C52: 9 | D52: Government Travel & Living | E52: 1.1.2.1.5 | F52: Subsystem | G52: Government.png | H52: This CBS includes any government Travel and Living expenses | J52: ="datatable["&A52-1&"] = new Array(""" & A52 &""",""" & B52 &""",""" & D52 & """,""" & C52&""","""&""&G52&""");" -> datatable[43] = new Array("44","34","Government Travel & Living","9","Government.png");
A53: =A52+1 -> 45 | B53: =A$42 -> 34 | C53: 9 | D53: Translation | E53: 1.1.2.1.6 | F53: Subsystem | G53: Government.png | H53: This CBS includes any translation costs | J53: ="datatable["&A53-1&"] = new Array(""" & A53 &""",""" & B53 &""",""" & D53 & """,""" & C53&""","""&""&G53&""");" -> datatable[44] = new Array("45","34","Translation","9","Government.png");
A54: =A53+1 -> 46 | B54: =A$42 -> 34 | C54: 9 | D54: Shipping | E54: 1.1.2.1.7 | F54: Subsystem | G54: Government.png | H54: This CBs includes any shipping cost, but not shipping flight HW which is under space segment | J54: ="datatable["&A54-1&"] = new Array(""" & A54 &""",""" & B54 &""",""" & D54 & """,""" & C54&""","""&""&G54&""");" -> datatable[45] = new Array("46","34","Shipping","9","Government.png");
A55: =A54+1 -> 47 | B55: =A$42 -> 34 | C55: 9 | D55: Software Licenses | E55: 1.1.2.1.8 | F55: Subsystem | G55: Government.png | H55: This CBS includes any COTs SW not flight Sw or ground SW | J55: ="datatable["&A55-1&"] = new Array(""" & A55 &""",""" & B55 &""",""" & D55 & """,""" & C55&""","""&""&G55&""");" -> datatable[46] = new Array("47","34","Software Licenses","9","Government.png");
A56: =A55+1 -> 48 | B56: =A$42 -> 34 | C56: 9 | D56: Public Outreach and STEM initiatives | E56: 1.1.2.1.9 | F56: Subsystem | G56: Government.png | H56: This CBS includes any public relations and STEM | J56: ="datatable["&A56-1&"] = new Array(""" & A56 &""",""" & B56 &""",""" & D56 & """,""" & C56&""","""&""&G56&""");" -> datatable[47] = new Array("48","34","Public Outreach and STEM initiatives","9","Government.png");
A57: =A56+1 -> 49 | B57: =A$42 -> 34 | C57: 9 | D57: Other Overhead (Specify) | E57: 1.1.2.1.10 | F57: Subsystem | G57: Government.png | H57: This CBS includes any other misc fees | J57: ="datatable["&A57-1&"] = new Array(""" & A57 &""",""" & B57 &""",""" & D57 & """,""" & C57&""","""&""&G57&""");" -> datatable[48] = new Array("49","34","Other Overhead (Specify)","9","Government.png");
A58: =A57+1 -> 50 | B58: =A$44 -> 36 | C58: 10 | D58: Consultants - Industrial Space Experts | E58: 1.1.2.1.2.1 | F58: Assembly | G58: Government.png | J58: ="datatable["&A58-1&"] = new Array(""" & A58 &""",""" & B58 &""",""" & D58 & """,""" & C58&""","""&""&G58&""");" -> datatable[49] = new Array("50","36","Consultants - Industrial Space Experts","10","Government.png");
A59: =A58+1 -> 51 | B59: =A$44 -> 36 | C59: 10 | D59: Consultants - Academia | E59: 1.1.2.1.2.2 | F59: Assembly | G59: Government.png | J59: ="datatable["&A59-1&"] = new Array(""" & A59 &""",""" & B59 &""",""" & D59 & """,""" & C59&""","""&""&G59&""");" -> datatable[50] = new Array("51","36","Consultants - Academia","10","Government.png");
A60: =A59+1 -> 52 | B60: =A$44 -> 36 | C60: 10 | D60: Consultants - Non-Space Experts | E60: 1.1.2.1.2.3 | F60: Assembly | G60: Government.png | J60: ="datatable["&A60-1&"] = new Array(""" & A60 &""",""" & B60 &""",""" & D60 & """,""" & C60&""","""&""&G60&""");" -> datatable[51] = new Array("52","36","Consultants - Non-Space Experts","10","Government.png");
A61: =A60+1 -> 53 | B61: 12 | C61: 6 | D61: Mission SEITPM and Support Equipment | F61: Segment | G61: SEITPM.png | J61: ="datatable["&A61-1&"] = new Array(""" & A61 &""",""" & B61 &""",""" & D61 & """,""" & C61&""","""&""&G61&""");" -> datatable[52] = new Array("53","12","Mission SEITPM and Support Equipment","6","SEITPM.png");
A62: =A61+1 -> 54 | B62: =A$56 -> 48 | C62: 7 | D62: Project Management | F62: System of Systems | G62: SEITPM.png | J62: ="datatable["&A62-1&"] = new Array(""" & A62 &""",""" & B62 &""",""" & D62 & """,""" & C62&""","""&""&G62&""");" -> datatable[53] = new Array("54","48","Project Management","7","SEITPM.png");
A63: =A62+1 -> 55 | B63: =A$56 -> 48 | C63: 7 | D63: Systems Engineering | F63: System of Systems | G63: SEITPM.png | J63: ="datatable["&A63-1&"] = new Array(""" & A63 &""",""" & B63 &""",""" & D63 & """,""" & C63&""","""&""&G63&""");" -> datatable[54] = new Array("55","48","Systems Engineering","7","SEITPM.png");
A64: =A63+1 -> 56 | B64: =A$56 -> 48 | C64: 7 | D64: Mission Assurance | F64: System of Systems | G64: SEITPM.png | J64: ="datatable["&A64-1&"] = new Array(""" & A64 &""",""" & B64 &""",""" & D64 & """,""" & C64&""","""&""&G64&""");" -> datatable[55] = new Array("56","48","Mission Assurance","7","SEITPM.png");
A65: =A64+1 -> 57 | B65: =A$56 -> 48 | C65: 7 | D65: Assembly, Integration and Testing | F65: System of Systems | G65: SEITPM.png | J65: ="datatable["&A65-1&"] = new Array(""" & A65 &""",""" & B65 &""",""" & D65 & """,""" & C65&""","""&""&G65&""");" -> datatable[56] = new Array("57","48","Assembly, Integration and Testing","7","SEITPM.png");
A66: =A65+1 -> 58 | B66: =A$56 -> 48 | C66: 7 | D66: Support Equipment | F66: System of Systems | G66: SEITPM.png | J66: ="datatable["&A66-1&"] = new Array(""" & A66 &""",""" & B66 &""",""" & D66 & """,""" & C66&""","""&""&G66&""");" -> datatable[57] = new Array("58","48","Support Equipment","7","SEITPM.png");
A67: =A66+1 -> 59 | B67: =A24 -> 16 | C67: 7 | D67: Space Vehicle 1 … i | F67: System of Systems | G67: Satellite.png | J67: ="datatable["&A67-1&"] = new Array(""" & A67 &""",""" & B67 &""",""" & D67 & """,""" & C67&""","""&""&G67&""");" -> datatable[58] = new Array("59","16","Space Vehicle 1 … i","7","Satellite.png");
A68: =A67+1 -> 60 | B68: =A67 -> 59 | C68: 8 | D68: Spacecraft SEITPM and Support Equipment | F68: System | G68: SEITPM.png | J68: ="datatable["&A68-1&"] = new Array(""" & A68 &""",""" & B68 &""",""" & D68 & """,""" & C68&""","""&""&G68&""");" -> datatable[59] = new Array("60","59","Spacecraft SEITPM and Support Equipment","8","SEITPM.png");
A69: =A68+1 -> 61 | B69: =A$63 -> 55 | C69: 9 | D69: Project Management | F69: Subsystem | G69: SEITPM.png | J69: ="datatable["&A69-1&"] = new Array(""" & A69 &""",""" & B69 &""",""" & D69 & """,""" & C69&""","""&""&G69&""");" -> datatable[60] = new Array("61","55","Project Management","9","SEITPM.png");
A70: =A69+1 -> 62 | B70: =A$63 -> 55 | C70: 9 | D70: Systems Engineering | F70: Subsystem | G70: SEITPM.png | J70: ="datatable["&A70-1&"] = new Array(""" & A70 &""",""" & B70 &""",""" & D70 & """,""" & C70&""","""&""&G70&""");" -> datatable[61] = new Array("62","55","Systems Engineering","9","SEITPM.png");
A71: =A70+1 -> 63 | B71: =A$63 -> 55 | C71: 9 | D71: Mission Assurance | F71: Subsystem | G71: SEITPM.png | J71: ="datatable["&A71-1&"] = new Array(""" & A71 &""",""" & B71 &""",""" & D71 & """,""" & C71&""","""&""&G71&""");" -> datatable[62] = new Array("63","55","Mission Assurance","9","SEITPM.png");
A72: =A71+1 -> 64 | B72: =A$63 -> 55 | C72: 9 | D72: Assembly, Integration and Testing | F72: Subsystem | G72: SEITPM.png | J72: ="datatable["&A72-1&"] = new Array(""" & A72 &""",""" & B72 &""",""" & D72 & """,""" & C72&""","""&""&G72&""");" -> datatable[63] = new Array("64","55","Assembly, Integration and Testing","9","SEITPM.png");
A73: =A72+1 -> 65 | B73: =A$63 -> 55 | C73: 9 | D73: Support Equipment | F73: Subsystem | G73: SEITPM.png | J73: ="datatable["&A73-1&"] = new Array(""" & A73 &""",""" & B73 &""",""" & D73 & """,""" & C73&""","""&""&G73&""");" -> datatable[64] = new Array("65","55","Support Equipment","9","SEITPM.png");
A74: =A73+1 -> 66 | B74: =A67 -> 59 | C74: 8 | D74: Bus/Platform | F74: System | G74: Widget.png | J74: ="datatable["&A74-1&"] = new Array(""" & A74 &""",""" & B74 &""",""" & D74 & """,""" & C74&""","""&""&G74&""");" -> datatable[65] = new Array("66","59","Bus/Platform","8","Widget.png");
A75: =A74+1 -> 67 | B75: =A74 -> 66 | C75: 9 | D75: Platform SEITPM and Support Equipment | F75: Subsystem | G75: SEITPM.png | J75: ="datatable["&A75-1&"] = new Array(""" & A75 &""",""" & B75 &""",""" & D75 & """,""" & C75&""","""&""&G75&""");" -> datatable[66] = new Array("67","66","Platform SEITPM and Support Equipment","9","SEITPM.png");
A76: =A75+1 -> 68 | B76: =A$70 -> 62 | C76: 10 | D76: Project Management | F76: Assembly | G76: SEITPM.png | J76: ="datatable["&A76-1&"] = new Array(""" & A76 &""",""" & B76 &""",""" & D76 & """,""" & C76&""","""&""&G76&""");" -> datatable[67] = new Array("68","62","Project Management","10","SEITPM.png");
A77: =A76+1 -> 69 | B77: =A$70 -> 62 | C77: 10 | D77: Systems Engineering | F77: Assembly | G77: SEITPM.png | J77: ="datatable["&A77-1&"] = new Array(""" & A77 &""",""" & B77 &""",""" & D77 & """,""" & C77&""","""&""&G77&""");" -> datatable[68] = new Array("69","62","Systems Engineering","10","SEITPM.png");
A78: =A77+1 -> 70 | B78: =A$70 -> 62 | C78: 10 | D78: Mission Assurance | F78: Assembly | G78: SEITPM.png | J78: ="datatable["&A78-1&"] = new Array(""" & A78 &""",""" & B78 &""",""" & D78 & """,""" & C78&""","""&""&G78&""");" -> datatable[69] = new Array("70","62","Mission Assurance","10","SEITPM.png");
A79: =A78+1 -> 71 | B79: =A$70 -> 62 | C79: 10 | D79: Assembly, Integration and Testing | F79: Assembly | G79: SEITPM.png | J79: ="datatable["&A79-1&"] = new Array(""" & A79 &""",""" & B79 &""",""" & D79 & """,""" & C79&""","""&""&G79&""");" -> datatable[70] = new Array("71","62","Assembly, Integration and Testing","10","SEITPM.png");
A80: =A79+1 -> 72 | B80: =A$70 -> 62 | C80: 10 | D80: Support Equipment | F80: Assembly | G80: SEITPM.png | J80: ="datatable["&A80-1&"] = new Array(""" & A80 &""",""" & B80 &""",""" & D80 & """,""" & C80&""","""&""&G80&""");" -> datatable[71] = new Array("72","62","Support Equipment","10","SEITPM.png");
A81: =A80+1 -> 73 | B81: =A$69 -> 61 | C81: 9 | D81: Structures and Mechanisms Subsystem (SMS) | F81: Subsystem | G81: Widget.png | J81: ="datatable["&A81-1&"] = new Array(""" & A81 &""",""" & B81 &""",""" & D81 & """,""" & C81&""","""&""&G81&""");" -> datatable[72] = new Array("73","61","Structures and Mechanisms Subsystem (SMS)","9","Widget.png");
A82: =A81+1 -> 74 | B82: =A$76 -> 68 | C82: 10 | D82: Structures and Mechanisms Subsystem SEITPM | F82: Assembly | G82: SEITPM.png | J82: ="datatable["&A82-1&"] = new Array(""" & A82 &""",""" & B82 &""",""" & D82 & """,""" & C82&""","""&""&G82&""");" -> datatable[73] = new Array("74","68","Structures and Mechanisms Subsystem SEITPM","10","SEITPM.png");
A83: =A82+1 -> 75 | B83: =A$77 -> 69 | C83: 11 | D83: Project Management | F83: Component | G83: SEITPM.png | J83: ="datatable["&A83-1&"] = new Array(""" & A83 &""",""" & B83 &""",""" & D83 & """,""" & C83&""","""&""&G83&""");" -> datatable[74] = new Array("75","69","Project Management","11","SEITPM.png");
A84: =A83+1 -> 76 | B84: =A$77 -> 69 | C84: 11 | D84: Systems Engineering | F84: Component | G84: SEITPM.png | J84: ="datatable["&A84-1&"] = new Array(""" & A84 &""",""" & B84 &""",""" & D84 & """,""" & C84&""","""&""&G84&""");" -> datatable[75] = new Array("76","69","Systems Engineering","11","SEITPM.png");
A85: =A84+1 -> 77 | B85: =A$77 -> 69 | C85: 11 | D85: Mission Assurance | F85: Component | G85: SEITPM.png | J85: ="datatable["&A85-1&"] = new Array(""" & A85 &""",""" & B85 &""",""" & D85 & """,""" & C85&""","""&""&G85&""");" -> datatable[76] = new Array("77","69","Mission Assurance","11","SEITPM.png");
A86: =A85+1 -> 78 | B86: =A$77 -> 69 | C86: 11 | D86: Assembly, Integration and Testing | F86: Component | G86: SEITPM.png | J86: ="datatable["&A86-1&"] = new Array(""" & A86 &""",""" & B86 &""",""" & D86 & """,""" & C86&""","""&""&G86&""");" -> datatable[77] = new Array("78","69","Assembly, Integration and Testing","11","SEITPM.png");
A87: =A86+1 -> 79 | B87: =A$77 -> 69 | C87: 11 | D87: Support Equipment | F87: Component | G87: SEITPM.png | J87: ="datatable["&A87-1&"] = new Array(""" & A87 &""",""" & B87 &""",""" & D87 & """,""" & C87&""","""&""&G87&""");" -> datatable[78] = new Array("79","69","Support Equipment","11","SEITPM.png");
A88: =A87+1 -> 80 | B88: =A$76 -> 68 | C88: 10 | D88: Primary Structures | F88: Assembly | G88: Widget.png | J88: ="datatable["&A88-1&"] = new Array(""" & A88 &""",""" & B88 &""",""" & D88 & """,""" & C88&""","""&""&G88&""");" -> datatable[79] = new Array("80","68","Primary Structures","10","Widget.png");
A89: =A88+1 -> 81 | B89: =A$83 -> 75 | C89: 11 | D89: Load Carrying Shell/Truss | F89: Component | G89: Widget.png | J89: ="datatable["&A89-1&"] = new Array(""" & A89 &""",""" & B89 &""",""" & D89 & """,""" & C89&""","""&""&G89&""");" -> datatable[80] = new Array("81","75","Load Carrying Shell/Truss","11","Widget.png");
A90: =A89+1 -> 82 | B90: =A$83 -> 75 | C90: 11 | D90: Equipment Compartments | F90: Component | G90: Widget.png | J90: ="datatable["&A90-1&"] = new Array(""" & A90 &""",""" & B90 &""",""" & D90 & """,""" & C90&""","""&""&G90&""");" -> datatable[81] = new Array("82","75","Equipment Compartments","11","Widget.png");
A91: =A90+1 -> 83 | B91: =A$83 -> 75 | C91: 11 | D91: Booms | F91: Component | G91: Widget.png | J91: ="datatable["&A91-1&"] = new Array(""" & A91 &""",""" & B91 &""",""" & D91 & """,""" & C91&""","""&""&G91&""");" -> datatable[82] = new Array("83","75","Booms","11","Widget.png");
A92: =A91+1 -> 84 | B92: =A$83 -> 75 | C92: 11 | D92: Adapters | F92: Component | G92: Widget.png | J92: ="datatable["&A92-1&"] = new Array(""" & A92 &""",""" & B92 &""",""" & D92 & """,""" & C92&""","""&""&G92&""");" -> datatable[83] = new Array("84","75","Adapters","11","Widget.png");
A93: =A92+1 -> 85 | B93: =A$83 -> 75 | C93: 11 | D93: Other Structures (Specify) | F93: Component | G93: Widget.png | J93: ="datatable["&A93-1&"] = new Array(""" & A93 &""",""" & B93 &""",""" & D93 & """,""" & C93&""","""&""&G93&""");" -> datatable[84] = new Array("85","75","Other Structures (Specify)","11","Widget.png");
A94: =A93+1 -> 86 | B94: =A$76 -> 68 | C94: 10 | D94: Secondary Structures | F94: Assembly | G94: Widget.png | J94: ="datatable["&A94-1&"] = new Array(""" & A94 &""",""" & B94 &""",""" & D94 & """,""" & C94&""","""&""&G94&""");" -> datatable[85] = new Array("86","68","Secondary Structures","10","Widget.png");
A95: =A94+1 -> 87 | B95: =A$89 -> 81 | C95: 11 | D95: Equipment (Instrument) Mountings | F95: Component | G95: Widget.png | J95: ="datatable["&A95-1&"] = new Array(""" & A95 &""",""" & B95 &""",""" & D95 & """,""" & C95&""","""&""&G95&""");" -> datatable[86] = new Array("87","81","Equipment (Instrument) Mountings","11","Widget.png");
A96: =A95+1 -> 88 | B96: =A$89 -> 81 | C96: 11 | D96: Ballast Mass | F96: Component | G96: Widget.png | J96: ="datatable["&A96-1&"] = new Array(""" & A96 &""",""" & B96 &""",""" & D96 & """,""" & C96&""","""&""&G96&""");" -> datatable[87] = new Array("88","81","Ballast Mass","11","Widget.png");
A97: =A96+1 -> 89 | B97: =A$89 -> 81 | C97: 11 | D97: Other Secondary Structures (Specify) | F97: Component | G97: Widget.png | J97: ="datatable["&A97-1&"] = new Array(""" & A97 &""",""" & B97 &""",""" & D97 & """,""" & C97&""","""&""&G97&""");" -> datatable[88] = new Array("89","81","Other Secondary Structures (Specify)","11","Widget.png");
A98: =A97+1 -> 90 | B98: =A$76 -> 68 | C98: 10 | D98: Mechanisms and Pyrotechnics | F98: Assembly | G98: Widget.png | J98: ="datatable["&A98-1&"] = new Array(""" & A98 &""",""" & B98 &""",""" & D98 & """,""" & C98&""","""&""&G98&""");" -> datatable[89] = new Array("90","68","Mechanisms and Pyrotechnics","10","Widget.png");
A99: =A98+1 -> 91 | B99: =A$93 -> 85 | C99: 11 | D99: Positioning | F99: Component | G99: Widget.png | J99: ="datatable["&A99-1&"] = new Array(""" & A99 &""",""" & B99 &""",""" & D99 & """,""" & C99&""","""&""&G99&""");" -> datatable[90] = new Array("91","85","Positioning","11","Widget.png");
A100: =A99+1 -> 92 | B100: =A$93 -> 85 | C100: 11 | D100: Deployment and Storage Equipment | F100: Component | G100: Widget.png | J100: ="datatable["&A100-1&"] = new Array(""" & A100 &""",""" & B100 &""",""" & D100 & """,""" & C100&""","""&""&G100&""");" -> datatable[91] = new Array("92","85","Deployment and Storage Equipment","11","Widget.png");
A101: =A100+1 -> 93 | B101: =A$93 -> 85 | C101: 11 | D101: Docking Mechanisms | F101: Component | G101: Widget.png | J101: ="datatable["&A101-1&"] = new Array(""" & A101 &""",""" & B101 &""",""" & D101 & """,""" & C101&""","""&""&G101&""");" -> datatable[92] = new Array("93","85","Docking Mechanisms","11","Widget.png");
A102: =A101+1 -> 94 | B102: =A$93 -> 85 | C102: 11 | D102: Other Mechanisms (Specify) | F102: Component | G102: Widget.png | J102: ="datatable["&A102-1&"] = new Array(""" & A102 &""",""" & B102 &""",""" & D102 & """,""" & C102&""","""&""&G102&""");" -> datatable[93] = new Array("94","85","Other Mechanisms (Specify)","11","Widget.png");
...

Sheet 5- OBS
A1: ` Table of Contents
A3: 5. OBS
A4: Purpose: | B4: The organizational breakdown structure identifies vendors, scientific teams, international partners, OGD clients and suppliers. It help specify their roles and hierarchy
A5: Why we are asking for this:
B6: This information helps us understand the procurement strategy.
B7: It also helps map SAP claims against cost elements
A10: Type | B10: Sub-Type | C10: Name | D10: Description | E10: Cost sharing Provisions, who pays? | F10: How are WPD defined? | G10: Oversight | H10: Overhead | I10: Mission Level SEITPM | J10: Space Segment | K10: Launch Segment | L10: Ground Segment | M10: Ops Segment | N10: Science Segment
A11: Government | B11: Mission Owner / Project Office | C11: Canadian Orbital Mission Directorate (COMD) | D11: Fictional government organization representing the ORCA mission owner and program authority. | E11: Government mission appropriation | F11: Mission workplan / SOW | G11: x | H11: x | I11: x
A12: Industry | B12: Prime Space Systems Integrator | C12: Asterion Orbital Integration Ltd. | D12: Fictional prime contractor supporting spacecraft-level integration, verification, and technical coordination. | E12: CSA-style fiscal framework | F12: Contract SOW / CWBS | I12: x | J12: x
A13: Industry | B13: Radar Subsystem Supplier | C13: Northstar Orbital Technologies | D13: Fictional supplier providing the ice-penetrating radar subsystem for ORCA. | E13: Contract funding | F13: Contract SOW / CWBS | I13: x | J13: x
A14: Industry | B14: Sampling Arm Supplier | C14: Aetheris Space Robotics | D14: Fictional supplier providing the sampling arm, end-effector, actuators, and sample-handling mechanisms. | E14: Contract funding | F14: Contract SOW / CWBS | I14: x | J14: x
A15: Industry | B15: Avionics Supplier | C15: Polarion Avionics Corporation | D15: Fictional supplier providing flight-computing, payload electronics, and avionics support. | E15: Contract funding | F15: Contract SOW / CWBS | I15: x | J15: x
A16: Industry | B16: Context Imaging Supplier | C16: Borealis Vision Systems | D16: Fictional supplier providing plume-context imaging cameras and optical calibration equipment. | E16: Contract funding | F16: Contract SOW / CWBS | I16: x | J16: x
A17: Industry | B17: Communications Supplier | C17: Canterra Space Communications | D17: Fictional supplier providing instrument command & data-handling electronics and data-interface hardware to the NEREID orbiter. | E17: Contract funding | F17: Contract SOW / CWBS | I17: x | K17: x | L17: x
A18: Industry | B18: Thermal & Structures Supplier | C18: Arcturon Space Structures | D18: Fictional supplier supporting spacecraft structures, thermal hardware, and payload mounting interfaces. | E18: Contract funding | F18: Contract SOW / CWBS | I18: x | J18: x
A19: Industry | B19: Launch Coordination (Partner-Procured) | C19: Peregrine Launch Services | D19: Fictional launch-campaign coordination role; the launch vehicle and services are procured by the partner agency (NASA). | E19: Launch services contract | F19: Launch SOW / ICD | K19: x
A20: Industry | B20: Ground Systems Supplier | C20: Meridian Ground Technologies | D20: Fictional supplier providing mission-control interfaces, telemetry processing, and ground-system equipment. | E20: Contract funding | F20: Ground SOW / ICD | K20: x | M20: x
A22: Academia | B22: Orbital Mechanics Team | C22: Northern Institute of Space Engineering | D22: Fictional university team supporting trajectory analysis, orbital mechanics, and plume-transit navigation research. | E22: Research agreement | F22: Research SOW / workplan | M22: x | N22: x
A23: Academia | B23: Robotics Research Team | C23: Laurentia University of Aerospace Technology | D23: Fictional university team supporting sampling-arm dynamics, end-effector testing, and sample-acquisition simulations. | E23: Research agreement | F23: Research SOW / test plan | I23: x | L23: x | M23: x
A24: Academia | B24: Space Environment Team | C24: Boreal Technical University | D24: Fictional university team supporting deep-space radiation-environment analysis and mission sustainability studies. | E24: Research agreement | F24: Research SOW / workplan | M24: x | N24: x
A26: Int'l partners | B26: European Technical Partner | C26: ESA | D26: International partner (ESA) contributing to the host orbiter and providing plume-transit trajectory analysis support. | E26: Partner contribution | F26: MOU / PIP | G26: x | H26: x | I26: x | J26: x | L26: x | M26: x | N26: x
A27: Int'l partners | B27: American Host-Platform Partner | C27: NASA | D27: International partner (NASA) providing and operating the NEREID orbiter host platform, including launch. | E27: Partner contribution | F27: MOU / PIP | G27: x | H27: x | I27: x | J27: x | M27: x | N27: x
A29: Government | B29: Space Environment OGD | C29: Canadian Orbital Safety Directorate (COSD) | D29: Fictional government organization supporting export-control compliance, planetary-protection oversight, and deep-space mission assurance. | E29: Government service | F29: MOU / service agreement | G29: x | I29: x | L29: x | M29: x
A30: Government | B30: Space Weather OGD | C30: Canadian Space Environment Office (CSEO) | D30: Fictional government organization providing space-weather and orbital-environment information. | E30: Government service | F30: MOU / service agreement | G30: x | I30: x | L30: x | M30: x
A31: Government | B31: Technical Assurance OGD | C31: National Aerospace Research Directorate (NARD) | D31: Fictional government organization providing independent engineering review, testing support, and technical assurance. | E31: Government service | F31: MOU / workplan | G31: x | I31: x | J31: x | L31: x | M31: x

Sheet 6 - Phase Name
A1: ` Table of Contents
A3: 7 - Phasing Nomenclature | I3: What do you call your phases?
A4: Why we we asking:
B5: 1. To normalize the naming convention across all investments.
B6: 2. Math Models are based on Costing Sub-Phase.
B7: 3. We want to output results in your naming convention and scope.
B10: Based on IGMF rev E | F10: Based on CSA-FIN-RPT-0072
A11: Phasing according to | E11: Phasing according to | I11: Phasing according to
A12: EPMO | E12: Costing | I12: PM
E13: PREP | F13: PREP 1 | G13: Prototyping Activities (before Gate 1)
A14: Pre-Project | B14: Option Analysis & Planning Phase | C14: Pre-Phase 0 | F14: PREP 2 | G14: Prototyping Activities (during Phase 0/A)
C15: Phase 0 | E15: Phase 0/A | F15: Phase 0 | G15: Concept & Feasibility | I15: Phase 0
A16: Project | B16: Definition Phase | C16: Detailed Project Requirements | F16: Phase A | G16: Mission Requirements | I16: Phase A
C17: Preliminary Definition | E17: Phase B/C | F17: Phase B | G17: Preliminary Design | I17: Phase B
C18: Detailed Definition | F18: Phase C | G18: Detailed Design | I18: Phase C
B19: Implementation Phase | C19: Implementation | E19: Phase D | F19: MAIT | G19: Manufacturing, Assembly, Integration and Test of Canadian Subsystems and Components | I19: Phase D
F20: SAIT | G20: Spacecraft Level Assembly, Test | I20: Phase D
F21: LEOP | G21: Lauch and early operations | I21: Phase D
A22: Post-Project | B22: Post-Implementation Phase | C22: Operations & Disposal | E22: Phase E | F22: Phase E | G22: Nominal Operations (per design life) | I22: Phase E
E23: Phase E (EXT) | F23: Phase X | G23: Extended operations (mission extension)
E24: Phase F | F24: Phase F | G24: Disposal (incl. post-mortem audit reports) | I24: Phase F
E25: Phase G | F25: Phase G | G25: Post-Mortem science utilization

Sheet 7 - Phase Durations
A1: ` Table of Contents
A3: 7b - Phasing Durations
A4: Why we we asking:
B5: 1. Durations affect Govt Salaries calculations
B6: 2. Durations affect Parametric estimates for Space segment, ground segment, ops
B7: 3. Schedule Scenarios are inputs to sensitivity analysis
B9: Schedule Scenario ID | C9: 1 | M9: Click to draw
B10: Scenario Name | C10: ORCA Nominal / Baseline Schedule
B11: Scenario Description | C11: Baseline ORCA schedule used for primary planning, salary calculations and parametric estimation.
B12: Rationale | C12: Uses the ORCA Phase 0 through Phase X dates established in CADRe Part C (§7 Phase Durations).
B13: Source Doc | C13: ORCA CADRe Part A — Project Phase Schedule
B15: Phase | C15: Expected Start | D15: Expected End | E15: Total D | F15: Total M | G15: 2020 | H15: 2021 | I15: 2022 | J15: 2023 | K15: 2024 | L15: 2025 | M15: 2026 | N15: 2027 | O15: 2028 | P15: 2029 | Q15: 2030 | R15: 2031 | S15: 2032 | T15: 2033 | U15: 2034 | V15: 2035 | W15: 2036 | X15: 2037 | Y15: 2038 | Z15: 2039 | AA15: 2040 | AB15: 2041 | AC15: 2042 | AD15: 2043 | AE15: 2044 | AF15: 2045 | AG15: 2046 | AH15: 2047 | AI15: 2048 | AJ15: 2049 | AK15: 2050 | AL15: 2051 | AM15: 2052 | AN15: 2053 | AO15: 2054 | AP15: 2055 | AQ15: 2056 | AR15: 2057 | AS15: 2058 | AT15: 2059 | AU15: 2060 | AV15: 2061 | AW15: 2062 | AX15: 2063 | AY15: 2064 | AZ15: 2065 | BA15: 2066 | BB15: 2067 | BC15: 2068 | BD15: 2069 | BE15: 2070 | BF15: 2071 | BG15: 2072 | BH15: 2073 | BI15: 2074 | BJ15: 2075 | BK15: 2076 | BL15: 2077 | BM15: 2078 | BN15: 2079 | BO15: 2080 | BP15: 2081 | BQ15: 2082 | BR15: 2083 | BS15: 2084 | BT15: 2085 | BU15: 2086 | BV15: 2087 | BW15: 2088 | BX15: 2089 | BY15: 2090 | BZ15: 2091 | CA15: 2092 | CB15: 2093
A16: Phase 0 | B16: 46023 | C16: 46752 | D16: 730 | E16: 24 | F16: 9.9 | G16: 0 | H16: 0 | I16: 0 | J16: 0 | K16: 0 | L16: 0 | M16: 3 | N16: 12 | O16: 9 | P16: 0 | Q16: 0 | R16: 0 | S16: 0 | T16: 0 | U16: 0 | V16: 0 | W16: 0 | X16: 0 | Y16: 0 | Z16: 0 | AA16: 0 | AB16: 0 | AC16: 0 | AD16: 0 | AE16: 0 | AF16: 0 | AG16: 0 | AH16: 0 | AI16: 0 | AJ16: 0 | AK16: 0 | AL16: 0 | AM16: 0 | AN16: 0 | AO16: 0 | AP16: 0 | AQ16: 0 | AR16: 0 | AS16: 0 | AT16: 0 | AU16: 0 | AV16: 0 | AW16: 0 | AX16: 0 | AY16: 0 | AZ16: 0 | BA16: 0 | BB16: 0 | BC16: 0 | BD16: 0 | BE16: 0 | BF16: 0 | BG16: 0 | BH16: 0 | BI16: 0 | BJ16: 0 | BK16: 0 | BL16: 0 | BM16: 0 | BN16: 0 | BO16: 0 | BP16: 0 | BQ16: 0 | BR16: 0 | BS16: 0 | BT16: 0 | BU16: 0 | BV16: 0 | BW16: 0 | BX16: 0 | BY16: 0 | BZ16: 0 | CA16: 0 | CB16: 0
A17: Phase A | B17: 46753 | C17: 47483 | D17: 731 | E17: 24 | F17: 10.2 | G17: 0 | H17: 0 | I17: 0 | J17: 0 | K17: 0 | L17: 0 | M17: 0 | N17: 0 | O17: 3 | P17: 12 | Q17: 9 | R17: 0 | S17: 0 | T17: 0 | U17: 0 | V17: 0 | W17: 0 | X17: 0 | Y17: 0 | Z17: 0 | AA17: 0 | AB17: 0 | AC17: 0 | AD17: 0 | AE17: 0 | AF17: 0 | AG17: 0 | AH17: 0 | AI17: 0 | AJ17: 0 | AK17: 0 | AL17: 0 | AM17: 0 | AN17: 0 | AO17: 0 | AP17: 0 | AQ17: 0 | AR17: 0 | AS17: 0 | AT17: 0 | AU17: 0 | AV17: 0 | AW17: 0 | AX17: 0 | AY17: 0 | AZ17: 0 | BA17: 0 | BB17: 0 | BC17: 0 | BD17: 0 | BE17: 0 | BF17: 0 | BG17: 0 | BH17: 0 | BI17: 0 | BJ17: 0 | BK17: 0 | BL17: 0 | BM17: 0 | BN17: 0 | BO17: 0 | BP17: 0 | BQ17: 0 | BR17: 0 | BS17: 0 | BT17: 0 | BU17: 0 | BV17: 0 | BW17: 0 | BX17: 0 | BY17: 0 | BZ17: 0 | CA17: 0 | CB17: 0
A18: Phase B | B18: 47484 | C18: 48213 | D18: 730 | E18: 24 | F18: 10.6 | G18: 0 | H18: 0 | I18: 0 | J18: 0 | K18: 0 | L18: 0 | M18: 0 | N18: 0 | O18: 0 | P18: 0 | Q18: 3 | R18: 12 | S18: 9 | T18: 0 | U18: 0 | V18: 0 | W18: 0 | X18: 0 | Y18: 0 | Z18: 0 | AA18: 0 | AB18: 0 | AC18: 0 | AD18: 0 | AE18: 0 | AF18: 0 | AG18: 0 | AH18: 0 | AI18: 0 | AJ18: 0 | AK18: 0 | AL18: 0 | AM18: 0 | AN18: 0 | AO18: 0 | AP18: 0 | AQ18: 0 | AR18: 0 | AS18: 0 | AT18: 0 | AU18: 0 | AV18: 0 | AW18: 0 | AX18: 0 | AY18: 0 | AZ18: 0 | BA18: 0 | BB18: 0 | BC18: 0 | BD18: 0 | BE18: 0 | BF18: 0 | BG18: 0 | BH18: 0 | BI18: 0 | BJ18: 0 | BK18: 0 | BL18: 0 | BM18: 0 | BN18: 0 | BO18: 0 | BP18: 0 | BQ18: 0 | BR18: 0 | BS18: 0 | BT18: 0 | BU18: 0 | BV18: 0 | BW18: 0 | BX18: 0 | BY18: 0 | BZ18: 0 | CA18: 0 | CB18: 0
A19: Phase C | B19: 48214 | C19: 48944 | D19: 731 | E19: 24 | F19: 13.2 | G19: 0 | H19: 0 | I19: 0 | J19: 0 | K19: 0 | L19: 0 | M19: 0 | N19: 0 | O19: 0 | P19: 0 | Q19: 0 | R19: 0 | S19: 3 | T19: 12 | U19: 9 | V19: 0 | W19: 0 | X19: 0 | Y19: 0 | Z19: 0 | AA19: 0 | AB19: 0 | AC19: 0 | AD19: 0 | AE19: 0 | AF19: 0 | AG19: 0 | AH19: 0 | AI19: 0 | AJ19: 0 | AK19: 0 | AL19: 0 | AM19: 0 | AN19: 0 | AO19: 0 | AP19: 0 | AQ19: 0 | AR19: 0 | AS19: 0 | AT19: 0 | AU19: 0 | AV19: 0 | AW19: 0 | AX19: 0 | AY19: 0 | AZ19: 0 | BA19: 0 | BB19: 0 | BC19: 0 | BD19: 0 | BE19: 0 | BF19: 0 | BG19: 0 | BH19: 0 | BI19: 0 | BJ19: 0 | BK19: 0 | BL19: 0 | BM19: 0 | BN19: 0 | BO19: 0 | BP19: 0 | BQ19: 0 | BR19: 0 | BS19: 0 | BT19: 0 | BU19: 0 | BV19: 0 | BW19: 0 | BX19: 0 | BY19: 0 | BZ19: 0 | CA19: 0 | CB19: 0
A20: Phase D | B20: 48945 | C20: 51501 | D20: 2557 | E20: 84.1 | F20: 26.1 | G20: 0 | H20: 0 | I20: 0 | J20: 0 | K20: 0 | L20: 0 | M20: 0 | N20: 0 | O20: 0 | P20: 0 | Q20: 0 | R20: 0 | S20: 0 | T20: 0 | U20: 3 | V20: 12 | W20: 12 | X20: 12 | Y20: 12 | Z20: 12 | AA20: 12 | AB20: 9 | AC20: 0 | AD20: 0 | AE20: 0 | AF20: 0 | AG20: 0 | AH20: 0 | AI20: 0 | AJ20: 0 | AK20: 0 | AL20: 0 | AM20: 0 | AN20: 0 | AO20: 0 | AP20: 0 | AQ20: 0 | AR20: 0 | AS20: 0 | AT20: 0 | AU20: 0 | AV20: 0 | AW20: 0 | AX20: 0 | AY20: 0 | AZ20: 0 | BA20: 0 | BB20: 0 | BC20: 0 | BD20: 0 | BE20: 0 | BF20: 0 | BG20: 0 | BH20: 0 | BI20: 0 | BJ20: 0 | BK20: 0 | BL20: 0 | BM20: 0 | BN20: 0 | BO20: 0 | BP20: 0 | BQ20: 0 | BR20: 0 | BS20: 0 | BT20: 0 | BU20: 0 | BV20: 0 | BW20: 0 | BX20: 0 | BY20: 0 | BZ20: 0 | CA20: 0 | CB20: 0
A21: Phase E | B21: 51502 | C21: 56979 | D21: 5478 | E21: 180.1 | F21: 12.7 | G21: 0 | H21: 0 | I21: 0 | J21: 0 | K21: 0 | L21: 0 | M21: 0 | N21: 0 | O21: 0 | P21: 0 | Q21: 0 | R21: 0 | S21: 0 | T21: 0 | U21: 0 | V21: 0 | W21: 0 | X21: 0 | Y21: 0 | Z21: 0 | AA21: 0 | AB21: 3 | AC21: 12 | AD21: 12 | AE21: 12 | AF21: 12 | AG21: 12 | AH21: 12 | AI21: 12 | AJ21: 12 | AK21: 12 | AL21: 12 | AM21: 12 | AN21: 12 | AO21: 12 | AP21: 12 | AQ21: 9 | AR21: 0 | AS21: 0 | AT21: 0 | AU21: 0 | AV21: 0 | AW21: 0 | AX21: 0 | AY21: 0 | AZ21: 0 | BA21: 0 | BB21: 0 | BC21: 0 | BD21: 0 | BE21: 0 | BF21: 0 | BG21: 0 | BH21: 0 | BI21: 0 | BJ21: 0 | BK21: 0 | BL21: 0 | BM21: 0 | BN21: 0 | BO21: 0 | BP21: 0 | BQ21: 0 | BR21: 0 | BS21: 0 | BT21: 0 | BU21: 0 | BV21: 0 | BW21: 0 | BX21: 0 | BY21: 0 | BZ21: 0 | CA21: 0 | CB21: 0
A22: Phase X | B22: 56980 | C22: 58256 | D22: 1277 | E22: 42 | F22: 41.8 | G22: 0 | H22: 0 | I22: 0 | J22: 0 | K22: 0 | L22: 0 | M22: 0 | N22: 0 | O22: 0 | P22: 0 | Q22: 0 | R22: 0 | S22: 0 | T22: 0 | U22: 0 | V22: 0 | W22: 0 | X22: 0 | Y22: 0 | Z22: 0 | AA22: 0 | AB22: 0 | AC22: 0 | AD22: 0 | AE22: 0 | AF22: 0 | AG22: 0 | AH22: 0 | AI22: 0 | AJ22: 0 | AK22: 0 | AL22: 0 | AM22: 0 | AN22: 0 | AO22: 0 | AP22: 0 | AQ22: 3 | AR22: 12 | AS22: 12 | AT22: 12 | AU22: 3 | AV22: 0 | AW22: 0 | AX22: 0 | AY22: 0 | AZ22: 0 | BA22: 0 | BB22: 0 | BC22: 0 | BD22: 0 | BE22: 0 | BF22: 0 | BG22: 0 | BH22: 0 | BI22: 0 | BJ22: 0 | BK22: 0 | BL22: 0 | BM22: 0 | BN22: 0 | BO22: 0 | BP22: 0 | BQ22: 0 | BR22: 0 | BS22: 0 | BT22: 0 | BU22: 0 | BV22: 0 | BW22: 0 | BX22: 0 | BY22: 0 | BZ22: 0 | CA22: 0 | CB22: 0
B25: Schedule Scenario ID | C25: 2 | L25: Click to draw
B26: Scenario Name | C26: ORCA Optimistic Schedule
B27: Scenario Description | C27: Accelerated schedule used for sensitivity analysis, assuming efficient design maturation, procurement and integration.
B28: Rationale | C28: Phase durations are reduced ~15% relative to the nominal schedule while retaining the ORCA phase structure.
B29: Source Doc | C29: ORCA CADRe Part A — Project Phase Schedule; sensitivity scenario
B31: Phase | C31: Expected Start | D31: Expected End | E31: Total D | F31: Total M | G31: 2020 | H31: 2021 | I31: 2022 | J31: 2023 | K31: 2024 | L31: 2025 | M31: 2026 | N31: 2027 | O31: 2028 | P31: 2029 | Q31: 2030 | R31: 2031 | S31: 2032 | T31: 2033 | U31: 2034 | V31: 2035 | W31: 2036 | X31: 2037 | Y31: 2038 | Z31: 2039 | AA31: 2040 | AB31: 2041 | AC31: 2042 | AD31: 2043 | AE31: 2044 | AF31: 2045 | AG31: 2046 | AH31: 2047 | AI31: 2048 | AJ31: 2049 | AK31: 2050 | AL31: 2051 | AM31: 2052 | AN31: 2053 | AO31: 2054 | AP31: 2055 | AQ31: 2056 | AR31: 2057 | AS31: 2058 | AT31: 2059 | AU31: 2060 | AV31: 2061 | AW31: 2062 | AX31: 2063 | AY31: 2064 | AZ31: 2065 | BA31: 2066 | BB31: 2067 | BC31: 2068 | BD31: 2069 | BE31: 2070 | BF31: 2071 | BG31: 2072 | BH31: 2073 | BI31: 2074 | BJ31: 2075 | BK31: 2076 | BL31: 2077 | BM31: 2078 | BN31: 2079 | BO31: 2080 | BP31: 2081 | BQ31: 2082 | BR31: 2083 | BS31: 2084 | BT31: 2085 | BU31: 2086 | BV31: 2087 | BW31: 2088 | BX31: 2089 | BY31: 2090 | BZ31: 2091 | CA31: 2092 | CB31: 2093
A32: Phase 0 | B32: 46023 | C32: 46643 | D32: 621 | E32: 20.4 | F32: 8.9 | G32: 0 | H32: 0 | I32: 0 | J32: 0 | K32: 0 | L32: 0 | M32: 3 | N32: 12 | O32: 5.5 | P32: 0 | Q32: 0 | R32: 0 | S32: 0 | T32: 0 | U32: 0 | V32: 0 | W32: 0 | X32: 0 | Y32: 0 | Z32: 0 | AA32: 0 | AB32: 0 | AC32: 0 | AD32: 0 | AE32: 0 | AF32: 0 | AG32: 0 | AH32: 0 | AI32: 0 | AJ32: 0 | AK32: 0 | AL32: 0 | AM32: 0 | AN32: 0 | AO32: 0 | AP32: 0 | AQ32: 0 | AR32: 0 | AS32: 0 | AT32: 0 | AU32: 0 | AV32: 0 | AW32: 0 | AX32: 0 | AY32: 0 | AZ32: 0 | BA32: 0 | BB32: 0 | BC32: 0 | BD32: 0 | BE32: 0 | BF32: 0 | BG32: 0 | BH32: 0 | BI32: 0 | BJ32: 0 | BK32: 0 | BL32: 0 | BM32: 0 | BN32: 0 | BO32: 0 | BP32: 0 | BQ32: 0 | BR32: 0 | BS32: 0 | BT32: 0 | BU32: 0 | BV32: 0 | BW32: 0 | BX32: 0 | BY32: 0 | BZ32: 0 | CA32: 0 | CB32: 0
A33: Phase A | B33: 46644 | C33: 47264 | D33: 621 | E33: 20.4 | F33: 9.1 | G33: 0 | H33: 0 | I33: 0 | J33: 0 | K33: 0 | L33: 0 | M33: 0 | N33: 0 | O33: 6.6 | P33: 12 | Q33: 1.8 | R33: 0 | S33: 0 | T33: 0 | U33: 0 | V33: 0 | W33: 0 | X33: 0 | Y33: 0 | Z33: 0 | AA33: 0 | AB33: 0 | AC33: 0 | AD33: 0 | AE33: 0 | AF33: 0 | AG33: 0 | AH33: 0 | AI33: 0 | AJ33: 0 | AK33: 0 | AL33: 0 | AM33: 0 | AN33: 0 | AO33: 0 | AP33: 0 | AQ33: 0 | AR33: 0 | AS33: 0 | AT33: 0 | AU33: 0 | AV33: 0 | AW33: 0 | AX33: 0 | AY33: 0 | AZ33: 0 | BA33: 0 | BB33: 0 | BC33: 0 | BD33: 0 | BE33: 0 | BF33: 0 | BG33: 0 | BH33: 0 | BI33: 0 | BJ33: 0 | BK33: 0 | BL33: 0 | BM33: 0 | BN33: 0 | BO33: 0 | BP33: 0 | BQ33: 0 | BR33: 0 | BS33: 0 | BT33: 0 | BU33: 0 | BV33: 0 | BW33: 0 | BX33: 0 | BY33: 0 | BZ33: 0 | CA33: 0 | CB33: 0
A34: Phase B | B34: 47265 | C34: 47885 | D34: 621 | E34: 20.4 | F34: 9.5 | G34: 0 | H34: 0 | I34: 0 | J34: 0 | K34: 0 | L34: 0 | M34: 0 | N34: 0 | O34: 0 | P34: 0 | Q34: 10.2 | R34: 10.3 | S34: 0 | T34: 0 | U34: 0 | V34: 0 | W34: 0 | X34: 0 | Y34: 0 | Z34: 0 | AA34: 0 | AB34: 0 | AC34: 0 | AD34: 0 | AE34: 0 | AF34: 0 | AG34: 0 | AH34: 0 | AI34: 0 | AJ34: 0 | AK34: 0 | AL34: 0 | AM34: 0 | AN34: 0 | AO34: 0 | AP34: 0 | AQ34: 0 | AR34: 0 | AS34: 0 | AT34: 0 | AU34: 0 | AV34: 0 | AW34: 0 | AX34: 0 | AY34: 0 | AZ34: 0 | BA34: 0 | BB34: 0 | BC34: 0 | BD34: 0 | BE34: 0 | BF34: 0 | BG34: 0 | BH34: 0 | BI34: 0 | BJ34: 0 | BK34: 0 | BL34: 0 | BM34: 0 | BN34: 0 | BO34: 0 | BP34: 0 | BQ34: 0 | BR34: 0 | BS34: 0 | BT34: 0 | BU34: 0 | BV34: 0 | BW34: 0 | BX34: 0 | BY34: 0 | BZ34: 0 | CA34: 0 | CB34: 0
A35: Phase C | B35: 47886 | C35: 48506 | D35: 621 | E35: 20.4 | F35: 11.9 | G35: 0 | H35: 0 | I35: 0 | J35: 0 | K35: 0 | L35: 0 | M35: 0 | N35: 0 | O35: 0 | P35: 0 | Q35: 0 | R35: 1.7 | S35: 12 | T35: 6.6 | U35: 0 | V35: 0 | W35: 0 | X35: 0 | Y35: 0 | Z35: 0 | AA35: 0 | AB35: 0 | AC35: 0 | AD35: 0 | AE35: 0 | AF35: 0 | AG35: 0 | AH35: 0 | AI35: 0 | AJ35: 0 | AK35: 0 | AL35: 0 | AM35: 0 | AN35: 0 | AO35: 0 | AP35: 0 | AQ35: 0 | AR35: 0 | AS35: 0 | AT35: 0 | AU35: 0 | AV35: 0 | AW35: 0 | AX35: 0 | AY35: 0 | AZ35: 0 | BA35: 0 | BB35: 0 | BC35: 0 | BD35: 0 | BE35: 0 | BF35: 0 | BG35: 0 | BH35: 0 | BI35: 0 | BJ35: 0 | BK35: 0 | BL35: 0 | BM35: 0 | BN35: 0 | BO35: 0 | BP35: 0 | BQ35: 0 | BR35: 0 | BS35: 0 | BT35: 0 | BU35: 0 | BV35: 0 | BW35: 0 | BX35: 0 | BY35: 0 | BZ35: 0 | CA35: 0 | CB35: 0
A36: Phase D | B36: 48507 | C36: 50680 | D36: 2174 | E36: 71.5 | F36: 23.5 | G36: 0 | H36: 0 | I36: 0 | J36: 0 | K36: 0 | L36: 0 | M36: 0 | N36: 0 | O36: 0 | P36: 0 | Q36: 0 | R36: 0 | S36: 0 | T36: 5.4 | U36: 12 | V36: 12 | W36: 12 | X36: 12 | Y36: 12 | Z36: 6.1 | AA36: 0 | AB36: 0 | AC36: 0 | AD36: 0 | AE36: 0 | AF36: 0 | AG36: 0 | AH36: 0 | AI36: 0 | AJ36: 0 | AK36: 0 | AL36: 0 | AM36: 0 | AN36: 0 | AO36: 0 | AP36: 0 | AQ36: 0 | AR36: 0 | AS36: 0 | AT36: 0 | AU36: 0 | AV36: 0 | AW36: 0 | AX36: 0 | AY36: 0 | AZ36: 0 | BA36: 0 | BB36: 0 | BC36: 0 | BD36: 0 | BE36: 0 | BF36: 0 | BG36: 0 | BH36: 0 | BI36: 0 | BJ36: 0 | BK36: 0 | BL36: 0 | BM36: 0 | BN36: 0 | BO36: 0 | BP36: 0 | BQ36: 0 | BR36: 0 | BS36: 0 | BT36: 0 | BU36: 0 | BV36: 0 | BW36: 0 | BX36: 0 | BY36: 0 | BZ36: 0 | CA36: 0 | CB36: 0
A37: Phase E | B37: 50681 | C37: 55336 | D37: 4656 | E37: 153.1 | F37: 11.4 | G37: 0 | H37: 0 | I37: 0 | J37: 0 | K37: 0 | L37: 0 | M37: 0 | N37: 0 | O37: 0 | P37: 0 | Q37: 0 | R37: 0 | S37: 0 | T37: 0 | U37: 0 | V37: 0 | W37: 0 | X37: 0 | Y37: 0 | Z37: 5.9 | AA37: 12 | AB37: 12 | AC37: 12 | AD37: 12 | AE37: 12 | AF37: 12 | AG37: 12 | AH37: 12 | AI37: 12 | AJ37: 12 | AK37: 12 | AL37: 12 | AM37: 3.1 | AN37: 0 | AO37: 0 | AP37: 0 | AQ37: 0 | AR37: 0 | AS37: 0 | AT37: 0 | AU37: 0 | AV37: 0 | AW37: 0 | AX37: 0 | AY37: 0 | AZ37: 0 | BA37: 0 | BB37: 0 | BC37: 0 | BD37: 0 | BE37: 0 | BF37: 0 | BG37: 0 | BH37: 0 | BI37: 0 | BJ37: 0 | BK37: 0 | BL37: 0 | BM37: 0 | BN37: 0 | BO37: 0 | BP37: 0 | BQ37: 0 | BR37: 0 | BS37: 0 | BT37: 0 | BU37: 0 | BV37: 0 | BW37: 0 | BX37: 0 | BY37: 0 | BZ37: 0 | CA37: 0 | CB37: 0
A38: Phase X | B38: 55337 | C38: 56422 | D38: 1086 | E38: 35.7 | F38: 37.6 | G38: 0 | H38: 0 | I38: 0 | J38: 0 | K38: 0 | L38: 0 | M38: 0 | N38: 0 | O38: 0 | P38: 0 | Q38: 0 | R38: 0 | S38: 0 | T38: 0 | U38: 0 | V38: 0 | W38: 0 | X38: 0 | Y38: 0 | Z38: 0 | AA38: 0 | AB38: 0 | AC38: 0 | AD38: 0 | AE38: 0 | AF38: 0 | AG38: 0 | AH38: 0 | AI38: 0 | AJ38: 0 | AK38: 0 | AL38: 0 | AM38: 9 | AN38: 12 | AO38: 12 | AP38: 2.7 | AQ38: 0 | AR38: 0 | AS38: 0 | AT38: 0 | AU38: 0 | AV38: 0 | AW38: 0 | AX38: 0 | AY38: 0 | AZ38: 0 | BA38: 0 | BB38: 0 | BC38: 0 | BD38: 0 | BE38: 0 | BF38: 0 | BG38: 0 | BH38: 0 | BI38: 0 | BJ38: 0 | BK38: 0 | BL38: 0 | BM38: 0 | BN38: 0 | BO38: 0 | BP38: 0 | BQ38: 0 | BR38: 0 | BS38: 0 | BT38: 0 | BU38: 0 | BV38: 0 | BW38: 0 | BX38: 0 | BY38: 0 | BZ38: 0 | CA38: 0 | CB38: 0
B48: Schedule Scenario ID | C48: 3 | L48: Click to draw
B49: Scenario Name | C49: ORCA Pessimistic Schedule
B50: Scenario Description | C50: Delayed schedule used for sensitivity analysis, assuming additional design, test, procurement and integration delays.
B51: Rationale | C51: Phase durations are increased ~20% relative to the nominal schedule to represent schedule-risk sensitivity.
B52: Source Doc | C52: ORCA CADRe Part A — Project Phase Schedule; sensitivity scenario
B54: PM | C54: Expected Start | D54: Expected End | E54: Total D | F54: Total M | G54: 2020 | H54: 2021 | I54: 2022 | J54: 2023 | K54: 2024 | L54: 2025 | M54: 2026 | N54: 2027 | O54: 2028 | P54: 2029 | Q54: 2030 | R54: 2031 | S54: 2032 | T54: 2033 | U54: 2034 | V54: 2035 | W54: 2036 | X54: 2037 | Y54: 2038 | Z54: 2039 | AA54: 2040 | AB54: 2041 | AC54: 2042 | AD54: 2043 | AE54: 2044 | AF54: 2045 | AG54: 2046 | AH54: 2047 | AI54: 2048 | AJ54: 2049 | AK54: 2050 | AL54: 2051 | AM54: 2052 | AN54: 2053 | AO54: 2054 | AP54: 2055 | AQ54: 2056 | AR54: 2057 | AS54: 2058 | AT54: 2059 | AU54: 2060 | AV54: 2061 | AW54: 2062 | AX54: 2063 | AY54: 2064 | AZ54: 2065 | BA54: 2066 | BB54: 2067 | BC54: 2068 | BD54: 2069 | BE54: 2070 | BF54: 2071 | BG54: 2072 | BH54: 2073 | BI54: 2074 | BJ54: 2075 | BK54: 2076 | BL54: 2077 | BM54: 2078 | BN54: 2079 | BO54: 2080 | BP54: 2081 | BQ54: 2082 | BR54: 2083 | BS54: 2084 | BT54: 2085 | BU54: 2086 | BV54: 2087 | BW54: 2088 | BX54: 2089 | BY54: 2090 | BZ54: 2091 | CA54: 2092 | CB54: 2093
A55: Phase 0 | B55: 46023 | C55: 46898 | D55: 876 | E55: 28.8 | F55: 11.3 | G55: 0 | H55: 0 | I55: 0 | J55: 0 | K55: 0 | L55: 0 | M55: 3 | N55: 12 | O55: 12 | P55: 1.8 | Q55: 0 | R55: 0 | S55: 0 | T55: 0 | U55: 0 | V55: 0 | W55: 0 | X55: 0 | Y55: 0 | Z55: 0 | AA55: 0 | AB55: 0 | AC55: 0 | AD55: 0 | AE55: 0 | AF55: 0 | AG55: 0 | AH55: 0 | AI55: 0 | AJ55: 0 | AK55: 0 | AL55: 0 | AM55: 0 | AN55: 0 | AO55: 0 | AP55: 0 | AQ55: 0 | AR55: 0 | AS55: 0 | AT55: 0 | AU55: 0 | AV55: 0 | AW55: 0 | AX55: 0 | AY55: 0 | AZ55: 0 | BA55: 0 | BB55: 0 | BC55: 0 | BD55: 0 | BE55: 0 | BF55: 0 | BG55: 0 | BH55: 0 | BI55: 0 | BJ55: 0 | BK55: 0 | BL55: 0 | BM55: 0 | BN55: 0 | BO55: 0 | BP55: 0 | BQ55: 0 | BR55: 0 | BS55: 0 | BT55: 0 | BU55: 0 | BV55: 0 | BW55: 0 | BX55: 0 | BY55: 0 | BZ55: 0 | CA55: 0 | CB55: 0
A56: Phase A | B56: 46899 | C56: 47775 | D56: 877 | E56: 28.8 | F56: 11.7 | G56: 0 | H56: 0 | I56: 0 | J56: 0 | K56: 0 | L56: 0 | M56: 0 | N56: 0 | O56: 0 | P56: 10.2 | Q56: 12 | R56: 6.6 | S56: 0 | T56: 0 | U56: 0 | V56: 0 | W56: 0 | X56: 0 | Y56: 0 | Z56: 0 | AA56: 0 | AB56: 0 | AC56: 0 | AD56: 0 | AE56: 0 | AF56: 0 | AG56: 0 | AH56: 0 | AI56: 0 | AJ56: 0 | AK56: 0 | AL56: 0 | AM56: 0 | AN56: 0 | AO56: 0 | AP56: 0 | AQ56: 0 | AR56: 0 | AS56: 0 | AT56: 0 | AU56: 0 | AV56: 0 | AW56: 0 | AX56: 0 | AY56: 0 | AZ56: 0 | BA56: 0 | BB56: 0 | BC56: 0 | BD56: 0 | BE56: 0 | BF56: 0 | BG56: 0 | BH56: 0 | BI56: 0 | BJ56: 0 | BK56: 0 | BL56: 0 | BM56: 0 | BN56: 0 | BO56: 0 | BP56: 0 | BQ56: 0 | BR56: 0 | BS56: 0 | BT56: 0 | BU56: 0 | BV56: 0 | BW56: 0 | BX56: 0 | BY56: 0 | BZ56: 0 | CA56: 0 | CB56: 0
A57: Phase B | B57: 47776 | C57: 48651 | D57: 876 | E57: 28.8 | F57: 12.2 | G57: 0 | H57: 0 | I57: 0 | J57: 0 | K57: 0 | L57: 0 | M57: 0 | N57: 0 | O57: 0 | P57: 0 | Q57: 0 | R57: 5.4 | S57: 12 | T57: 11.4 | U57: 0 | V57: 0 | W57: 0 | X57: 0 | Y57: 0 | Z57: 0 | AA57: 0 | AB57: 0 | AC57: 0 | AD57: 0 | AE57: 0 | AF57: 0 | AG57: 0 | AH57: 0 | AI57: 0 | AJ57: 0 | AK57: 0 | AL57: 0 | AM57: 0 | AN57: 0 | AO57: 0 | AP57: 0 | AQ57: 0 | AR57: 0 | AS57: 0 | AT57: 0 | AU57: 0 | AV57: 0 | AW57: 0 | AX57: 0 | AY57: 0 | AZ57: 0 | BA57: 0 | BB57: 0 | BC57: 0 | BD57: 0 | BE57: 0 | BF57: 0 | BG57: 0 | BH57: 0 | BI57: 0 | BJ57: 0 | BK57: 0 | BL57: 0 | BM57: 0 | BN57: 0 | BO57: 0 | BP57: 0 | BQ57: 0 | BR57: 0 | BS57: 0 | BT57: 0 | BU57: 0 | BV57: 0 | BW57: 0 | BX57: 0 | BY57: 0 | BZ57: 0 | CA57: 0 | CB57: 0
A58: Phase C | B58: 48652 | C58: 49528 | D58: 877 | E58: 28.8 | F58: 15.2 | G58: 0 | H58: 0 | I58: 0 | J58: 0 | K58: 0 | L58: 0 | M58: 0 | N58: 0 | O58: 0 | P58: 0 | Q58: 0 | R58: 0 | S58: 0 | T58: 0.6 | U58: 12 | V58: 12 | W58: 4.2 | X58: 0 | Y58: 0 | Z58: 0 | AA58: 0 | AB58: 0 | AC58: 0 | AD58: 0 | AE58: 0 | AF58: 0 | AG58: 0 | AH58: 0 | AI58: 0 | AJ58: 0 | AK58: 0 | AL58: 0 | AM58: 0 | AN58: 0 | AO58: 0 | AP58: 0 | AQ58: 0 | AR58: 0 | AS58: 0 | AT58: 0 | AU58: 0 | AV58: 0 | AW58: 0 | AX58: 0 | AY58: 0 | AZ58: 0 | BA58: 0 | BB58: 0 | BC58: 0 | BD58: 0 | BE58: 0 | BF58: 0 | BG58: 0 | BH58: 0 | BI58: 0 | BJ58: 0 | BK58: 0 | BL58: 0 | BM58: 0 | BN58: 0 | BO58: 0 | BP58: 0 | BQ58: 0 | BR58: 0 | BS58: 0 | BT58: 0 | BU58: 0 | BV58: 0 | BW58: 0 | BX58: 0 | BY58: 0 | BZ58: 0 | CA58: 0 | CB58: 0
A59: Phase D | B59: 49529 | C59: 52596 | D59: 3068 | E59: 100.9 | F59: 30 | G59: 0 | H59: 0 | I59: 0 | J59: 0 | K59: 0 | L59: 0 | M59: 0 | N59: 0 | O59: 0 | P59: 0 | Q59: 0 | R59: 0 | S59: 0 | T59: 0 | U59: 0 | V59: 0 | W59: 7.8 | X59: 12 | Y59: 12 | Z59: 12 | AA59: 12 | AB59: 12 | AC59: 12 | AD59: 12 | AE59: 9 | AF59: 0 | AG59: 0 | AH59: 0 | AI59: 0 | AJ59: 0 | AK59: 0 | AL59: 0 | AM59: 0 | AN59: 0 | AO59: 0 | AP59: 0 | AQ59: 0 | AR59: 0 | AS59: 0 | AT59: 0 | AU59: 0 | AV59: 0 | AW59: 0 | AX59: 0 | AY59: 0 | AZ59: 0 | BA59: 0 | BB59: 0 | BC59: 0 | BD59: 0 | BE59: 0 | BF59: 0 | BG59: 0 | BH59: 0 | BI59: 0 | BJ59: 0 | BK59: 0 | BL59: 0 | BM59: 0 | BN59: 0 | BO59: 0 | BP59: 0 | BQ59: 0 | BR59: 0 | BS59: 0 | BT59: 0 | BU59: 0 | BV59: 0 | BW59: 0 | BX59: 0 | BY59: 0 | BZ59: 0 | CA59: 0 | CB59: 0
A60: Phase E | B60: 52597 | C60: 59169 | D60: 6573 | E60: 216.1 | F60: 14.6 | G60: 0 | H60: 0 | I60: 0 | J60: 0 | K60: 0 | L60: 0 | M60: 0 | N60: 0 | O60: 0 | P60: 0 | Q60: 0 | R60: 0 | S60: 0 | T60: 0 | U60: 0 | V60: 0 | W60: 0 | X60: 0 | Y60: 0 | Z60: 0 | AA60: 0 | AB60: 0 | AC60: 0 | AD60: 0 | AE60: 3 | AF60: 12 | AG60: 12 | AH60: 12 | AI60: 12 | AJ60: 12 | AK60: 12 | AL60: 12 | AM60: 12 | AN60: 12 | AO60: 12 | AP60: 12 | AQ60: 12 | AR60: 12 | AS60: 12 | AT60: 12 | AU60: 12 | AV60: 12 | AW60: 9 | AX60: 0 | AY60: 0 | AZ60: 0 | BA60: 0 | BB60: 0 | BC60: 0 | BD60: 0 | BE60: 0 | BF60: 0 | BG60: 0 | BH60: 0 | BI60: 0 | BJ60: 0 | BK60: 0 | BL60: 0 | BM60: 0 | BN60: 0 | BO60: 0 | BP60: 0 | BQ60: 0 | BR60: 0 | BS60: 0 | BT60: 0 | BU60: 0 | BV60: 0 | BW60: 0 | BX60: 0 | BY60: 0 | BZ60: 0 | CA60: 0 | CB60: 0
A61: Phase X | B61: 59170 | C61: 60701 | D61: 1532 | E61: 50.4 | F61: 48 | G61: 0 | H61: 0 | I61: 0 | J61: 0 | K61: 0 | L61: 0 | M61: 0 | N61: 0 | O61: 0 | P61: 0 | Q61: 0 | R61: 0 | S61: 0 | T61: 0 | U61: 0 | V61: 0 | W61: 0 | X61: 0 | Y61: 0 | Z61: 0 | AA61: 0 | AB61: 0 | AC61: 0 | AD61: 0 | AE61: 0 | AF61: 0 | AG61: 0 | AH61: 0 | AI61: 0 | AJ61: 0 | AK61: 0 | AL61: 0 | AM61: 0 | AN61: 0 | AO61: 0 | AP61: 0 | AQ61: 0 | AR61: 0 | AS61: 0 | AT61: 0 | AU61: 0 | AV61: 0 | AW61: 3 | AX61: 12 | AY61: 12 | AZ61: 12 | BA61: 11.3 | BB61: 0 | BC61: 0 | BD61: 0 | BE61: 0 | BF61: 0 | BG61: 0 | BH61: 0 | BI61: 0 | BJ61: 0 | BK61: 0 | BL61: 0 | BM61: 0 | BN61: 0 | BO61: 0 | BP61: 0 | BQ61: 0 | BR61: 0 | BS61: 0 | BT61: 0 | BU61: 0 | BV61: 0 | BW61: 0 | BX61: 0 | BY61: 0 | BZ61: 0 | CA61: 0 | CB61: 0

Sheet 8 -  Milestones 
A1: ` Table of Contents
A3: 8 - Milestone Register
A4: Why we we asking:
B5: to double check your schedule
B6: based in IGMF rev F
B9: ID | C9: Phase | D9: Milestone | E9: Description | F9: Specify Date | G9: Actual or Planned? | H9: Type | I9: Milestone Description | J9: Used in Analysis?
B10: M1 | C10: Prep 1 | D10: Primus | E10: First Gate 0 of first dollar spent | H10: Governance | J10: Used to calculate sunk costs
B11: M2 | D11: Contract Award | E11: First R&D contract, grant or contribution signed | H11: Contract | J11: Used to calculate sunk costs
B12: M3 | D12: Final Review | E12: Last R&D contract, grant or contribution before Mission Gate 0 is Completed | H12: Contract | J12: Used to calculate sunk costs
B13: M4 | C13: Prep 2 | D13: Secundus | E13: Gate 0 which will lead to an R&D contract during Phase 0/A. Could be same as Mission Gate 0 but not always | H13: Governance | J13: not used in costing, used only for graphics on Gantt Chart
B14: M5 | D14: Contract Award | E14: First R&D contract signed after Mission Gate 1 | H14: Contract | J14: Used for parametric analysis
B15: M6 | D15: Final Review | E15: Last R&D contract ends after Mission Gate 1 | H15: Contract | J15: Used for parametric analysis
B16: M7 | C16: Phase 0 | D16: Phase 0 Start | E16: RAM Effort to prepare Gate 0 or Gate 1 Begins | H16: RAM | J16: Used to compute CSA Salaries
B17: M8 | D17: Gate 0 | E17: Policy cover (possibly though a Strategic Retreat) | H17: Governance | J17: not used in costing, used only for graphics on Gantt Chart
B18: M9 | D18: KDP-0 / Gate 1 | E18: Key Decision Point in CSA Governance Framework | H18: Governance | J18: not used in costing, used only for graphics on Gantt Chart
B19: M10 | D19: R1 | E19: Identification of Investment Options | H19: Governance | J19: not used in costing, used only for graphics on Gantt Chart
B20: M11 | D20: Contract Award | E20: Phase 0 Contract Award | H20: Contract | J20: Used for parametric analysis
B21: M12 | D21: PL-MCR | E21: Mission Concept Review | H21: Major Milestone | I21: MCR is conducted early in the mission planning process to assess the feasibility and viability of the mission concept. | J21: Major Milestones used to compute durations in paramateric and analogy
B22: M13 | D22: PL-MRR | E22: Mission Requirements Review | H22: Major Milestone | I22: MRR is conducted to establish and validate the specific requirements that the mission must meet to achieve its objectives. | J22: Major Milestones used to compute durations in paramateric and analogy
B23: M14 | D23: MDR | E23: Mission Definition Review | H23: Interim Milestone | I23: MDR is conducted to refine the mission concept and requirements further and to establish a more detailed plan for mission implementation. | J23: Minor Milestones are sometimes used to infer Major Milestones when those have not been specified
B24: M15 | D24: FR | E24: Contractor Phase 0 Final Review | H24: Contract | J24: Used for parametric analysis
B25: M16 | D25: R2 | E25: Investment Option Recommendation | H25: Governance | J25: not used in costing, used only for graphics on Gantt Chart
B26: M17 | D26: Phase 0 End | E26: RAM Effort for Phase 0 Ends | H26: RAM | J26: Used to compute CSA Salaries
B27: M18 | C27: Phase A | D27: Phase A Start | E27: RAM Effort to prepare Gate 2 Begins | H27: RAM | J27: Used to compute CSA Salaries
B28: M19 | D28: KDP-A / Gate 2 | E28: Key Decision Point in CSA Governance Framework | H28: Governance | J28: not used in costing, used only for graphics on Gantt Chart
B29: M20 | D29: Contract Award | E29: Phase A Contract Award | H29: Contract | J29: Used for parametric analysis
B30: M21 | D30: PL-SRR | E30: 47469 | G30: Planned | H30: Major Milestone | I30: SRR is conducted to establish and validate the high-level requirements that the system must meet to achieve its mission objectives. | J30: Minor Milestones are sometimes used to infer Major Milestones when those have not been specified
B31: M24 | D31: M-SRR | E31: 47483 | G31: Planned | H31: External Dependency | J31: Major Milestones used to compute durations in paramateric and analogy
D32: M-SDR | E32: 47362 | G32: Planned | H32: External Dependency
B33: M27 | D33: Final Review | E33: Contractor Phase A Final Review | H33: Contract | J33: Used for parametric analysis
B34: M28 | D34: Phase A End | E34: RAM Effort for Phase A Ends | H34: RAM | J34: Used to compute CSA Salaries
B35: M29 | C35: Phase B | D35: Phase B Start | E35: RAM Effort to prepare Phase B Begins | H35: RAM | J35: Used to compute CSA Salaries
B36: M30 | D36: KDP-B / Review R3 | E36: Key Decision Point in CSA Governance Framework | H36: Governance | J36: not used in costing, used only for graphics on Gantt Chart
B37: M31 | D37: Contract Award | E37: Phase B Contract Award | H37: Contract | J37: Used for parametric analysis
B38: M32 | D38: PL-PDR | E38: 48168 | G38: Planned | H38: Major Milestone | I38: The main purpose of PDR is to assess and evaluate the preliminary design of the spacecraft or system. | J38: Minor Milestones are sometimes used to infer Major Milestones when those have not been specified
B39: M35 | D39: M-PDR | E39: 48213 | G39: Planned | H39: External Dependency | J39: Major Milestones used to compute durations in paramateric and analogy
B40: M36 | D40: Final Review | E40: Contractor Phase B Final Review | H40: Contract | J40: Used for parametric analysis
B41: M37 | D41: Phase B End | E41: RAM Effort for Phase B Ends | H41: RAM | J41: Used to compute CSA Salaries
B42: M38 | C42: Phase C | D42: Phase C Start | E42: RAM Effort to prepare Phase B Begins | H42: RAM | J42: Used to compute CSA Salaries
B43: M39 | D43: KDP-C / Review R4 | E43: Key Decision Point in CSA Governance Framework | H43: Governance | J43: not used in costing, used only for graphics on Gantt Chart
B44: M40 | D44: Contract Award | E44: Phase C Contract Award or PDR | H44: Contract | J44: Used for parametric analysis
B45: M41 | D45: PL-CDR | E45: 48883 | G45: Planned | H45: Major Milestone | I45: CDR serves as a critical milestone to evaluate and approve the detailed design of the spacecraft or system. | J45: Minor Milestones are sometimes used to infer Major Milestones when those have not been specified
B46: M44 | D46: M-CDR | E46: 48944 | G46: Planned | H46: External Dependency | J46: Major Milestones used to compute durations in paramateric and analogy
B47: M45 | D47: Final Review | E47: Contractor Phase C Final Review | H47: Contract | J47: Used for parametric analysis
B48: M46 | D48: Phase C End | E48: RAM Effort for Phase C Ends | H48: RAM | J48: Used to compute CSA Salaries
B49: M47 | C49: MAIT | D49: Phase D Start | E49: RAM Effort to prepare Phase D Begins | H49: RAM | J49: Used to compute CSA Salaries
B50: M48 | D50: KDP-D / Gate 3 / Review R5 | E50: Key Decision Point in CSA Governance Framework | H50: Governance | J50: not used in costing, used only for graphics on Gantt Chart
B51: M49 | D51: Contract Award | E51: Phase D Contract Award or CDR | H51: Contract | J51: Used for parametric analysis
B52: M50 | D52: Subsystem Integration | E52: Sub-System Integration Review (SIR) | H52: External Dependency | I52: SIR evaluates the integration of all subsystems and components to ensure they function together as a cohesive system. | J52: Major Milestones used to compute durations in paramateric and analogy
B53: M51 | D53: PL-PSR | E53: 51321 | G53: Planned | H53: Major Milestone | J53: Minor Milestones are sometimes used to infer Major Milestones when those have not been specified
B54: M56 | C54: SAIT | D54: Arrive date at Prime | E54: ORCA space segment arrives at Prime (EDA) for spacecraft integration | H54: Interim Milestone | J54: Minor Milestones are sometimes used to infer Major Milestones when those have not been specified
B55: M57 | D55: SIR | E55: System Integration Review (SIR) | H55: Interim Milestone | J55: Minor Milestones are sometimes used to infer Major Milestones when those have not been specified
B56: M59 | D56: PSR to LV | E56: Pre-Ship Review (PSR) (to LV) | H56: External Dependency | J56: Major Milestones used to compute durations in paramateric and analogy
B57: M60 | C57: LEOP | D57: Arrive date to LV | E57: Space Segment arrives at Launch provider for integration with LV | H57: Interim Milestone | J57: Minor Milestones are sometimes used to infer Major Milestones when those have not been specified
B58: M61 | D58: FRR | E58: Flight Readiness Review (FRR) | H58: Interim Milestone | I58: FRR evaluates the readiness of the spacecraft, launch vehicle, and ground support systems for launch. | J58: Minor Milestones are sometimes used to infer Major Milestones when those have not been specified
B59: M62 | D59: ORR | E59: Ops Readiness Review (ORR) | H59: Interim Milestone | I59: ORR evaluates the readiness of mission operations personnel, procedures, and facilities for mission execution. | J59: Minor Milestones are sometimes used to infer Major Milestones when those have not been specified
B60: M63 | D60: Launch | E60: 51501 | G60: Planned | H60: External Dependency | I60: Launch marks the initiation of the space mission, with the primary goal of placing the spacecraft into its designated orbit or trajectory. | J60: Major Milestones used to compute durations in paramateric and analogy
B61: M64 | D61: Orbit-Insertion Start | E61: Start of orbit-raising / transit to the Enceladus science orbit | H61: Interim Milestone | J61: Minor Milestones are sometimes used to infer Major Milestones when those have not been specified
B62: M65 | D62: Orbit Insertion | E62: Orbital insertion into the Enceladus science orbit | H62: Interim Milestone | I62: Orbit insertion maneuvers adjust the NEREID orbiter's trajectory to place ORCA into its intended science orbit around Enceladus. | J62: Minor Milestones are sometimes used to infer Major Milestones when those have not been specified
B63: M69 | D63: CR | E63: Commissioning Review (CR) | H63: Interim Milestone | I63: CR evaluates the initial performance of the spacecraft and its systems after deployment or landing. | J63: Minor Milestones are sometimes used to infer Major Milestones when those have not been specified
B64: M71 | C64: Phase E | D64: Phase E Start | E64: RAM Effort to prepare Phase E Begins | H64: RAM | J64: Used to compute CSA Salaries
B65: M72 | D65: KDP-E / Gate 4 | E65: Key Decision Point in CSA Governance Framework | H65: Governance | J65: not used in costing, used only for graphics on Gantt Chart
B66: M74 | D66: Phase E Start | E66: Start of nominal Ops or CR | H66: Major Milestone | J66: Major Milestones used to compute durations in paramateric and analogy
B67: M75 | D67: End of Nominal Ops | E67: End of Nominal Ops | H67: Major Milestone | J67: Major Milestones used to compute durations in paramateric and analogy
B68: M76 | D68: End of operations | E68: End of Extended Operations | H68: Major Milestone | J68: Major Milestones used to compute durations in paramateric and analogy
B69: M77 | D69: Final Review | E69: Contractor Final Review after extended Ops | H69: Contract | J69: Used for parametric analysis
B70: M78 | C70: Phase X | D70: RAM Effort to prepare Phase X (Extended Operations & Disposal) Begins | E70: RAM Effort to prepare Phase X (Disposal & Disposal) Begins | H70: RAM | J70: Used to compute CSA Salaries
B71: M79 | D71: KDP-X / Gate 5 | E71: Key Decision Point in CSA Governance Framework (IGMF Gate 5) | H71: Governance | J71: not used in costing, used only for graphics on Gantt Chart
B72: M80 | D72: DR | E72: Decommissioning & Disposal Review (disposal of NEREID Orbiter) | H72: Interim Milestone | I72: The Decommissioning Review marks the transition from operations to the disposal phase of mission assets | J72: Minor Milestones are sometimes used to infer Major Milestones when those have not been specified
B73: M81 | D73: Final Review | E73: Contractor Final Review for Phase X | H73: Contract | J73: Used for parametric analysis

Sheet 9 - Sched Dependencies
A1: ` Table of Contents
A3: 10 - Schedule Constraints and dependencies
A4: Why we are asking
B5: To conduct a JCL analysis
A8: Critical Path Analysis
B9: 45658 | D9: ORCA concept & science maturation studies initiated
B10: 46023 | D10: Phase 0 Start — Gate 0 / KDP-0 (first dollar spent)
B11: 46752 | C11: M-MCR | D11: Mission Concept Review (MCR)
B12: 46753 | D12: Phase A Start — KDP-A / Gate 2
B13: 47300 | D13: ORCA Concept Rebaseline
B14: 47483 | C14: M-SRR | D14: System Requirements Review (SRR)
B15: 47484 | D15: Phase B Start — KDP-B / Review R3
B16: 47921 | D16: Orbiter / ORCA Instrument Suite Interface Complete
B17: 48213 | C17: M-PDR | D17: Preliminary Design Review (PDR) — Phase B End
B18: 48214 | D18: Phase C Start — KDP-C / Review R4
B19: 48652 | D19: Instrument Suite Environmental Qualification Complete
B20: 48944 | C20: M-CDR | D20: Critical Design Review (CDR) — Phase C End
B21: 48945 | D21: Phase D Start — KDP-D / Gate 3 / R5 (MAIT/SAIT)
B22: 49765 | C22: M-MRR | D22: Manufacturing Readiness Review (MRR)
B23: 51321 | C23: L-6mo | D23: Pre-Ship Review of Systems to Prime (PSR) — flight units ship to Prime (EDA)
B24: 51379 | D24: Integrated Instrument Suite Functional Test Complete
B25: 51409 | C25: M-SIR | D25: System Integration Review (SIR)
B26: 51411 | C26: M-AR | D26: Acceptance Review (AR) — Flight Acceptance
B27: 51441 | D27: Flight Software and Autonomy Verification Complete
B28: 51456 | C28: L-45d | D28: Pre-Ship Review — Spacecraft to Launch Site
B29: 51501 | C29: L | D29: Launch (NASA / host orbiter NEREID) — Phase E Start
B30: 51502 | C30: L+1d | D30: Orbital insertion into Enceladus science orbit; commissioning start
B31: 51515 | C31: M-CR | D31: Commissioning Review (CR) — start of nominal Ops
B32: 56979 | D32: End of Nominal Ops (Phase E End); Phase X disposal through 2059-06-30
A34: Assumption | B34: dependencies | C34: CSA instrument flight units must be delivered to the Prime (EDA) ahead of Mission CDR to support host-orbiter integration
A35: Assumption | B35: Phase 0 | C35: CSA conducted a Phase 0 previously; it is assumed to have been sufficient to meet the exit criteria of a real Phase 0
A36: Assumption | B36: Phase A | C36: The CSA Phase A must be completed before Mission SRR
A37: Assumption | B37: Phase B | C37: The Orbiter/Instrument Suite Interface Control Document must be complete before PDR
A38: Assumption | B38: Phase C | C38: Instrument suite environmental qualification must be complete ~9 months before CDR
A39: Assumption | B39: Phase MAIT | C39: The Manufacturing Readiness Review (MRR) precedes the CSA flight-hardware build by ~4 years, reflecting long-lead radiation-hardened parts
A40: Assumption | B40: SAIT | C40: The CSA flight-hardware ship date (Pre-Ship Review) is ~6 months before Launch
A41: Assumption | B41: SAIT | C41: Mission CDR is planned for Dec 2033 in the ORCA Scenario 1 baseline
A42: Assumption | B42: SAIT | C42: The assumed duration between Mission CDR and Launch is ~84 months (Scenario 1), driven by the host orbiter's (NASA-led) integration and launch-window schedule
A43: Assumption | B43: LEOP | C43: ORCA Scenario 1 assumes a launch date of Dec 31 2040 on the NEREID orbiter (NASA-led launch)
A44: Assumption | B44: LEOP | C44: Interplanetary cruise to Enceladus (via Jupiter gravity assist) is carried on the NEREID orbiter; no CSA-specific cruise operations are costed
A45: Assumption | B45: LEOP | C45: Post-orbit-insertion checkout of the ORCA instrument suite is assumed ~30 days (20 days optimistic, 50 days pessimistic)
... A50: Assumption | B50: Phase X | C50: End of Phase X (mission close-out / final disposal) occurs on 2059-06-30 in Scenario 1
A62: Brainstorming Questions about Schedule GR&A
B64: Schedule constraints and Dependencies
A65: Assumption 01 | B65: Mission Milestones are external dependencies for the CSA activities. Per the ORCA Scenario 1 baseline, these dates are:
C66: Mission Milestone | D66: Planned Date | F66: CSA Dependency | G66: CSA Planned Date
A67: Assumption 02 | C67: Mission SRR | D67: 47483 | E67: ---> | F67: CSA PL SRR (M-SRR-14d) | G67: =D67-14 -> 47469
A68: Assumption 03 | C68: Mission SDR | D68: 47362 | E68: ---> | F68: CSA PDR preparation start | G68: =D68 -> 47362
A69: Assumption 04 | C69: Mission PDR | D69: 48213 | E69: ---> | F69: CSA PL-PDR (M-PDR-30d) | G69: =D69-30 -> 48183
A70: Assumption 05 | C70: Mission CDR | D70: 48944 | E70: ---> | F70: CSA PL-CDR (M-CDR-61d) | G70: =D70-61 -> 48883
A71: Assumption 06 | C71: Launch | D71: 51501 | E71: ---> | F71: CSA PSR (L-88d) | G71: =D71-88 -> 51413
B73: Schedule Assumptions for Long Lead Items
A74: Assumption 07 | C74: Long-lead items (sampling-arm actuators, radiation-hardened electronics, long-lead detector components) — when is the list ready? When are they procured and paid?
B76: Schedule Assumptions for Integrated Testing (Assembly at Mission Level) - SAIT
C77: Is the Prime (EDA) expecting delivery at a given date?
C78: Assuming the Prime (EDA) will handle spacecraft assembly, integration and test during SAIT. The Prime need date for flight units is driven by the Mission CDR schedule. The CSA must ship the flight units ahead of Mission CDR (see Assumption 05).
C79: How long is SAIT expected to last?
C80: In the ORCA Scenario 1 baseline, MAIT/SAIT / Phase D spans ~84 months (Jan 2034 - Dec 2040), reflecting long-lead radiation-hardened parts and the host-orbiter integration schedule.
C81: Any extended long term storage planned? No
B83: Schedule Assumptions for Launch & Early Ops
C84: ORCA's interplanetary cruise to Enceladus (via Jupiter gravity assist) is carried on the NEREID orbiter. Post-orbit-insertion checkout of the ORCA instrument suite is assumed ~30 days (20-50 day range).
C85: how much time for commissioning? 1 -3 months
C86: Any launch window constraints? The launch window is set by planetary alignment for the Jupiter gravity assist and is a hard constraint (host orbiter, NASA-led).
B88: Schedule Assumptions for Ground Segment
C89: Ground-segment dependency: instrument telemetry and commands are relayed via the NEREID orbiter's (NASA-led) Deep Space Network downlink; CSA operates its own Mission Operations Centre and processes instrument science data.
B91: Schedule Assumptions for Ops Segment
C92: Nominal Phase E operations ≈ 180 months (~15 years) in Scenario 1, reflecting the long-duration Enceladus science campaign
C93: Assumed total operating life including extended ops & disposal (Phase E + Phase X) ≈ 18.5 years (Scenario 1)
B95: Schedule Assumptions for Science Segment
C96: Did Science activities (science maturation studies) occur before Phase 0? Yes
C97: Did Science team participate in Phase 0/A to refine requirements? Yes
C98: Did Science team participate in Phase BCD to assist in mission design? Yes
C99: Will science team condut any calibration, validation activities (ex. Sub-orbital capaign) before end of commissioning?
C100: Will science team condut any calibration, validation activities (ex. Sub-orbital capaign) after commissioning?
C101: How long after the space segment ends will the collected data still be considered useful (duration of Phase X)?

Sheet GR&A
A2: Costing CSA Ground Rules & Assumptions template
A3: Last review | D3: 45747
A5: ID | B5: Catégorie | C5: Category | D5: Category | E5: Sub-category | F5: Items | G5: GR or A | H5: Title | I5: Description | J5: Phase | K5: CBS # linked to GR&A | L5: Impact on Project | M5: Impact on costing, methodology, models, tools & analysis | N5: Excepted source | O5: Do not delete - Mireille | P5: Source/Link | Q5: Other rational | R5: Waiver deviation
A6: 1 | B6: Hypothèses Programmatiques | C6: Strategy Naratives | D6: Objectifs politiques et stratégiques | E6: Alignement sur la stratégie de l’ASC | N6: Business Case et/ou CADRE Part C onglet CM list | O6: Strategy
A7: 2 | B7: Hypothèses Programmatiques | C7: Strategy Naratives | D7: Objectifs politiques et stratégiques | E7: Contraintes gouvernementales ou directives de haut niveau | N7: Business Case et/ou CADRE Part C onglet CM list | O7: Strategy
A8: 3 | B8: Hypothèses Programmatiques | D8: Objectifs politiques et stratégiques | E8: Type de mission : Flagship, LargeSat, SmallSat, NanoSat, Hosted Payload, Data stream partnership, data stream purchase | N8: CADRE Part A | O8: CADRE Part A ou contants
A9: 4 | B9: Hypothèses Programmatiques | D9: Objectifs politiques et stratégiques | E9: Disciplines et secteur : SatCom, Astronomie, exploration spatiale,... | N9: CADRE Part A | O9: CADRE Part A
A10: 5 | B10: Hypothèses Programmatiques | D10: Objectifs politiques et stratégiques | E10: Dépendances avec d'autres projets/missions | N10: CADRE Part A | O10: CADRE Part A
A11: 6 | B11: Hypothèses Programmatiques | C11: Strategy Naratives | D11: Budget global et financement | E11: Soumission au Conseil du Tésor (TBSub) - But de l'exercice de costing : Budget Ask, Reprofiling,… Définir le nombre de TBSub + échéancier associé aux TBSub | N11: CADRE Part C onglet Stratégie contractuelle | O11: Strategy
A12: 7 | B12: Hypothèses Programmatiques | C12: Strategy Naratives | D12: Budget global et financement | E12: Enveloppe de la masse salariale | N12: CADRE Part C onglet RAM | O12: Strategy
A13: 8 | B13: Hypothèses Programmatiques | C13: Strategy Naratives | D13: Budget global et financement | E13: Enveloppe des frais de gestion et plan de voyages | N13: CADRE Part C onglet Overhead Costs | O13: Strategy
A14: 9 | B14: Hypothèses Programmatiques | C14: Costign Plan | D14: Budget global et financement | E14: Méthodologie d'établissement des coûts | N14: Plan de l’exercice d’établissement des coûts | O14: Costing Plan
A15: 10 | B15: Hypothèses Programmatiques | C15: Costign Plan | D15: Budget global et financement | E15: Note de réflexion supplémentaire | O15: Costing Plan
A16: 11 | B16: Hypothèses Programmatiques | C16: Costign Plan | D16: Budget global et financement | E16: Au moins 2 façon différentes pour chaque incluant RAM | N16: Plan de l’exercice d’établissement des coûts - Méthodologies | O16: Costing Plan
A17: 12 | B17: Hypothèses Programmatiques | C17: Costign Plan | D17: Budget global et financement | E17: Analyse de sensibilité | N17: À compléter par Finance | O17: Costing Plan
A18: 13 | B18: Hypothèses Programmatiques | C18: Costign Plan | D18: Budget global et financement | E18: Sufficiency Report or Independent Cost Estimate or Independent Cost Review | N18: À compléter par Finance | O18: Costing Plan
A19: 14 | B19: Hypothèses Programmatiques | C19: Costign Plan | D19: Budget global et financement | E19: Analogie (nearest neighboors), lesquels. | N19: Plan de l’exercice d’établissement des coûts - Méthodologies | O19: Costing Plan
A20: 15 | B20: Hypothèses Programmatiques | C20: Costign Plan | D20: Budget global et financement | E20: Analyse paramétrique (True planning, PCEC, NCIM, SEER, Compact). CER Calibration Plan. | N20: Plan de l’exercice d’établissement des coûts - Méthodologies | O20: Costing Plan
A21: 16 | B21: Hypothèses Programmatiques | C21: Costign Plan | D21: Budget global et financement | E21: Soumission de l'industrie et jugement d'expert | N21: Plan de l’exercice d’établissement des coûts - Méthodologies | O21: Costing Plan
A22: 17 | B22: Hypothèses Programmatiques | C22: Costign Plan | D22: Budget global et financement | E22: Analyse Monte Carlo (crystal ball) | N22: Plan de l’exercice d’établissement des coûts - Méthodologies | O22: Costing Plan
A23: 18 | B23: Hypothèses Programmatiques | C23: Costign Plan | D23: Budget global et financement | E23: Bottom up, qui le fait et comment | N23: Plan de l’exercice d’établissement des coûts - Méthodologies | O23: Costing Plan
A24: 19 | B24: Hypothèses Programmatiques | C24: Costign Plan | D24: Budget global et financement | E24: Learning curves | N24: RASCI = qui fait quoi. bottom up = Plan de l’exercice d’établissement des coûts | O24: Costing Plan
A25: 20 | B25: Hypothèses Programmatiques | C25: Costign Plan | D25: Budget global et financement | E25: Inducteurs de coûts princicaux | N25: CADRE Part C onglet CER & Tools | O25: Costing Plan
A26: 21 | B26: Hypothèses Programmatiques | C26: Costign Plan | D26: Budget global et financement | E26: Normalisation ( Stochométrie) - si applicable | N26: le choix de l'outil dicte CADRE part B qui collecte info pour l'analyse paramétrique | O26: Costing Plan
A27: 22 | B27: Hypothèses Programmatiques | C27: Costign Plan | D27: Budget global et financement | E27: Tracabilité - accès aux sources - répertoires normalisés -liens | N27: CADRE Part C onglet CER & Tools | O27: Costing Plan
... A42: 37 | B42: Hypothèses Financières | C42: 8. Inflation Model | D42: Indices économiques et inflation | E42: Modèle d'inflation appliqué | N42: Inflation Model dans son propre document - Oracle db ID | O42: Inflation Model
A43: 38 | B43: Hypothèses Financières | C43: 8. Economic Constants and short answers | D43: Indices économiques et inflation | E43: Année de base / Base year | O43: Constants
A44: 39 | B44: Hypothèses Financières | C44: 8. Economic Constants and short answers | D44: Indices économiques et inflation | E44: SSC 4% | N44: Financial Constants Reports - CSA-FIN-RPT-XXXX rev 3 | O44: Constants
A45: 40 | B45: Hypothèses Financières | C45: 8. Economic Constants and short answers | D45: Indices économiques et inflation | E45: PSPC 13% | N45: Financial Constants Reports - CSA-FIN-RPT-XXXX rev 3 | O45: Constants
A46: 41 | B46: Hypothèses Financières | C46: 8. Economic Constants and short answers | D46: Indices économiques et inflation | E46: Taux du Fairness Monitor | N46: Financial Constants Reports - CSA-FIN-RPT-XXXX rev 3 | O46: Constants
A47: 42 | B47: Hypothèses Financières | C47: 8. Economic Constants and short answers | D47: Taux de change | E47: Monnaies concernées et valeur de référence (CAD, USD, EUR, etc.) | N47: Financial Constants Reports - CSA-FIN-RPT-XXXX rev 3 | O47: Constants
A48: 43 | B48: Hypothèses Financières | C48: 8. Economic Constants and short answers | D48: Taux de change | E48: Seuil de variation accepté avant révision budgétaire | N48: Defined in constnats, used in risk analysis. risk reserve - Risk register | O48: Constants
A49: 44 | B49: Hypothèses Financières | C49: 8. Economic Constants and short answers | D49: Contingence et marges de sécurité | E49: Pourcentage de contingence sur le coût total du projet (p. ex. 10 à 20 %) | N49: Defined in constnats, used in risk analysis. risk register onglet. Unknown-Unknown Risk margin | O49: Constants
A50: 45 | B50: Hypothèses Financières | C50: Strategy Naratives | D50: Contingence et marges de sécurité | E50: Barème d’évaluation des risques majeurs pour justifier la marge appliquée (modèle d’analyse de risques) | N50: À définir ici | O50: Strategy | P50: Je ne comprends pas la question
A51: 46 | B51: Hypothèses Financières | C51: Procurement Plan | D51: Stratégie contractuelle, coûts de main-d’œuvre et de sous-traitance | E51: Sunk Costs Report (STDP, EOADP, Cap Demo, Stedia FAST, ESA Program, Cubesats, space hub, Pre-Phase 0 etc) | N51: CADRe part C - Expenditure plan | O51: Procurement Plan
A52: 47 | B52: Hypothèses Financières | C52: Strategy Naratives | D52: Stratégie contractuelle, coûts de main-d’œuvre et de sous-traitance | E52: Stratégie contractuel Phase 0/A - 1 / 2 contrats | N52: CADRe Part C - Procurement strategy | O52: Strategy
A53: 48 | B53: Hypothèses Financières | C53: Strategy Naratives | D53: Stratégie contractuelle, coûts de main-d’œuvre et de sous-traitance | E53: Note de réflexion supplémentaire | O53: Strategy
A54: 49 | B54: Hypothèses Financières | C54: Procurement Plan | D54: Stratégie contractuelle, coûts de main-d’œuvre et de sous-traitance | E54: Nombre de contrats et valeur approximative prévus par phase | N54: CADRe Part C - Procurement Plan (list) | O54: Procurement Plan
A55: 50 | B55: Hypothèses Financières | C55: Strategy Naratives | D55: Stratégie contractuelle, coûts de main-d’œuvre et de sous-traitance | E55: Contrats en parallèle avec des concepts différents et un down select | N55: CADRe Part C - Procurement strategy | O55: Strategy
A56: 51 | B56: Hypothèses Financières | C56: Strategy Naratives | D56: Stratégie contractuelle, coûts de main-d’œuvre et de sous-traitance | E56: Agile ou waterfall | N56: CADRe Part C - Procurement strategy | O56: Strategy
A57: 52 | B57: Hypothèses Financières | C57: Strategy Naratives | D57: Stratégie contractuelle, coûts de main-d’œuvre et de sous-traitance | E57: STDP ou CapDemo en même temps que la phase 0 ou A | N57: PREP 2 | O57: Strategy
A58: 53 | B58: Hypothèses Financières | C58: OBS | D58: Stratégie contractuelle, coûts de main-d’œuvre et de sous-traitance | E58: Les fournisseurs attendus et leur capacite de production | N58: OBS | O58: OBS
A59: 54 | B59: Hypothèses Financières | C59: Strategy Naratives | D59: Stratégie contractuelle, coûts de main-d’œuvre et de sous-traitance | E59: Type de SOW - SOW directif versus une architecture de mission proposée par le fournisseur | N59: CADRe Part C - Procurement strategy | O59: Strategy
A60: 55 | B60: Hypothèses Financières | C60: Strategy Naratives | D60: Stratégie contractuelle, coûts de main-d’œuvre et de sous-traitance | E60: Freedom of Design of Vendor | N60: CADRE Part C onglet OBS Maturité orgnisationelle du fourniseur | O60: Strategy
A61: 56 | B61: Hypothèses Financières | C61: Strategy Naratives | D61: Stratégie contractuelle, coûts de main-d’œuvre et de sous-traitance | E61: Types de contrat – source unique ou compétitif (Contrat dirigé en Phase E ops aura une incidence sur le design du ground segment) | N61: CADRe Part C - Procurement strategy | O61: Strategy
A62: 57 | B62: Hypothèses Financières | C62: Strategy Naratives | D62: Stratégie contractuelle, coûts de main-d’œuvre et de sous-traitance | E62: Types de contrat – cout remboursable ou prix ferme | N62: CADRe Part C - Procurement strategy | O62: Strategy
B63: Hypothèses Financières | C63: Strategy Naratives | D63: Stratégie contractuelle, coûts de main-d’œuvre et de sous-traitance | E63: Type de contrat: gonogo, options, milestones in April for CAFÉ | O63: Strategy | P63: Split next line into 2
A64: 58 | B64: Hypothèses Financières | C64: 12 - Dispose, Divest, Descope, Delay | D64: Stratégie contractuelle, coûts de main-d’œuvre et de sous-traitance | E64: Gestion du scope change et des risques dans chaque situation : cout remboursable (TA, options, gouvernance) ; prix ferme (descope, go no go, qualité du SOW a décrire le scope) | N64: Descope est dans DDD | O64: DDDD
A65: 59 | B65: Hypothèses Financières | D65: Stratégie contractuelle, coûts de main-d’œuvre et de sous-traitance | E65: G&C (cassiope ou radarsat 2) nous appartient pas | N65: Business model (CADRe part A) et le procurement strategy le repete | O65: CADRE Part A
A66: 60 | B66: Hypothèses Financières | C66: Strategy Naratives | D66: Stratégie contractuelle, coûts de main-d’œuvre et de sous-traitance | E66: incitatif commercial (ex. modele de commercialization comme WFS) | N66: CADRe Part C - Procurement strategy | O66: Strategy
A67: 61 | B67: Hypothèses Financières | C67: Strategy Naratives | D67: Stratégie contractuelle, coûts de main-d’œuvre et de sous-traitance | E67: Pour chaque phase et sous-systeme majeur - CSA led, industry led, academia led (ex. En Phase E, CSA va mener les operations) | N67: CADRe Part C - Procurement strategy | O67: Strategy
A68: 62 | B68: Hypothèses Financières | C68: Strategy Naratives | D68: Stratégie contractuelle, coûts de main-d’œuvre et de sous-traitance | E68: Competitif - ouvert a l'international | N68: CADRe Part C - Procurement strategy | O68: Strategy
A69: 63 | B69: Hypothèses Financières | C69: Strategy Naratives | D69: Stratégie contractuelle, coûts de main-d’œuvre et de sous-traitance | E69: Competitif - ouvert au Canada | N69: CADRe Part C - Procurement strategy | O69: Strategy
A70: 64 | B70: Hypothèses Financières | C70: Strategy Naratives | D70: Stratégie contractuelle, coûts de main-d’œuvre et de sous-traitance | E70: Fausse competition | N70: CADRe Part C - Procurement strategy | O70: Strategy
A71: 65 | B71: Hypothèses Financières | C71: Strategy Naratives | D71: Stratégie contractuelle, coûts de main-d’œuvre et de sous-traitance | E71: monopole | N71: CADRe Part C - Procurement strategy | O71: Strategy
A72: 66 | B72: Hypothèses Financières | C72: Strategy Naratives | D72: Stratégie contractuelle, coûts de main-d’œuvre et de sous-traitance | E72: Dependences : Le fournisseur X doit etre le meme fournisseur que le fournisseur Y (Ex. Data processing handled by same supplier) | N72: CADRe Part C - Procurement strategy | O72: Strategy
A73: 67 | B73: Hypothèses Financières | C73: Strategy Naratives | D73: Stratégie contractuelle, coûts de main-d’œuvre et de sous-traitance | E73: Long lead Item - flux de trésorie en capital vs contrat vs échéancier | N73: CADRE Part C onglet QUANTITIES - LLI, spares, EM, PFM, RE-NRE | O73: Strategy
A74: 68 | B74: Hypothèses Financières | C74: Strategy Naratives | D74: Stratégie contractuelle, coûts de main-d’œuvre et de sous-traitance | E74: Contenu Canadien | N74: CADRe Part C - Procurement strategy | O74: Strategy
A75: 69 | B75: Hypothèses Financières | C75: Strategy Naratives | D75: Stratégie contractuelle, coûts de main-d’œuvre et de sous-traitance | E75: Chaque contrat couvre quel partie du travail, liste d'inclusions et exclusions. List of inclusions and exclusions | N75: CBS Dictionary | O75: Strategy
A76: 70 | B76: Hypothèses Financières | C76: Strategy Naratives | D76: Stratégie contractuelle, coûts de main-d’œuvre et de sous-traitance | E76: GFE and GFS (ex. DFL) | N76: CBS Dictionary | O76: Strategy
A77: 71 | B77: Hypothèses Financières | C77: Strategy Naratives | D77: Stratégie contractuelle, coûts de main-d’œuvre et de sous-traitance | E77: Frais de transport et responsabilité | N77: CBS Dictionary | O77: Strategy
... A97: 91 | B97: Hypothèses Techniques (Space & Ground Segment) | C97: Costign Plan | D97: Sous-systèmes et architecture globale | E97: This ground rule should state, at a high level, what is within scope of the estimate. For example, an estimate may cover the space segment, ground segment, and government oversight during phases B, C and D. Further clarification should be given if required, such as refurbishment of the ground segment rather than complete rebuild. | N97: Perimeter of costing exercise. Further Claraifications in CBs dictionary | O97: Costing Plan
A98: 92 | B98: Hypothèses Techniques (Space & Ground Segment) | D98: Durée de vie du projet et cycles de développement | E98: Stratégie de validation (modèles d’ingénierie, prototypes, simulations) | N98: CADRE Part C onglet QUANTITIES - LLI, spares, EM, PFM, RE-NRE | O98: Quantities
A99: 93 | B99: Hypothèses Techniques (Space & Ground Segment) | D99: Durée de vie du projet et cycles de développement | E99: Méthodes d’essais en environnement (thermique, vibration, vide, etc.) | N99: CADRE Part C onglet QUANTITIES - LLI, spares, EM, PFM, RE-NRE | O99: Quantities
A100: 94 | B100: Hypothèses Techniques (Space & Ground Segment) | D100: Durée de vie du projet et cycles de développement | E100: This assumption should state the expected build approach for the mission. For example, the bus/platform and payloads could be built in series or parallel. | N100: CADRE Part C onglet QUANTITIES - LLI, spares, EM, PFM, RE-NRE | O100: Quantities
A101: 95 | B101: Hypothèses Techniques (Space & Ground Segment) | D101: Durée de vie du projet et cycles de développement | E101: This assumption should state the cost improvement curve, as a percentile, for any items to be acquired with more than a single unit. If appropriate, items should be marked as Xth unit within a lot, such as the 8th unit, to allow for cost improvement curve theory to be reflected. | N101: CADRE Part C onglet QUANTITIES - LLI, spares, EM, PFM, RE-NRE | O101: Quantities
A102: 96 | B102: Hypothèses Techniques (Space & Ground Segment) | C102: Engineering Parameters in CADRe part B | D102: Contraintes techniques spécifiques | E102: Estimation de masse et de volume du système | N102: CADRE part B | O102: CADRE part B
A103: 97 | B103: Hypothèses Techniques (Space & Ground Segment) | C103: Engineering Parameters in CADRe part B | D103: Contraintes techniques spécifiques | E103: Consommation électrique maximale | N103: CADRE part B | O103: CADRE part B
A104: 98 | B104: Hypothèses Techniques (Space & Ground Segment) | C104: Engineering Parameters in CADRe part B | D104: Contraintes techniques spécifiques | E104: Besoins minimaux pour assurer la fiabilité | N104: CADRE part B | O104: CADRE part B
A105: 99 | B105: Hypothèses Qualité, Fiabilité et Sécurité | C105: Strategy Naratives | D105: Normes et standards de qualité | E105: ECSS-Q-ST-20, ISO 9001, etc. | N105: À définir ici | O105: Strategy
A106: 100 | B106: Hypothèses Qualité, Fiabilité et Sécurité | C106: Strategy Naratives | D106: Normes et standards de qualité | E106: Méthodes d’assurance qualité (revues, audits internes et externes) | N106: À définir ici | O106: Strategy
A107: 101 | B107: Hypothèses Qualité, Fiabilité et Sécurité | C107: 8. Economic Constants and short answers | D107: Safety and mission assurance | E107: Classe de Mission | N107: À définir ici | O107: Constants
A108: 102 | B108: Hypothèses Qualité, Fiabilité et Sécurité | C108: Strategy Naratives | D108: Safety and mission assurance | E108: La mesure de la surveillance et de la rigueur appliquées par la CSA | N108: À définir ici | O108: Strategy
A109: 103 | B109: Hypothèses Opérationnelles | C109: RAM | D109: Ressources humaines et expertise | E109: Équipe de base (ETP internes) et besoins en personnel spécialisé externe | N109: CADRE Part C onglet RAM | O109: RAM
A110: 104 | B110: Hypothèses Opérationnelles | C110: Strategy Naratives | D110: Ressources humaines et expertise | E110: Disponibilité du personnel et plan de montée en compétence | N110: À définir ici | O110: Strategy
A111: 105 | B111: Hypothèses Opérationnelles | C111: Milestone Register | D111: Calendrier, jalons et ressources temporelles | E111: Dates clés (ex. PDR – Preliminary Design Review, CDR – Critical Design Review, FRR – Flight Readiness Review) / Project Milestone Register (short report, detailed report) | N111: milestone Register | O111: Milestone Register
A112: 106 | B112: Hypothèses Opérationnelles | D112: Calendrier, jalons et ressources temporelles | E112: Diagram of Phase Overlaps and Gaps | N112: we draw it form phasing | O112: GANTT Charts
A113: 107 | B113: Hypothèses Opérationnelles | C113: Schedule Constraints and Dependencies | D113: Calendrier, jalons et ressources temporelles | E113: Marges pour délais | N113: Phasing Model, phases | O113: Schedule Constraints
A114: 108 | B114: Hypothèses Opérationnelles | C114: 12 - Dispose, Divest, Descope, Delay | D114: Calendrier, jalons et ressources temporelles | E114: Gestion des retards : conditions de replanification, procédures d’escalade | N114: À définir ici et lié au CADRE Part C - onglet DDDD | O114: DDDD
A115: 109 | B115: Hypothèses Opérationnelles | C115: Phasing Schedules | D115: Calendrier, jalons et ressources temporelles | E115: Modèle de phase utilisé pour analyse de sensibilité (Phasing Model) | N115: Phasing model (for risk analysis) | O115: Phasing Schedules
A116: 110 | B116: Hypothèses Opérationnelles | C116: Phasing Schedules | D116: Calendrier, jalons et ressources temporelles | E116: Échéancier de l'industrie | N116: Phasing model (for risk analysis) | O116: Phasing Schedules
A117: 111 | B117: Hypothèses Opérationnelles | C117: Phasing Schedules | D117: Calendrier, jalons et ressources temporelles | E117: Schedule Scenarios for sensitivity analysis : Adjust Durations - optimistic, pessimistic and expected | N117: Phasing model (for risk analysis) | O117: Phasing Schedules
A118: 112 | B118: Hypothèses Opérationnelles | C118: Strategy Naratives | D118: Planification des infrastructures et installations | E118: Is DFL being used as GFE | N118: DFL being used? Strategy | O118: Strategy
A119: 112 | B119: Hypothèses Opérationnelles | C119: 4a. CBS and CBS Dictionary | D119: Planification des infrastructures et installations | E119: Lieux de développement, sites d’intégration et de test (chambres à vide, bancs de test) | N119: CBS Dictionary - Ground Segment - Test facilities | O119: CBS Dictionary
A120: 113 | B120: Hypothèses Opérationnelles | C120: Schedule Constraints and Dependencies | D120: Planification des infrastructures et installations | E120: Disponibilité des installations (ex. créneaux de test partagés avec d’autres projets) | N120: schedule risk = risk register -> pessimistic schedule model | O120: Schedule Constraints
A121: 114 | B121: Hypothèses Opérationnelles | C121: Schedule Constraints and Dependencies | D121: Gestion de la logistique et de la chaîne d’approvisionnement | E121: Délai de livraison des composants critiques (satellites, propulseurs, éléments électroniques) | N121: schedule risk = risk register -> pessimistic schedule model | O121: Schedule Constraints
A122: 115 | B122: Hypothèses Opérationnelles | C122: Strategy Naratives | D122: Gestion de la logistique et de la chaîne d’approvisionnement | E122: Plans de contingence en cas de rupture d’approvisionnement | N122: CADRE Part C onglet DDDD - dispose, descope, divest, delay | O122: Strategy
A123: 116 | B123: Hypothèses Opérationnelles | D123: Plan de gestion de mission (SatOps) | E123: Description des opérations prévues : phases de lancement, mise à l’orbite, opérations nominales, etc. | N123: Cadre part A | O123: CADRE Part A
A124: 117 | B124: Hypothèses Opérationnelles | D124: Plan de gestion de mission (SatOps) | E124: Mode de supervision et contrôle (centres de contrôle, horaires, équipes) | N124: À définir ici | O124: Cadre Part A
A125: 118 | B125: Hypothèses Opérationnelles | D125: Plan de gestion de mission (SatOps) | E125: Mission Operation Center | N125: À définir ici | O125: Cadre Part A
A126: 119 | B126: Hypothèses Opérationnelles | D126: Plan de gestion de mission (SatOps) | E126: GoC Science Operation Centers (SOCs) | N126: À définir ici | O126: Cadre Part A
A127: 120 | B127: Hypothèses Opérationnelles | D127: Plan de gestion de mission (SatOps) | E127: External Science Operation Centers (ESOCs) | N127: À définir ici | O127: Cadre Part A
A128: 121 | B128: Hypothèses sur la science | C128: Schedule Constraints and Dependencies | D128: Science et applications | E128: Échéancier lié au volet de science du projet | O128: Schedule Constraints
A129: 122 | B129: Hypothèses sur la science | C129: Strategy Naratives | D129: Science et applications | E129: Expected cost of science utilization related to the mission. | O129: Strategy
A130: 123 | B130: Hypothèses sur la science | C130: Strategy Naratives | D130: Portée de la mission sur le milieu public et académique | E130: Coût en lien avec la portée de la mission | N130: À définir ici | O130: Strategy
A131: 124 | B131: Hypothèses Lancement | D131: Véhicule de lancement | E131: Sélection du lanceur (ex. Falcon 9, Ariane, etc.) ou fenêtre de lancement partagée | N131: Cadre part A | O131: CADRE Part A
A132: 125 | B132: Hypothèses Lancement | D132: Véhicule de lancement | E132: Capacités du lanceur (masse, volume, orbite cible) | N132: Cadre part A un petit peu et le reste dans le LV database CM list | O132: CADRE Part A
A133: 126 | B133: Hypothèses Lancement | C133: Schedule Constraints and Dependencies | D133: Calendrier de lancement | E133: Fenêtres de lancement disponibles (contraintes de météo, alignement orbital, etc.) | N133: schedule risk = risk register -> pessimistic schedule model | O133: Schedule assumptions and constraints for JCL Analysis
A134: 127 | B134: Hypothèses Lancement | C134: 12 - Dispose, Divest, Descope, Delay | D134: Calendrier de lancement | E134: Contingences pour reports éventuels | N134: schedule risk = risk register -> pessimistic schedule model | O134: DDDD
A135: 128 | B135: Hypothèses Lancement | C135: OBS | D135: Contrat et services associés | E135: Responsabilités du fournisseur de lancement (intégration, tests, qualification) | N135: OBS (roles et responsiblity) - CSa qui paye ou MDa qui paye | O135: OBS
...

Sheet 10 - Strategies
A1: ` Table of Contents
A3: 11 - Strategy Narratives
A4: Why we we asking:
B5: Part of GRA
B6: This page is full of essays, tell us what you have in mind
B8: Section 1 - Strategic Direction
C9: ID | D9: Category | E9: Question | F9: Expected Response | G9: Classification | H9: Status | I9: Response / Narrative | J9: Basis / Source | K9: Owner | L9: Confidence | M9: Cost / Schedule / Risk Impact
C10: STR-01 | D10: Policy alignment | E10: What policy outcome or strategic objective is the mission intended to advance? | F10: Narrative with references | G10: Ground rule | H10: Drafted | I10: ORCA advances Canada's Space Policy Framework commitment to Canadian leadership in planetary science by contributing instruments to an international flagship mission to characterize Enceladus's sub-surface ocean and plume chemistry. | J10: GC Space Policy Framework; ORCA CADRe Part A §2.3 | K10: Marie Tremblay (ORCA Mission Manager) | L10: High | M10: Strategic driver; defines ADR demonstration scope. Low direct cost impact.
C11: STR-02 | D11: CSA alignment | E11: How does the mission align with CSA priorities, programs, and expected results? | F11: Narrative with references | G11: Assumption | H11: Drafted | I11: Aligns with CSA priorities in planetary exploration, astrobiology-relevant science, and Canadian instrument leadership, building on heritage radar and in-situ sampling technologies. | J11: CSA program priorities; Part A §2.2-2.3 | K11: Alan Whitfield (Portfolio Manager) | L11: High | M11: Reinforces robotics workforce investment.
C12: STR-03 | D12: Government direction | E12: What government decisions, mandates, commitments, or high-level directives constrain the mission? | F12: List and implications | G12: Ground rule | H12: Drafted | I12: CSA-owned and -operated mission, executed by the Canadian Orbital Mission Directorate (COMD) project office; must stay within the approved envelope and comply with GC procurement and Canadian-content direction. | J12: TB submission / GC direction (assumed) | K12: Alan Whitfield (Portfolio Manager) | L12: Medium | M12: Constrains procurement approach and gate schedule.
C13: STR-04 | D13: Success criteria | E13: What strategic outcomes define mission success, and how will they be measured? | F13: Outcomes and measures | G13: Ground rule | H13: Drafted | I13: Success = ORCA instrument suite delivered to the host orbiter on schedule, successful commissioning at Enceladus, and at least the primary plume-transit science passes completed to specification. | J13: Part A §2.4 mission requirements | K13: Naomi Fitzgerald (Lead Spacecraft Systems Engineer) | L13: High | M13: Defines verification scope; drives test cost.
C14: STR-05 | D14: Priority and trade-offs | E14: When cost, schedule, scope, performance, and risk conflict, what is the order of priority? | F14: Ranked priorities | G14: Ground rule | H14: Drafted | I14: Priority order: (1) safety / planetary protection, (2) performance (successful plume sampling and analysis), (3) schedule (host-orbiter launch window), (4) cost, (5) extended scope. | J14: SMA Class B posture (Part A §6.4) | K14: Marie Tremblay (ORCA Mission Manager) | L14: Medium | M14: Guides reserve release and descope decisions.
B16: Section 2 - Funding and Affordability
C17: ID | D17: Category | E17: Question | F17: Expected Response | G17: Classification | H17: Status | I17: Response / Narrative | J17: Basis / Source | K17: Owner | L17: Confidence | M17: Cost / Schedule / Risk Impact
C18: FND-01 | D18: Funding strategy | E18: What is the planned source and timing of funding by mission phase? | F18: Funding profile by phase | G18: Assumption | H18: Drafted | I18: A-base CSA appropriation phased across Phase 0-X (FY2020-FY2032), weighted to the Phase C/D build (FY2024-FY2027). | J18: ORCA Scenario 1 phasing (Part D §7) | K18: Samuel Boucher (Schedule and Cost Management Engineer) | L18: Medium | M18: Funding profile matches Scenario 1 durations.
C19: FND-02 | D19: Affordability limit | E19: Is there a cost ceiling, target, annual limit, or approval threshold that must not be exceeded? | F19: Amounts, years, and basis | G19: Ground rule | H19: Drafted | I19: A not-to-exceed program ceiling is set at TB approval, with annual cash-flow limits by fiscal year. | J19: TB authority (assumed) | K19: Samuel Boucher (Schedule and Cost Management Engineer) | L19: Low | M19: Cost ceiling drives descope triggers.
C20: FND-03 | D20: Funding stability | E20: How stable is the expected funding profile, and what changes or interruptions should be assumed? | F20: Scenario or constraints | G20: Assumption | H20: Drafted | I20: Assume stable A-base funding with risk of single-year deferrals; a one-year slip is carried in the Pessimistic schedule. | J20: Scenario 3 sensitivity (Part D §7) | K20: Samuel Boucher (Schedule and Cost Management Engineer) | L20: Medium | M20: Slip drives salary and escalation growth.
C21: FND-04 | D21: Cost responsibility | E21: Which organization will fund each phase, segment, major subsystem, and in-kind contribution? | F21: Responsibility matrix | G21: Assumption | H21: Drafted | I21: CSA funds all phases and segments; no partner cost-share. Partner contributions (ESA, NASA) and academic support are in-kind only. | J21: CSA-owned mission (Part D §5 OBS) | K21: Samuel Boucher (Schedule and Cost Management Engineer) | L21: High | M21: Limited external funding offset.
C22: FND-05 | D22: Contingency and reserves | E22: Who holds cost and schedule contingency, at what level, and under what release authority? | F22: Reserve approach | G22: Ground rule | H22: Drafted | I22: CSA holds project-level cost and schedule reserve, released by the ORCA Project Board at gates. | J22: IGMF governance | K22: Priya Raman (Lead Project Manager) | L22: Medium | M22: Reserve sized for Class B risk.
C23: FND-06 | D23: Eligible expenditures | E23: Are any costs eligible for NATO or other special funding, reimbursement, or cost-sharing arrangements? | F23: Eligibility and conditions | G23: Assumption | H23: Drafted | I23: No NATO or special eligible-cost arrangements; standard CSA appropriation only. | J23: Mission classification | K23: Samuel Boucher (Schedule and Cost Management Engineer) | L23: High | M23: None.
B25: Section 3 - Delivery and Acquisition
C26: ID | D26: Category | E26: Question | F26: Expected Response | G26: Classification | H26: Status | I26: Response / Narrative | J26: Basis / Source | K26: Owner | L26: Confidence | M26: Cost / Schedule / Risk Impact
C27: DEL-01 | D27: Delivery model | E27: For each phase and major element, will delivery be CSA-led, industry-led, partner-led, or academia-led? | F27: Responsibility by phase/element | G27: Ground rule | H27: Drafted | I27: Phase 0/A CSA-led studies; Phase B-D industry-led under the Prime (Asterion Orbital Integration Ltd.); Phase E-X CSA-led operations with Prime support. | J27: OBS (Part D §5) | K27: Priya Raman (Lead Project Manager) | L27: Medium | M27: Sets contract boundaries by phase.
C28: DEL-02 | D28: Development approach | E28: Will the work use waterfall, agile, incremental, spiral, or a hybrid approach? | F28: Approach by workstream | G28: Ground rule | H28: Drafted | I28: Hybrid: waterfall for flight hardware (gated reviews) and agile for flight software and autonomy. | J28: Class B / GOLD Rules (Part A §6.5) | K28: Naomi Fitzgerald (Lead Spacecraft Systems Engineer) | L28: Medium | M28: Affects test cadence and integration.
C29: DEL-03 | D29: Concept competition | E29: Will multiple concepts or parallel contracts be funded before a down-selection? | F29: Number, duration, and down-select point | G29: Assumption | H29: Drafted | I29: Two parallel Phase 0 concept studies are funded, with down-select at Gate 2 (KDP-A). | J29: Acquisition assumption | K29: Étienne Lacroix (Deputy Project Manager) | L29: Low | M29: Adds Phase 0 cost, reduces Phase B risk.
C30: DEL-04 | D30: Procurement packaging | E30: How will the mission be divided into contracts, and what are the approximate number and value of contracts by phase? | F30: Contract map by phase | G30: Assumption | H30: Drafted | I30: ~7 industry contracts for the ORCA instrument suite: prime/integration (Asterion), Ice-Penetrating Radar (Northstar Orbital Technologies), Sampling Arm (Aetheris Space Robotics), instrument avionics (Polarion Avionics), context imaging (Borealis Vision Systems), instrument data interface (Canterra Space Communications), and structures/thermal (Arcturon Space Structures); plus academic research agreements. Launch and the NEREID orbiter itself are procured by the partner agencies, not CSA. | J30: OBS (Part D §5) | K30: Étienne Lacroix (Deputy Project Manager) | L30: Medium | M30: Contract count drives oversight cost.
C31: DEL-05 | D31: Statement of work | E31: Will requirements be prescriptive, performance-based, or allow the supplier to propose the mission architecture? | F31: SOW approach and rationale | G31: Ground rule | H31: Drafted | I31: Performance-based for the Prime, with prescriptive interface and safety requirements for the sampling-arm subsystem and for the host-orbiter interface control document. | J31: Ground rule | K31: Naomi Fitzgerald (Lead Spacecraft Systems Engineer) | L31: Medium | M31: Balances innovation against safety rigor.
C32: DEL-06 | D32: Competition strategy | E32: For each major procurement, will the approach be competitive, directed, or sole-source? | F32: Approach and rationale by procurement | G32: Ground rule | H32: Drafted | I32: Competitive for prime and ground systems; the sampling-arm subsystem may be directed to the heritage supplier (Aetheris Space Robotics). | J32: Market assessment | K32: Étienne Lacroix (Deputy Project Manager) | L32: Low | M32: Sole-source premium on sampling-arm subsystem.
C33: DEL-07 | D33: Market access | E33: Will competitions be open to Canadian suppliers only or to international suppliers? | F33: Eligibility by procurement | G33: Ground rule | H33: Drafted | I33: Prime and major subcontracts favour Canadian suppliers per content targets; the host orbiter and launch services are provided by the international partner agencies (ESA, NASA). | J33: Canadian-content direction; OBS | K33: Étienne Lacroix (Deputy Project Manager) | L33: Medium | M33: Mixed domestic/international eligibility.
C34: DEL-08 | D34: Market conditions | E34: Are there monopoly, limited-competition, incumbent, or vendor-lock-in conditions that affect price or schedule? | F34: Market assessment | G34: Assumption | H34: Drafted | I34: Limited domestic competition for the sampling-arm subsystem (near-incumbent Aetheris Space Robotics); vendor lock-in risk monitored. | J34: RFI findings (assumed) | K34: Étienne Lacroix (Deputy Project Manager) | L34: Low | M34: Price risk on sampling-arm subsystem.
C35: DEL-09 | D35: Contract pricing | E35: Will contracts use firm price, cost-reimbursable, time-and-materials, incentive-based, or mixed pricing? | F35: Pricing basis by phase/contract | G35: Ground rule | H35: Drafted | I35: Firm price for ground systems; cost-reimbursable with incentive fee for Prime integration and sampling-arm development. | J35: Ground rule | K35: Étienne Lacroix (Deputy Project Manager) | L35: Medium | M35: Cost risk concentrated on development items.
C36: DEL-10 | D36: Commercial incentives | E36: Will revenue sharing, commercialization, service purchases, or other commercial incentives be used? | F36: Model and cost implications | G36: Assumption | H36: Drafted | I36: No revenue-share or commercialization; single government-owned instrument suite hosted on an international partner orbiter. | J36: Acquisition assumption | K36: Samuel Boucher (Schedule and Cost Management Engineer) | L36: High | M36: None.
C37: DEL-11 | D37: Supplier dependencies | E37: Must any elements be supplied, integrated, or operated by the same organization? | F37: Dependencies and rationale | G37: Assumption | H37: Drafted | I37: The Prime (Asterion) integrates the NEREID orbiter and the ORCA instrument suite; Aetheris Space Robotics supports SAIT and early operations. | J37: Acquisition assumption | K37: Naomi Fitzgerald (Lead Spacecraft Systems Engineer) | L37: Medium | M37: Integration continuity requirement.
... C40: DEL-14 | D40: Phase transition | E40: Will the Phase B–D contractor be expected or required to support Phase E–F operations? | F40: Continuity strategy | G40: Ground rule | H40: Drafted | I40: The Phase B-D Prime is required to support Phase E operations and the Phase X disposal campaign under an options clause. | J40: Ground rule | K40: Priya Raman (Lead Project Manager) | L40: Medium | M40: Operations-continuity cost.
B42: Section 4 - Partnerships
C43: ID | D43: Category | E43: Question | F43: Expected Response | G43: Classification | H43: Status | I43: Response / Narrative | J43: Basis / Source | K43: Owner | L43: Confidence | M43: Cost / Schedule / Risk Impact
C44: PAR-01 | D44: Partner roles | E44: Which federal, international, industry, academic, or other partners will participate, and what will each provide? | F44: Roles and contributions | G44: Assumption | H44: Drafted | I44: Industry: Asterion Orbital Integration (prime), Northstar Orbital Technologies (radar), Aetheris Space Robotics (sampling arm), Polarion Avionics, Borealis Vision Systems (context imaging), Canterra Space Communications, Arcturon Space Structures, Meridian Ground Technologies. Academia: Northern Institute of Space Engineering, Laurentia University of Aerospace Technology, Boreal Technical University. International: ESA (host-orbiter contribution) and NASA (host-orbiter lead and launch). OGDs: COSD, CSEO, NARD. | J44: OBS (Part D §5) | K44: Marie Tremblay (ORCA Mission Manager) | L44: High | M44: Defines interfaces and governance load.
C45: PAR-02 | D45: Decision authority | E45: How are decision rights, governance, configuration control, and dispute resolution shared among partners? | F45: Governance model | G45: Ground rule | H45: Drafted | I45: CSA (COMD project office) retains full decision, configuration-control and dispute authority; partners contribute under MOUs; the Prime holds delegated design authority within the approved baseline. | J45: IGMF governance; OBS | K45: Marie Tremblay (ORCA Mission Manager) | L45: High | M45: Clear authority reduces schedule risk.
C46: PAR-03 | D46: Dependencies | E46: What partner deliverables, approvals, facilities, data, or schedules are mission dependencies? | F46: Dependency register | G46: Assumption | H46: Drafted | I46: The NEREID orbiter's launch slot and interface schedule (NASA-led), the sampling-arm delivery from Aetheris, and ESA technical inputs are the key external dependencies. | J46: Sched Dependencies (Part D §10) | K46: Naomi Fitzgerald (Lead Spacecraft Systems Engineer) | L46: Medium | M46: Schedule risk if any slips.
C47: PAR-04 | D47: Contribution valuation | E47: How will in-kind contributions, shared assets, and partner-provided services be valued in the estimate? | F47: Valuation method | G47: Ground rule | H47: Drafted | I47: International-partner (ESA/NASA) contributions are valued as in-kind under MOU; academic research agreements at cost; CSA in-kind at standard rates. | J47: Costing GR&A | K47: Samuel Boucher (Schedule and Cost Management Engineer) | L47: Medium | M47: Adds in-kind value to the estimate.
B49: Section 5 - Governance and Oversight and Assurance
C50: ID | D50: Category | E50: Question | F50: Expected Response | G50: Classification | H50: Status | I50: Response / Narrative | J50: Basis / Source | K50: Owner | L50: Confidence | M50: Cost / Schedule / Risk Impact
C51: GOV-01 | D51: Governance | E51: What governance bodies, decision gates, reviews, and approval authorities apply? | F51: Governance and gate map | G51: Ground rule | H51: Drafted | I51: CSA IGMF gates apply (Gate 0/SR, Gate 1, Gate 2/KDP-A, R3, R4, Gate 3/KDP-D, Gate 4/KDP-E, Gate 5/KDP-X), administered by the COMD project office. | J51: IGMF rev F; Part D §8 | K51: Priya Raman (Lead Project Manager) | L51: High | M51: Defines review cost and cadence.
C52: GOV-02 | D52: CSA oversight | E52: What level of CSA technical, programmatic, financial, and contractual oversight is required? | F52: Oversight model and staffing | G52: Ground rule | H52: Drafted | I52: Full technical, programmatic, financial and contractual oversight, with an embedded CSA systems-engineering and project office through Phase D. | J52: Ground rule | K52: Priya Raman (Lead Project Manager) | L52: Medium | M52: CSA staffing cost through build.
C53: GOV-03 | D53: Reporting | E53: What reporting products, data requirements, and reporting frequency are required? | F53: Reporting calendar | G53: Ground rule | H53: Drafted | I53: Monthly cost/performance reports, quarterly Project Board, and milestone reviews at each gate. | J53: IGMF reporting | K53: Ethan Parker (Project Management Engineer) | L53: Medium | M53: Reporting workload.
C54: GOV-04 | D54: Change control | E54: How will changes to scope, requirements, baseline, schedule, and funding be approved and documented? | F54: Change-control process | G54: Ground rule | H54: Drafted | I54: Baseline changes go through the CSA Configuration Control Board; the Prime submits engineering change requests; TB-threshold changes escalate. | J54: IGMF change control | K54: Ethan Parker (Project Management Engineer) | L54: Medium | M54: Change discipline protects baseline.
C55: ASM-01 | D55: Applicable standards | E55: Which CSA, ECSS, ISO, NASA, engineering, quality, safety, and mission-assurance standards apply? | F55: Tailored standards list | G55: Ground rule | H55: Drafted | I55: Tailored CSA/ECSS standards with GSFC GOLD Rules for Class B, and ISO 9001 quality. | J55: Part A §6.5 | K55: Fatima Haidari (Safety and Mission Assurance Engineer) | L55: High | M55: Sets verification rigor.
C56: ASM-02 | D56: Quality assurance | E56: What reviews, inspections, audits, independent assessments, and acceptance evidence are required? | F56: Assurance plan | G56: Ground rule | H56: Drafted | I56: Gate reviews, a unit/subsystem/system test campaign, independent SMA audits (supported by NARD), and acceptance data packages. | J56: Part A §6.5; OBS | K56: Fatima Haidari (Safety and Mission Assurance Engineer) | L56: Medium | M56: Drives test and audit cost.
C57: ASM-03 | D57: Mission class and rigor | E57: What mission class, risk tolerance, redundancy, qualification, and verification rigor should be assumed? | F57: Classification and tailoring | G57: Ground rule | H57: Drafted | I57: Class B, selective redundancy on critical systems, and a protoflight approach (EM/QM/PFM). | J57: Part A §6.4-6.5 | K57: Fatima Haidari (Safety and Mission Assurance Engineer) | L57: High | M57: Drives redundancy and qualification cost.
B59: Section 6 - Workforce and Facilities
C60: ID | D60: Category | E60: Question | F60: Expected Response | G60: Classification | H60: Status | I60: Response / Narrative | J60: Basis / Source | K60: Owner | L60: Confidence | M60: Cost / Schedule / Risk Impact
C61: RES-01 | D61: Workforce availability | E61: What workforce availability constraints, capability gaps, recruitment challenges, or dependencies on external expertise should be assumed beyond the information documented in the RAM? | F61: Staffing profile and constraints | G61: Assumption | H61: Drafted | I61: Space-robotics and autonomy talent is scarce; assume reliance on Prime/Aetheris specialists and the CSA robotics group beyond the RAM baseline. | J61: RAM (Part C §5) + assumption | K61: Priya Raman (Lead Project Manager) | L61: Low | M61: Recruitment risk to schedule.
C62: RES-02 | D62: Capability development | E62: What recruitment, training, knowledge-transfer, or competency-development effort is required? | F62: Capability plan | G62: Assumption | H62: Drafted | I62: Training and knowledge transfer for autonomous instrument operations and plume-sampling sequencing; the ops team is stood up in Phase C/D. | J62: Assumption | K62: Simone Bergeron (Mission Operations and Ground Systems Engineer) | L62: Medium | M62: Training cost in Phase C/D.
C63: RES-03 | D63: Facilities and tools | E63: What facilities, laboratories, ground infrastructure, software, licenses, and development environments are required? | F63: Asset list and ownership | G63: Assumption | H63: Drafted | I63: CSA integration and test facilities, a robotics testbed (with Laurentia University support), the MOC, and a flight-software development environment are assumed CSA-owned. | J63: Assumption; OBS academia | K63: Naomi Fitzgerald (Lead Spacecraft Systems Engineer) | L63: Medium | M63: Facility availability constraint.
B65: Section 7 - Operations and Sustainment
C66: ID | D66: Category | E66: Question | F66: Expected Response | G66: Classification | H66: Status | I66: Response / Narrative | J66: Basis / Source | K66: Owner | L66: Confidence | M66: Cost / Schedule / Risk Impact
C67: OPS-01 | D67: Operations concept | E67: Who will lead mission operations, and what control centres, coverage hours, staffing, and support model are assumed? | F67: Operations concept by phase | G67: Ground rule | H67: Drafted | I67: CSA-led operations from the CSA MOC (ground systems by Meridian Ground Technologies): 24/7 coverage during plume-transit science passes and business hours otherwise, with the Prime on call during early ops. | J67: Part A §5; OBS | K67: Simone Bergeron (Mission Operations and Ground Systems Engineer) | L67: Medium | M67: Operations staffing profile.
C68: OPS-02 | D68: Mission duration | E68: What commissioning, nominal operations, extension, disposal, and close-out durations should be costed? | F68: Durations and dates | G68: Ground rule | H68: Drafted | I68: Commissioning ~1-3 months; nominal Phase E ~180 months (15 years, per ORCA Scenario 1); extended ops plus disposal (Phase X) ~42 months; close-out ends 2059-12-28. | J68: Scenario 1 (Part D §7) | K68: Simone Bergeron (Mission Operations and Ground Systems Engineer) | L68: High | M68: Sets operations cost duration.
C69: OPS-03 | D69: Service levels | E69: What availability, responsiveness, latency, throughput, and continuity targets apply to operations? | F69: Service-level targets | G69: Ground rule | H69: Drafted | I69: Target >=95% command availability during science-pass windows; disposal maneuvers planned with margin. | J69: Ground rule | K69: Simone Bergeron (Mission Operations and Ground Systems Engineer) | L69: Low | M69: Ground-segment sizing.
C70: OPS-04 | D70: Spares and obsolescence | E70: What strategy applies to spares, replenishment, maintenance, obsolescence, and technology refresh? | F70: Sustainment strategy | G70: Assumption | H70: Drafted | I70: No on-orbit spares (single spacecraft); ground spares held for the MOC; obsolescence managed to end of Phase X. | J70: Assumption | K70: Simone Bergeron (Mission Operations and Ground Systems Engineer) | L70: Medium | M70: Sustainment cost.
B72: Section 8 - Legal and Regulatory
C73: ID | D73: Category | E73: Question | F73: Expected Response | G73: Classification | H73: Status | I73: Response / Narrative | J73: Basis / Source | K73: Owner | L73: Confidence | M73: Cost / Schedule / Risk Impact
C74: REG-01 | D74: Regulatory requirements | E74: Which federal, provincial, international, licensing, spectrum, orbital, environmental, or other regulatory requirements apply? | F74: Requirements and authorities | G74: Ground rule | H74: Drafted | I74: Canadian remote-sensing/space licensing, ITU spectrum filing, export-control (technology transfer) approvals, and planetary-protection approvals apply. | J74: Ground rule | K74: Étienne Lacroix (Deputy Project Manager) | L74: Medium | M74: Licensing lead time.
C75: REG-02 | D75: Export controls | E75: What ITAR, EAR, Controlled Goods, sanctions, or other export-control restrictions affect suppliers and partners? | F75: Restrictions and mitigations | G75: Ground rule | H75: Drafted | I75: Controlled Goods Program applies; ITAR/EAR exposure is managed at the international-partner (ESA, NASA) and launch-provider interfaces, with the Canadian-content strategy limiting exposure. | J75: Ground rule; OBS | K75: Étienne Lacroix (Deputy Project Manager) | L75: Medium | M75: Supplier and partner constraints.
C76: REG-03 | D76: Liability and insurance | E76: What liability, indemnification, insurance, launch, or third-party risk provisions should be assumed? | F76: Legal allocation and cost basis | G76: Assumption | H76: Drafted | I76: Launch liability is carried under the partner agency (NASA) launch arrangement; the Crown self-insures its own instrument hardware on-orbit; re-entry casualty risk is assessed for the host orbiter disposal. | J76: Assumption | K76: Étienne Lacroix (Deputy Project Manager) | L76: Low | M76: Insurance/liability cost.
C77: REG-04 | D77: Space and data law | E77: Who may own, access, distribute, commercialize, or restrict mission data and derived products? | F77: Rights and restrictions | G77: Ground rule | H77: Drafted | I77: CSA owns ORCA instrument data and derived science products; distribution follows the mission's international data-rights agreement and is coordinated with the partner agencies. | J77: Ground rule; OBS | K77: Devon Okafor (Mission Operations Scientist) | L77: Medium | M77: Data rights defined.
C78: REG-05 | D78: Intellectual property | E78: Who will own background and foreground IP, and what licensing or reuse rights are required? | F78: IP allocation | G78: Ground rule | H78: Drafted | I78: CSA holds a licence to foreground IP; contractors retain background IP; sampling-arm mechanism IP licensing with Aetheris is negotiated. | J78: Ground rule | K78: Étienne Lacroix (Deputy Project Manager) | L78: Medium | M78: IP negotiation effort.
B80: Section 9 - Security and Information
C81: ID | D81: Category | E81: Question | F81: Expected Response | G81: Classification | H81: Status | I81: Response / Narrative | J81: Basis / Source | K81: Owner | L81: Confidence | M81: Cost / Schedule / Risk Impact
C82: SEC-01 | D82: Security classification | E82: What security category or classification applies to the mission, systems, information, and contracts? | F82: Classification by asset | G82: Ground rule | H82: Drafted | I82: Mission baseline is Protected B; certain instrument performance and export-controlled technical data are Protected or classified. | J82: Ground rule | K82: Étienne Lacroix (Deputy Project Manager) | L82: Medium | M82: Contract security cost.
C83: SEC-02 | D83: Cybersecurity | E83: What cybersecurity, accreditation, monitoring, data-protection, and communications-security controls apply? | F83: Control baseline | G83: Ground rule | H83: Drafted | I83: ITSG-33 controls, command-link authentication/COMSEC, and ground-system accreditation apply. | J83: Ground rule | K83: Étienne Lacroix (Deputy Project Manager) | L83: Medium | M83: Cybersecurity cost.
C84: SEC-03 | D84: Personnel and facilities | E84: What clearances, access restrictions, controlled facilities, and physical-security measures are required? | F84: Security requirements | G84: Ground rule | H84: Drafted | I84: Secret-cleared key personnel, a controlled integration facility, and physical security per Controlled Goods requirements. | J84: Ground rule | K84: Étienne Lacroix (Deputy Project Manager) | L84: Medium | M84: Clearance schedule.
C85: SEC-04 | D85: Information sharing | E85: What publication, disclosure, data-residency, records-management, and information-sharing restrictions apply? | F85: Rules by information type | G85: Ground rule | H85: Drafted | I85: Publication review for sensitive ConOps, data residency in Canada, and records management per CSA IM policy. | J85: Ground rule | K85: Étienne Lacroix (Deputy Project Manager) | L85: Medium | M85: Disclosure controls.
B87: Section 10 - Science and Data Utilization
C88: ID | D88: Category | E88: Question | F88: Expected Response | G88: Classification | H88: Status | I88: Response / Narrative | J88: Basis / Source | K88: Owner | L88: Confidence | M88: Cost / Schedule / Risk Impact
C89: SCI-01 | D89: Science utilization scope | E89: What science planning, calibration, validation, analysis, archiving, user support, and exploitation activities are included? | F89: Included activities and duration | G89: Ground rule | H89: Drafted | I89: Primarily science data: radar sounding and mass-spectrometry analysis, plume-chemistry validation, and a lessons-learned archive; deep-space radiation-environment studies supported by Boreal Technical University. | J89: Part A §2.1; OBS | K89: Devon Okafor (Mission Operations Scientist) | L89: Medium | M89: Modest science scope.
C90: SCI-02 | D90: Science cost responsibility | E90: Who funds and performs science utilization, and are grants, calls for proposals, or partner contributions expected? | F90: Funding and delivery model | G90: Assumption | H90: Drafted | I90: CSA funds and performs data analysis in-house with academic support; no external grants or calls for proposals are assumed. | J90: Assumption | K90: Devon Okafor (Mission Operations Scientist) | L90: Medium | M90: Low cost impact.
C91: SCI-03 | D91: Data products | E91: What data products, processing levels, archives, access services, and retention periods must be delivered? | F91: Product and service scope | G91: Ground rule | H91: Drafted | I91: Level 0-2 telemetry and instrument science data, plume-composition products, and a mission archive retained to end of Phase X + 5 years. | J91: Ground rule | K91: Devon Okafor (Mission Operations Scientist) | L91: Medium | M91: Archive cost.
B94: Section 11 - Risk and Resilience
C95: ID | D95: Category | E95: Question | F95: Expected Response | G95: Classification | H95: Status | I95: Response / Narrative | J95: Basis / Source | K95: Owner | L95: Confidence | M95: Cost / Schedule / Risk Impact
C96: RSK-01 | D96: Supply chain | E96: Which critical suppliers, materials, components, or services have supply-chain risk? | F96: Critical-item assessment | G96: Assumption | H96: Drafted | I96: Critical items: robotic actuators/end-effector (Aetheris Space Robotics), the radar subsystem (Northstar Orbital Technologies), and imaging/proximity sensors (Borealis Vision Systems). | J96: Assumption; OBS | K96: Naomi Fitzgerald (Lead Spacecraft Systems Engineer) | L96: Medium | M96: Long-lead supply risk.
C97: RSK-02 | D97: Delay response | E97: What contingency plans, alternate suppliers, schedule margin, or advance purchases are assumed for supply-chain delays? | F97: Mitigation and cost treatment | G97: Assumption | H97: Drafted | I97: Schedule margin held in Phase C/D, an alternate sensor source qualified, and advance purchase of long-lead propulsion from Northstar. | J97: Assumption | K97: Samuel Boucher (Schedule and Cost Management Engineer) | L97: Low | M97: Margin and advance-buy cost.
C98: RSK-03 | D98: Foreign exchange and escalation | E98: What inflation, escalation, exchange-rate, tariff, and commodity-price assumptions apply? | F98: Rates, dates, and sources | G98: Assumption | H98: Drafted | I98: CAD-base estimate; assume 2.5%/yr escalation, limited USD exposure on launch and some components, FY2024 economic base. | J98: Costing GR&A (Part C) | K98: Samuel Boucher (Schedule and Cost Management Engineer) | L98: Medium | M98: Escalation on multi-year build.
C99: RSK-04 | D99: Schedule constraints | E99: What fixed dates, launch windows, partner milestones, seasonal constraints, or long-lead items drive the schedule? | F99: Constraints and margins | G99: Ground rule | H99: Drafted | I99: Launch window is fixed by planetary alignment for the Jupiter gravity assist (host orbiter, NASA-led); long-lead sampling-arm hardware drives the ORCA-side critical path. | J99: Sched Dependencies (Part D §10) | K99: Naomi Fitzgerald (Lead Spacecraft Systems Engineer) | L99: Medium | M99: Critical-path driver.
C100: RSK-05 | D100: Fallback strategy | E100: What scope, performance, schedule, or acquisition alternatives are available if affordability or feasibility targets are not met? | F100: Off-ramps and decision triggers | G100: Ground rule | H100: Drafted | I100: Off-ramps: reduce plume-pass count from multi- to single-pass, defer extended ops (Phase X), or descope autonomy to ground-in-the-loop. | J100: Ground rule | K100: Marie Tremblay (ORCA Mission Manager) | L100: Medium | M100: Descope levers protect affordability.
B102: Section 12 - Planetary Protection and End-of-Mission Disposal
C103: ID | D103: Category | E103: Question | F103: Expected Response | G103: Classification | H103: Status | I103: Response / Narrative | J103: Basis / Source | K103: Owner | L103: Confidence | M103: Cost / Schedule / Risk Impact
C104: SUS-01 | D104: Disposal compliance | E104: How will ORCA comply with post-mission disposal and planetary-protection guidelines? | F104: Compliance approach | G104: Ground rule | H104: Drafted | I104: Controlled disposal of the NEREID orbiter and its science payload complement to atmospheric re-entry within guideline timelines; compliant with COSPAR Planetary Protection Policy and NASA/ESA Enceladus contamination-control requirements, and Canadian direction. | J104: COSPAR / NASA-ESA planetary-protection requirements; Part A §2.1 | K104: Naomi Fitzgerald (Lead Spacecraft Systems Engineer) | L104: High | M104: Central mission objective; drives disposal-plan coordination.
C105: SUS-02 | D105: Planetary-protection assurance | E105: How is planetary-protection compliance during plume sampling verified? | F105: Verification approach | G105: Ground rule | H105: Drafted | I105: Plume-sampling ConOps designed for controlled instrument operation with abort-to-safe if sampling parameters fall outside limits; verified in SAIT and operational rehearsals. | J105: Part A §3.2 payload safety | K105: Fatima Haidari (Safety and Mission Assurance Engineer) | L105: Medium | M105: Adds test and rehearsal cost.
C106: SUS-03 | D106: Re-entry safety | E106: What re-entry casualty-risk and public-safety analysis is required? | F106: Risk analysis and threshold | G106: Ground rule | H106: Drafted | I106: Controlled re-entry targeted over an uninhabited ocean corridor; casualty risk assessed below the 1e-4 per-event threshold. | J106: Safety/SMA assumption | K106: Fatima Haidari (Safety and Mission Assurance Engineer) | L106: Low | M106: Analysis effort; constrains disposal ops.
C107: SUS-04 | D107: Orbital coordination | E107: How are conjunction and orbital-traffic coordination handled during plume transit? | F107: Coordination approach | G107: Assumption | H107: Drafted | I107: Planetary-protection and export-control compliance coordination with the Canadian Orbital Safety Directorate (COSD); deep-space radiation and thermal-environment inputs from CSEO; trajectory and communications-window coordination pre-planned for each Enceladus plume pass. | J107: Ops assumption; Part D §5 OBS | K107: Simone Bergeron (Mission Operations and Ground Systems Engineer) | L107: Medium | M107: Ground-segment and ops workload.

Sheet 11 - DDDD
A1: ` Table of Contents
A3: 12 - Dispose, Divest, Descope, Delay (DDDD)
A4: Why we we asking:
A5: This section helps assess program risk, maturity, and readiness for Earned Value Management (EVM). It explores how you would respond to cost overruns, schedule delays, and end-of-life considerations.
A8: Q1. COST OVERRUNS
A9: If the cost exceeds the approved allocation, what mitigation strategies would you consider? ☐ Descope ☐ Request additional funding ☐ Delay ☐ Cannibalize from the A-Base ☐ Other (specify) | B9: Selected: [x] Descope [x] Delay [x] Request additional funding. Primary response is to descope (reduce plume-pass count) before seeking new funds; cannibalizing the A-Base is a last resort.
A10: If you have a Descope Plan, please describe it. | B10: Yes. Tiered descope: (1) reduce plume-pass count from multi- to single-pass; (2) defer extended operations / disposal (Phase X); (3) descope onboard autonomy to ground-in-the-loop operations. Each ties to a KDP off-ramp.
A11: If you would request more funding, would this be an A-Base pressure or a Fiscal Framework Ask ? | B11: A Fiscal Framework Ask for material growth; minor pressures absorbed as an A-Base pressure within the CSA envelope.
A12: If an A-Base pressure, which other investment would be most at risk of cannibalization? | B12: If A-Base, the CSA space-robotics technology development line would be most at risk of cannibalization.
A13: Do you have a Scope Management Strategy in place? | B13: Yes - baseline is held under the CSA Configuration Control Board; a RID (Review Item Disposition) process runs at each gate; scope changes above the TB threshold escalate.
A14: Who is your Systems Engineer, and what is their approach to RIDs and scope escalation? | B14: Lead Spacecraft Systems Engineer: Naomi Fitzgerald. RIDs are dispositioned at each gate review; scope escalation is controlled via ECR to the CCB with a cost/schedule impact assessment.
A15: How well is the scope defined? What level of uncertainty exists in the scope? | B15: Scope is well defined for the ORCA instrument suite but carries moderate uncertainty in the sampling-arm and autonomy elements (TRL 6). Overall Mission Class B.
A16: Do you have a vendor exit strategy, such as go/no-go milestones? | B16: Yes - go/no-go at Gate 2 (down-select of the two Phase 0 concepts) and at each subsequent gate; option clauses allow an off-ramp before the Phase D commitment.
A17: What thresholds would trigger a replanning or a rebaseline? | B17: Rebaseline if cost variance exceeds +15% of the approved envelope, or schedule variance exceeds 6 months at a gate.
A19: Q2. DELAYS
A20: If the mission extends beyond nominal operations, do you have a Divestiture Plan? Who would you divest to? Are there any financial interests involved in the divestiture? | B20: No divestiture - ORCA is a single-use CSA science payload. Extended operations run under Phase X until end-of-life, then controlled disposal. No third-party financial interest.
A21: What would be the impacts of a significant launch delay? | B21: A launch slip on the host orbiter (NASA-led) delays science-data return, extends CSA salary/O&M carrying cost, and may miss the Jupiter gravity-assist window entirely. Roughly $0.3-0.5M per month of standing-army cost (the Pessimistic scenario carries a 1-year slip).
A22: Do you have contingency plans for schedule delays? | B22: Yes - schedule margin is held in Phase C/D, an alternate sensor source is qualified, and long-lead sampling-arm hardware is advance-purchased. Three schedule scenarios (Nominal / Optimistic / Pessimistic) bound the risk.
A23: What schedule delays would trigger a replanning or a rebaseline? | B23: A slip greater than 6 months against the Scenario 1 baseline at any gate triggers replanning; greater than 12 months triggers a formal rebaseline.
A26: Q3. END OF LIFE
A27: Do you have a general idea of the Disposal Plan for Phase F? | B27: Disposal is handled in Phase X (Phase F/G collapsed into Phase X for ORCA): controlled disposal of the NEREID orbiter and its science payload complement per the partner agency plan, compliant with COSPAR / NASA-ESA planetary-protection requirements.
A28: Are you planning an Audit after launch? | B28: Yes - a post-launch / close-out audit and a lessons-learned review are planned at the end of Phase X.
A29: What are your plans for retiring the space segment after nominal operations? Do you plan to divest any components? If so, how? And to whom? | B29: The space segment is disposed of per the partner agency's end-of-mission plan, not retired for reuse; no components are divested. Ground assets (the MOC) revert to CSA sustaining use.
A30: Do you plan to de-orbit the spacecraft or transfer it to a parking orbit? What is your strategy for managing space debris? | B30: Controlled end-of-mission disposal per the partner agency's planetary-protection plan - never left in an uncontrolled state. The mission is planetary-protection compliant (controlled instrument operations with abort-to-safe).
A31: What is the source of funds for a potential Phase E Extension? | B31: A-Base O&M appropriation funds nominal Phase E; any extension (Phase X) is funded through a subsequent Fiscal Framework Ask or reprofiled A-Base.

Sheet 12 - Procurement Plan 
A1: ` Table of Contents
A3: 13 - Procurement Plan
A4: Why we we asking:
B5: Part of GRA
B10: List all contracts and G&C and MOUs
B12: Segment | C12: Phase | D12: Type | E12: Vendor | F12: PO Number | G12: Contract Title | H12: Sub-contractor | I12: CWBS | J12: Color of Money
B13: Space Segment | C13: PREP1 | D13: Contract | E13: Aetheris Space Robotics | F13: 9F063-190007 | G13: Instrument Accommodation Risk-Reduction Prototype | I13: CWBS 3 | J13: STDP Contribution
B14: Space Segment | C14: PREP1 | D14: Contract | E14: Asterion Orbital Integration | F14: 9F063-190012 | G14: Plume Transit & Sampling Ops Risk-Reduction Study | I14: CWBS 2 | J14: STDP O&M Contract
B15: Space Segment | C15: PREP2 | D15: Contract | E15: Northstar Orbital Technologies | F15: 9F063-200019 | G15: Host Orbiter Interface Concept Prototyping | I15: CWBS 4 | J15: STDP Contribution
B16: Space Segment | C16: PREP2 | D16: Contract | E16: Aetheris Space Robotics | F16: 9F063-200024 | G16: Sampling Arm End-Effector Breadboard | I16: CWBS 3 | J16: STDP O&M Contract
B17: Mission SEITPM | C17: Phase 0 | D17: Contract | E17: Asterion Orbital Integration | F17: 9F063-200031 | G17: ORCA Phase 0 Concept Study A | I17: CWBS 1 | J17: O&M Contract
B18: Mission SEITPM | C18: Phase 0 | D18: Contract | E18: Northstar Orbital Technologies | F18: 9F063-200033 | G18: ORCA Phase 0 Concept Study B | I18: CWBS 1 | J18: O&M Contract
B19: Mission SEITPM | C19: Phase A | D19: Contract | E19: Asterion Orbital Integration | F19: 9F063-220045 | G19: ORCA Phase A Definition | I19: CWBS 1 | J19: None
B20: Space Segment | C20: Phase BCD | D20: Contract | E20: Asterion Orbital Integration | F20: 9F063-230061 | G20: ORCA Phase B-D Space Segment (Prime) | H20: Northstar / Aetheris / Polarion / Borealis / Arcturon | I20: CWBS 2-8 | J20: Capital Contract
B21: Ground Segment | C21: Phase BCD | D21: Contract | E21: Meridian Ground Technologies | F21: 9F063-230064 | G21: ORCA Ground Segment | H21: Canterra Space Communications | I21: CWBS 9 | J21: Capital Contract
B22: Overhead & Oversight | C22: Phase BCD | D22: MOU | E22: NASA | G22: MOU with NASA - launch of the NEREID orbiter and the ORCA instrument suite (partner-procured, no CSA launch contract) | J22: Capital Contract
B23: Science Segment | C23: Phase 0 | D23: Contract | E23: Northern Institute of Space Engineering | F23: 9F063-200052 | G23: Science Support during Phase 0 | I23: CWBS 11 | J23: O&M Contract
B24: Science Segment | C24: Phase A | D24: Contract | E24: Laurentia University of Aerospace Technology | F24: 9F063-220057 | G24: Science Support during Phase A | I24: CWBS 11 | J24: Capital Contract
B25: Science Segment | C25: Phase BCD | D25: Contract | E25: Boreal Technical University | F25: 9F063-230059 | G25: Science Support during Phase B-D | I25: CWBS 11 | J25: Capital Contract
B26: Science Segment | C26: Phase E | D26: G&C | E26: Northern Institute of Space Engineering | F26: 9F063-270081 | G26: Science Utilization Grant | I26: CWBS 11 | J26: Grants
B27: Overhead & Oversight | C27: Phase 0 | D27: MOU | E27: COSD | G27: MOU with Canadian Orbital Safety Directorate (COSD)
B28: Overhead & Oversight | C28: Phase A | D28: MOU | E28: COSD | G28: MOU with COSD
B29: Overhead & Oversight | C29: Phase BCD | D29: MOU | E29: CSEO | G29: MOU with Canadian Space Environment Office (CSEO)
B30: Overhead & Oversight | C30: Phase E | D30: MOU | E30: COSD | G30: MOU with COSD
B31: Overhead & Oversight | C31: Phase 0 | D31: MOU | E31: NARD | G31: MOU with National Aerospace Research Directorate (NARD)
B32: Overhead & Oversight | C32: Phase BCD | D32: MOU | E32: NARD | G32: MOU with NARD
B33: Overhead & Oversight | C33: Phase BCD | D33: MOU | E33: ESA | G33: MOU with ESA - plume-transit trajectory analysis
B34: Overhead & Oversight | C34: Phase BCD | D34: MOU | E34: NASA | G34: MOU with NASA - host-orbiter interface expertise
B35: Overhead & Oversight | C35: Phase 0 | D35: RAM | E35: CSA | G35: RAM | J35: O&M Salary
B36: Overhead & Oversight | C36: Phase A | D36: RAM | E36: CSA | G36: RAM | J36: Capital Salary
B37: Overhead & Oversight | C37: Phase BCD | D37: RAM | E37: CSA | G37: RAM | J37: Capital Salary
B38: Overhead & Oversight | C38: Phase E | D38: RAM | E38: CSA | G38: RAM | J38: O&M Salary
B41: Charter of Accounts
B42: CBS x OBS

Sheet 13 - Govt Overhead
A1: ` Table of Contents
A3: 14. Overhead costs
A4: Why we we asking:
D8: RO | E8: GL | F8: ballpark
B9: IS Management Overhead | C9: This is a % tax based on project size and complexity | D9: multiple | E9: multiple | F9: 0.01
B10: Management Consulting Services | C10: Contracts with management consultants
B11: Consultants - Industrial Space Experts | C11: Technomics support at KDP-0 | D11: RO-14.1 | F11: 10000
C12: Technomics support at KDP-A | D12: RO-14.1 | F12: 2000
C13: Technomics support at KDP-B | D13: RO-14.1 | F13: 1000
C14: Technomics support at KDP-C | D14: RO-14.1 | F14: 1000
C15: Technomics support at KDP-D | D15: RO-14.1 | F15: 1000
B16: Consultants - Academia | C16: Northern Institute of Space Engineering | D16: RO-14.1 | F16: 50000
B17: Consultants - Non-Space Experts | C17: N/A | F17: 0
B18: Temporary Help | C18: N/A | F18: 0
B19: Students | C19: Student Term 1 | F19: 16000
C20: Student Term 2 | F20: 16000
C21: Student Term 3 | F21: 16000
C22: Student Term 4 | F22: 16000
B23: Government Travel & Living | C23: T&L Phase 0 | F23: 25000 | G23: Should be linked to Travel Plan roll-up
C24: T&L Phase A | F24: 25000
C25: T&L Phase B | F25: 25000
C26: T&L Phase C | F26: 25000
C27: T&L Phase D | F27: 25000
C28: T&L Phase E | F28: 25000
B29: Translation | C29: Phase 0 Docs | F29: 2000
C30: Phase A Docs | F30: 5000
C31: Phase BCD Docs | F31: 5000
B32: Shipping | F32: 0
B33: Software Licenses | C33: Matlab, STK, etc | F33: 50000
B34: Public Outreach and STEM initiatives | F34: 20000
B35: Other Overhead (Specify)

Sheet 14 - Constants 
A1: ` Table of Contents
A3: 15 - Economic Constants and short answers
A4: This tab contains one word or one number answers
A8: Parameter | B8: Value | C8: Description
A9: EBP Rate | B9: 0.27 | C9: The Employee Benefit Payments (EBP) rate for federal government initiatives is currently calculated at 27% of total salary costs for new initiatives, according to the Treasury Board Secretariat (TBS).
A10: Shared Services Rate | B10: 0.04 | C10: Shared Services Canada (SSC) charges federal government departments for IT services; this equal 4% of FTE salary costs to align with the actual cost of providing services.
A11: PSPC Rate | B11: 0.13 | C11: PSPC accommodation premium is set at 13% and is calculated as a percentage of personnel costs.
A12: PSPC Fairness Monitor Rate | B12: 300000 | C12: The Fairness Monitoring Program of Public Services and Procurement Canada (PSPC) ensures independent assurance that procurement activities are fair, open, and transparent. It involves a third-party fairness monitor who assesses the fairness, openness, and transparency of the monitored activity.
A13: Labour Rates | B13: 205$/hr | C13: As per recent Asterion Orbital Integration quote; estimated contractor rate per hour.
A14: Vendor Fee Rate % | B14: 0.11 | C14: As per recent Asterion Orbital Integration quote; contractor general fee applied before tax.
A15: Costing Complexity | B15: Medium | C15: Low, Medium, High
A16: Palier/ Tier | B16: Tier 2 | C16: Gated investments are classified into Tiers. Tier determination is made based on the estimated project cost; the use of Tiers enables the implementation of a tailored approach, whereby authority level, reporting, and deliverables are proportionate to the investment materiality, risk, and complexity.
A17: PCRA | B17: PCRA 3 | C17: In accordance with the Standard for Project Complexity and Risk Assessment.
A18: Classe de Mission | B18: Class B | C18: Classification system to group space missions according to their budget size, technical complexity, scientific goals, and acceptable levels of risk.
A19: Investment Type | B19: Space Mission | C19: space mission, real property, software solutions
A20: Mission Type | B20: Hosted Payload | C20: Flagship, LargeSat, SmallSat, NanoSat, Hosted Payload, Data stream partnership, data stream purchase
A21: Discipline | B21: planetary exploration | C21: SatCom, Earth Observation, Atmospheric science, Solar Terrestrial Science, Space surveillance, Astronomy, planetary exploration, human space flight, health and life science, space robotics, platform technologies
A22: Mission Name | B22: ORCA
A23: Current Phase | B23: Phase D (MAIT/SAIT)
A24: Next KDP | B24: KDP-E / Gate 4 | C24: Key decision point
A25: Base year | B25: 2026 | C25: Base year is the reference year used as a benchmark for comparing costs, prices, or other economic indicators over time.
A26: Exchange Rate USD | B26: 1.36 | C26: Exchange rate is the rate at which the USD currency can be exchanged for the Canadian currency at a specific point in time.
A27: Exchange Rate Euro | B27: 1.49 | C27: Exchange rate is the rate at which the Euro currency can be exchanged for the Canadian currency at a specific point in time.
A28: Unknown-Unknown Risk Margin | B28: 0.1
A29: tax rates | B29: 0.14975 | C29: Assuming the 5% for Goods and Services Tax (GST) and 9.975% for the Quebec Sales Tax (QST).

Sheet 15 - Inflation
A1: ` Table of Contents
A3: 16 - Inflation Model
A9: Inflation | B9: 21/22 | C9: 22/23 | D9: 23/24 | E9: 24/25 | F9: 25/26 | G9: 26/27 | H9: 27/28 | I9: 28/29 | J9: 29/30 | K9: 30/31 | L9: 31/32 | M9: 32/33 | N9: 33/34 | O9: 34/35 | P9: 35/36 | Q9: 36/37 | R9: 37/38 | S9: 38/39 | T9: 39/40 | U9: 40/41 | V9: 41/42 | W9: 42/43 | X9: 43/44 | Y9: 44/45 | Z9: Justification
A10: Csa Salaries | C10: 0.0475 | D10: 0.035 | E10: 0.025 | F10: 0.023 | G10: 0.023 | H10: 0.023 | I10: 0.023 | J10: 0.02 | K10: 0.02 | L10: 0.02 | M10: 0.02 | N10: 0.02 | O10: 0.02 | P10: 0.02 | Q10: 0.02 | R10: 0.02 | S10: 0.02 | T10: 0.02 | U10: 0.02 | V10: 0.02 | W10: 0.02 | X10: 0.02 | Y10: 0.02 | Z10: Convention collective des ingénieurs signées jusqu'en octobre 2025 (plus grosse partie du salaire) Hypothèse de 2.3% jusqu'en 2030 et par la suite 2% | AC10: This section of the sheet should not be modified by the user
A11: CSA Mgt | C11: 0.0632 | D11: 0.037 | E11: 0.024 | F11: 0.022 | G11: 0.02 | H11: 0.02 | I11: 0.02 | J11: 0.02 | K11: 0.02 | L11: 0.02 | M11: 0.02 | N11: 0.02 | O11: 0.02 | P11: 0.02 | Q11: 0.02 | R11: 0.02 | S11: 0.02 | T11: 0.02 | U11: 0.02 | V11: 0.02 | W11: 0.02 | X11: 0.02 | Y11: 0.02 | Z11: Inflation moyenne de 2% utilisée
A12: Contract Labor | B12: 0.025 | C12: 0.03 | D12: 0.03 | E12: 0.03 | F12: 0.03 | G12: 0.03 | H12: 0.03 | I12: 0.03 | J12: 0.03 | K12: 0.03 | L12: 0.03 | M12: 0.03 | N12: 0.03 | O12: 0.03 | P12: 0.03 | Q12: 0.03 | R12: 0.03 | S12: 0.03 | T12: 0.03 | U12: 0.03 | V12: 0.03 | W12: 0.03 | X12: 0.03 | Y12: 0.03 | Z12: Hypothèse de 3% annuellement donnée par différents contracteurs dans d'autres projets
A13: Contract Non Labor | C13: 0.037887 | D13: 0.040461 | E13: 0.025 | F13: 0.024 | G13: 0.022 | H13: 0.022 | I13: 0.022 | J13: 0.022 | K13: 0.022 | L13: 0.022 | M13: 0.022 | N13: 0.022587 | O13: 0.022587 | P13: 0.022587 | Q13: 0.022587 | R13: 0.022587 | S13: 0.022587 | T13: 0.022587 | U13: 0.022587 | V13: 0.022587 | W13: 0.022587 | X13: 0.022587 | Y13: 0.022587 | Z13: Hypothèse que l'inflation va se rapprocher de 2.1%- 2.2% dans les prochaines années
A14: Risk | C14: 0.03 | D14: 0.03 | E14: 0.03 | F14: 0.03 | G14: 0.03 | H14: 0.03 | I14: 0.03 | J14: 0.03 | K14: 0.03 | L14: 0.03 | M14: 0.03 | N14: 0.03 | O14: 0.03 | P14: 0.03 | Q14: 0.03 | R14: 0.03 | S14: 0.03 | T14: 0.03 | U14: 0.03 | V14: 0.03 | W14: 0.03 | X14: 0.03 | Y14: 0.03 | Z14: Hypothèse de 3% annuellement donnée par différents contracteurs dans d'autres projets
A15: No Inflation | C15: 0 | D15: 0 | E15: 0 | F15: 0 | G15: 0 | H15: 0 | I15: 0 | J15: 0 | K15: 0 | L15: 0 | M15: 0 | N15: 0 | O15: 0 | P15: 0 | Q15: 0 | R15: 0 | S15: 0 | T15: 0 | U15: 0 | V15: 0 | W15: 0 | X15: 0 | Y15: 0 | Z15: Not use | AB15: 1 | AC15: Inf. GL | AD15: FY of Source Cost | AE15: Inf. GL - FY of Source Cost (Unique ID) | AF15: 21/22 | AG15: 22/23 | AH15: 23/24 | AI15: 24/25 | AJ15: 25/26 | AK15: 26/27 | AL15: 27/28 | AM15: 28/29 | AN15: 29/30 | AO15: 30/31 | AP15: 31/32 | AQ15: 32/33 | AR15: 33/34 | AS15: 34/35 | AT15: 35/36 | AU15: 36/37 | AV15: 37/38 | AW15: 38/39 | AX15: 39/40 | AY15: 40/41 | AZ15: 41/42 | BA15: 42/43 | BB15: 43/44 | BC15: 44/45 | BD15: 45/46 | BG15: DND V1 R&D Near Term Adjusted
A16: Salary Funding Rate | C16: 0.0475 | D16: 0.035 | E16: 0.0225 | F16: 0.0225 | G16: 0 | H16: 0 | I16: 0 | J16: 0 | K16: 0 | L16: 0 | M16: 0 | N16: 0 | O16: 0 | P16: 0 | Q16: 0 | R16: 0 | S16: 0 | T16: 0 | U16: 0 | V16: 0 | W16: 0 | X16: 0 | Y16: 0 | Z16: Pour onglet 35a et 35b concernant les nouveaux FTE. Financement 4 ans de la 1ere tranche des conventions collectives et les renouvellements subséquents seront financés via le SCT pour les prochaines conventions collectives comme à l'habitude. Le risque ici dans les 1ere années est lorsque le SCT prendra la photo des effectifs à une date X, il est fort possible que les nouveaux employés ne seront pas prises en compte dans les effectifs et l'ASC n'aura pas le financement de l'augmentation pour les nouveaux postes. | AB16: 2 | AC16: Csa Salaries | AD16: 22/23 | AE16: Csa Salaries - 22/23 | AG16: 1 | AH16: =AG16*(1+D$10) -> 1.035 | AI16: =AH16*(1+E$10) -> 1.060875 | AJ16: =AI16*(1+F$10) -> 1.0852751 | AK16: =AJ16*(1+G$10) -> 1.1102365 | AL16: =AK16*(1+H$10) -> 1.1357719 | AM16: =AL16*(1+I$10) -> 1.1618946 | AN16: =AM16*(1+J$10) -> 1.1851325 | AO16: =AN16*(1+K$10) -> 1.2088352 | ... BC16: =BB16*(1+Y$10) -> 1.5950324 | BG16: Fiscal Year | BH16: Annual Inflation | BI16: Raw Index | BJ16: Weighted Index | BL16: FY | BM16: Fiscal Year | BN16: Annual Inflation | BO16: Raw Index | BP16: Weighted Index
A17: Ground segment | B17: 0.05 | C17: 0.05 | D17: 0.05 | E17: 0.05 | F17: 0.05 | G17: 0.05 | H17: 0.05 | I17: 0.05 | J17: 0.05 | K17: 0.05 | L17: 0.05 | M17: 0.05 | N17: 0.05 | O17: 0.05 | P17: 0.05 | Q17: 0.05 | R17: 0.05 | S17: 0.05 | T17: 0.05 | U17: 0.05 | V17: 0.05 | W17: 0.05 | X17: 0.05 | Y17: 0.05 | Z17: NR CAN | AB17: 3 | AC17: Csa Salaries | AD17: 23/24 | AE17: Csa Salaries - 23/24 | AG17: =AH17/(1+C$10) -> 0.95465394 | AH17: 1 | AI17: =AH17*(1+E$10) -> 1.025 | AJ17: =AI17*(1+F$10) -> 1.048575 | AK17: =AJ17*(1+G$10) -> 1.0726922 | AL17: =AK17*(1+H$10) -> 1.0973641 | AM17: =AL17*(1+I$10) -> 1.1226035 | AN17: =AM17*(1+J$10) -> 1.1450556 | AO17: =AN17*(1+K$10) -> 1.1679567 | AP17: =AO17*(1+L$10) -> 1.1913158 | ... BC17: =BB17*(1+Y$10) -> 1.5410941 | BF17: 1 | BG17: 1990 | BH17: 0.053 | BI17: 0.60277383 | BJ17: 0.62028784 | BL17: 21/22 | BM17: 2021 | BN17: 0.007 | BO17: 1 | BP17: 1.0197914
A18: DND Table | B18: =BH48 -> 0.007 | C18: =BH49 -> 0.034 | D18: =BH50 -> 0.069 | E18: =BH51 -> 0.042 | F18: =BH52 -> 0.024 | G18: =$BH53 -> 0.021089 | H18: =$BH54 -> 0.021089 | I18: =$BH55 -> 0.021089 | J18: =$BH56 -> 0.021089 | K18: =$BH57 -> 0.021089 | L18: =$BH58 -> 0.020773 | M18: =$BH59 -> 0.020773 | N18: =$BH60 -> 0.020773 | O18: =$BH61 -> 0.020773 | P18: =$BH62 -> 0.020773 | Q18: =$BH63 -> 0.020773 | R18: =$BH64 -> 0.020773 | S18: =$BH65 -> 0.020773 | T18: =$BH66 -> 0.020773 | U18: =$BH67 -> 0.020773 | V18: =$BH68 -> 0.020773 | W18: =$BH69 -> 0.020773 | X18: =$BH70 -> 0.020773 | Y18: =$BH71 -> 0.020773 | Z18: Fournit par Technomics | AB18: 4 | AC18: Csa Salaries | AD18: 24/25 | AE18: Csa Salaries - 24/25 | AG18: =AH18/(1+C$10) -> 0.92237095 | AH18: =AI18/(1+D$10) -> 0.96618357 | AI18: 1 | AJ18: =AI18*(1+F$10) -> 1.023 | AK18: =AJ18*(1+G$10) -> 1.046529 | AL18: =AK18*(1+H$10) -> 1.0705992 | AM18: =AL18*(1+I$10) -> 1.0952229 | AN18: =AM18*(1+J$10) -> 1.1171274 | AO18: =AN18*(1+K$10) -> 1.13947 | AP18: =AO18*(1+L$10) -> 1.1622594 | AQ18: =AP18*(1+M$10) -> 1.1855045 | ... BC18: =BB18*(1+Y$10) -> 1.5035064 | BF18: 2 | BG18: 1991 | BH18: 0.048 | BI18: 0.63170697 | BJ18: 0.64478352 | BL18: 22/23 | BM18: 2022 | BN18: 0.034 | BO18: 1.034 | BP18: 1.0544169
A19: Inflation 1,5% | B19: 0.015 | C19: 0.015 | D19: 0.015 | E19: 0.015 | F19: 0.015 | G19: 0.015 | H19: 0.015 | I19: 0.015 | J19: 0.015 | K19: 0.015 | L19: 0.015 | M19: 0.015 | N19: 0.015 | O19: 0.015 | P19: 0.015 | Q19: 0.015 | R19: 0.015 | S19: 0.015 | T19: 0.015 | U19: 0.015 | V19: 0.015 | W19: 0.015 | X19: 0.015 | Y19: 0.015 | AB19: 5 | AC19: Csa Salaries | AD19: 25/26 | AE19: Csa Salaries - 25/26 | AG19: =AH19/(1+C$10) -> 0.8998741 | AH19: =AI19/(1+D$10) -> 0.94261812 | AI19: =AJ19/(1+E$10) -> 0.97560976 | AJ19: 1 | AK19: =AJ19*(1+G$10) -> 1.023 | AL19: =AK19*(1+H$10) -> 1.046529 | AM19: =AL19*(1+I$10) -> 1.0705992 | AN19: =AM19*(1+J$10) -> 1.0920112 | AO19: =AN19*(1+K$10) -> 1.1138514 | AP19: =AO19*(1+L$10) -> 1.1361284 | AQ19: =AP19*(1+M$10) -> 1.158851 | AR19: =AQ19*(1+N$10) -> 1.182028 | ... BC19: =BB19*(1+Y$10) -> 1.4697032 | BF19: 3 | BG19: 1992 | BH19: 0.018 | BI19: 0.6430777 | BJ19: 0.65554232 | BL19: 23/24 | BM19: 2023 | BN19: 0.069 | BO19: 1.105346 | BP19: 1.1271076
A20: Inflation 8% | B20: 0.08 | C20: 0.08 | D20: 0.08 | E20: 0.06 | F20: =E20 -> 0.06 | G20: =F20 -> 0.06 | H20: =G20 -> 0.06 | I20: =H20 -> 0.06 | J20: =I20 -> 0.06 | K20: =J20 -> 0.06 | L20: =K20 -> 0.06 | M20: =L20 -> 0.06 | ... Y20: =X20 -> 0.06 | AB20: 6 | AC20: Csa Salaries | AD20: 26/27 | AE20: Csa Salaries - 26/27 | AG20: =AH20/(1+C$10) -> 0.87964233 | AH20: =AI20/(1+D$10) -> 0.92142534 | AI20: =AJ20/(1+E$10) -> 0.95367523 | AJ20: =AK20/(1+F$10) -> 0.97751711 | AK20: 1 | AL20: =AK20*(1+H$10) -> 1.023 | AM20: =AL20*(1+I$10) -> 1.046529 | AN20: =AM20*(1+J$10) -> 1.0674596 | AO20: =AN20*(1+K$10) -> 1.0888088 | AP20: =AO20*(1+L$10) -> 1.1105849 | AQ20: =AP20*(1+M$10) -> 1.1327966 | AR20: =AQ20*(1+N$10) -> 1.1554526 | AS20: =AR20*(1+O$10) -> 1.1785616 | ... BC20: =BB20*(1+Y$10) -> 1.4366601 | BF20: 4 | BG20: 1993 | BH20: 0.029 | BI20: 0.66172695 | BJ20: 0.67264054 | BL20: 24/25 | BM20: 2024 | BN20: 0.042 | BO20: 1.1517705 | BP20: 1.1744742
AB21: 7 | AC21: Csa Salaries | AD21: 27/28 | AE21: Csa Salaries - 27/28 | AG21: =AH21/(1+C$10) -> 0.85986542 | AH21: =AI21/(1+D$10) -> 0.90070903 | AI21: =AJ21/(1+E$10) -> 0.93223385 | AJ21: =AK21/(1+F$10) -> 0.95553969 | AK21: =AL21/(1+G$10) -> 0.97751711 | AL21: 1 | AM21: =AL21*(1+I$10) -> 1.023 | AN21: =AM21*(1+J$10) -> 1.04346 | AO21: =AN21*(1+K$10) -> 1.0643292 | AP21: =AO21*(1+L$10) -> 1.0856158 | AQ21: =AP21*(1+M$10) -> 1.1073281 | AR21: =AQ21*(1+N$10) -> 1.1294747 | AS21: =AR21*(1+O$10) -> 1.1520642 | AT21: =AS21*(1+P$10) -> 1.1751054 | ... BC21: =BB21*(1+Y$10) -> 1.4043598 | BF21: 5 | BG21: 1994 | BH21: -0.014 | BI21: 0.65246278 | BJ21: 0.66500563 | BL21: 25/26 | BM21: 2025 | BN21: 0.024 | BO21: 1.179413 | BP21: 1.2023564
AB22: 8 | AC22: Csa Salaries | AD22: 28/29 | AE22: Csa Salaries - 28/29 | AG22: =AH22/(1+C$10) -> 0.84053316 | AH22: =AI22/(1+D$10) -> 0.88045849 | AI22: =AJ22/(1+E$10) -> 0.91127453 | AJ22: =AK22/(1+F$10) -> 0.9340564 | AK22: =AL22/(1+G$10) -> 0.95553969 | AL22: =AM22/(1+H$10) -> 0.97751711 | AM22: 1 | AN22: =AM22*(1+J$10) -> 1.02 | AO22: =AN22*(1+K$10) -> 1.0404 | AP22: =AO22*(1+L$10) -> 1.061208 | AQ22: =AP22*(1+M$10) -> 1.0824322 | AR22: =AQ22*(1+N$10) -> 1.1040808 | AS22: =AR22*(1+O$10) -> 1.1261624 | AT22: =AS22*(1+P$10) -> 1.1486857 | AU22: =AT22*(1+Q$10) -> 1.1716594 | ... BC22: =BB22*(1+Y$10) -> 1.3727857 | BF22: 6 | BG22: 1995 | BH22: 0 | BI22: 0.65246278 | BJ22: 0.66527411 | BL22: 26/27 | BM22: 2026 | BN22: 0.021089 | BO22: 1.2042857 | BP22: 1.2272
A23: Cellule BG7 | B23: pour inflation DND | AB23: 9 | AC23: Csa Salaries | AD23: 29/30 | AE23: Csa Salaries - 29/30 | AG23: =AH23/(1+C$10) -> 0.82163554 | AH23: =AI23/(1+D$10) -> 0.86066323 | AI23: =AJ23/(1+E$10) -> 0.89078644 | AJ23: =AK23/(1+F$10) -> 0.91305611 | AK23: =AL23/(1+G$10) -> 0.9340564 | AL23: =AM23/(1+H$10) -> 0.95553969 | AM23: =AN23/(1+I$10) -> 0.97751711 | AN23: 1 | AO23: =AN23*(1+K$10) -> 1.02 | AP23: =AO23*(1+L$10) -> 1.0404 | AQ23: =AP23*(1+M$10) -> 1.061208 | AR23: =AQ23*(1+N$10) -> 1.0824322 | AS23: =AR23*(1+O$10) -> 1.1040808 | AT23: =AS23*(1+P$10) -> 1.1261624 | AU23: =AT23*(1+Q$10) -> 1.1486857 | AV23: =AU23*(1+R$10) -> 1.1716594 | ... BC23: =BB23*(1+Y$10) -> 1.3458683 | BF23: 7 | BG23: 1996 | BH23: 0.011093 | BI23: 0.65970055 | BJ23: 0.67278179 | BL23: 27/28 | BM23: 2027 | BN23: 0.021089 | BO23: 1.2296828 | BP23: 1.2527841
AB24: 10 | AC24: Csa Salaries | AD24: 30/31 | AE24: Csa Salaries - 30/31 | AG24: =AH24/(1+C$10) -> 0.80552504 | AH24: =AI24/(1+D$10) -> 0.84378748 | AI24: =AJ24/(1+E$10) -> 0.87332004 | AJ24: =AK24/(1+F$10) -> 0.89515305 | AK24: =AL24/(1+G$10) -> 0.91574157 | AL24: =AM24/(1+H$10) -> 0.93680362 | AM24: =AN24/(1+I$10) -> 0.9583501 | AN24: =AO24/(1+J$10) -> 0.98039216 | AO24: 1 | AP24: =AO24*(1+L$10) -> 1.02 | AQ24: =AP24*(1+M$10) -> 1.0404 | AR24: =AQ24*(1+N$10) -> 1.061208 | AS24: =AR24*(1+O$10) -> 1.0824322 | AT24: =AS24*(1+P$10) -> 1.1040808 | AU24: =AT24*(1+Q$10) -> 1.1261624 | AV24: =AU24*(1+R$10) -> 1.1486857 | AW24: =AV24*(1+S$10) -> 1.1716594 | ... BC24: =BB24*(1+Y$10) -> 1.3194788 | BF24: 8 | BG24: 1997 | BH24: 0.011 | BI24: 0.66695725 | BJ24: 0.67984317 | BL24: 28/29 | BM24: 2028 | BN24: 0.021089 | BO24: 1.2556156 | BP24: 1.2781917
AB25: 11 | AC25: Csa Salaries | AD25: 31/32 | AE25: Csa Salaries - 31/32 | AG25: =AH25/(1+C$10) -> 0.78973043 | AH25: =AI25/(1+D$10) -> 0.82724263 | AI25: =AJ25/(1+E$10) -> 0.85619612 | AJ25: =AK25/(1+F$10) -> 0.87760102 | AK25: =AL25/(1+G$10) -> 0.89778585 | AL25: =AM25/(1+H$10) -> 0.91843492 | AM25: =AN25/(1+I$10) -> 0.93955893 | AN25: =AO25/(1+J$10) -> 0.96116878 | AO25: =AP25/(1+K$10) -> 0.98039216 | AP25: 1 | AQ25: =AP25*(1+M$10) -> 1.02 | AR25: =AQ25*(1+N$10) -> 1.0404 | AS25: =AR25*(1+O$10) -> 1.061208 | AT25: =AS25*(1+P$10) -> 1.0824322 | AU25: =AT25*(1+Q$10) -> 1.1040808 | AV25: =AU25*(1+R$10) -> 1.1261624 | AW25: =AV25*(1+S$10) -> 1.1486857 | AX25: =AW25*(1+T$10) -> 1.1716594 | ... BC25: =BB25*(1+Y$10) -> 1.2936066 | BF25: 9 | BG25: 1998 | BH25: 0.018 | BI25: 0.67896248 | BJ25: 0.69264768 | BL25: 29/30 | BM25: 2029 | BN25: 0.021089 | BO25: 1.2820953 | BP25: 1.3022372
AB26: 12 | AC26: Csa Salaries | AD26: 32/33 | AE26: Csa Salaries - 32/33 | AG26: =AH26/(1+C$10) -> 0.77424552 | AH26: =AI26/(1+D$10) -> 0.81102219 | AI26: =AJ26/(1+E$10) -> 0.83940796 | AJ26: =AK26/(1+F$10) -> 0.86039316 | AK26: =AL26/(1+G$10) -> 0.8801822 | AL26: =AM26/(1+H$10) -> 0.90042639 | AM26: =AN26/(1+I$10) -> 0.9211362 | AN26: =AO26/(1+J$10) -> 0.94232233 | ... AP26: =AQ26/(1+L$10) -> 0.98039216 | AQ26: 1 | AR26: =AQ26*(1+N$10) -> 1.02 | AS26: =AR26*(1+O$10) -> 1.0404 | AT26: =AS26*(1+P$10) -> 1.061208 | AU26: =AT26*(1+Q$10) -> 1.0824322 | AV26: =AU26*(1+R$10) -> 1.1040808 | AW26: =AV26*(1+S$10) -> 1.1261624 | AX26: =AW26*(1+T$10) -> 1.1486857 | AY26: =AX26*(1+U$10) -> 1.1716594 | ... BC26: =BB26*(1+Y$10) -> 1.2682418 | BF26: 10 | BG26: 1999 | BH26: -0.003324 | BI26: 0.67670561 | BJ26: 0.69153104 | BL26: 30/31 | BM26: 2030 | BN26: 0.021089 | BO26: 1.3091334 | BP26: 1.329674
AB27: 13 | AC27: Csa Salaries | AD27: 33/34 | AE27: Csa Salaries - 33/34 | AG27: =AH27/(1+C$10) -> 0.75906424 | AH27: =AI27/(1+D$10) -> 0.79511979 | AI27: =AJ27/(1+E$10) -> 0.82294898 | AJ27: =AK27/(1+F$10) -> 0.84352271 | AK27: =AL27/(1+G$10) -> 0.86292373 | AL27: =AM27/(1+H$10) -> 0.88277098 | AM27: =AN27/(1+I$10) -> 0.90307471 | AN27: =AO27/(1+J$10) -> 0.92384543 | ... AQ27: =AR27/(1+M$10) -> 0.98039216 | AR27: 1 | AS27: =AR27*(1+O$10) -> 1.02 | AT27: =AS27*(1+P$10) -> 1.0404 | AU27: =AT27*(1+Q$10) -> 1.061208 | AV27: =AU27*(1+R$10) -> 1.0824322 | AW27: =AV27*(1+S$10) -> 1.1040808 | AX27: =AW27*(1+T$10) -> 1.1261624 | AY27: =AX27*(1+U$10) -> 1.1486857 | AZ27: =AY27*(1+V$10) -> 1.1716594 | ... BC27: =BB27*(1+Y$10) -> 1.2433743 | BF27: 11 | BG27: 2000 | BH27: 0.027 | BI27: 0.69497666 | BJ27: 0.70759122 | BL27: 31/32 | BM27: 2031 | BN27: 0.020773 | BO27: 1.336328 | BP27: 1.357363
AB28: 14 | AC28: Csa Salaries | AD28: 34/35 | AE28: Csa Salaries - 34/35 | AG28: =AH28/(1+C$10) -> 0.74418063 | AH28: =AI28/(1+D$10) -> 0.77952921 | AI28: =AJ28/(1+E$10) -> 0.80681273 | AJ28: =AK28/(1+F$10) -> 0.82698305 | AK28: =AL28/(1+G$10) -> 0.84600366 | AL28: =AM28/(1+H$10) -> 0.86546174 | AM28: =AN28/(1+I$10) -> 0.88536736 | AN28: =AO28/(1+J$10) -> 0.90573081 | ... AR28: =AS28/(1+N$10) -> 0.98039216 | AS28: 1 | AT28: =AS28*(1+P$10) -> 1.02 | AU28: =AT28*(1+Q$10) -> 1.0404 | AV28: =AU28*(1+R$10) -> 1.061208 | AW28: =AV28*(1+S$10) -> 1.0824322 | AX28: =AW28*(1+T$10) -> 1.1040808 | AY28: =AX28*(1+U$10) -> 1.1261624 | AZ28: =AY28*(1+V$10) -> 1.1486857 | BA28: =AZ28*(1+W$10) -> 1.1716594 | ... BC28: =BB28*(1+Y$10) -> 1.2189944 | BF28: 12 | BG28: 2001 | BH28: 0.048396183 | BI28: 0.72861088 | BJ28: 0.73703787 | BL28: 32/33 | BM28: 2032 | BN28: 0.020773 | BO28: 1.3640876 | BP28: 1.3855136
AB29: 15 | AC29: Csa Salaries | AD29: 35/36 | AE29: Csa Salaries - 35/36 | AG29: =AH29/(1+C$10) -> 0.72958885 | AH29: =AI29/(1+D$10) -> 0.76424432 | AI29: =AJ29/(1+E$10) -> 0.79099287 | AJ29: =AK29/(1+F$10) -> 0.81076769 | AK29: =AL29/(1+G$10) -> 0.82941535 | AL29: =AM29/(1+H$10) -> 0.8484919 | AM29: =AN29/(1+I$10) -> 0.86800722 | AN29: =AO29/(1+J$10) -> 0.88797138 | ... AS29: =AT29/(1+O$10) -> 0.98039216 | AT29: 1 | AU29: =AT29*(1+Q$10) -> 1.02 | AV29: =AU29*(1+R$10) -> 1.0404 | AW29: =AV29*(1+S$10) -> 1.061208 | AX29: =AW29*(1+T$10) -> 1.0824322 | AY29: =AX29*(1+U$10) -> 1.1040808 | AZ29: =AY29*(1+V$10) -> 1.1261624 | BA29: =AZ29*(1+W$10) -> 1.1486857 | BB29: =BA29*(1+X$10) -> 1.1716594 | BC29: =BB29*(1+Y$10) -> 1.1950926 | BF29: 13 | BG29: 2002 | BH29: 0.021557496 | BI29: 0.74431791 | BJ29: 0.75155478 | BL29: 33/34 | BM29: 2033 | BN29: 0.020773 | BO29: 1.3924238 | BP29: 1.4142404
AB30: 16 | AC30: Csa Salaries | AD30: 36/37 | AE30: Csa Salaries - 36/37 | AG30: =AH30/(1+C$10) -> 0.71528319 | AH30: =AI30/(1+D$10) -> 0.74925914 | AI30: =AJ30/(1+E$10) -> 0.77548321 | AJ30: =AK30/(1+F$10) -> 0.79487029 | AK30: =AL30/(1+G$10) -> 0.8131523 | AL30: =AM30/(1+H$10) -> 0.83185481 | AM30: =AN30/(1+I$10) -> 0.85098747 | AN30: =AO30/(1+J$10) -> 0.87056018 | ... AT30: =AU30/(1+P$10) -> 0.98039216 | AU30: 1 | AV30: =AU30*(1+R$10) -> 1.02 | AW30: =AV30*(1+S$10) -> 1.0404 | AX30: =AW30*(1+T$10) -> 1.061208 | AY30: =AX30*(1+U$10) -> 1.0824322 | AZ30: =AY30*(1+V$10) -> 1.1040808 | BA30: =AZ30*(1+W$10) -> 1.1261624 | BB30: =BA30*(1+X$10) -> 1.1486857 | BC30: =BB30*(1+Y$10) -> 1.1716594 | BF30: 14 | BG30: 2003 | BH30: -0.013340213 | BI30: 0.73438855 | BJ30: 0.74498472 | BL30: 34/35 | BM30: 2034 | BN30: 0.020773 | BO30: 1.4213486 | BP30: 1.4437591
AB31: 17 | AC31: Csa Salaries | AD31: 37/38 | AE31: Csa Salaries - 37/38 | AG31: =AH31/(1+C$10) -> 0.70125802 | AH31: =AI31/(1+D$10) -> 0.73456778 | AI31: =AJ31/(1+E$10) -> 0.76027765 | AJ31: =AK31/(1+F$10) -> 0.77928459 | AK31: =AL31/(1+G$10) -> 0.79720814 | AL31: =AM31/(1+H$10) -> 0.81554393 | AM31: =AN31/(1+I$10) -> 0.83430144 | AN31: =AO31/(1+J$10) -> 0.85349037 | ... AU31: =AV31/(1+Q$10) -> 0.98039216 | AV31: 1 | AW31: =AV31*(1+S$10) -> 1.02 | AX31: =AW31*(1+T$10) -> 1.0404 | AY31: =AX31*(1+U$10) -> 1.061208 | AZ31: =AY31*(1+V$10) -> 1.0824322 | BA31: =AZ31*(1+W$10) -> 1.1040808 | BB31: =BA31*(1+X$10) -> 1.1261624 | BC31: =BB31*(1+Y$10) -> 1.1486857 | BF31: 15 | BG31: 2004 | BH31: -0.0158 | BI31: 0.72278521 | BJ31: 0.73393124 | BL31: 35/36 | BM31: 2035 | BN31: 0.020773 | BO31: 1.4508743 | BP31: 1.4736734
AB32: 18 | AC32: Csa Salaries | AD32: 38/39 | AE32: Csa Salaries - 38/39 | AG32: =AH32/(1+C$10) -> 0.68750787 | AH32: =AI32/(1+D$10) -> 0.72016449 | AI32: =AJ32/(1+E$10) -> 0.74537025 | AJ32: =AK32/(1+F$10) -> 0.7640045 | AK32: =AL32/(1+G$10) -> 0.78157661 | AL32: =AM32/(1+H$10) -> 0.79955287 | AM32: =AN32/(1+I$10) -> 0.81794259 | AN32: =AO32/(1+J$10) -> 0.83675527 | ... AV32: =AW32/(1+R$10) -> 0.98039216 | AW32: 1 | AX32: =AW32*(1+T$10) -> 1.02 | AY32: =AX32*(1+U$10) -> 1.0404 | AZ32: =AY32*(1+V$10) -> 1.061208 | BA32: =AZ32*(1+W$10) -> 1.0824322 | BB32: =BA32*(1+X$10) -> 1.1040808 | BC32: =BB32*(1+Y$10) -> 1.1261624 | BF32: 16 | BG32: 2005 | BH32: 0.00050010089 | BI32: 0.72314667 | BJ32: 0.73420276 | BL32: 36/37 | BM32: 2036 | BN32: 0.020773 | BO32: 1.4810133 | BP32: 1.5043038
AB33: 19 | AC33: Csa Salaries | AD33: 39/40 | AE33: Csa Salaries - 39/40 | AG33: =AH33/(1+C$10) -> 0.67402732 | AH33: =AI33/(1+D$10) -> 0.70604362 | AI33: =AJ33/(1+E$10) -> 0.73075515 | AJ33: =AK33/(1+F$10) -> 0.74902402 | AK33: =AL33/(1+G$10) -> 0.76625158 | AL33: =AM33/(1+H$10) -> 0.78387536 | AM33: =AN33/(1+I$10) -> 0.8019045 | AN33: =AO33/(1+J$10) -> 0.8203483 | ... AW33: =AX33/(1+S$10) -> 0.98039216 | AX33: 1 | AY33: =AX33*(1+U$10) -> 1.02 | AZ33: =AY33*(1+V$10) -> 1.0404 | BA33: =AZ33*(1+W$10) -> 1.061208 | BB33: =BA33*(1+X$10) -> 1.0824322 | BC33: =BB33*(1+Y$10) -> 1.1040808 | BF33: 17 | BG33: 2006 | BH33: 0.0073646938 | BI33: 0.72847243 | BJ33: 0.74264914 | BL33: 37/38 | BM33: 2037 | BN33: 0.020773 | BO33: 1.5117784 | BP33: 1.5355589
AB34: 20 | AC34: Csa Salaries | AD34: 40/41 | AE34: Csa Salaries - 40/41 | AG34: =AH34/(1+C$10) -> 0.6608111 | AH34: =AI34/(1+D$10) -> 0.69219963 | AI34: =AJ34/(1+E$10) -> 0.71642661 | AJ34: =AK34/(1+F$10) -> 0.73433728 | AK34: =AL34/(1+G$10) -> 0.75122704 | AL34: =AM34/(1+H$10) -> 0.76850526 | AM34: =AN34/(1+I$10) -> 0.78618088 | AN34: =AO34/(1+J$10) -> 0.80426304 | ... AX34: =AY34/(1+T$10) -> 0.98039216 | AY34: 1 | AZ34: =AY34*(1+V$10) -> 1.02 | BA34: =AZ34*(1+W$10) -> 1.0404 | BB34: =BA34*(1+X$10) -> 1.061208 | BC34: =BB34*(1+Y$10) -> 1.0824322 | BF34: 18 | BG34: 2007 | BH34: 0.024658943 | BI34: 0.74643579 | BJ34: 0.75695431 | BL34: 38/39 | BM34: 2038 | BN34: 0.020773 | BO34: 1.5431825 | BP34: 1.5674521
AB35: 21 | AC35: Csa Salaries | AD35: 41/42 | AE35: Csa Salaries - 41/42 | AG35: =AH35/(1+C$10) -> 0.64785402 | AH35: =AI35/(1+D$10) -> 0.67862708 | AI35: =AJ35/(1+E$10) -> 0.70237903 | AJ35: =AK35/(1+F$10) -> 0.71993851 | AK35: =AL35/(1+G$10) -> 0.73649709 | AL35: =AM35/(1+H$10) -> 0.75343653 | AM35: =AN35/(1+I$10) -> 0.77076557 | AN35: =AO35/(1+J$10) -> 0.78849318 | ... AY35: =AZ35/(1+U$10) -> 0.98039216 | AZ35: 1 | BA35: =AZ35*(1+W$10) -> 1.02 | BB35: =BA35*(1+X$10) -> 1.0404 | BC35: =BB35*(1+Y$10) -> 1.061208 | BF35: 19 | BG35: 2008 | BH35: 0.047893964 | BI35: 0.78218556 | BJ35: 0.79016214 | BL35: 39/40 | BM35: 2039 | BN35: 0.020773 | BO35: 1.5752391 | BP35: 1.5999969
AB36: 22 | AC36: CSA Mgt | AD36: 22/23 | AE36: CSA Mgt - 22/23 | AG36: 1 | AH36: =AG36*(1+D$11) -> 1.037 | AI36: =AH36*(1+E$11) -> 1.061888 | AJ36: =AI36*(1+F$11) -> 1.0852495 | AK36: =AJ36*(1+G$11) -> 1.1069545 | AL36: =AK36*(1+H$11) -> 1.1290936 | AM36: =AL36*(1+I$11) -> 1.1516755 | AN36: =AM36*(1+J$11) -> 1.174709 | AO36: =AN36*(1+K$11) -> 1.1982032 | ... AZ36: =AY36*(1+V$11) -> 1.489815 | BF36: 20 | BG36: 2009 | BH36: 0.040711829 | BI36: 0.81402976 | BJ36: 0.82098226 | BL36: 40/41 | BM36: 2040 | BN36: 0.020773 | BO36: 1.6079615 | BP36: 1.6332069
AB37: 23 | AC37: CSA Mgt | AD37: 23/24 | AE37: CSA Mgt - 23/24 | AG37: =AH37/(1+C$11) -> 0.94055681 | AH37: 1 | AI37: =AH37*(1+E$11) -> 1.024 | AJ37: =AI37*(1+F$11) -> 1.046528 | AK37: =AJ37*(1+G$11) -> 1.0674586 | AL37: =AK37*(1+H$11) -> 1.0888077 | AM37: =AL37*(1+I$11) -> 1.1105839 | AN37: =AM37*(1+J$11) -> 1.1327956 | AO37: =AN37*(1+K$11) -> 1.1554515 | AP37: =AO37*(1+L$11) -> 1.1785605 | ... BC37: =BB37*(1+Y$11) -> 1.5245937 | BD37: =IFERROR(BC37*(1+Z$11),BC37) -> 1.5245937 | BF37: 21 | BG37: 2010 | BH37: -0.019 | BI37: 0.79856319 | BJ37: 0.80576087 | BL37: 41/42 | BM37: 2041 | BN37: 0.020773 | BO37: 1.6413637 | BP37: 1.6670964
AB38: 24 | AC38: CSA Mgt | AD38: 24/25 | AE38: CSA Mgt - 24/25 | AG38: =AH38/(1+C$11) -> 0.90699789 | AH38: =AI38/(1+D$11) -> 0.96432015 | AI38: 1 | AJ38: =AI38*(1+F$11) -> 1.022 | AK38: =AJ38*(1+G$11) -> 1.04244 | AL38: =AK38*(1+H$11) -> 1.0632888 | AM38: =AL38*(1+I$11) -> 1.0845546 | AN38: =AM38*(1+J$11) -> 1.1062457 | AO38: =AN38*(1+K$11) -> 1.1283706 | AP38: =AO38*(1+L$11) -> 1.150938 | AQ38: =AP38*(1+M$11) -> 1.1739568 | ... AZ38: =AY38*(1+V$11) -> 1.402987 | BF38: 22 | BG38: 2011 | BH38: 0.045 | BI38: 0.83449854 | BJ38: 0.84053575 | BL38: 42/43 | BM38: 2042 | BN38: 0.020773 | BO38: 1.6754597 | BP38: 1.7017801
AB39: 25 | AC39: CSA Mgt | AD39: 25/26 | AE39: CSA Mgt - 25/26 | AG39: =AH39/(1+C$11) -> 0.88574012 | AH39: =AI39/(1+D$11) -> 0.9417189 | AI39: =AJ39/(1+E$11) -> 0.9765625 | AJ39: 1 | AK39: =AJ39*(1+G$11) -> 1.02 | AL39: =AK39*(1+H$11) -> 1.0404 | AM39: =AL39*(1+I$11) -> 1.061208 | AN39: =AM39*(1+J$11) -> 1.0824322 | AO39: =AN39*(1+K$11) -> 1.1040808 | AP39: =AO39*(1+L$11) -> 1.1261624 | AQ39: =AP39*(1+M$11) -> 1.1486857 | AR39: =AQ39*(1+N$11) -> 1.1716594 | ... AZ39: =AY39*(1+V$11) -> 1.3727857 | BF39: 23 | BG39: 2012 | BH39: 0.016629 | BI39: 0.84837541 | BJ39: 0.855424 | BL39: 43/44 | BM39: 2043 | BN39: 0.020773 | BO39: 1.7102641 | BP39: 1.7372725
AB40: 26 | AC40: CSA Mgt | AD40: 26/27 | AE40: CSA Mgt - 26/27 | AG40: =AH40/(1+C$11) -> 0.86667331 | AH40: =AI40/(1+D$11) -> 0.92144707 | AI40: =AJ40/(1+E$11) -> 0.95554061 | AJ40: =AK40/(1+F$11) -> 0.97847358 | AK40: 1 | AL40: =AK40*(1+H$11) -> 1.02 | AM40: =AL40*(1+I$11) -> 1.0404 | AN40: =AM40*(1+J$11) -> 1.061208 | AO40: =AN40*(1+K$11) -> 1.0824322 | AP40: =AO40*(1+L$11) -> 1.1040808 | AQ40: =AP40*(1+M$11) -> 1.1261624 | AR40: =AQ40*(1+N$11) -> 1.1486857 | AS40: =AR40*(1+O$11) -> 1.1716594 | ... AZ40: =AY40*(1+V$11) -> 1.3458683 | BF40: 24 | BG40: 2013 | BH40: 0.09075 | BI40: 0.92536548 | BJ40: 0.93537912 | BL40: 44/45 | BM40: 2044 | BN40: 0.020773 | BO40: 1.7457914 | BP40: 1.7732842
AB41: 27 | AC41: CSA Mgt | AD41: 27/28 | AE41: CSA Mgt - 27/28 | AG41: =AH41/(1+C$11) -> 0.84967972 | AH41: =AI41/(1+D$11) -> 0.90337948 | AI41: =AJ41/(1+E$11) -> 0.93680452 | AJ41: =AK41/(1+F$11) -> 0.95928782 | AK41: =AL41/(1+G$11) -> 0.98039216 | AL41: 1 | AM41: =AL41*(1+I$11) -> 1.02 | AN41: =AM41*(1+J$11) -> 1.0404 | AO41: =AN41*(1+K$11) -> 1.061208 | AP41: =AO41*(1+L$11) -> 1.0824322 | AQ41: =AP41*(1+M$11) -> 1.1040808 | AR41: =AQ41*(1+N$11) -> 1.1261624 | AS41: =AR41*(1+O$11) -> 1.1486857 | AT41: =AS41*(1+P$11) -> 1.1716594 | ... AZ41: =AY41*(1+V$11) -> 1.3194788 | BF41: 25 | BG41: 2014 | BH41: -0.031298 | BI41: 0.89640339 | BJ41: 0.90805021
AB42: 28 | AC42: CSA Mgt | AD42: 28/29 | AE42: CSA Mgt - 28/29 | AG42: =AH42/(1+C$11) -> 0.83301933 | AH42: =AI42/(1+D$11) -> 0.88566615 | AI42: =AJ42/(1+E$11) -> 0.9184358 | AJ42: =AK42/(1+F$11) -> 0.94047826 | AK42: =AL42/(1+G$11) -> 0.96116878 | AL42: =AM42/(1+H$11) -> 0.98039216 | AM42: 1 | AN42: =AM42*(1+J$11) -> 1.02 | AO42: =AN42*(1+K$11) -> 1.0404 | AP42: =AO42*(1+L$11) -> 1.061208 | AQ42: =AP42*(1+M$11) -> 1.0824322 | AR42: =AQ42*(1+N$11) -> 1.1040808 | AS42: =AR42*(1+O$11) -> 1.1261624 | AT42: =AS42*(1+P$11) -> 1.1486857 | AU42: =AT42*(1+Q$11) -> 1.1716594 | ... AZ42: =AY42*(1+V$11) -> 1.2936066 | BF42: 26 | BG42: 2015 | BH42: 0.036389 | BI42: 0.92902262 | BJ42: 0.94017744
AB43: 29 | AC43: CSA Mgt | AD43: 29/30 | AE43: CSA Mgt - 29/30 | AG43: =AH43/(1+C$11) -> 0.81668562 | AH43: =AI43/(1+D$11) -> 0.86830015 | AI43: =AJ43/(1+E$11) -> 0.90042726 | AJ43: =AK43/(1+F$11) -> 0.92203751 | AK43: =AL43/(1+G$11) -> 0.94232233 | AL43: =AM43/(1+H$11) -> 0.96116878 | AM43: =AN43/(1+I$11) -> 0.98039216 | AN43: 1 | AO43: =AN43*(1+K$11) -> 1.02 | AP43: =AO43*(1+L$11) -> 1.0404 | AQ43: =AP43*(1+M$11) -> 1.061208 | AR43: =AQ43*(1+N$11) -> 1.0824322 | AS43: =AR43*(1+O$11) -> 1.1040808 | AT43: =AS43*(1+P$11) -> 1.1261624 | AU43: =AT43*(1+Q$11) -> 1.1486857 | AV43: =AU43*(1+R$11) -> 1.1716594 | ... AZ43: =AY43*(1+V$11) -> 1.2682418 | BF43: 27 | BG43: 2016 | BH43: 0.004839 | BI43: 0.93351816 | BJ43: 0.9459298
