Workbook
Name Costing_Phases: '2 - Phasing Nomenclature'!$F$13:$F$26
Name Costing_Phases_PM: '2 - Phasing Nomenclature'!$I$13:$I$25

Sheet Cover Page
B3: CSA-FIN-RD-0589
B4: Version Draft 1.0
B5: 46286
B8: Cost Analysis Data Requirement (CADRe)
D9: CADRe Part C - Essential Programmatic Inputs
D10: ORCA (Ocean Reconnaissance and Chemistry Analyzer)
C16: Prepared by ORCA Project Team
C17: Reviewed by [TBD] | D17: TBD

Sheet Table of Contents
A1: ORCA CADRe Part C - Table of Contents
A3: # | B3: Sheet
A4: 1 | B4: Cover Page
A5: 2 | B5: 1 - Change History
A6: 3 | B6: 4d - CBS in JS format
A7: 4 | B7: 2 - Phasing Nomenclature
A8: 5 | B8: 3 - Phase Durations
A9: 6 | B9: PM's sched Scenarios
A10: 7 | B10: GR&A
A11: 8 | B11: 4 - RAM LoE
A12: 9 | B12: 5 - Risk Register
A13: 10 | B13: Risk Breakdown Structure
A14: 11 | B14: Raw Labour Rates
A15: 12 | B15: Labour Rates lookup
... A17: 14 | B17: Inflation Rate

Sheet 1 - Change History
A1: ` Table of Contents
A3: 2. Version Control - Baseline Tracker
A4: Purpose: | B4: To track the baseline across time
B5: hold the major and minor releases of the baseline
B9: Change history and associated files that contain the relevant data | G9: Reserved
B10: File Number | C10: Date | D10: File Version | E10: Author | F10: Changes | G10: Parent Baseline Name | H10: Baseline ID
G11: ORCA @ PREP1 | H11: 1
G12: ORCA @ KDP-0 | H12: 2
E13: MB | F13: Rebaseline: cruise duration increased following updated Jupiter gravity-assist trajectory analysis. | G13: ORCA @ MDR#2 | H13: 3
G14: ORCA @ PREP2 | H14: 4
G15: ORCA @ KDP-A | H15: 5
B16: CSA-FIN-RD-0587 | C16: 48933 | D16: Draft 1 | E16: MB | F16: Initial document ahead of Phase B | G16: ORCA @ KDP-B | H16: 6
G17: ORCA @ PDR | H17: 7
G18: ORCA @ CDR | H18: 8
B19: CSA-FIN-RD-0590 | C19: 46286 | D19: Draft 1 | E19: MB | F19: Update ahead of Gate 4: PDR and CDR complete, System Integration Review baseline. | G19: ORCA @ SIR | H19: 9 | I19: <<--- We are here now
G20: ORCA @ Launch (as flown) | H20: 10
G21: ORCA @ CR | H21: 11
G22: ORCA @ KDP-X | H22: 12
G23: ORCA @ end of life | H23: 13

Sheet 4d - CBS in JS format
A1: ` Table of Contents
A3: 4d. CBS (as self referencing list) for use as a javascript array
A4: Why we we asking:
B5: this page is auto-generated and used for drawing it out
E6: Self referencing list for dtree
A8: UID | B8: Parent ID | C8: Level | D8: Node Name | E8: CBS Code | F8: Depth | G8: Icon | H8: Notes | J8: Javascript Code | N8: Depth
A9: 1 | B9: -1 | C9: 1 | D9: Space Missions | F9: Taxon 1 | G9: Box.png | J9: ="datatable["&A9-1&"] = new Array(""" & A9 &""",""" & B9 &""",""" & D9 & """,""" & C9&""","""&""&G9&""");" -> datatable[0] = new Array("1","-1","Space Missions","1","Box.png"); | N9: Taxon 1
A10: 2 | B10: =A9 -> 1 | C10: 2 | D10: EO SAR Missions | F10: Taxon 2 | G10: EO.png | J10: ="datatable["&A10-1&"] = new Array(""" & A10 &""",""" & B10 &""",""" & D10 & """,""" & C10&""","""&""&G10&""");" -> datatable[1] = new Array("2","1","EO SAR Missions","2","EO.png"); | N10: Taxon 2
A11: =A10+1 -> 3 | B11: =A10 -> 2 | C11: 3 | D11: Radarsat Portfolio | F11: Phylum | G11: Pouch.png | J11: ="datatable["&A11-1&"] = new Array(""" & A11 &""",""" & B11 &""",""" & D11 & """,""" & C11&""","""&""&G11&""");" -> datatable[2] = new Array("3","2","Radarsat Portfolio","3","Pouch.png"); | N11: Phylum
A12: =A11+1 -> 4 | B12: =A$6 -> 0 | C12: 4 | D12: Radarsat 1 | F12: Mission | G12: Satellite.png | J12: ="datatable["&A12-1&"] = new Array(""" & A12 &""",""" & B12 &""",""" & D12 & """,""" & C12&""","""&""&G12&""");" -> datatable[3] = new Array("4","0","Radarsat 1","4","Satellite.png"); | N12: Mission
A13: =A12+1 -> 5 | B13: =A$6 -> 0 | C13: 4 | D13: Radarsat 2 | F13: Mission | G13: Satellite.png | J13: ="datatable["&A13-1&"] = new Array(""" & A13 &""",""" & B13 &""",""" & D13 & """,""" & C13&""","""&""&G13&""");" -> datatable[4] = new Array("5","0","Radarsat 2","4","Satellite.png"); | N13: Design Reference Mission
A14: =A13+1 -> 6 | B14: =A$6 -> 0 | C14: 4 | D14: Radarsat Constellation Mission | F14: Mission | G14: Satellite.png | J14: ="datatable["&A14-1&"] = new Array(""" & A14 &""",""" & B14 &""",""" & D14 & """,""" & C14&""","""&""&G14&""");" -> datatable[5] = new Array("6","0","Radarsat Constellation Mission","4","Satellite.png"); | N14: Segment
A15: =A14+1 -> 7 | B15: =A$6 -> 0 | C15: 4 | D15: Radarsat+ Replenishment | E15: 1 | F15: Mission | G15: Satellite.png | J15: ="datatable["&A15-1&"] = new Array(""" & A15 &""",""" & B15 &""",""" & D15 & """,""" & C15&""","""&""&G15&""");" -> datatable[6] = new Array("7","0","Radarsat+ Replenishment","4","Satellite.png"); | N15: System of Systems
A16: =A15+1 -> 8 | B16: =A$6 -> 0 | C16: 4 | D16: Radarsat+ Next Generation | F16: Mission | G16: Satellite.png | J16: ="datatable["&A16-1&"] = new Array(""" & A16 &""",""" & B16 &""",""" & D16 & """,""" & C16&""","""&""&G16&""");" -> datatable[7] = new Array("8","0","Radarsat+ Next Generation","4","Satellite.png"); | N16: System
A17: =A16+1 -> 9 | B17: =A$10 -> 2 | C17: 5 | D17: Analysis Scenario 1: RCM Proxy | F17: Design Reference Mission | G17: Scenario.png | J17: ="datatable["&A17-1&"] = new Array(""" & A17 &""",""" & B17 &""",""" & D17 & """,""" & C17&""","""&""&G17&""");" -> datatable[8] = new Array("9","2","Analysis Scenario 1: RCM Proxy","5","Scenario.png"); | N17: Subsystem
A18: =A17+1 -> 10 | B18: =A$10 -> 2 | C18: 5 | D18: Analysis Scenario 2: RCM+ | F18: Design Reference Mission | G18: Scenario.png | J18: ="datatable["&A18-1&"] = new Array(""" & A18 &""",""" & B18 &""",""" & D18 & """,""" & C18&""","""&""&G18&""");" -> datatable[9] = new Array("10","2","Analysis Scenario 2: RCM+","5","Scenario.png"); | N18: Assembly
A19: =A18+1 -> 11 | B19: =A$10 -> 2 | C19: 5 | D19: Analysis Scenario 3: Airbus concept | F19: Design Reference Mission | G19: Scenario.png | J19: ="datatable["&A19-1&"] = new Array(""" & A19 &""",""" & B19 &""",""" & D19 & """,""" & C19&""","""&""&G19&""");" -> datatable[10] = new Array("11","2","Analysis Scenario 3: Airbus concept","5","Scenario.png"); | N19: Component
A20: =A19+1 -> 12 | B20: =A$10 -> 2 | C20: 5 | D20: Analysis Scenario 4: MDA Chorus Data Buy | F20: Design Reference Mission | G20: Scenario.png | J20: ="datatable["&A20-1&"] = new Array(""" & A20 &""",""" & B20 &""",""" & D20 & """,""" & C20&""","""&""&G20&""");" -> datatable[11] = new Array("12","2","Analysis Scenario 4: MDA Chorus Data Buy","5","Scenario.png");
A21: =A20+1 -> 13 | B21: =A$10 -> 2 | C21: 5 | D21: Analysis Scenario 5: MDA Chorus+ | F21: Design Reference Mission | G21: Scenario.png | J21: ="datatable["&A21-1&"] = new Array(""" & A21 &""",""" & B21 &""",""" & D21 & """,""" & C21&""","""&""&G21&""");" -> datatable[12] = new Array("13","2","Analysis Scenario 5: MDA Chorus+","5","Scenario.png");
A22: =A21+1 -> 14 | B22: =A$10 -> 2 | C22: 5 | D22: Analysis Scenario 6: Airbus Sentinel 2 | F22: Design Reference Mission | G22: Scenario.png | J22: ="datatable["&A22-1&"] = new Array(""" & A22 &""",""" & B22 &""",""" & D22 & """,""" & C22&""","""&""&G22&""");" -> datatable[13] = new Array("14","2","Analysis Scenario 6: Airbus Sentinel 2","5","Scenario.png");
A23: =A22+1 -> 15 | B23: =A$16 -> 8 | C23: 6 | D23: Government Overhead and Oversight | E23: 1.1 | F23: Segment | G23: Government.png | H23: This WBS includes all CSA Oversight, OGD salaries, and basic overhead for the care and maintenance of CSA staff | J23: ="datatable["&A23-1&"] = new Array(""" & A23 &""",""" & B23 &""",""" & D23 & """,""" & C23&""","""&""&G23&""");" -> datatable[14] = new Array("15","8","Government Overhead and Oversight","6","Government.png");
A24: =A23+1 -> 16 | B24: =A$16 -> 8 | C24: 6 | D24: Space Segment | E24: 1.2 | F24: Segment | G24: Satellite.png | H24: The Space Segment includes things we launch into space | J24: ="datatable["&A24-1&"] = new Array(""" & A24 &""",""" & B24 &""",""" & D24 & """,""" & C24&""","""&""&G24&""");" -> datatable[15] = new Array("16","8","Space Segment","6","Satellite.png");
A25: =A24+1 -> 17 | B25: =A$16 -> 8 | C25: 6 | D25: Launch Segment | E25: 1.3 | F25: Segment | G25: Rocket.png | H25: The launch segment includes the launch vehicle and seom support services | J25: ="datatable["&A25-1&"] = new Array(""" & A25 &""",""" & B25 &""",""" & D25 & """,""" & C25&""","""&""&G25&""");" -> datatable[16] = new Array("17","8","Launch Segment","6","Rocket.png");
A26: =A25+1 -> 18 | B26: =A$16 -> 8 | C26: 6 | D26: Ground Segment | E26: 1.4 | F26: Segment | G26: Facility.png | H26: The ground segment includes the planning desgin and development of the GS, but not the Ops | J26: ="datatable["&A26-1&"] = new Array(""" & A26 &""",""" & B26 &""",""" & D26 & """,""" & C26&""","""&""&G26&""");" -> datatable[17] = new Array("18","8","Ground Segment","6","Facility.png");
A27: =A26+1 -> 19 | B27: =A$16 -> 8 | C27: 6 | D27: Ops Segment | E27: 1.5 | F27: Segment | G27: Ops.png | H27: Ops includes SatOps, Mission Ops, Science Ops - typically contracts | J27: ="datatable["&A27-1&"] = new Array(""" & A27 &""",""" & B27 &""",""" & D27 & """,""" & C27&""","""&""&G27&""");" -> datatable[18] = new Array("19","8","Ops Segment","6","Ops.png");
A28: =A27+1 -> 20 | B28: =A$16 -> 8 | C28: 6 | D28: Science Segment | E28: 1.6 | F28: Segment | G28: Science.png | H28: Typically G&C | J28: ="datatable["&A28-1&"] = new Array(""" & A28 &""",""" & B28 &""",""" & D28 & """,""" & C28&""","""&""&G28&""");" -> datatable[19] = new Array("20","8","Science Segment","6","Science.png");
A29: =A28+1 -> 21 | B29: =A$18 -> 10 | C29: 7 | D29: Gov't Oversight (Salaries and EBP) | E29: 1.1.1 | F29: System of Systems | G29: Government.png | J29: ="datatable["&A29-1&"] = new Array(""" & A29 &""",""" & B29 &""",""" & D29 & """,""" & C29&""","""&""&G29&""");" -> datatable[20] = new Array("21","10","Gov't Oversight (Salaries and EBP)","7","Government.png");
A30: =A29+1 -> 22 | B30: =A$18 -> 10 | C30: 7 | D30: Government Overhead | E30: 1.1.2 | F30: System of Systems | G30: Government.png | J30: ="datatable["&A30-1&"] = new Array(""" & A30 &""",""" & B30 &""",""" & D30 & """,""" & C30&""","""&""&G30&""");" -> datatable[21] = new Array("22","10","Government Overhead","7","Government.png");
A31: =A30+1 -> 23 | B31: =A29 -> 21 | C31: 8 | D31: CSA Oversight | E31: 1.1.1.1 | F31: System | G31: Government.png | J31: ="datatable["&A31-1&"] = new Array(""" & A31 &""",""" & B31 &""",""" & D31 & """,""" & C31&""","""&""&G31&""");" -> datatable[22] = new Array("23","21","CSA Oversight","8","Government.png");
A32: =A31+1 -> 24 | B32: =A29 -> 21 | C32: 8 | D32: OGD Oversight | E32: 1.1.1.2 | F32: System | G32: Government.png | J32: ="datatable["&A32-1&"] = new Array(""" & A32 &""",""" & B32 &""",""" & D32 & """,""" & C32&""","""&""&G32&""");" -> datatable[23] = new Array("24","21","OGD Oversight","8","Government.png");
A33: =A32+1 -> 25 | B33: =A31 -> 23 | C33: 9 | D33: CSA Project Team | E33: 1.1.1.1.1 | F33: Subsystem | G33: Government.png | H33: This CBS contains all salaries associated with the RAM of the Project team | J33: ="datatable["&A33-1&"] = new Array(""" & A33 &""",""" & B33 &""",""" & D33 & """,""" & C33&""","""&""&G33&""");" -> datatable[24] = new Array("25","23","CSA Project Team","9","Government.png");
A34: =A33+1 -> 26 | B34: =A31 -> 23 | C34: 9 | D34: CSA Internal Services | E34: 1.1.1.1.2 | F34: Subsystem | G34: Government.png | H34: This CBS contains all salaries associated with CSA internal services (finance, HR, audit, eval, policy, Executives, IM, IT, contracts, shipping, etc) | J34: ="datatable["&A34-1&"] = new Array(""" & A34 &""",""" & B34 &""",""" & D34 & """,""" & C34&""","""&""&G34&""");" -> datatable[25] = new Array("26","23","CSA Internal Services","9","Government.png");
A35: =A34+1 -> 27 | B35: =A32 -> 24 | C35: 9 | D35: OGD Internal Services by MOU | E35: 1.1.1.2.1 | F35: Subsystem | G35: Government.png | J35: ="datatable["&A35-1&"] = new Array(""" & A35 &""",""" & B35 &""",""" & D35 & """,""" & C35&""","""&""&G35&""");" -> datatable[26] = new Array("27","24","OGD Internal Services by MOU","9","Government.png");
A36: =A35+1 -> 28 | B36: =A32 -> 24 | C36: 9 | D36: OGD User Departments by MOU (RAM portion) | E36: 1.1.1.2.2 | F36: Subsystem | G36: Government.png | J36: ="datatable["&A36-1&"] = new Array(""" & A36 &""",""" & B36 &""",""" & D36 & """,""" & C36&""","""&""&G36&""");" -> datatable[27] = new Array("28","24","OGD User Departments by MOU (RAM portion)","9","Government.png");
A37: =A36+1 -> 29 | B37: =A$29 -> 21 | C37: 10 | D37: Shared Services | E37: 1.1.1.2.1.1 | F37: Assembly | G37: Government.png | J37: ="datatable["&A37-1&"] = new Array(""" & A37 &""",""" & B37 &""",""" & D37 & """,""" & C37&""","""&""&G37&""");" -> datatable[28] = new Array("29","21","Shared Services","10","Government.png");
A38: =A37+1 -> 30 | B38: =A$29 -> 21 | C38: 10 | D38: SPAC | E38: 1.1.1.2.1.2 | F38: Assembly | G38: Government.png | J38: ="datatable["&A38-1&"] = new Array(""" & A38 &""",""" & B38 &""",""" & D38 & """,""" & C38&""","""&""&G38&""");" -> datatable[29] = new Array("30","21","SPAC","10","Government.png");
A39: =A38+1 -> 31 | B39: =A$29 -> 21 | C39: 10 | D39: Justice Canada | E39: 1.1.1.2.1.3 | F39: Assembly | G39: Government.png | J39: ="datatable["&A39-1&"] = new Array(""" & A39 &""",""" & B39 &""",""" & D39 & """,""" & C39&""","""&""&G39&""");" -> datatable[30] = new Array("31","21","Justice Canada","10","Government.png");
A40: =A39+1 -> 32 | B40: =A$31 -> 23 | C40: 10 | D40: ECCC | E40: 1.1.1.2.2.1 | F40: Assembly | G40: Government.png | J40: ="datatable["&A40-1&"] = new Array(""" & A40 &""",""" & B40 &""",""" & D40 & """,""" & C40&""","""&""&G40&""");" -> datatable[31] = new Array("32","23","ECCC","10","Government.png");
A41: =A40+1 -> 33 | B41: =A$31 -> 23 | C41: 10 | D41: NRCAN | E41: 1.1.1.2.2.2 | F41: Assembly | G41: Government.png | J41: ="datatable["&A41-1&"] = new Array(""" & A41 &""",""" & B41 &""",""" & D41 & """,""" & C41&""","""&""&G41&""");" -> datatable[32] = new Array("33","23","NRCAN","10","Government.png");
A42: =A41+1 -> 34 | B42: =A$31 -> 23 | C42: 10 | D42: DND | E42: 1.1.1.2.2.3 | F42: Assembly | G42: Government.png | J42: ="datatable["&A42-1&"] = new Array(""" & A42 &""",""" & B42 &""",""" & D42 & """,""" & C42&""","""&""&G42&""");" -> datatable[33] = new Array("34","23","DND","10","Government.png");
A43: =A42+1 -> 35 | B43: =A33 -> 25 | C43: 11 | D43: RAM per Person per FY and Phase | E43: 1.1.1.1.1.1 | F43: Component | G43: Government.png | J43: ="datatable["&A43-1&"] = new Array(""" & A43 &""",""" & B43 &""",""" & D43 & """,""" & C43&""","""&""&G43&""");" -> datatable[34] = new Array("35","25","RAM per Person per FY and Phase","11","Government.png");
A44: =A43+1 -> 36 | B44: =A$33 -> 25 | C44: 11 | D44: PSPC Procurement Services | E44: 1.1.1.2.1.2.1 | F44: Component | G44: Government.png | J44: ="datatable["&A44-1&"] = new Array(""" & A44 &""",""" & B44 &""",""" & D44 & """,""" & C44&""","""&""&G44&""");" -> datatable[35] = new Array("36","25","PSPC Procurement Services","11","Government.png");
A45: =A44+1 -> 37 | B45: =A$33 -> 25 | C45: 11 | D45: PSPC Fairness Monitor | E45: 1.1.1.2.1.2.2 | F45: Component | G45: Government.png | J45: ="datatable["&A45-1&"] = new Array(""" & A45 &""",""" & B45 &""",""" & D45 & """,""" & C45&""","""&""&G45&""");" -> datatable[36] = new Array("37","25","PSPC Fairness Monitor","11","Government.png");
A46: =A45+1 -> 38 | B46: =A39 -> 31 | C46: 11 | D46: Legal Services | E46: 1.1.1.2.1.3.1 | F46: Component | G46: Government.png | J46: ="datatable["&A46-1&"] = new Array(""" & A46 &""",""" & B46 &""",""" & D46 & """,""" & C46&""","""&""&G46&""");" -> datatable[37] = new Array("38","31","Legal Services","11","Government.png");
A47: =A46+1 -> 39 | B47: =A30 -> 22 | C47: 8 | D47: CSA Overhead | E47: 1.1.2.1 | F47: System | G47: Government.png | J47: ="datatable["&A47-1&"] = new Array(""" & A47 &""",""" & B47 &""",""" & D47 & """,""" & C47&""","""&""&G47&""");" -> datatable[38] = new Array("39","22","CSA Overhead","8","Government.png");
A48: =A47+1 -> 40 | B48: =A$42 -> 34 | C48: 9 | D48: IS Management Overhead | E48: 1.1.2.1.1 | F48: Subsystem | G48: Government.png | J48: ="datatable["&A48-1&"] = new Array(""" & A48 &""",""" & B48 &""",""" & D48 & """,""" & C48&""","""&""&G48&""");" -> datatable[39] = new Array("40","34","IS Management Overhead ","9","Government.png");
A49: =A48+1 -> 41 | B49: =A$42 -> 34 | C49: 9 | D49: Management Consulting Services | E49: 1.1.2.1.2 | F49: Subsystem | G49: Government.png | J49: ="datatable["&A49-1&"] = new Array(""" & A49 &""",""" & B49 &""",""" & D49 & """,""" & C49&""","""&""&G49&""");" -> datatable[40] = new Array("41","34","Management Consulting Services","9","Government.png");
A50: =A49+1 -> 42 | B50: =A$42 -> 34 | C50: 9 | D50: Temporary Help | E50: 1.1.2.1.3 | F50: Subsystem | G50: Government.png | J50: ="datatable["&A50-1&"] = new Array(""" & A50 &""",""" & B50 &""",""" & D50 & """,""" & C50&""","""&""&G50&""");" -> datatable[41] = new Array("42","34","Temporary Help","9","Government.png");
A51: =A50+1 -> 43 | B51: =A$42 -> 34 | C51: 9 | D51: Students | E51: 1.1.2.1.4 | F51: Subsystem | G51: Government.png | H51: This CBS includes any students, FSWEP or PDF assisint Csa project team | J51: ="datatable["&A51-1&"] = new Array(""" & A51 &""",""" & B51 &""",""" & D51 & """,""" & C51&""","""&""&G51&""");" -> datatable[42] = new Array("43","34","Students","9","Government.png");
A52: =A51+1 -> 44 | B52: =A$42 -> 34 | C52: 9 | D52: Government Travel & Living | E52: 1.1.2.1.5 | F52: Subsystem | G52: Government.png | H52: This CBS includes any government Travel and Living expenses | J52: ="datatable["&A52-1&"] = new Array(""" & A52 &""",""" & B52 &""",""" & D52 & """,""" & C52&""","""&""&G52&""");" -> datatable[43] = new Array("44","34","Government Travel & Living","9","Government.png");
A53: =A52+1 -> 45 | B53: =A$42 -> 34 | C53: 9 | D53: Translation | E53: 1.1.2.1.6 | F53: Subsystem | G53: Government.png | H53: This CBS includes any translation costs | J53: ="datatable["&A53-1&"] = new Array(""" & A53 &""",""" & B53 &""",""" & D53 & """,""" & C53&""","""&""&G53&""");" -> datatable[44] = new Array("45","34","Translation","9","Government.png");
A54: =A53+1 -> 46 | B54: =A$42 -> 34 | C54: 9 | D54: Shipping | E54: 1.1.2.1.7 | F54: Subsystem | G54: Government.png | H54: This CBs includes any shipping cost, but not shipping flight HW which is under space segment | J54: ="datatable["&A54-1&"] = new Array(""" & A54 &""",""" & B54 &""",""" & D54 & """,""" & C54&""","""&""&G54&""");" -> datatable[45] = new Array("46","34","Shipping","9","Government.png");
A55: =A54+1 -> 47 | B55: =A$42 -> 34 | C55: 9 | D55: Software Licenses | E55: 1.1.2.1.8 | F55: Subsystem | G55: Government.png | H55: This CBS includes any COTs SW not flight Sw or ground SW | J55: ="datatable["&A55-1&"] = new Array(""" & A55 &""",""" & B55 &""",""" & D55 & """,""" & C55&""","""&""&G55&""");" -> datatable[46] = new Array("47","34","Software Licenses","9","Government.png");
A56: =A55+1 -> 48 | B56: =A$42 -> 34 | C56: 9 | D56: Public Outreach and STEM initiatives | E56: 1.1.2.1.9 | F56: Subsystem | G56: Government.png | H56: This CBS includes any public relations and STEM | J56: ="datatable["&A56-1&"] = new Array(""" & A56 &""",""" & B56 &""",""" & D56 & """,""" & C56&""","""&""&G56&""");" -> datatable[47] = new Array("48","34","Public Outreach and STEM initiatives","9","Government.png");
A57: =A56+1 -> 49 | B57: =A$42 -> 34 | C57: 9 | D57: Other Overhead (Specify) | E57: 1.1.2.1.10 | F57: Subsystem | G57: Government.png | H57: This CBS includes any other misc fees | J57: ="datatable["&A57-1&"] = new Array(""" & A57 &""",""" & B57 &""",""" & D57 & """,""" & C57&""","""&""&G57&""");" -> datatable[48] = new Array("49","34","Other Overhead (Specify)","9","Government.png");
A58: =A57+1 -> 50 | B58: =A$44 -> 36 | C58: 10 | D58: Consultants - Industrial Space Experts | E58: 1.1.2.1.2.1 | F58: Assembly | G58: Government.png | J58: ="datatable["&A58-1&"] = new Array(""" & A58 &""",""" & B58 &""",""" & D58 & """,""" & C58&""","""&""&G58&""");" -> datatable[49] = new Array("50","36","Consultants - Industrial Space Experts","10","Government.png");
A59: =A58+1 -> 51 | B59: =A$44 -> 36 | C59: 10 | D59: Consultants - Academia | E59: 1.1.2.1.2.2 | F59: Assembly | G59: Government.png | J59: ="datatable["&A59-1&"] = new Array(""" & A59 &""",""" & B59 &""",""" & D59 & """,""" & C59&""","""&""&G59&""");" -> datatable[50] = new Array("51","36","Consultants - Academia","10","Government.png");
A60: =A59+1 -> 52 | B60: =A$44 -> 36 | C60: 10 | D60: Consultants - Non-Space Experts | E60: 1.1.2.1.2.3 | F60: Assembly | G60: Government.png | J60: ="datatable["&A60-1&"] = new Array(""" & A60 &""",""" & B60 &""",""" & D60 & """,""" & C60&""","""&""&G60&""");" -> datatable[51] = new Array("52","36","Consultants - Non-Space Experts","10","Government.png");
A61: =A60+1 -> 53 | B61: 12 | C61: 6 | D61: Mission SEITPM and Support Equipment | F61: Segment | G61: SEITPM.png | J61: ="datatable["&A61-1&"] = new Array(""" & A61 &""",""" & B61 &""",""" & D61 & """,""" & C61&""","""&""&G61&""");" -> datatable[52] = new Array("53","12","Mission SEITPM and Support Equipment","6","SEITPM.png");
A62: =A61+1 -> 54 | B62: =A$56 -> 48 | C62: 7 | D62: Project Management | F62: System of Systems | G62: SEITPM.png | J62: ="datatable["&A62-1&"] = new Array(""" & A62 &""",""" & B62 &""",""" & D62 & """,""" & C62&""","""&""&G62&""");" -> datatable[53] = new Array("54","48","Project Management","7","SEITPM.png");
A63: =A62+1 -> 55 | B63: =A$56 -> 48 | C63: 7 | D63: Systems Engineering | F63: System of Systems | G63: SEITPM.png | J63: ="datatable["&A63-1&"] = new Array(""" & A63 &""",""" & B63 &""",""" & D63 & """,""" & C63&""","""&""&G63&""");" -> datatable[54] = new Array("55","48","Systems Engineering","7","SEITPM.png");
A64: =A63+1 -> 56 | B64: =A$56 -> 48 | C64: 7 | D64: Mission Assurance | F64: System of Systems | G64: SEITPM.png | J64: ="datatable["&A64-1&"] = new Array(""" & A64 &""",""" & B64 &""",""" & D64 & """,""" & C64&""","""&""&G64&""");" -> datatable[55] = new Array("56","48","Mission Assurance","7","SEITPM.png");
A65: =A64+1 -> 57 | B65: =A$56 -> 48 | C65: 7 | D65: Assembly, Integration and Testing | F65: System of Systems | G65: SEITPM.png | J65: ="datatable["&A65-1&"] = new Array(""" & A65 &""",""" & B65 &""",""" & D65 & """,""" & C65&""","""&""&G65&""");" -> datatable[56] = new Array("57","48","Assembly, Integration and Testing","7","SEITPM.png");
A66: =A65+1 -> 58 | B66: =A$56 -> 48 | C66: 7 | D66: Support Equipment | F66: System of Systems | G66: SEITPM.png | J66: ="datatable["&A66-1&"] = new Array(""" & A66 &""",""" & B66 &""",""" & D66 & """,""" & C66&""","""&""&G66&""");" -> datatable[57] = new Array("58","48","Support Equipment","7","SEITPM.png");
A67: =A66+1 -> 59 | B67: =A24 -> 16 | C67: 7 | D67: Space Vehicle 1 … i | F67: System of Systems | G67: Satellite.png | J67: ="datatable["&A67-1&"] = new Array(""" & A67 &""",""" & B67 &""",""" & D67 & """,""" & C67&""","""&""&G67&""");" -> datatable[58] = new Array("59","16","Space Vehicle 1 … i","7","Satellite.png");
A68: =A67+1 -> 60 | B68: =A67 -> 59 | C68: 8 | D68: Spacecraft SEITPM and Support Equipment | F68: System | G68: SEITPM.png | J68: ="datatable["&A68-1&"] = new Array(""" & A68 &""",""" & B68 &""",""" & D68 & """,""" & C68&""","""&""&G68&""");" -> datatable[59] = new Array("60","59","Spacecraft SEITPM and Support Equipment","8","SEITPM.png");
A69: =A68+1 -> 61 | B69: =A$63 -> 55 | C69: 9 | D69: Project Management | F69: Subsystem | G69: SEITPM.png | J69: ="datatable["&A69-1&"] = new Array(""" & A69 &""",""" & B69 &""",""" & D69 & """,""" & C69&""","""&""&G69&""");" -> datatable[60] = new Array("61","55","Project Management","9","SEITPM.png");
A70: =A69+1 -> 62 | B70: =A$63 -> 55 | C70: 9 | D70: Systems Engineering | F70: Subsystem | G70: SEITPM.png | J70: ="datatable["&A70-1&"] = new Array(""" & A70 &""",""" & B70 &""",""" & D70 & """,""" & C70&""","""&""&G70&""");" -> datatable[61] = new Array("62","55","Systems Engineering","9","SEITPM.png");
A71: =A70+1 -> 63 | B71: =A$63 -> 55 | C71: 9 | D71: Mission Assurance | F71: Subsystem | G71: SEITPM.png | J71: ="datatable["&A71-1&"] = new Array(""" & A71 &""",""" & B71 &""",""" & D71 & """,""" & C71&""","""&""&G71&""");" -> datatable[62] = new Array("63","55","Mission Assurance","9","SEITPM.png");
A72: =A71+1 -> 64 | B72: =A$63 -> 55 | C72: 9 | D72: Assembly, Integration and Testing | F72: Subsystem | G72: SEITPM.png | J72: ="datatable["&A72-1&"] = new Array(""" & A72 &""",""" & B72 &""",""" & D72 & """,""" & C72&""","""&""&G72&""");" -> datatable[63] = new Array("64","55","Assembly, Integration and Testing","9","SEITPM.png");
A73: =A72+1 -> 65 | B73: =A$63 -> 55 | C73: 9 | D73: Support Equipment | F73: Subsystem | G73: SEITPM.png | J73: ="datatable["&A73-1&"] = new Array(""" & A73 &""",""" & B73 &""",""" & D73 & """,""" & C73&""","""&""&G73&""");" -> datatable[64] = new Array("65","55","Support Equipment","9","SEITPM.png");
A74: =A73+1 -> 66 | B74: =A67 -> 59 | C74: 8 | D74: Bus/Platform | F74: System | G74: Widget.png | J74: ="datatable["&A74-1&"] = new Array(""" & A74 &""",""" & B74 &""",""" & D74 & """,""" & C74&""","""&""&G74&""");" -> datatable[65] = new Array("66","59","Bus/Platform","8","Widget.png");
A75: =A74+1 -> 67 | B75: =A74 -> 66 | C75: 9 | D75: Platform SEITPM and Support Equipment | F75: Subsystem | G75: SEITPM.png | J75: ="datatable["&A75-1&"] = new Array(""" & A75 &""",""" & B75 &""",""" & D75 & """,""" & C75&""","""&""&G75&""");" -> datatable[66] = new Array("67","66","Platform SEITPM and Support Equipment","9","SEITPM.png");
A76: =A75+1 -> 68 | B76: =A$70 -> 62 | C76: 10 | D76: Project Management | F76: Assembly | G76: SEITPM.png | J76: ="datatable["&A76-1&"] = new Array(""" & A76 &""",""" & B76 &""",""" & D76 & """,""" & C76&""","""&""&G76&""");" -> datatable[67] = new Array("68","62","Project Management","10","SEITPM.png");
A77: =A76+1 -> 69 | B77: =A$70 -> 62 | C77: 10 | D77: Systems Engineering | F77: Assembly | G77: SEITPM.png | J77: ="datatable["&A77-1&"] = new Array(""" & A77 &""",""" & B77 &""",""" & D77 & """,""" & C77&""","""&""&G77&""");" -> datatable[68] = new Array("69","62","Systems Engineering","10","SEITPM.png");
A78: =A77+1 -> 70 | B78: =A$70 -> 62 | C78: 10 | D78: Mission Assurance | F78: Assembly | G78: SEITPM.png | J78: ="datatable["&A78-1&"] = new Array(""" & A78 &""",""" & B78 &""",""" & D78 & """,""" & C78&""","""&""&G78&""");" -> datatable[69] = new Array("70","62","Mission Assurance","10","SEITPM.png");
A79: =A78+1 -> 71 | B79: =A$70 -> 62 | C79: 10 | D79: Assembly, Integration and Testing | F79: Assembly | G79: SEITPM.png | J79: ="datatable["&A79-1&"] = new Array(""" & A79 &""",""" & B79 &""",""" & D79 & """,""" & C79&""","""&""&G79&""");" -> datatable[70] = new Array("71","62","Assembly, Integration and Testing","10","SEITPM.png");
A80: =A79+1 -> 72 | B80: =A$70 -> 62 | C80: 10 | D80: Support Equipment | F80: Assembly | G80: SEITPM.png | J80: ="datatable["&A80-1&"] = new Array(""" & A80 &""",""" & B80 &""",""" & D80 & """,""" & C80&""","""&""&G80&""");" -> datatable[71] = new Array("72","62","Support Equipment","10","SEITPM.png");
A81: =A80+1 -> 73 | B81: =A$69 -> 61 | C81: 9 | D81: Structures and Mechanisms Subsystem (SMS) | F81: Subsystem | G81: Widget.png | J81: ="datatable["&A81-1&"] = new Array(""" & A81 &""",""" & B81 &""",""" & D81 & """,""" & C81&""","""&""&G81&""");" -> datatable[72] = new Array("73","61","Structures and Mechanisms Subsystem (SMS)","9","Widget.png");
A82: =A81+1 -> 74 | B82: =A$76 -> 68 | C82: 10 | D82: Structures and Mechanisms Subsystem SEITPM | F82: Assembly | G82: SEITPM.png | J82: ="datatable["&A82-1&"] = new Array(""" & A82 &""",""" & B82 &""",""" & D82 & """,""" & C82&""","""&""&G82&""");" -> datatable[73] = new Array("74","68","Structures and Mechanisms Subsystem SEITPM","10","SEITPM.png");
A83: =A82+1 -> 75 | B83: =A$77 -> 69 | C83: 11 | D83: Project Management | F83: Component | G83: SEITPM.png | J83: ="datatable["&A83-1&"] = new Array(""" & A83 &""",""" & B83 &""",""" & D83 & """,""" & C83&""","""&""&G83&""");" -> datatable[74] = new Array("75","69","Project Management","11","SEITPM.png");
A84: =A83+1 -> 76 | B84: =A$77 -> 69 | C84: 11 | D84: Systems Engineering | F84: Component | G84: SEITPM.png | J84: ="datatable["&A84-1&"] = new Array(""" & A84 &""",""" & B84 &""",""" & D84 & """,""" & C84&""","""&""&G84&""");" -> datatable[75] = new Array("76","69","Systems Engineering","11","SEITPM.png");
A85: =A84+1 -> 77 | B85: =A$77 -> 69 | C85: 11 | D85: Mission Assurance | F85: Component | G85: SEITPM.png | J85: ="datatable["&A85-1&"] = new Array(""" & A85 &""",""" & B85 &""",""" & D85 & """,""" & C85&""","""&""&G85&""");" -> datatable[76] = new Array("77","69","Mission Assurance","11","SEITPM.png");
A86: =A85+1 -> 78 | B86: =A$77 -> 69 | C86: 11 | D86: Assembly, Integration and Testing | F86: Component | G86: SEITPM.png | J86: ="datatable["&A86-1&"] = new Array(""" & A86 &""",""" & B86 &""",""" & D86 & """,""" & C86&""","""&""&G86&""");" -> datatable[77] = new Array("78","69","Assembly, Integration and Testing","11","SEITPM.png");
A87: =A86+1 -> 79 | B87: =A$77 -> 69 | C87: 11 | D87: Support Equipment | F87: Component | G87: SEITPM.png | J87: ="datatable["&A87-1&"] = new Array(""" & A87 &""",""" & B87 &""",""" & D87 & """,""" & C87&""","""&""&G87&""");" -> datatable[78] = new Array("79","69","Support Equipment","11","SEITPM.png");
A88: =A87+1 -> 80 | B88: =A$76 -> 68 | C88: 10 | D88: Primary Structures | F88: Assembly | G88: Widget.png | J88: ="datatable["&A88-1&"] = new Array(""" & A88 &""",""" & B88 &""",""" & D88 & """,""" & C88&""","""&""&G88&""");" -> datatable[79] = new Array("80","68","Primary Structures","10","Widget.png");
A89: =A88+1 -> 81 | B89: =A$83 -> 75 | C89: 11 | D89: Load Carrying Shell/Truss | F89: Component | G89: Widget.png | J89: ="datatable["&A89-1&"] = new Array(""" & A89 &""",""" & B89 &""",""" & D89 & """,""" & C89&""","""&""&G89&""");" -> datatable[80] = new Array("81","75","Load Carrying Shell/Truss","11","Widget.png");
A90: =A89+1 -> 82 | B90: =A$83 -> 75 | C90: 11 | D90: Equipment Compartments | F90: Component | G90: Widget.png | J90: ="datatable["&A90-1&"] = new Array(""" & A90 &""",""" & B90 &""",""" & D90 & """,""" & C90&""","""&""&G90&""");" -> datatable[81] = new Array("82","75","Equipment Compartments","11","Widget.png");
A91: =A90+1 -> 83 | B91: =A$83 -> 75 | C91: 11 | D91: Booms | F91: Component | G91: Widget.png | J91: ="datatable["&A91-1&"] = new Array(""" & A91 &""",""" & B91 &""",""" & D91 & """,""" & C91&""","""&""&G91&""");" -> datatable[82] = new Array("83","75","Booms","11","Widget.png");
A92: =A91+1 -> 84 | B92: =A$83 -> 75 | C92: 11 | D92: Adapters | F92: Component | G92: Widget.png | J92: ="datatable["&A92-1&"] = new Array(""" & A92 &""",""" & B92 &""",""" & D92 & """,""" & C92&""","""&""&G92&""");" -> datatable[83] = new Array("84","75","Adapters","11","Widget.png");
A93: =A92+1 -> 85 | B93: =A$83 -> 75 | C93: 11 | D93: Other Structures (Specify) | F93: Component | G93: Widget.png | J93: ="datatable["&A93-1&"] = new Array(""" & A93 &""",""" & B93 &""",""" & D93 & """,""" & C93&""","""&""&G93&""");" -> datatable[84] = new Array("85","75","Other Structures (Specify)","11","Widget.png");
A94: =A93+1 -> 86 | B94: =A$76 -> 68 | C94: 10 | D94: Secondary Structures | F94: Assembly | G94: Widget.png | J94: ="datatable["&A94-1&"] = new Array(""" & A94 &""",""" & B94 &""",""" & D94 & """,""" & C94&""","""&""&G94&""");" -> datatable[85] = new Array("86","68","Secondary Structures","10","Widget.png");
A95: =A94+1 -> 87 | B95: =A$89 -> 81 | C95: 11 | D95: Equipment (Instrument) Mountings | F95: Component | G95: Widget.png | J95: ="datatable["&A95-1&"] = new Array(""" & A95 &""",""" & B95 &""",""" & D95 & """,""" & C95&""","""&""&G95&""");" -> datatable[86] = new Array("87","81","Equipment (Instrument) Mountings","11","Widget.png");
A96: =A95+1 -> 88 | B96: =A$89 -> 81 | C96: 11 | D96: Ballast Mass | F96: Component | G96: Widget.png | J96: ="datatable["&A96-1&"] = new Array(""" & A96 &""",""" & B96 &""",""" & D96 & """,""" & C96&""","""&""&G96&""");" -> datatable[87] = new Array("88","81","Ballast Mass","11","Widget.png");
A97: =A96+1 -> 89 | B97: =A$89 -> 81 | C97: 11 | D97: Other Secondary Structures (Specify) | F97: Component | G97: Widget.png | J97: ="datatable["&A97-1&"] = new Array(""" & A97 &""",""" & B97 &""",""" & D97 & """,""" & C97&""","""&""&G97&""");" -> datatable[88] = new Array("89","81","Other Secondary Structures (Specify)","11","Widget.png");
A98: =A97+1 -> 90 | B98: =A$76 -> 68 | C98: 10 | D98: Mechanisms and Pyrotechnics | F98: Assembly | G98: Widget.png | J98: ="datatable["&A98-1&"] = new Array(""" & A98 &""",""" & B98 &""",""" & D98 & """,""" & C98&""","""&""&G98&""");" -> datatable[89] = new Array("90","68","Mechanisms and Pyrotechnics","10","Widget.png");
A99: =A98+1 -> 91 | B99: =A$93 -> 85 | C99: 11 | D99: Positioning | F99: Component | G99: Widget.png | J99: ="datatable["&A99-1&"] = new Array(""" & A99 &""",""" & B99 &""",""" & D99 & """,""" & C99&""","""&""&G99&""");" -> datatable[90] = new Array("91","85","Positioning","11","Widget.png");
A100: =A99+1 -> 92 | B100: =A$93 -> 85 | C100: 11 | D100: Deployment and Storage Equipment | F100: Component | G100: Widget.png | J100: ="datatable["&A100-1&"] = new Array(""" & A100 &""",""" & B100 &""",""" & D100 & """,""" & C100&""","""&""&G100&""");" -> datatable[91] = new Array("92","85","Deployment and Storage Equipment","11","Widget.png");
A101: =A100+1 -> 93 | B101: =A$93 -> 85 | C101: 11 | D101: Docking Mechanisms | F101: Component | G101: Widget.png | J101: ="datatable["&A101-1&"] = new Array(""" & A101 &""",""" & B101 &""",""" & D101 & """,""" & C101&""","""&""&G101&""");" -> datatable[92] = new Array("93","85","Docking Mechanisms","11","Widget.png");
A102: =A101+1 -> 94 | B102: =A$93 -> 85 | C102: 11 | D102: Other Mechanisms (Specify) | F102: Component | G102: Widget.png | J102: ="datatable["&A102-1&"] = new Array(""" & A102 &""",""" & B102 &""",""" & D102 & """,""" & C102&""","""&""&G102&""");" -> datatable[93] = new Array("94","85","Other Mechanisms (Specify)","11","Widget.png");
...

Sheet 2 - Phasing Nomenclature
A1: ` Table of Contents
A3: 7 - Phasing Nomenclature | I3: What do you call your phases?
A4: Why we we asking:
B5: 1. To normalize the naming convention across all investments.
B6: 2. Math Models are based on Costing Sub-Phase.
B7: 3. We want to output results in your naming convention and scope.
B10: Based on IGMF rev E | F10: Based on CSA-FIN-RPT-0072
A11: Phasing according to | E11: Phasing according to | I11: Phasing according to
A12: EPMO | E12: Costing | I12: PM
E13: PREP | F13: PREP 1 | G13: Prototyping Activities (before Gate 1)
A14: Pre-Project | B14: Option Analysis & Planning Phase | C14: Pre-Phase 0 | F14: PREP 2 | G14: Prototyping Activities (during Phase 0/A)
C15: Phase 0 | E15: Phase 0/A | F15: Phase 0 | G15: Concept & Feasibility | I15: Phase 0
A16: Project | B16: Definition Phase | C16: Detailed Project Requirements | F16: Phase A | G16: Mission Requirements | I16: Phase A
C17: Preliminary Definition | E17: Phase B/C | F17: Phase B | G17: Preliminary Design | I17: Phase B
C18: Detailed Definition | F18: Phase C | G18: Detailed Design | I18: Phase C
B19: Implementation Phase | C19: Implementation | E19: Phase D | F19: MAIT | G19: Manufacturing, Assembly, Integration and Test of Canadian Subsystems and Components | I19: Phase D
F20: SAIT | G20: Spacecraft Level Assembly, Test | I20: Phase D
F21: LEOP | G21: Lauch and early operations | I21: Phase D
A22: Post-Project | B22: Post-Implementation Phase | C22: Operations & Disposal | E22: Phase E | F22: Phase E | G22: Nominal Operations (per design life) | I22: Phase E
E23: Phase E (EXT) | F23: Phase X | G23: Extended operations (mission extension)
E24: Phase F | F24: Phase F | G24: Disposal (incl. post-mortem audit reports) | I24: Phase F
E25: Phase G | F25: Phase G | G25: Post-Mortem science utilization

Sheet 3 - Phase Durations
A1: ` Table of Contents
A3: 7b - Phasing Durations
A4: Why we we asking:
B5: 1. Durations affect Govt Salaries calculations
B6: 2. Durations affect Parametric estimates for Space segment, ground segment, ops
B7: 3. Schedule Scenarios are inputs to sensitivity analysis
B9: Schedule Scenario ID | C9: 1
B10: Scenario Name | C10: Nominal Schedule Used by Gaby for RAM calculation (PM Nomenclature)
B11: Scenario Description | C11: Phases 0 through F
B12: Rationale | C12: ORCA concept-stage schedule, consistent with CADRe Part A section 2.5
B13: Source Doc | C13: CADRe Part A
B15: Phase | C15: Expected Start | D15: Expected End | E15: Total D | F15: Total M | G15: 2026 | H15: =G15+1 -> 2027 | I15: =H15+1 -> 2028 | J15: =I15+1 -> 2029 | K15: =J15+1 -> 2030 | L15: =K15+1 -> 2031 | M15: =L15+1 -> 2032 | N15: =M15+1 -> 2033 | O15: =N15+1 -> 2034 | ... AO15: =AN15+1 -> 2060
B16: Phase 0 | C16: 46023 | D16: 46752 | E16: =D16-C16 -> 729 | F16: =E16/365*12 -> 23.967123 | G16: =MAX(MIN($D16,DATE(G$15,3,31))-MAX($C16,DATE(G$15-1,4,1))+1,0)/365*12 -> 2.9589041 | H16: =MAX(MIN($D16,DATE(H$15,3,31))-MAX($C16,DATE(H$15-1,4,1))+1,0)/365*12 -> 12 | I16: =MAX(MIN($D16,DATE(I$15,3,31))-MAX($C16,DATE(I$15-1,4,1))+1,0)/365*12 -> 9.0410959 | J16: =MAX(MIN($D16,DATE(J$15,3,31))-MAX($C16,DATE(J$15-1,4,1))+1,0)/365*12 -> 0 | K16: =MAX(MIN($D16,DATE(K$15,3,31))-MAX($C16,DATE(K$15-1,4,1))+1,0)/365*12 -> 0 | L16: =MAX(MIN($D16,DATE(L$15,3,31))-MAX($C16,DATE(L$15-1,4,1))+1,0)/365*12 -> 0 | M16: =MAX(MIN($D16,DATE(M$15,3,31))-MAX($C16,DATE(M$15-1,4,1))+1,0)/365*12 -> 0 | N16: =MAX(MIN($D16,DATE(N$15,3,31))-MAX($C16,DATE(N$15-1,4,1))+1,0)/365*12 -> 0 | ... AO16: =MAX(MIN($D16,DATE(AO$15,3,31))-MAX($C16,DATE(AO$15-1,4,1))+1,0)/365*12 -> 0
B17: Phase A | C17: =D16+1 -> 46753 | D17: 47483 | E17: =D17-C17 -> 730 | F17: =E17/365*12 -> 24 | G17: =MAX(MIN($D17,DATE(G$15,3,31))-MAX($C17,DATE(G$15-1,4,1))+1,0)/365*12 -> 0 | H17: =MAX(MIN($D17,DATE(H$15,3,31))-MAX($C17,DATE(H$15-1,4,1))+1,0)/365*12 -> 0 | I17: =MAX(MIN($D17,DATE(I$15,3,31))-MAX($C17,DATE(I$15-1,4,1))+1,0)/365*12 -> 2.9917808 | J17: =MAX(MIN($D17,DATE(J$15,3,31))-MAX($C17,DATE(J$15-1,4,1))+1,0)/365*12 -> 12 | K17: =MAX(MIN($D17,DATE(K$15,3,31))-MAX($C17,DATE(K$15-1,4,1))+1,0)/365*12 -> 9.0410959 | L17: =MAX(MIN($D17,DATE(L$15,3,31))-MAX($C17,DATE(L$15-1,4,1))+1,0)/365*12 -> 0 | M17: =MAX(MIN($D17,DATE(M$15,3,31))-MAX($C17,DATE(M$15-1,4,1))+1,0)/365*12 -> 0 | N17: =MAX(MIN($D17,DATE(N$15,3,31))-MAX($C17,DATE(N$15-1,4,1))+1,0)/365*12 -> 0 | ... AO17: =MAX(MIN($D17,DATE(AO$15,3,31))-MAX($C17,DATE(AO$15-1,4,1))+1,0)/365*12 -> 0
B18: Phase B1 | C18: =D17+1 -> 47484 | D18: 47848 | E18: =D18-C18 -> 364 | F18: =E18/365*12 -> 11.967123 | G18: =MAX(MIN($D18,DATE(G$15,3,31))-MAX($C18,DATE(G$15-1,4,1))+1,0)/365*12 -> 0 | H18: =MAX(MIN($D18,DATE(H$15,3,31))-MAX($C18,DATE(H$15-1,4,1))+1,0)/365*12 -> 0 | I18: =MAX(MIN($D18,DATE(I$15,3,31))-MAX($C18,DATE(I$15-1,4,1))+1,0)/365*12 -> 0 | J18: =MAX(MIN($D18,DATE(J$15,3,31))-MAX($C18,DATE(J$15-1,4,1))+1,0)/365*12 -> 0 | K18: =MAX(MIN($D18,DATE(K$15,3,31))-MAX($C18,DATE(K$15-1,4,1))+1,0)/365*12 -> 2.9589041 | L18: =MAX(MIN($D18,DATE(L$15,3,31))-MAX($C18,DATE(L$15-1,4,1))+1,0)/365*12 -> 9.0410959 | M18: =MAX(MIN($D18,DATE(M$15,3,31))-MAX($C18,DATE(M$15-1,4,1))+1,0)/365*12 -> 0 | N18: =MAX(MIN($D18,DATE(N$15,3,31))-MAX($C18,DATE(N$15-1,4,1))+1,0)/365*12 -> 0 | ... AO18: =MAX(MIN($D18,DATE(AO$15,3,31))-MAX($C18,DATE(AO$15-1,4,1))+1,0)/365*12 -> 0
B19: Phase B2 | C19: =D18+1 -> 47849 | D19: 48213 | E19: =D19-C19 -> 364 | F19: =E19/365*12 -> 11.967123 | G19: =MAX(MIN($D19,DATE(G$15,3,31))-MAX($C19,DATE(G$15-1,4,1))+1,0)/365*12 -> 0 | H19: =MAX(MIN($D19,DATE(H$15,3,31))-MAX($C19,DATE(H$15-1,4,1))+1,0)/365*12 -> 0 | I19: =MAX(MIN($D19,DATE(I$15,3,31))-MAX($C19,DATE(I$15-1,4,1))+1,0)/365*12 -> 0 | J19: =MAX(MIN($D19,DATE(J$15,3,31))-MAX($C19,DATE(J$15-1,4,1))+1,0)/365*12 -> 0 | K19: =MAX(MIN($D19,DATE(K$15,3,31))-MAX($C19,DATE(K$15-1,4,1))+1,0)/365*12 -> 0 | L19: =MAX(MIN($D19,DATE(L$15,3,31))-MAX($C19,DATE(L$15-1,4,1))+1,0)/365*12 -> 2.9589041 | M19: =MAX(MIN($D19,DATE(M$15,3,31))-MAX($C19,DATE(M$15-1,4,1))+1,0)/365*12 -> 9.0410959 | N19: =MAX(MIN($D19,DATE(N$15,3,31))-MAX($C19,DATE(N$15-1,4,1))+1,0)/365*12 -> 0 | ... AO19: =MAX(MIN($D19,DATE(AO$15,3,31))-MAX($C19,DATE(AO$15-1,4,1))+1,0)/365*12 -> 0
B20: Phase C | C20: =D19+1 -> 48214 | D20: 48944 | E20: =D20-C20 -> 730 | F20: =E20/365*12 -> 24 | G20: =MAX(MIN($D20,DATE(G$15,3,31))-MAX($C20,DATE(G$15-1,4,1))+1,0)/365*12 -> 0 | H20: =MAX(MIN($D20,DATE(H$15,3,31))-MAX($C20,DATE(H$15-1,4,1))+1,0)/365*12 -> 0 | I20: =MAX(MIN($D20,DATE(I$15,3,31))-MAX($C20,DATE(I$15-1,4,1))+1,0)/365*12 -> 0 | J20: =MAX(MIN($D20,DATE(J$15,3,31))-MAX($C20,DATE(J$15-1,4,1))+1,0)/365*12 -> 0 | K20: =MAX(MIN($D20,DATE(K$15,3,31))-MAX($C20,DATE(K$15-1,4,1))+1,0)/365*12 -> 0 | L20: =MAX(MIN($D20,DATE(L$15,3,31))-MAX($C20,DATE(L$15-1,4,1))+1,0)/365*12 -> 0 | M20: =MAX(MIN($D20,DATE(M$15,3,31))-MAX($C20,DATE(M$15-1,4,1))+1,0)/365*12 -> 2.9917808 | N20: =MAX(MIN($D20,DATE(N$15,3,31))-MAX($C20,DATE(N$15-1,4,1))+1,0)/365*12 -> 12 | ... AO20: =MAX(MIN($D20,DATE(AO$15,3,31))-MAX($C20,DATE(AO$15-1,4,1))+1,0)/365*12 -> 0
B21: Phase D | C21: =D20+1 -> 48945 | D21: 51501 | E21: =D21-C21 -> 2556 | F21: =E21/365*12 -> 84.032877 | G21: =MAX(MIN($D21,DATE(G$15,3,31))-MAX($C21,DATE(G$15-1,4,1))+1,0)/365*12 -> 0 | H21: =MAX(MIN($D21,DATE(H$15,3,31))-MAX($C21,DATE(H$15-1,4,1))+1,0)/365*12 -> 0 | I21: =MAX(MIN($D21,DATE(I$15,3,31))-MAX($C21,DATE(I$15-1,4,1))+1,0)/365*12 -> 0 | J21: =MAX(MIN($D21,DATE(J$15,3,31))-MAX($C21,DATE(J$15-1,4,1))+1,0)/365*12 -> 0 | K21: =MAX(MIN($D21,DATE(K$15,3,31))-MAX($C21,DATE(K$15-1,4,1))+1,0)/365*12 -> 0 | L21: =MAX(MIN($D21,DATE(L$15,3,31))-MAX($C21,DATE(L$15-1,4,1))+1,0)/365*12 -> 0 | M21: =MAX(MIN($D21,DATE(M$15,3,31))-MAX($C21,DATE(M$15-1,4,1))+1,0)/365*12 -> 0 | N21: =MAX(MIN($D21,DATE(N$15,3,31))-MAX($C21,DATE(N$15-1,4,1))+1,0)/365*12 -> 0 | ... AO21: =MAX(MIN($D21,DATE(AO$15,3,31))-MAX($C21,DATE(AO$15-1,4,1))+1,0)/365*12 -> 0
B22: Phase E | C22: =D21+1 -> 51502 | D22: 56979 | E22: =D22-C22 -> 5477 | F22: =E22/365*12 -> 180.06575 | G22: =MAX(MIN($D22,DATE(G$15,3,31))-MAX($C22,DATE(G$15-1,4,1))+1,0)/365*12 -> 0 | H22: =MAX(MIN($D22,DATE(H$15,3,31))-MAX($C22,DATE(H$15-1,4,1))+1,0)/365*12 -> 0 | I22: =MAX(MIN($D22,DATE(I$15,3,31))-MAX($C22,DATE(I$15-1,4,1))+1,0)/365*12 -> 0 | J22: =MAX(MIN($D22,DATE(J$15,3,31))-MAX($C22,DATE(J$15-1,4,1))+1,0)/365*12 -> 0 | K22: =MAX(MIN($D22,DATE(K$15,3,31))-MAX($C22,DATE(K$15-1,4,1))+1,0)/365*12 -> 0 | L22: =MAX(MIN($D22,DATE(L$15,3,31))-MAX($C22,DATE(L$15-1,4,1))+1,0)/365*12 -> 0 | M22: =MAX(MIN($D22,DATE(M$15,3,31))-MAX($C22,DATE(M$15-1,4,1))+1,0)/365*12 -> 0 | N22: =MAX(MIN($D22,DATE(N$15,3,31))-MAX($C22,DATE(N$15-1,4,1))+1,0)/365*12 -> 0 | ... AO22: =MAX(MIN($D22,DATE(AO$15,3,31))-MAX($C22,DATE(AO$15-1,4,1))+1,0)/365*12 -> 0
B23: Phase X | C23: =D22+1 -> 56980 | D23: 58256 | E23: =D23-C23 -> 1276 | F23: =E23/365*12 -> 41.950685 | G23: =MAX(MIN($D23,DATE(G$15,3,31))-MAX($C23,DATE(G$15-1,4,1))+1,0)/365*12 -> 0 | H23: =MAX(MIN($D23,DATE(H$15,3,31))-MAX($C23,DATE(H$15-1,4,1))+1,0)/365*12 -> 0 | I23: =MAX(MIN($D23,DATE(I$15,3,31))-MAX($C23,DATE(I$15-1,4,1))+1,0)/365*12 -> 0 | J23: =MAX(MIN($D23,DATE(J$15,3,31))-MAX($C23,DATE(J$15-1,4,1))+1,0)/365*12 -> 0 | K23: =MAX(MIN($D23,DATE(K$15,3,31))-MAX($C23,DATE(K$15-1,4,1))+1,0)/365*12 -> 0 | L23: =MAX(MIN($D23,DATE(L$15,3,31))-MAX($C23,DATE(L$15-1,4,1))+1,0)/365*12 -> 0 | M23: =MAX(MIN($D23,DATE(M$15,3,31))-MAX($C23,DATE(M$15-1,4,1))+1,0)/365*12 -> 0 | N23: =MAX(MIN($D23,DATE(N$15,3,31))-MAX($C23,DATE(N$15-1,4,1))+1,0)/365*12 -> 0 | ... AO23: =MAX(MIN($D23,DATE(AO$15,3,31))-MAX($C23,DATE(AO$15-1,4,1))+1,0)/365*12 -> 2.9917808
B24: Phase F | C24: =D23+1 -> 58257 | D24: =C24+180 -> 58437 | E24: =D24-C24 -> 180 | F24: =E24/365*12 -> 5.9178082 | G24: =MAX(MIN($D24,DATE(G$15,3,31))-MAX($C24,DATE(G$15-1,4,1))+1,0)/365*12 -> 0 | H24: =MAX(MIN($D24,DATE(H$15,3,31))-MAX($C24,DATE(H$15-1,4,1))+1,0)/365*12 -> 0 | I24: =MAX(MIN($D24,DATE(I$15,3,31))-MAX($C24,DATE(I$15-1,4,1))+1,0)/365*12 -> 0 | J24: =MAX(MIN($D24,DATE(J$15,3,31))-MAX($C24,DATE(J$15-1,4,1))+1,0)/365*12 -> 0 | K24: =MAX(MIN($D24,DATE(K$15,3,31))-MAX($C24,DATE(K$15-1,4,1))+1,0)/365*12 -> 0 | L24: =MAX(MIN($D24,DATE(L$15,3,31))-MAX($C24,DATE(L$15-1,4,1))+1,0)/365*12 -> 0 | M24: =MAX(MIN($D24,DATE(M$15,3,31))-MAX($C24,DATE(M$15-1,4,1))+1,0)/365*12 -> 0 | N24: =MAX(MIN($D24,DATE(N$15,3,31))-MAX($C24,DATE(N$15-1,4,1))+1,0)/365*12 -> 0 | ... AO24: =MAX(MIN($D24,DATE(AO$15,3,31))-MAX($C24,DATE(AO$15-1,4,1))+1,0)/365*12 -> 5.9506849
B26: Phase D1-MAIT | C26: =C21 -> 48945 | D26: =EDATE(C26,54)-1 -> 50586 | E26: =D26-C26 -> 1641 | F26: =E26/365*12 -> 53.950685 | G26: =MAX(MIN($D26,DATE(G$15,3,31))-MAX($C26,DATE(G$15-1,4,1))+1,0)/365*12 -> 0 | H26: =MAX(MIN($D26,DATE(H$15,3,31))-MAX($C26,DATE(H$15-1,4,1))+1,0)/365*12 -> 0 | I26: =MAX(MIN($D26,DATE(I$15,3,31))-MAX($C26,DATE(I$15-1,4,1))+1,0)/365*12 -> 0 | J26: =MAX(MIN($D26,DATE(J$15,3,31))-MAX($C26,DATE(J$15-1,4,1))+1,0)/365*12 -> 0 | K26: =MAX(MIN($D26,DATE(K$15,3,31))-MAX($C26,DATE(K$15-1,4,1))+1,0)/365*12 -> 0 | L26: =MAX(MIN($D26,DATE(L$15,3,31))-MAX($C26,DATE(L$15-1,4,1))+1,0)/365*12 -> 0 | M26: =MAX(MIN($D26,DATE(M$15,3,31))-MAX($C26,DATE(M$15-1,4,1))+1,0)/365*12 -> 0 | N26: =MAX(MIN($D26,DATE(N$15,3,31))-MAX($C26,DATE(N$15-1,4,1))+1,0)/365*12 -> 0 | ... AO26: =MAX(MIN($D26,DATE(AO$15,3,31))-MAX($C26,DATE(AO$15-1,4,1))+1,0)/365*12 -> 0
B27: Phase D2-SAIT | C27: =D26+1 -> 50587 | D27: =EDATE(C27,27)-1 -> 51409 | E27: =D27-C27 -> 822 | F27: =E27/365*12 -> 27.024658 | G27: =MAX(MIN($D27,DATE(G$15,3,31))-MAX($C27,DATE(G$15-1,4,1))+1,0)/365*12 -> 0 | H27: =MAX(MIN($D27,DATE(H$15,3,31))-MAX($C27,DATE(H$15-1,4,1))+1,0)/365*12 -> 0 | I27: =MAX(MIN($D27,DATE(I$15,3,31))-MAX($C27,DATE(I$15-1,4,1))+1,0)/365*12 -> 0 | J27: =MAX(MIN($D27,DATE(J$15,3,31))-MAX($C27,DATE(J$15-1,4,1))+1,0)/365*12 -> 0 | K27: =MAX(MIN($D27,DATE(K$15,3,31))-MAX($C27,DATE(K$15-1,4,1))+1,0)/365*12 -> 0 | L27: =MAX(MIN($D27,DATE(L$15,3,31))-MAX($C27,DATE(L$15-1,4,1))+1,0)/365*12 -> 0 | M27: =MAX(MIN($D27,DATE(M$15,3,31))-MAX($C27,DATE(M$15-1,4,1))+1,0)/365*12 -> 0 | N27: =MAX(MIN($D27,DATE(N$15,3,31))-MAX($C27,DATE(N$15-1,4,1))+1,0)/365*12 -> 0 | ... AO27: =MAX(MIN($D27,DATE(AO$15,3,31))-MAX($C27,DATE(AO$15-1,4,1))+1,0)/365*12 -> 0
B28: Phase D3-LEOP | C28: =D27+1 -> 51410 | D28: =D21 -> 51501 | E28: =D28-C28 -> 91 | F28: =E28/365*12 -> 2.9917808 | G28: =MAX(MIN($D28,DATE(G$15,3,31))-MAX($C28,DATE(G$15-1,4,1))+1,0)/365*12 -> 0 | H28: =MAX(MIN($D28,DATE(H$15,3,31))-MAX($C28,DATE(H$15-1,4,1))+1,0)/365*12 -> 0 | I28: =MAX(MIN($D28,DATE(I$15,3,31))-MAX($C28,DATE(I$15-1,4,1))+1,0)/365*12 -> 0 | J28: =MAX(MIN($D28,DATE(J$15,3,31))-MAX($C28,DATE(J$15-1,4,1))+1,0)/365*12 -> 0 | K28: =MAX(MIN($D28,DATE(K$15,3,31))-MAX($C28,DATE(K$15-1,4,1))+1,0)/365*12 -> 0 | L28: =MAX(MIN($D28,DATE(L$15,3,31))-MAX($C28,DATE(L$15-1,4,1))+1,0)/365*12 -> 0 | M28: =MAX(MIN($D28,DATE(M$15,3,31))-MAX($C28,DATE(M$15-1,4,1))+1,0)/365*12 -> 0 | N28: =MAX(MIN($D28,DATE(N$15,3,31))-MAX($C28,DATE(N$15-1,4,1))+1,0)/365*12 -> 0 | ... AO28: =MAX(MIN($D28,DATE(AO$15,3,31))-MAX($C28,DATE(AO$15-1,4,1))+1,0)/365*12 -> 0

Sheet PM's sched Scenarios
C1: ORCA Ref. | D1: ='3 - Phase Durations'!C16 -> 46023
A3: Phase | B3: Milestone | C3: ORCA Baseline | D3: Orbiter Platform (Partner Agency) | E3: ORCA Instrument Suite | F3: Worst case duration | G3: Worst case (+2 mo/phase) | H3: Realistic case duration | I3: Baseline: Realistic case date (1 month delay per phase) | J3: Optimistic case duration | K3: Optimistic case | L3: Comments
A4: Phase 0 | B4: Mission Concept Review (MCR) | C4: ='3 - Phase Durations'!D16 -> 46752 | D4: N/A | E4: N/A | F4: =(G4-'3 - Phase Durations'!C16)/30.44 -> 25.919842 | G4: =EDATE(C4,2) -> 46812 | H4: =(I4-'3 - Phase Durations'!C16)/30.44 -> 24.967148 | I4: =EDATE(C4,1) -> 46783 | J4: =(K4-'3 - Phase Durations'!C16)/30.44 -> 22.930355 | K4: =EDATE(C4,-1) -> 46721 | L4: End of Phase 0; mission concept baseline.
A5: Phase A | B5: System Requirements Review (SRR) | C5: ='3 - Phase Durations'!D17 -> 47483 | D5: N/A | E5: N/A | F5: =(G5-'3 - Phase Durations'!C16)/30.44 -> 51.905388 | G5: =EDATE(C5,4) -> 47603 | H5: =(I5-'3 - Phase Durations'!C16)/30.44 -> 49.901445 | I5: =EDATE(C5,2) -> 47542 | J5: =(K5-'3 - Phase Durations'!C16)/30.44 -> 45.959264 | K5: =EDATE(C5,-2) -> 47422 | L5: End of Phase A.
A6: Phase A | B6: ORCA Concept Rebaseline | C6: ='3 - Phase Durations'!C17+0.75*('3 - Phase Durations'!D17-'3 - Phase Durations'!C17) -> 47300.5 | D6: N/A | E6: N/A | F6: =(G6-'3 - Phase Durations'!C16)/30.44 -> 45.992116 | G6: =EDATE(C6,4) -> 47423 | H6: =(I6-'3 - Phase Durations'!C16)/30.44 -> 43.988173 | I6: =EDATE(C6,2) -> 47362 | J6: =(K6-'3 - Phase Durations'!C16)/30.44 -> 39.947438 | K6: =EDATE(C6,-2) -> 47239 | L6: Programmatic baseline update within Phase A. | N6: Phases | O6: Duration (months) | P6: Expected start | Q6: Expected finish
A7: Phase B | B7: Orbiter Bus / ORCA Instrument Suite Interface Complete | C7: ='3 - Phase Durations'!C18+0.6*('3 - Phase Durations'!D19-'3 - Phase Durations'!C18) -> 47921.4 | D7: Interface requirements | E7: Interface requirements | F7: =(G7-'3 - Phase Durations'!C16)/30.44 -> 68.396846 | G7: =EDATE(C7,6) -> 48105 | H7: =(I7-'3 - Phase Durations'!C16)/30.44 -> 65.374507 | I7: =EDATE(C7,3) -> 48013 | J7: =(K7-'3 - Phase Durations'!C16)/30.44 -> 59.395532 | K7: =EDATE(C7,-3) -> 47831 | L7: Partner-agency orbiter interface control document (ICD) finalized. | N7: ='3 - Phase Durations'!B16 -> Phase 0 | O7: ='3 - Phase Durations'!F16 -> 23.967123 | P7: ='3 - Phase Durations'!C16 -> 46023 | Q7: ='3 - Phase Durations'!D16 -> 46752
A8: Phase B | B8: Preliminary Design Review (PDR) | C8: ='3 - Phase Durations'!D19 -> 48213 | D8: Bus accommodation | E8: Preliminary design | F8: =(G8-'3 - Phase Durations'!C16)/30.44 -> 77.923784 | G8: =EDATE(C8,6) -> 48395 | H8: =(I8-'3 - Phase Durations'!C16)/30.44 -> 74.934297 | I8: =EDATE(C8,3) -> 48304 | J8: =(K8-'3 - Phase Durations'!C16)/30.44 -> 68.92247 | K8: =EDATE(C8,-3) -> 48121 | L8: End of Phase B (B1+B2). | N8: ='3 - Phase Durations'!B17 -> Phase A | O8: ='3 - Phase Durations'!F17 -> 24 | P8: ='3 - Phase Durations'!C17 -> 46753 | Q8: ='3 - Phase Durations'!D17 -> 47483
A9: Phase C | B9: Instrument Suite Environmental Qualification Complete | C9: ='3 - Phase Durations'!C20+0.6*('3 - Phase Durations'!D20-'3 - Phase Durations'!C20) -> 48652 | D9: N/A | E9: Qualification | F9: =(G9-'3 - Phase Durations'!C16)/30.44 -> 94.415243 | G9: =EDATE(C9,8) -> 48897 | H9: =(I9-'3 - Phase Durations'!C16)/30.44 -> 90.374507 | I9: =EDATE(C9,4) -> 48774 | J9: =(K9-'3 - Phase Durations'!C16)/30.44 -> 82.424442 | K9: =EDATE(C9,-4) -> 48532 | L9: Vibration / thermal-vacuum qualification of the ORCA instrument suite. | N9: ='3 - Phase Durations'!B18 -> Phase B1 | O9: ='3 - Phase Durations'!F18 -> 11.967123 | P9: ='3 - Phase Durations'!C18 -> 47484 | Q9: ='3 - Phase Durations'!D18 -> 47848
A10: Phase C | B10: Critical Design Review (CDR) | C10: ='3 - Phase Durations'!D20 -> 48944 | D10: Bus accommodation | E10: Critical design | F10: =(G10-'3 - Phase Durations'!C16)/30.44 -> 103.94218 | G10: =EDATE(C10,8) -> 49187 | H10: =(I10-'3 - Phase Durations'!C16)/30.44 -> 99.901445 | I10: =EDATE(C10,4) -> 49064 | J10: =(K10-'3 - Phase Durations'!C16)/30.44 -> 91.95138 | K10: =EDATE(C10,-4) -> 48822 | L10: End of Phase C. | N10: ='3 - Phase Durations'!B19 -> Phase B2 | O10: ='3 - Phase Durations'!F19 -> 11.967123 | P10: ='3 - Phase Durations'!C19 -> 47849 | Q10: ='3 - Phase Durations'!D19 -> 48213
A11: MAIT | B11: Manufacturing Readiness Review (MRR) | C11: ='3 - Phase Durations'!C26+0.5*('3 - Phase Durations'!D26-'3 - Phase Durations'!C26) -> 49765.5 | D11: N/A | E11: N/A | F11: =(G11-'3 - Phase Durations'!C16)/30.44 -> 132.98292 | G11: =EDATE(C11,10) -> 50071 | H11: =(I11-'3 - Phase Durations'!C16)/30.44 -> 127.95664 | I11: =EDATE(C11,5) -> 49918 | J11: =(K11-'3 - Phase Durations'!C16)/30.44 -> 117.93693 | K11: =EDATE(C11,-5) -> 49613 | L11: Mid-MAIT manufacturing readiness checkpoint. | N11: ='3 - Phase Durations'!B20 -> Phase C | O11: ='3 - Phase Durations'!F20 -> 24 | P11: ='3 - Phase Durations'!C20 -> 48214 | Q11: ='3 - Phase Durations'!D20 -> 48944
A12: MAIT | B12: Pre-Ship Review of Systems to Prime (PSR) | C12: ='3 - Phase Durations'!D21-180 -> 51321 | D12: Integration readiness | E12: Integration readiness | F12: =(G12-'3 - Phase Durations'!C16)/30.44 -> 184.03417 | G12: =EDATE(C12,10) -> 51625 | H12: =(I12-'3 - Phase Durations'!C16)/30.44 -> 179.07359 | I12: =EDATE(C12,5) -> 51474 | J12: =(K12-'3 - Phase Durations'!C16)/30.44 -> 169.08673 | K12: =EDATE(C12,-5) -> 51170 | L12: ~6 months before launch. | N12: ='3 - Phase Durations'!B21 -> Phase D | O12: ='3 - Phase Durations'!F21 -> 84.032877 | P12: ='3 - Phase Durations'!C21 -> 48945 | Q12: ='3 - Phase Durations'!D21 -> 51501
A13: SAIT | B13: Integrated Instrument Suite Functional Test Complete | C13: ='3 - Phase Durations'!D27-30 -> 51379 | D13: N/A | E13: Functional test | F13: =(G13-'3 - Phase Durations'!C16)/30.44 -> 185.9067 | G13: =EDATE(C13,10) -> 51682 | H13: =(I13-'3 - Phase Durations'!C16)/30.44 -> 180.97898 | I13: =EDATE(C13,5) -> 51532 | J13: =(K13-'3 - Phase Durations'!C16)/30.44 -> 170.92641 | K13: =EDATE(C13,-5) -> 51226 | L13: Ahead of System Integration Review. | N13: ='3 - Phase Durations'!B22 -> Phase E | O13: ='3 - Phase Durations'!F22 -> 180.06575 | P13: ='3 - Phase Durations'!C22 -> 51502 | Q13: ='3 - Phase Durations'!D22 -> 56979
A14: SAIT | B14: System Integration Review (SIR) | C14: ='3 - Phase Durations'!D27 -> 51409 | D14: Bus integration | E14: Instrument integration | F14: =(G14-'3 - Phase Durations'!C16)/30.44 -> 186.89225 | G14: =EDATE(C14,10) -> 51712 | H14: =(I14-'3 - Phase Durations'!C16)/30.44 -> 181.89882 | I14: =EDATE(C14,5) -> 51560 | J14: =(K14-'3 - Phase Durations'!C16)/30.44 -> 171.91196 | K14: =EDATE(C14,-5) -> 51256 | L14: ORCA integrated onto partner-agency orbiter bus. | N14: ='3 - Phase Durations'!B23 -> Phase X | O14: ='3 - Phase Durations'!F23 -> 41.950685 | P14: ='3 - Phase Durations'!C23 -> 56980 | Q14: ='3 - Phase Durations'!D23 -> 58256
A15: SAIT | B15: Acceptance Review (AR) | C15: ='3 - Phase Durations'!D21-90 -> 51411 | D15: Flight acceptance | E15: Flight acceptance | F15: =(G15-'3 - Phase Durations'!C16)/30.44 -> 186.9908 | G15: =EDATE(C15,10) -> 51715 | H15: =(I15-'3 - Phase Durations'!C16)/30.44 -> 181.96452 | I15: =EDATE(C15,5) -> 51562 | J15: =(K15-'3 - Phase Durations'!C16)/30.44 -> 171.97766 | K15: =EDATE(C15,-5) -> 51258 | L15: ~3 months before launch. | N15: ='3 - Phase Durations'!B24 -> Phase F | O15: ='3 - Phase Durations'!F24 -> 5.9178082 | P15: ='3 - Phase Durations'!C24 -> 58257 | Q15: ='3 - Phase Durations'!D24 -> 58437
A16: SAIT | B16: Flight Software and Autonomy Verification Complete | C16: ='3 - Phase Durations'!D21-60 -> 51441 | D16: N/A | E16: N/A | F16: =(G16-'3 - Phase Durations'!C16)/30.44 -> 187.97635 | G16: =EDATE(C16,10) -> 51745 | H16: =(I16-'3 - Phase Durations'!C16)/30.44 -> 182.95007 | I16: =EDATE(C16,5) -> 51592 | J16: =(K16-'3 - Phase Durations'!C16)/30.44 -> 172.96321 | K16: =EDATE(C16,-5) -> 51288 | L16: Autonomy and fault-management software verified. | N16: Total | O16: =SUM(O7:O15) -> 407.86849
A17: LEOP | B17: Pre-Ship Review – Spacecraft to Launch Site | C17: ='3 - Phase Durations'!D21-45 -> 51456 | D17: Bus checkout | E17: N/A | F17: =(G17-'3 - Phase Durations'!C16)/30.44 -> 188.46912 | G17: =EDATE(C17,10) -> 51760 | H17: =(I17-'3 - Phase Durations'!C16)/30.44 -> 183.44284 | I17: =EDATE(C17,5) -> 51607 | J17: =(K17-'3 - Phase Durations'!C16)/30.44 -> 173.45598 | K17: =EDATE(C17,-5) -> 51303 | L17: Before shipment to launch site.
A18: LEOP | B18: Launch | C18: ='3 - Phase Durations'!D21 -> 51501 | D18: N/A | E18: N/A | F18: =(G18-'3 - Phase Durations'!C16)/30.44 -> 189.94744 | G18: =EDATE(C18,10) -> 51805 | H18: =(I18-'3 - Phase Durations'!C16)/30.44 -> 184.92116 | I18: =EDATE(C18,5) -> 51652 | J18: =(K18-'3 - Phase Durations'!C16)/30.44 -> 174.9343 | K18: =EDATE(C18,-5) -> 51348 | L18: End of Phase D; Jupiter gravity-assist trajectory.
A19: LEOP | B19: Commissioning Review (CR) | C19: =C18+14 -> 51515 | D19: Bus checkout | E19: Instrument checkout | F19: =(G19-'3 - Phase Durations'!C16)/30.44 -> 190.40736 | G19: =EDATE(C19,10) -> 51819 | H19: =(I19-'3 - Phase Durations'!C16)/30.44 -> 185.38108 | I19: =EDATE(C19,5) -> 51666 | J19: =(K19-'3 - Phase Durations'!C16)/30.44 -> 175.39422 | K19: =EDATE(C19,-5) -> 51362 | L19: Post-launch systems checkout, ~2 weeks after launch.
A20: Phase E | B20: Start of Nominal Operations | C20: ='3 - Phase Durations'!C22 -> 51502 | D20: N/A | E20: Plume sampling begins | F20: =(G20-'3 - Phase Durations'!C16)/30.44 -> 191.98423 | G20: =EDATE(C20,12) -> 51867 | H20: =(I20-'3 - Phase Durations'!C16)/30.44 -> 185.93955 | I20: =EDATE(C20,6) -> 51683 | J20: =(K20-'3 - Phase Durations'!C16)/30.44 -> 173.94875 | K20: =EDATE(C20,-6) -> 51318 | L20: Start of Phase E.
A21: Phase E | B21: End of Nominal Operations | C21: ='3 - Phase Durations'!D22 -> 56979 | D21: N/A | E21: N/A | F21: =(G21-'3 - Phase Durations'!C16)/30.44 -> 371.94481 | G21: =EDATE(C21,12) -> 57345 | H21: =(I21-'3 - Phase Durations'!C16)/30.44 -> 365.90013 | I21: =EDATE(C21,6) -> 57161 | J21: =(K21-'3 - Phase Durations'!C16)/30.44 -> 353.87648 | K21: =EDATE(C21,-6) -> 56795 | L21: End of Phase E; 4-year prime science mission.
A22: Phase X | B22: End of Life / Disposal Operations Complete | C22: ='3 - Phase Durations'!D23 -> 58256 | D22: N/A | E22: N/A | F22: =(G22-'3 - Phase Durations'!C16)/30.44 -> 415.90013 | G22: =EDATE(C22,14) -> 58683 | H22: =(I22-'3 - Phase Durations'!C16)/30.44 -> 408.90276 | I22: =EDATE(C22,7) -> 58470 | J22: =(K22-'3 - Phase Durations'!C16)/30.44 -> 394.90802 | K22: =EDATE(C22,-7) -> 58044 | L22: End of Phase X; optional mission extension.
B29: ORCA Milestone Reference
B30: Milestone | C30: Realistic Date | E30: Phase | F30: Purpose
B31: Mission Concept Review (MCR) | C31: =C4 -> 46752 | E31: Phase 0 | F31: Mission concept baseline
B32: System Requirements Review (SRR) | C32: =C5 -> 47483 | E32: Phase A | F32: Requirements baseline
B33: ORCA Concept Rebaseline | C33: =C6 -> 47300.5 | E33: Phase A | F33: Programmatic baseline update
B34: Orbiter Bus / ORCA Instrument Suite Interface Complete | C34: =C7 -> 47921.4 | E34: Phase B | F34: Interface control document finalized
B35: Preliminary Design Review (PDR) | C35: =C8 -> 48213 | E35: Phase B | F35: Preliminary design maturity
B36: Instrument Suite Environmental Qualification Complete | C36: =C9 -> 48652 | E36: Phase C | F36: Instrument suite qualification
B37: Critical Design Review (CDR) | C37: =C10 -> 48944 | E37: Phase C | F37: Design baseline approval
B38: Manufacturing Readiness Review (MRR) | C38: =C11 -> 49765.5 | E38: MAIT | F38: Manufacturing readiness
B39: Pre-Ship Review of Systems to Prime (PSR) | C39: =C12 -> 51321 | E39: MAIT | F39: Transfer readiness
B40: Integrated Instrument Suite Functional Test Complete | C40: =C13 -> 51379 | E40: SAIT | F40: Functional test readiness
B41: System Integration Review (SIR) | C41: =C14 -> 51409 | E41: SAIT | F41: Integrated system readiness
B42: Acceptance Review (AR) | C42: =C15 -> 51411 | E42: SAIT | F42: Flight acceptance
... B49: End of Life / Disposal Operations Complete | C49: =C22 -> 58256 | E49: Phase X | F49: Mission closeout

Sheet GR&A
A2: Costing CSA Ground Rules & Assumptions template
A3: Last review | D3: 45747
A5: ID | B5: Catégorie | C5: Category | D5: Category | E5: Sub-category | F5: Items | G5: GR or A | H5: Title | I5: Description | J5: Phase | K5: CBS # linked to GR&A | L5: Impact on Project | M5: Impact on costing, methodology, models, tools & analysis | N5: Excepted source | O5: Do not delete | P5: Source/Link | Q5: Other rational | R5: Waiver deviation
A6: 1 | B6: Hypothèses Programmatiques | C6: Strategy Naratives | D6: Objectifs politiques et stratégiques | E6: Alignement sur la stratégie de l’ASC | N6: Business Case et/ou CADRE Part C onglet CM list | O6: Strategy
A7: 2 | B7: Hypothèses Programmatiques | C7: Strategy Naratives | D7: Objectifs politiques et stratégiques | E7: Contraintes gouvernementales ou directives de haut niveau | N7: Business Case et/ou CADRE Part C onglet CM list | O7: Strategy
A8: 3 | B8: Hypothèses Programmatiques | D8: Objectifs politiques et stratégiques | E8: Type de mission : Flagship, LargeSat, SmallSat, NanoSat, Hosted Payload, Data stream partnership, data stream purchase | N8: CADRE Part A | O8: CADRE Part A ou contants
A9: 4 | B9: Hypothèses Programmatiques | D9: Objectifs politiques et stratégiques | E9: Disciplines et secteur : SatCom, Astronomie, exploration spatiale,... | N9: CADRE Part A | O9: CADRE Part A
A10: 5 | B10: Hypothèses Programmatiques | D10: Objectifs politiques et stratégiques | E10: Dépendances avec d'autres projets/missions | N10: CADRE Part A | O10: CADRE Part A
A11: 6 | B11: Hypothèses Programmatiques | C11: Strategy Naratives | D11: Budget global et financement | E11: Soumission au Conseil du Tésor (TBSub) - But de l'exercice de costing : Budget Ask, Reprofiling,… Définir le nombre de TBSub + échéancier associé aux TBSub | N11: CADRE Part C onglet Stratégie contractuelle | O11: Strategy
A12: 7 | B12: Hypothèses Programmatiques | C12: Strategy Naratives | D12: Budget global et financement | E12: Enveloppe de la masse salariale | N12: CADRE Part C onglet RAM | O12: Strategy
A13: 8 | B13: Hypothèses Programmatiques | C13: Strategy Naratives | D13: Budget global et financement | E13: Enveloppe des frais de gestion et plan de voyages | N13: CADRE Part C onglet Overhead Costs | O13: Strategy
A14: 9 | B14: Hypothèses Programmatiques | C14: Costign Plan | D14: Budget global et financement | E14: Méthodologie d'établissement des coûts | N14: Plan de l’exercice d’établissement des coûts | O14: Costing Plan
A15: 10 | B15: Hypothèses Programmatiques | C15: Costign Plan | D15: Budget global et financement | E15: Note de réflexion supplémentaire | O15: Costing Plan
A16: 11 | B16: Hypothèses Programmatiques | C16: Costign Plan | D16: Budget global et financement | E16: Au moins 2 façon différentes pour chaque incluant RAM | N16: Plan de l’exercice d’établissement des coûts - Méthodologies | O16: Costing Plan
A17: 12 | B17: Hypothèses Programmatiques | C17: Costign Plan | D17: Budget global et financement | E17: Analyse de sensibilité | N17: À compléter par Finance | O17: Costing Plan
A18: 13 | B18: Hypothèses Programmatiques | C18: Costign Plan | D18: Budget global et financement | E18: Sufficiency Report or Independent Cost Estimate or Independent Cost Review | N18: À compléter par Finance | O18: Costing Plan
A19: 14 | B19: Hypothèses Programmatiques | C19: Costign Plan | D19: Budget global et financement | E19: Analogie (nearest neighboors), lesquels. | N19: Plan de l’exercice d’établissement des coûts - Méthodologies | O19: Costing Plan
A20: 15 | B20: Hypothèses Programmatiques | C20: Costign Plan | D20: Budget global et financement | E20: Analyse paramétrique (True planning, PCEC, NCIM, SEER, Compact). CER Calibration Plan. | N20: Plan de l’exercice d’établissement des coûts - Méthodologies | O20: Costing Plan
A21: 16 | B21: Hypothèses Programmatiques | C21: Costign Plan | D21: Budget global et financement | E21: Soumission de l'industrie et jugement d'expert | N21: Plan de l’exercice d’établissement des coûts - Méthodologies | O21: Costing Plan
A22: 17 | B22: Hypothèses Programmatiques | C22: Costign Plan | D22: Budget global et financement | E22: Analyse Monte Carlo (crystal ball) | N22: Plan de l’exercice d’établissement des coûts - Méthodologies | O22: Costing Plan
A23: 18 | B23: Hypothèses Programmatiques | C23: Costign Plan | D23: Budget global et financement | E23: Bottom up, qui le fait et comment | N23: Plan de l’exercice d’établissement des coûts - Méthodologies | O23: Costing Plan
A24: 19 | B24: Hypothèses Programmatiques | C24: Costign Plan | D24: Budget global et financement | E24: Learning curves | N24: RASCI = qui fait quoi. bottom up = Plan de l’exercice d’établissement des coûts | O24: Costing Plan
A25: 20 | B25: Hypothèses Programmatiques | C25: Costign Plan | D25: Budget global et financement | E25: Inducteurs de coûts princicaux | N25: CADRE Part C onglet CER & Tools | O25: Costing Plan
A26: 21 | B26: Hypothèses Programmatiques | C26: Costign Plan | D26: Budget global et financement | E26: Normalisation ( Stochométrie) - si applicable | N26: le choix de l'outil dicte CADRE part B qui collecte info pour l'analyse paramétrique | O26: Costing Plan
A27: 22 | B27: Hypothèses Programmatiques | C27: Costign Plan | D27: Budget global et financement | E27: Tracabilité - accès aux sources - répertoires normalisés -liens | N27: CADRE Part C onglet CER & Tools | O27: Costing Plan
... A42: 37 | B42: Hypothèses Financières | C42: 8. Inflation Model | D42: Indices économiques et inflation | E42: Modèle d'inflation appliqué | N42: Inflation Model dans son propre document - Oracle db ID | O42: Inflation Model
A43: 38 | B43: Hypothèses Financières | C43: 8. Economic Constants and short answers | D43: Indices économiques et inflation | E43: Année de base / Base year | O43: Constants
A44: 39 | B44: Hypothèses Financières | C44: 8. Economic Constants and short answers | D44: Indices économiques et inflation | E44: SSC 4% | N44: Financial Constants Reports - CSA-FIN-RPT-XXXX rev 3 | O44: Constants
A45: 40 | B45: Hypothèses Financières | C45: 8. Economic Constants and short answers | D45: Indices économiques et inflation | E45: PSPC 13% | N45: Financial Constants Reports - CSA-FIN-RPT-XXXX rev 3 | O45: Constants
A46: 41 | B46: Hypothèses Financières | C46: 8. Economic Constants and short answers | D46: Indices économiques et inflation | E46: Taux du Fairness Monitor | N46: Financial Constants Reports - CSA-FIN-RPT-XXXX rev 3 | O46: Constants
A47: 42 | B47: Hypothèses Financières | C47: 8. Economic Constants and short answers | D47: Taux de change | E47: Monnaies concernées et valeur de référence (CAD, USD, EUR, etc.) | N47: Financial Constants Reports - CSA-FIN-RPT-XXXX rev 3 | O47: Constants
A48: 43 | B48: Hypothèses Financières | C48: 8. Economic Constants and short answers | D48: Taux de change | E48: Seuil de variation accepté avant révision budgétaire | N48: Defined in constnats, used in risk analysis. risk reserve - Risk register | O48: Constants
A49: 44 | B49: Hypothèses Financières | C49: 8. Economic Constants and short answers | D49: Contingence et marges de sécurité | E49: Pourcentage de contingence sur le coût total du projet (p. ex. 10 à 20 %) | N49: Defined in constnats, used in risk analysis. risk register onglet. Unknown-Unknown Risk margin | O49: Constants
A50: 45 | B50: Hypothèses Financières | C50: Strategy Naratives | D50: Contingence et marges de sécurité | E50: Barème d’évaluation des risques majeurs pour justifier la marge appliquée (modèle d’analyse de risques) | N50: À définir ici | O50: Strategy | P50: Je ne comprends pas la question
A51: 46 | B51: Hypothèses Financières | C51: Procurement Plan | D51: Stratégie contractuelle, coûts de main-d’œuvre et de sous-traitance | E51: Sunk Costs Report (STDP, EOADP, Cap Demo, Stedia FAST, ESA Program, Cubesats, space hub, Pre-Phase 0 etc) | N51: CADRe part C - Expenditure plan | O51: Procurement Plan
A52: 47 | B52: Hypothèses Financières | C52: Strategy Naratives | D52: Stratégie contractuelle, coûts de main-d’œuvre et de sous-traitance | E52: Stratégie contractuel Phase 0/A - 1 / 2 contrats | N52: CADRe Part C - Procurement strategy | O52: Strategy
A53: 48 | B53: Hypothèses Financières | C53: Strategy Naratives | D53: Stratégie contractuelle, coûts de main-d’œuvre et de sous-traitance | E53: Note de réflexion supplémentaire | O53: Strategy
A54: 49 | B54: Hypothèses Financières | C54: Procurement Plan | D54: Stratégie contractuelle, coûts de main-d’œuvre et de sous-traitance | E54: Nombre de contrats et valeur approximative prévus par phase | N54: CADRe Part C - Procurement Plan (list) | O54: Procurement Plan
A55: 50 | B55: Hypothèses Financières | C55: Strategy Naratives | D55: Stratégie contractuelle, coûts de main-d’œuvre et de sous-traitance | E55: Contrats en parallèle avec des concepts différents et un down select | N55: CADRe Part C - Procurement strategy | O55: Strategy
A56: 51 | B56: Hypothèses Financières | C56: Strategy Naratives | D56: Stratégie contractuelle, coûts de main-d’œuvre et de sous-traitance | E56: Agile ou waterfall | N56: CADRe Part C - Procurement strategy | O56: Strategy
A57: 52 | B57: Hypothèses Financières | C57: Strategy Naratives | D57: Stratégie contractuelle, coûts de main-d’œuvre et de sous-traitance | E57: STDP ou CapDemo en même temps que la phase 0 ou A | N57: PREP 2 | O57: Strategy
A58: 53 | B58: Hypothèses Financières | C58: OBS | D58: Stratégie contractuelle, coûts de main-d’œuvre et de sous-traitance | E58: Les fournisseurs attendus et leur capacite de production | N58: OBS | O58: OBS
A59: 54 | B59: Hypothèses Financières | C59: Strategy Naratives | D59: Stratégie contractuelle, coûts de main-d’œuvre et de sous-traitance | E59: Type de SOW - SOW directif versus une architecture de mission proposée par le fournisseur | N59: CADRe Part C - Procurement strategy | O59: Strategy
A60: 55 | B60: Hypothèses Financières | C60: Strategy Naratives | D60: Stratégie contractuelle, coûts de main-d’œuvre et de sous-traitance | E60: Freedom of Design of Vendor | N60: CADRE Part C onglet OBS Maturité orgnisationelle du fourniseur | O60: Strategy
A61: 56 | B61: Hypothèses Financières | C61: Strategy Naratives | D61: Stratégie contractuelle, coûts de main-d’œuvre et de sous-traitance | E61: Types de contrat – source unique ou compétitif (Contrat dirigé en Phase E ops aura une incidence sur le design du ground segment) | N61: CADRe Part C - Procurement strategy | O61: Strategy
A62: 57 | B62: Hypothèses Financières | C62: Strategy Naratives | D62: Stratégie contractuelle, coûts de main-d’œuvre et de sous-traitance | E62: Types de contrat – cout remboursable ou prix ferme | N62: CADRe Part C - Procurement strategy | O62: Strategy
B63: Hypothèses Financières | C63: Strategy Naratives | D63: Stratégie contractuelle, coûts de main-d’œuvre et de sous-traitance | E63: Type de contrat: gonogo, options, milestones in April for CAFÉ | O63: Strategy | P63: Split next line into 2
A64: 58 | B64: Hypothèses Financières | C64: 12 - Dispose, Divest, Descope, Delay | D64: Stratégie contractuelle, coûts de main-d’œuvre et de sous-traitance | E64: Gestion du scope change et des risques dans chaque situation : cout remboursable (TA, options, gouvernance) ; prix ferme (descope, go no go, qualité du SOW a décrire le scope) | N64: Descope est dans DDD | O64: DDDD
A65: 59 | B65: Hypothèses Financières | D65: Stratégie contractuelle, coûts de main-d’œuvre et de sous-traitance | E65: G&C (cassiope ou radarsat 2) nous appartient pas | N65: Business model (CADRe part A) et le procurement strategy le repete | O65: CADRE Part A
A66: 60 | B66: Hypothèses Financières | C66: Strategy Naratives | D66: Stratégie contractuelle, coûts de main-d’œuvre et de sous-traitance | E66: incitatif commercial (ex. modele de commercialization comme a prior mission) | N66: CADRe Part C - Procurement strategy | O66: Strategy
A67: 61 | B67: Hypothèses Financières | C67: Strategy Naratives | D67: Stratégie contractuelle, coûts de main-d’œuvre et de sous-traitance | E67: Pour chaque phase et sous-systeme majeur - CSA led, industry led, academia led (ex. En Phase E, CSA va mener les operations) | N67: CADRe Part C - Procurement strategy | O67: Strategy
A68: 62 | B68: Hypothèses Financières | C68: Strategy Naratives | D68: Stratégie contractuelle, coûts de main-d’œuvre et de sous-traitance | E68: Competitif - ouvert a l'international | N68: CADRe Part C - Procurement strategy | O68: Strategy
A69: 63 | B69: Hypothèses Financières | C69: Strategy Naratives | D69: Stratégie contractuelle, coûts de main-d’œuvre et de sous-traitance | E69: Competitif - ouvert au Canada | N69: CADRe Part C - Procurement strategy | O69: Strategy
A70: 64 | B70: Hypothèses Financières | C70: Strategy Naratives | D70: Stratégie contractuelle, coûts de main-d’œuvre et de sous-traitance | E70: Fausse competition | N70: CADRe Part C - Procurement strategy | O70: Strategy
A71: 65 | B71: Hypothèses Financières | C71: Strategy Naratives | D71: Stratégie contractuelle, coûts de main-d’œuvre et de sous-traitance | E71: monopole | N71: CADRe Part C - Procurement strategy | O71: Strategy
A72: 66 | B72: Hypothèses Financières | C72: Strategy Naratives | D72: Stratégie contractuelle, coûts de main-d’œuvre et de sous-traitance | E72: Dependences : Le fournisseur X doit etre le meme fournisseur que le fournisseur Y (Ex. Data processing handled by same supplier) | N72: CADRe Part C - Procurement strategy | O72: Strategy
A73: 67 | B73: Hypothèses Financières | C73: Strategy Naratives | D73: Stratégie contractuelle, coûts de main-d’œuvre et de sous-traitance | E73: Long lead Item - flux de trésorie en capital vs contrat vs échéancier | N73: CADRE Part C onglet QUANTITIES - LLI, spares, EM, PFM, RE-NRE | O73: Strategy
A74: 68 | B74: Hypothèses Financières | C74: Strategy Naratives | D74: Stratégie contractuelle, coûts de main-d’œuvre et de sous-traitance | E74: Contenu Canadien | N74: CADRe Part C - Procurement strategy | O74: Strategy
A75: 69 | B75: Hypothèses Financières | C75: Strategy Naratives | D75: Stratégie contractuelle, coûts de main-d’œuvre et de sous-traitance | E75: Chaque contrat couvre quel partie du travail, liste d'inclusions et exclusions. List of inclusions and exclusions | N75: CBS Dictionary | O75: Strategy
A76: 70 | B76: Hypothèses Financières | C76: Strategy Naratives | D76: Stratégie contractuelle, coûts de main-d’œuvre et de sous-traitance | E76: GFE and GFS (ex. DFL) | N76: CBS Dictionary | O76: Strategy
A77: 71 | B77: Hypothèses Financières | C77: Strategy Naratives | D77: Stratégie contractuelle, coûts de main-d’œuvre et de sous-traitance | E77: Frais de transport et responsabilité | N77: CBS Dictionary | O77: Strategy
... A97: 91 | B97: Hypothèses Techniques (Space & Ground Segment) | C97: Costign Plan | D97: Sous-systèmes et architecture globale | E97: This ground rule should state, at a high level, what is within scope of the estimate. For example, an estimate may cover the space segment, ground segment, and government oversight during phases B, C and D. Further clarification should be given if required, such as refurbishment of the ground segment rather than complete rebuild. | N97: Perimeter of costing exercise. Further Claraifications in CBs dictionary | O97: Costing Plan
A98: 92 | B98: Hypothèses Techniques (Space & Ground Segment) | D98: Durée de vie du projet et cycles de développement | E98: Stratégie de validation (modèles d’ingénierie, prototypes, simulations) | N98: CADRE Part C onglet QUANTITIES - LLI, spares, EM, PFM, RE-NRE | O98: Quantities
A99: 93 | B99: Hypothèses Techniques (Space & Ground Segment) | D99: Durée de vie du projet et cycles de développement | E99: Méthodes d’essais en environnement (thermique, vibration, vide, etc.) | N99: CADRE Part C onglet QUANTITIES - LLI, spares, EM, PFM, RE-NRE | O99: Quantities
A100: 94 | B100: Hypothèses Techniques (Space & Ground Segment) | D100: Durée de vie du projet et cycles de développement | E100: This assumption should state the expected build approach for the mission. For example, the bus/platform and payloads could be built in series or parallel. | N100: CADRE Part C onglet QUANTITIES - LLI, spares, EM, PFM, RE-NRE | O100: Quantities
A101: 95 | B101: Hypothèses Techniques (Space & Ground Segment) | D101: Durée de vie du projet et cycles de développement | E101: This assumption should state the cost improvement curve, as a percentile, for any items to be acquired with more than a single unit. If appropriate, items should be marked as Xth unit within a lot, such as the 8th unit, to allow for cost improvement curve theory to be reflected. | N101: CADRE Part C onglet QUANTITIES - LLI, spares, EM, PFM, RE-NRE | O101: Quantities
A102: 96 | B102: Hypothèses Techniques (Space & Ground Segment) | C102: Engineering Parameters in CADRe part B | D102: Contraintes techniques spécifiques | E102: Estimation de masse et de volume du système | N102: CADRE part B | O102: CADRE part B
A103: 97 | B103: Hypothèses Techniques (Space & Ground Segment) | C103: Engineering Parameters in CADRe part B | D103: Contraintes techniques spécifiques | E103: Consommation électrique maximale | N103: CADRE part B | O103: CADRE part B
A104: 98 | B104: Hypothèses Techniques (Space & Ground Segment) | C104: Engineering Parameters in CADRe part B | D104: Contraintes techniques spécifiques | E104: Besoins minimaux pour assurer la fiabilité | N104: CADRE part B | O104: CADRE part B
A105: 99 | B105: Hypothèses Qualité, Fiabilité et Sécurité | C105: Strategy Naratives | D105: Normes et standards de qualité | E105: ECSS-Q-ST-20, ISO 9001, etc. | N105: À définir ici | O105: Strategy
A106: 100 | B106: Hypothèses Qualité, Fiabilité et Sécurité | C106: Strategy Naratives | D106: Normes et standards de qualité | E106: Méthodes d’assurance qualité (revues, audits internes et externes) | N106: À définir ici | O106: Strategy
A107: 101 | B107: Hypothèses Qualité, Fiabilité et Sécurité | C107: 8. Economic Constants and short answers | D107: Safety and mission assurance | E107: Classe de Mission | N107: À définir ici | O107: Constants
A108: 102 | B108: Hypothèses Qualité, Fiabilité et Sécurité | C108: Strategy Naratives | D108: Safety and mission assurance | E108: La mesure de la surveillance et de la rigueur appliquées par la CSA | N108: À définir ici | O108: Strategy
A109: 103 | B109: Hypothèses Opérationnelles | C109: RAM | D109: Ressources humaines et expertise | E109: Équipe de base (ETP internes) et besoins en personnel spécialisé externe | N109: CADRE Part C onglet RAM | O109: RAM
A110: 104 | B110: Hypothèses Opérationnelles | C110: Strategy Naratives | D110: Ressources humaines et expertise | E110: Disponibilité du personnel et plan de montée en compétence | N110: À définir ici | O110: Strategy
A111: 105 | B111: Hypothèses Opérationnelles | C111: Milestone Register | D111: Calendrier, jalons et ressources temporelles | E111: Dates clés (ex. PDR – Preliminary Design Review, CDR – Critical Design Review, FRR – Flight Readiness Review) / Project Milestone Register (short report, detailed report) | N111: milestone Register | O111: Milestone Register
A112: 106 | B112: Hypothèses Opérationnelles | D112: Calendrier, jalons et ressources temporelles | E112: Diagram of Phase Overlaps and Gaps | N112: we draw it form phasing | O112: GANTT Charts
A113: 107 | B113: Hypothèses Opérationnelles | C113: Schedule Constraints and Dependencies | D113: Calendrier, jalons et ressources temporelles | E113: Marges pour délais | N113: Phasing Model, phases | O113: Schedule Constraints
A114: 108 | B114: Hypothèses Opérationnelles | C114: 12 - Dispose, Divest, Descope, Delay | D114: Calendrier, jalons et ressources temporelles | E114: Gestion des retards : conditions de replanification, procédures d’escalade | N114: À définir ici et lié au CADRE Part C - onglet DDDD | O114: DDDD
A115: 109 | B115: Hypothèses Opérationnelles | C115: Phasing Schedules | D115: Calendrier, jalons et ressources temporelles | E115: Modèle de phase utilisé pour analyse de sensibilité (Phasing Model) | N115: Phasing model (for risk analysis) | O115: Phasing Schedules
A116: 110 | B116: Hypothèses Opérationnelles | C116: Phasing Schedules | D116: Calendrier, jalons et ressources temporelles | E116: Échéancier de l'industrie | N116: Phasing model (for risk analysis) | O116: Phasing Schedules
A117: 111 | B117: Hypothèses Opérationnelles | C117: Phasing Schedules | D117: Calendrier, jalons et ressources temporelles | E117: Schedule Scenarios for sensitivity analysis : Adjust Durations - optimistic, pessimistic and expected | N117: Phasing model (for risk analysis) | O117: Phasing Schedules
A118: 112 | B118: Hypothèses Opérationnelles | C118: Strategy Naratives | D118: Planification des infrastructures et installations | E118: Is DFL being used as GFE | N118: DFL being used? Strategy | O118: Strategy
A119: 112 | B119: Hypothèses Opérationnelles | C119: 4a. CBS and CBS Dictionary | D119: Planification des infrastructures et installations | E119: Lieux de développement, sites d’intégration et de test (chambres à vide, bancs de test) | N119: CBS Dictionary - Ground Segment - Test facilities | O119: CBS Dictionary
A120: 113 | B120: Hypothèses Opérationnelles | C120: Schedule Constraints and Dependencies | D120: Planification des infrastructures et installations | E120: Disponibilité des installations (ex. créneaux de test partagés avec d’autres projets) | N120: schedule risk = risk register -> pessimistic schedule model | O120: Schedule Constraints
A121: 114 | B121: Hypothèses Opérationnelles | C121: Schedule Constraints and Dependencies | D121: Gestion de la logistique et de la chaîne d’approvisionnement | E121: Délai de livraison des composants critiques (satellites, propulseurs, éléments électroniques) | N121: schedule risk = risk register -> pessimistic schedule model | O121: Schedule Constraints
A122: 115 | B122: Hypothèses Opérationnelles | C122: Strategy Naratives | D122: Gestion de la logistique et de la chaîne d’approvisionnement | E122: Plans de contingence en cas de rupture d’approvisionnement | N122: CADRE Part C onglet DDDD - dispose, descope, divest, delay | O122: Strategy
A123: 116 | B123: Hypothèses Opérationnelles | D123: Plan de gestion de mission (SatOps) | E123: Description des opérations prévues : phases de lancement, mise à l’orbite, opérations nominales, etc. | N123: Cadre part A | O123: CADRE Part A
A124: 117 | B124: Hypothèses Opérationnelles | D124: Plan de gestion de mission (SatOps) | E124: Mode de supervision et contrôle (centres de contrôle, horaires, équipes) | N124: À définir ici | O124: Cadre Part A
A125: 118 | B125: Hypothèses Opérationnelles | D125: Plan de gestion de mission (SatOps) | E125: Mission Operation Center | N125: À définir ici | O125: Cadre Part A
A126: 119 | B126: Hypothèses Opérationnelles | D126: Plan de gestion de mission (SatOps) | E126: GoC Science Operation Centers (SOCs) | N126: À définir ici | O126: Cadre Part A
A127: 120 | B127: Hypothèses Opérationnelles | D127: Plan de gestion de mission (SatOps) | E127: External Science Operation Centers (ESOCs) | N127: À définir ici | O127: Cadre Part A
A128: 121 | B128: Hypothèses sur la science | C128: Schedule Constraints and Dependencies | D128: Science et applications | E128: Échéancier lié au volet de science du projet | O128: Schedule Constraints
A129: 122 | B129: Hypothèses sur la science | C129: Strategy Naratives | D129: Science et applications | E129: Expected cost of science utilization related to the mission. | O129: Strategy
A130: 123 | B130: Hypothèses sur la science | C130: Strategy Naratives | D130: Portée de la mission sur le milieu public et académique | E130: Coût en lien avec la portée de la mission | N130: À définir ici | O130: Strategy
A131: 124 | B131: Hypothèses Lancement | D131: Véhicule de lancement | E131: Sélection du lanceur (ex. Falcon 9, Ariane, etc.) ou fenêtre de lancement partagée | N131: Cadre part A | O131: CADRE Part A
A132: 125 | B132: Hypothèses Lancement | D132: Véhicule de lancement | E132: Capacités du lanceur (masse, volume, orbite cible) | N132: Cadre part A un petit peu et le reste dans le LV database CM list | O132: CADRE Part A
A133: 126 | B133: Hypothèses Lancement | C133: Schedule Constraints and Dependencies | D133: Calendrier de lancement | E133: Fenêtres de lancement disponibles (contraintes de météo, alignement orbital, etc.) | N133: schedule risk = risk register -> pessimistic schedule model | O133: Schedule assumptions and constraints for JCL Analysis
A134: 127 | B134: Hypothèses Lancement | C134: 12 - Dispose, Divest, Descope, Delay | D134: Calendrier de lancement | E134: Contingences pour reports éventuels | N134: schedule risk = risk register -> pessimistic schedule model | O134: DDDD
A135: 128 | B135: Hypothèses Lancement | C135: OBS | D135: Contrat et services associés | E135: Responsabilités du fournisseur de lancement (intégration, tests, qualification) | N135: OBS (roles et responsiblity) - CSa qui paye ou MDa qui paye | O135: OBS
...

Sheet 4 - RAM LoE
A3: 9 - RAM LoE Inputs
A4: Why we are asking:
B5: To capture the ORCA project's Resource Allocation Matrix: every position on the team, its classification, and its Level of Effort (LoE) as a fraction of full-time equivalent (FTE) by mission phase. Rate is looked up from 'Labour Rates lookup' by Classification, and the fiscal-year \$ columns are computed self-contained on this sheet from LoE x rate x schedule-phase-month overlap (see '3 - Phase Durations'). EBP and inflation figures are illustrative placeholders.
B10: RAM Scenario ID | C10: 1
B11: Scenario Name | C11: Nominal RAM
B12: Scenario Description | C12: The baseline RAM used for ORCA's staffing plan.
B13: Rationale | C13: Derived from the ORCA instrument suite WBS/CBS and the Phase Durations schedule.
B14: Source Doc | C14: N/A - illustrative, pending confirmed CSA staffing plan
A16: Defaults | J16: Provided by PM | Q16: LoE as % of one FTE, by phase (PM input) | X16: Rates tab | Y16: FTE per fiscal year, calculated from '3 - Phase Durations' and the phase LoE on the left
A17: Row Num | B17: Agency / Dep't | C17: Team | D17: Skillset Group | E17: Skillset | F17: Title - Role | G17: Additional Labels | H17: Branch | I17: Directorate | J17: Employee Name | K17: Position No | L17: New or Existing | M17: Classification | N17: Echelon | O17: Math Model | P17: Funding Source | Q17: Phase 0 | R17: Phase A | S17: Phase B | T17: Phase C | U17: Phase D | V17: Phase E | W17: Phase F | X17: Rate ($) | Y17: 2026 | Z17: 2027 | AA17: 2028 | AB17: 2029 | AC17: 2030 | AD17: 2031 | AE17: 2032 | AF17: 2033 | AG17: 2034 | AH17: 2035 | AI17: 2036 | AJ17: 2037 | AK17: 2038 | AL17: 2039 | AM17: 2040 | AN17: 2041 | AO17: 2042 | AP17: 2043 | AQ17: 2044 | AR17: 2045 | AS17: 2046 | AT17: 2047 | AU17: 2048 | AV17: 2049 | AW17: 2050 | AX17: 2051 | AY17: 2052 | AZ17: 2053 | BA17: 2054 | BB17: 2055 | BC17: 2056 | BD17: 2057 | BE17: 2058 | BF17: 2059 | BG17: 2060 | BH17: Total (FTE-yrs)
A18: 1 | B18: CSA | C18: Project Team | D18: Project Manager | E18: PM | F18: Portfolio Manager | G18: Program Office | H18: Space Exploration | I18: Program Management | J18: Alan Whitfield | K18: ORCA-PM-001 | L18: Existing | M18: EN-ENG-6 | N18: Max Echelon | O18: Labour Rates | P18: FF-CSA | Q18: 0 | R18: 0 | S18: 0.21 | T18: 0 | U18: 0.42 | V18: 1 | W18: 0 | X18: =IFERROR(VLOOKUP($M18,'Labour Rates lookup'!$A:$B,2,FALSE()),0) -> 165000 | Y18: =($Q18*'3 - Phase Durations'!$G$16+$R18*'3 - Phase Durations'!$G$17+$S18*('3 - Phase Durations'!$G$18+'3 - Phase Durations'!$G$19)+$T18*'3 - Phase Durations'!$G$20+$U18*'3 - Phase Durations'!$G$21+$V18*('3 - Phase Durations'!$G$22+'3 - Phase Durations'!$G$23)+$W18*'3 - Phase Durations'!$G$24)/12 -> 0 | Z18: =($Q18*'3 - Phase Durations'!$H$16+$R18*'3 - Phase Durations'!$H$17+$S18*('3 - Phase Durations'!$H$18+'3 - Phase Durations'!$H$19)+$T18*'3 - Phase Durations'!$H$20+$U18*'3 - Phase Durations'!$H$21+$V18*('3 - Phase Durations'!$H$22+'3 - Phase Durations'!$H$23)+$W18*'3 - Phase Durations'!$H$24)/12 -> 0 | AA18: =($Q18*'3 - Phase Durations'!$I$16+$R18*'3 - Phase Durations'!$I$17+$S18*('3 - Phase Durations'!$I$18+'3 - Phase Durations'!$I$19)+$T18*'3 - Phase Durations'!$I$20+$U18*'3 - Phase Durations'!$I$21+$V18*('3 - Phase Durations'!$I$22+'3 - Phase Durations'!$I$23)+$W18*'3 - Phase Durations'!$I$24)/12 -> 0 | AB18: =($Q18*'3 - Phase Durations'!$J$16+$R18*'3 - Phase Durations'!$J$17+$S18*('3 - Phase Durations'!$J$18+'3 - Phase Durations'!$J$19)+$T18*'3 - Phase Durations'!$J$20+$U18*'3 - Phase Durations'!$J$21+$V18*('3 - Phase Durations'!$J$22+'3 - Phase Durations'!$J$23)+$W18*'3 - Phase Durations'!$J$24)/12 -> 0 | AC18: =($Q18*'3 - Phase Durations'!$K$16+$R18*'3 - Phase Durations'!$K$17+$S18*('3 - Phase Durations'!$K$18+'3 - Phase Durations'!$K$19)+$T18*'3 - Phase Durations'!$K$20+$U18*'3 - Phase Durations'!$K$21+$V18*('3 - Phase Durations'!$K$22+'3 - Phase Durations'!$K$23)+$W18*'3 - Phase Durations'!$K$24)/12 -> 0.051780822 | AD18: =($Q18*'3 - Phase Durations'!$L$16+$R18*'3 - Phase Durations'!$L$17+$S18*('3 - Phase Durations'!$L$18+'3 - Phase Durations'!$L$19)+$T18*'3 - Phase Durations'!$L$20+$U18*'3 - Phase Durations'!$L$21+$V18*('3 - Phase Durations'!$L$22+'3 - Phase Durations'!$L$23)+$W18*'3 - Phase Durations'!$L$24)/12 -> 0.21 | AE18: =($Q18*'3 - Phase Durations'!$M$16+$R18*'3 - Phase Durations'!$M$17+$S18*('3 - Phase Durations'!$M$18+'3 - Phase Durations'!$M$19)+$T18*'3 - Phase Durations'!$M$20+$U18*'3 - Phase Durations'!$M$21+$V18*('3 - Phase Durations'!$M$22+'3 - Phase Durations'!$M$23)+$W18*'3 - Phase Durations'!$M$24)/12 -> 0.15821918 | AF18: =($Q18*'3 - Phase Durations'!$N$16+$R18*'3 - Phase Durations'!$N$17+$S18*('3 - Phase Durations'!$N$18+'3 - Phase Durations'!$N$19)+$T18*'3 - Phase Durations'!$N$20+$U18*'3 - Phase Durations'!$N$21+$V18*('3 - Phase Durations'!$N$22+'3 - Phase Durations'!$N$23)+$W18*'3 - Phase Durations'!$N$24)/12 -> 0 | AG18: =($Q18*'3 - Phase Durations'!$O$16+$R18*'3 - Phase Durations'!$O$17+$S18*('3 - Phase Durations'!$O$18+'3 - Phase Durations'!$O$19)+$T18*'3 - Phase Durations'!$O$20+$U18*'3 - Phase Durations'!$O$21+$V18*('3 - Phase Durations'!$O$22+'3 - Phase Durations'!$O$23)+$W18*'3 - Phase Durations'!$O$24)/12 -> 0.10356164 | AH18: =($Q18*'3 - Phase Durations'!$P$16+$R18*'3 - Phase Durations'!$P$17+$S18*('3 - Phase Durations'!$P$18+'3 - Phase Durations'!$P$19)+$T18*'3 - Phase Durations'!$P$20+$U18*'3 - Phase Durations'!$P$21+$V18*('3 - Phase Durations'!$P$22+'3 - Phase Durations'!$P$23)+$W18*'3 - Phase Durations'!$P$24)/12 -> 0.42 | AI18: =($Q18*'3 - Phase Durations'!$Q$16+$R18*'3 - Phase Durations'!$Q$17+$S18*('3 - Phase Durations'!$Q$18+'3 - Phase Durations'!$Q$19)+$T18*'3 - Phase Durations'!$Q$20+$U18*'3 - Phase Durations'!$Q$21+$V18*('3 - Phase Durations'!$Q$22+'3 - Phase Durations'!$Q$23)+$W18*'3 - Phase Durations'!$Q$24)/12 -> 0.42115068 | AJ18: =($Q18*'3 - Phase Durations'!$R$16+$R18*'3 - Phase Durations'!$R$17+$S18*('3 - Phase Durations'!$R$18+'3 - Phase Durations'!$R$19)+$T18*'3 - Phase Durations'!$R$20+$U18*'3 - Phase Durations'!$R$21+$V18*('3 - Phase Durations'!$R$22+'3 - Phase Durations'!$R$23)+$W18*'3 - Phase Durations'!$R$24)/12 -> 0.42 | AK18: =($Q18*'3 - Phase Durations'!$S$16+$R18*'3 - Phase Durations'!$S$17+$S18*('3 - Phase Durations'!$S$18+'3 - Phase Durations'!$S$19)+$T18*'3 - Phase Durations'!$S$20+$U18*'3 - Phase Durations'!$S$21+$V18*('3 - Phase Durations'!$S$22+'3 - Phase Durations'!$S$23)+$W18*'3 - Phase Durations'!$S$24)/12 -> 0.42 | AL18: =($Q18*'3 - Phase Durations'!$T$16+$R18*'3 - Phase Durations'!$T$17+$S18*('3 - Phase Durations'!$T$18+'3 - Phase Durations'!$T$19)+$T18*'3 - Phase Durations'!$T$20+$U18*'3 - Phase Durations'!$T$21+$V18*('3 - Phase Durations'!$T$22+'3 - Phase Durations'!$T$23)+$W18*'3 - Phase Durations'!$T$24)/12 -> 0.42 | AM18: =($Q18*'3 - Phase Durations'!$U$16+$R18*'3 - Phase Durations'!$U$17+$S18*('3 - Phase Durations'!$U$18+'3 - Phase Durations'!$U$19)+$T18*'3 - Phase Durations'!$U$20+$U18*'3 - Phase Durations'!$U$21+$V18*('3 - Phase Durations'!$U$22+'3 - Phase Durations'!$U$23)+$W18*'3 - Phase Durations'!$U$24)/12 -> 0.42115068 | AN18: =($Q18*'3 - Phase Durations'!$V$16+$R18*'3 - Phase Durations'!$V$17+$S18*('3 - Phase Durations'!$V$18+'3 - Phase Durations'!$V$19)+$T18*'3 - Phase Durations'!$V$20+$U18*'3 - Phase Durations'!$V$21+$V18*('3 - Phase Durations'!$V$22+'3 - Phase Durations'!$V$23)+$W18*'3 - Phase Durations'!$V$24)/12 -> 0.5630137 | AO18: =($Q18*'3 - Phase Durations'!$W$16+$R18*'3 - Phase Durations'!$W$17+$S18*('3 - Phase Durations'!$W$18+'3 - Phase Durations'!$W$19)+$T18*'3 - Phase Durations'!$W$20+$U18*'3 - Phase Durations'!$W$21+$V18*('3 - Phase Durations'!$W$22+'3 - Phase Durations'!$W$23)+$W18*'3 - Phase Durations'!$W$24)/12 -> 1 | AP18: =($Q18*'3 - Phase Durations'!$X$16+$R18*'3 - Phase Durations'!$X$17+$S18*('3 - Phase Durations'!$X$18+'3 - Phase Durations'!$X$19)+$T18*'3 - Phase Durations'!$X$20+$U18*'3 - Phase Durations'!$X$21+$V18*('3 - Phase Durations'!$X$22+'3 - Phase Durations'!$X$23)+$W18*'3 - Phase Durations'!$X$24)/12 -> 1 | AQ18: =($Q18*'3 - Phase Durations'!$Y$16+$R18*'3 - Phase Durations'!$Y$17+$S18*('3 - Phase Durations'!$Y$18+'3 - Phase Durations'!$Y$19)+$T18*'3 - Phase Durations'!$Y$20+$U18*'3 - Phase Durations'!$Y$21+$V18*('3 - Phase Durations'!$Y$22+'3 - Phase Durations'!$Y$23)+$W18*'3 - Phase Durations'!$Y$24)/12 -> 1.0027397 | AR18: =($Q18*'3 - Phase Durations'!$Z$16+$R18*'3 - Phase Durations'!$Z$17+$S18*('3 - Phase Durations'!$Z$18+'3 - Phase Durations'!$Z$19)+$T18*'3 - Phase Durations'!$Z$20+$U18*'3 - Phase Durations'!$Z$21+$V18*('3 - Phase Durations'!$Z$22+'3 - Phase Durations'!$Z$23)+$W18*'3 - Phase Durations'!$Z$24)/12 -> 1 | AS18: =($Q18*'3 - Phase Durations'!$AA$16+$R18*'3 - Phase Durations'!$AA$17+$S18*('3 - Phase Durations'!$AA$18+'3 - Phase Durations'!$AA$19)+$T18*'3 - Phase Durations'!$AA$20+$U18*'3 - Phase Durations'!$AA$21+$V18*('3 - Phase Durations'!$AA$22+'3 - Phase Durations'!$AA$23)+$W18*'3 - Phase Durations'!$AA$24)/12 -> 1 | AT18: =($Q18*'3 - Phase Durations'!$AB$16+$R18*'3 - Phase Durations'!$AB$17+$S18*('3 - Phase Durations'!$AB$18+'3 - Phase Durations'!$AB$19)+$T18*'3 - Phase Durations'!$AB$20+$U18*'3 - Phase Durations'!$AB$21+$V18*('3 - Phase Durations'!$AB$22+'3 - Phase Durations'!$AB$23)+$W18*'3 - Phase Durations'!$AB$24)/12 -> 1 | AU18: =($Q18*'3 - Phase Durations'!$AC$16+$R18*'3 - Phase Durations'!$AC$17+$S18*('3 - Phase Durations'!$AC$18+'3 - Phase Durations'!$AC$19)+$T18*'3 - Phase Durations'!$AC$20+$U18*'3 - Phase Durations'!$AC$21+$V18*('3 - Phase Durations'!$AC$22+'3 - Phase Durations'!$AC$23)+$W18*'3 - Phase Durations'!$AC$24)/12 -> 1.0027397 | AV18: =($Q18*'3 - Phase Durations'!$AD$16+$R18*'3 - Phase Durations'!$AD$17+$S18*('3 - Phase Durations'!$AD$18+'3 - Phase Durations'!$AD$19)+$T18*'3 - Phase Durations'!$AD$20+$U18*'3 - Phase Durations'!$AD$21+$V18*('3 - Phase Durations'!$AD$22+'3 - Phase Durations'!$AD$23)+$W18*'3 - Phase Durations'!$AD$24)/12 -> 1 | AW18: =($Q18*'3 - Phase Durations'!$AE$16+$R18*'3 - Phase Durations'!$AE$17+$S18*('3 - Phase Durations'!$AE$18+'3 - Phase Durations'!$AE$19)+$T18*'3 - Phase Durations'!$AE$20+$U18*'3 - Phase Durations'!$AE$21+$V18*('3 - Phase Durations'!$AE$22+'3 - Phase Durations'!$AE$23)+$W18*'3 - Phase Durations'!$AE$24)/12 -> 1 | AX18: =($Q18*'3 - Phase Durations'!$AF$16+$R18*'3 - Phase Durations'!$AF$17+$S18*('3 - Phase Durations'!$AF$18+'3 - Phase Durations'!$AF$19)+$T18*'3 - Phase Durations'!$AF$20+$U18*'3 - Phase Durations'!$AF$21+$V18*('3 - Phase Durations'!$AF$22+'3 - Phase Durations'!$AF$23)+$W18*'3 - Phase Durations'!$AF$24)/12 -> 1 | AY18: =($Q18*'3 - Phase Durations'!$AG$16+$R18*'3 - Phase Durations'!$AG$17+$S18*('3 - Phase Durations'!$AG$18+'3 - Phase Durations'!$AG$19)+$T18*'3 - Phase Durations'!$AG$20+$U18*'3 - Phase Durations'!$AG$21+$V18*('3 - Phase Durations'!$AG$22+'3 - Phase Durations'!$AG$23)+$W18*'3 - Phase Durations'!$AG$24)/12 -> 1.0027397 | AZ18: =($Q18*'3 - Phase Durations'!$AH$16+$R18*'3 - Phase Durations'!$AH$17+$S18*('3 - Phase Durations'!$AH$18+'3 - Phase Durations'!$AH$19)+$T18*'3 - Phase Durations'!$AH$20+$U18*'3 - Phase Durations'!$AH$21+$V18*('3 - Phase Durations'!$AH$22+'3 - Phase Durations'!$AH$23)+$W18*'3 - Phase Durations'!$AH$24)/12 -> 1 | BA18: =($Q18*'3 - Phase Durations'!$AI$16+$R18*'3 - Phase Durations'!$AI$17+$S18*('3 - Phase Durations'!$AI$18+'3 - Phase Durations'!$AI$19)+$T18*'3 - Phase Durations'!$AI$20+$U18*'3 - Phase Durations'!$AI$21+$V18*('3 - Phase Durations'!$AI$22+'3 - Phase Durations'!$AI$23)+$W18*'3 - Phase Durations'!$AI$24)/12 -> 1 | BB18: =($Q18*'3 - Phase Durations'!$AJ$16+$R18*'3 - Phase Durations'!$AJ$17+$S18*('3 - Phase Durations'!$AJ$18+'3 - Phase Durations'!$AJ$19)+$T18*'3 - Phase Durations'!$AJ$20+$U18*'3 - Phase Durations'!$AJ$21+$V18*('3 - Phase Durations'!$AJ$22+'3 - Phase Durations'!$AJ$23)+$W18*'3 - Phase Durations'!$AJ$24)/12 -> 1 | BC18: =($Q18*'3 - Phase Durations'!$AK$16+$R18*'3 - Phase Durations'!$AK$17+$S18*('3 - Phase Durations'!$AK$18+'3 - Phase Durations'!$AK$19)+$T18*'3 - Phase Durations'!$AK$20+$U18*'3 - Phase Durations'!$AK$21+$V18*('3 - Phase Durations'!$AK$22+'3 - Phase Durations'!$AK$23)+$W18*'3 - Phase Durations'!$AK$24)/12 -> 1.0027397 | BD18: =($Q18*'3 - Phase Durations'!$AL$16+$R18*'3 - Phase Durations'!$AL$17+$S18*('3 - Phase Durations'!$AL$18+'3 - Phase Durations'!$AL$19)+$T18*'3 - Phase Durations'!$AL$20+$U18*'3 - Phase Durations'!$AL$21+$V18*('3 - Phase Durations'!$AL$22+'3 - Phase Durations'!$AL$23)+$W18*'3 - Phase Durations'!$AL$24)/12 -> 1 | BE18: =($Q18*'3 - Phase Durations'!$AM$16+$R18*'3 - Phase Durations'!$AM$17+$S18*('3 - Phase Durations'!$AM$18+'3 - Phase Durations'!$AM$19)+$T18*'3 - Phase Durations'!$AM$20+$U18*'3 - Phase Durations'!$AM$21+$V18*('3 - Phase Durations'!$AM$22+'3 - Phase Durations'!$AM$23)+$W18*'3 - Phase Durations'!$AM$24)/12 -> 1 | BF18: =($Q18*'3 - Phase Durations'!$AN$16+$R18*'3 - Phase Durations'!$AN$17+$S18*('3 - Phase Durations'!$AN$18+'3 - Phase Durations'!$AN$19)+$T18*'3 - Phase Durations'!$AN$20+$U18*'3 - Phase Durations'!$AN$21+$V18*('3 - Phase Durations'!$AN$22+'3 - Phase Durations'!$AN$23)+$W18*'3 - Phase Durations'!$AN$24)/12 -> 1 | BG18: =($Q18*'3 - Phase Durations'!$AO$16+$R18*'3 - Phase Durations'!$AO$17+$S18*('3 - Phase Durations'!$AO$18+'3 - Phase Durations'!$AO$19)+$T18*'3 - Phase Durations'!$AO$20+$U18*'3 - Phase Durations'!$AO$21+$V18*('3 - Phase Durations'!$AO$22+'3 - Phase Durations'!$AO$23)+$W18*'3 - Phase Durations'!$AO$24)/12 -> 0.24931507 | BH18: =SUM(Y18:BG18) -> 21.869151
A19: 2 | B19: CSA | C19: Project Team | D19: Project Manager | E19: Mission Management | F19: ORCA Mission Manager | G19: Program Office | H19: Space Exploration | I19: Program Management | J19: Marie Tremblay | K19: ORCA-PM-002 | L19: Existing | M19: PC-4 | N19: Max Echelon | O19: Labour Rates | P19: FF-CSA | Q19: 0 | R19: 1 | S19: 0.05 | T19: 0.1 | U19: 0.67 | V19: 1 | W19: 0 | X19: =IFERROR(VLOOKUP($M19,'Labour Rates lookup'!$A:$B,2,FALSE()),0) -> 122000 | Y19: =($Q19*'3 - Phase Durations'!$G$16+$R19*'3 - Phase Durations'!$G$17+$S19*('3 - Phase Durations'!$G$18+'3 - Phase Durations'!$G$19)+$T19*'3 - Phase Durations'!$G$20+$U19*'3 - Phase Durations'!$G$21+$V19*('3 - Phase Durations'!$G$22+'3 - Phase Durations'!$G$23)+$W19*'3 - Phase Durations'!$G$24)/12 -> 0 | Z19: =($Q19*'3 - Phase Durations'!$H$16+$R19*'3 - Phase Durations'!$H$17+$S19*('3 - Phase Durations'!$H$18+'3 - Phase Durations'!$H$19)+$T19*'3 - Phase Durations'!$H$20+$U19*'3 - Phase Durations'!$H$21+$V19*('3 - Phase Durations'!$H$22+'3 - Phase Durations'!$H$23)+$W19*'3 - Phase Durations'!$H$24)/12 -> 0 | AA19: =($Q19*'3 - Phase Durations'!$I$16+$R19*'3 - Phase Durations'!$I$17+$S19*('3 - Phase Durations'!$I$18+'3 - Phase Durations'!$I$19)+$T19*'3 - Phase Durations'!$I$20+$U19*'3 - Phase Durations'!$I$21+$V19*('3 - Phase Durations'!$I$22+'3 - Phase Durations'!$I$23)+$W19*'3 - Phase Durations'!$I$24)/12 -> 0.24931507 | AB19: =($Q19*'3 - Phase Durations'!$J$16+$R19*'3 - Phase Durations'!$J$17+$S19*('3 - Phase Durations'!$J$18+'3 - Phase Durations'!$J$19)+$T19*'3 - Phase Durations'!$J$20+$U19*'3 - Phase Durations'!$J$21+$V19*('3 - Phase Durations'!$J$22+'3 - Phase Durations'!$J$23)+$W19*'3 - Phase Durations'!$J$24)/12 -> 1 | AC19: =($Q19*'3 - Phase Durations'!$K$16+$R19*'3 - Phase Durations'!$K$17+$S19*('3 - Phase Durations'!$K$18+'3 - Phase Durations'!$K$19)+$T19*'3 - Phase Durations'!$K$20+$U19*'3 - Phase Durations'!$K$21+$V19*('3 - Phase Durations'!$K$22+'3 - Phase Durations'!$K$23)+$W19*'3 - Phase Durations'!$K$24)/12 -> 0.76575342 | AD19: =($Q19*'3 - Phase Durations'!$L$16+$R19*'3 - Phase Durations'!$L$17+$S19*('3 - Phase Durations'!$L$18+'3 - Phase Durations'!$L$19)+$T19*'3 - Phase Durations'!$L$20+$U19*'3 - Phase Durations'!$L$21+$V19*('3 - Phase Durations'!$L$22+'3 - Phase Durations'!$L$23)+$W19*'3 - Phase Durations'!$L$24)/12 -> 0.05 | AE19: =($Q19*'3 - Phase Durations'!$M$16+$R19*'3 - Phase Durations'!$M$17+$S19*('3 - Phase Durations'!$M$18+'3 - Phase Durations'!$M$19)+$T19*'3 - Phase Durations'!$M$20+$U19*'3 - Phase Durations'!$M$21+$V19*('3 - Phase Durations'!$M$22+'3 - Phase Durations'!$M$23)+$W19*'3 - Phase Durations'!$M$24)/12 -> 0.06260274 | AF19: =($Q19*'3 - Phase Durations'!$N$16+$R19*'3 - Phase Durations'!$N$17+$S19*('3 - Phase Durations'!$N$18+'3 - Phase Durations'!$N$19)+$T19*'3 - Phase Durations'!$N$20+$U19*'3 - Phase Durations'!$N$21+$V19*('3 - Phase Durations'!$N$22+'3 - Phase Durations'!$N$23)+$W19*'3 - Phase Durations'!$N$24)/12 -> 0.1 | AG19: =($Q19*'3 - Phase Durations'!$O$16+$R19*'3 - Phase Durations'!$O$17+$S19*('3 - Phase Durations'!$O$18+'3 - Phase Durations'!$O$19)+$T19*'3 - Phase Durations'!$O$20+$U19*'3 - Phase Durations'!$O$21+$V19*('3 - Phase Durations'!$O$22+'3 - Phase Durations'!$O$23)+$W19*'3 - Phase Durations'!$O$24)/12 -> 0.24054795 | AH19: =($Q19*'3 - Phase Durations'!$P$16+$R19*'3 - Phase Durations'!$P$17+$S19*('3 - Phase Durations'!$P$18+'3 - Phase Durations'!$P$19)+$T19*'3 - Phase Durations'!$P$20+$U19*'3 - Phase Durations'!$P$21+$V19*('3 - Phase Durations'!$P$22+'3 - Phase Durations'!$P$23)+$W19*'3 - Phase Durations'!$P$24)/12 -> 0.67 | AI19: =($Q19*'3 - Phase Durations'!$Q$16+$R19*'3 - Phase Durations'!$Q$17+$S19*('3 - Phase Durations'!$Q$18+'3 - Phase Durations'!$Q$19)+$T19*'3 - Phase Durations'!$Q$20+$U19*'3 - Phase Durations'!$Q$21+$V19*('3 - Phase Durations'!$Q$22+'3 - Phase Durations'!$Q$23)+$W19*'3 - Phase Durations'!$Q$24)/12 -> 0.67183562 | AJ19: =($Q19*'3 - Phase Durations'!$R$16+$R19*'3 - Phase Durations'!$R$17+$S19*('3 - Phase Durations'!$R$18+'3 - Phase Durations'!$R$19)+$T19*'3 - Phase Durations'!$R$20+$U19*'3 - Phase Durations'!$R$21+$V19*('3 - Phase Durations'!$R$22+'3 - Phase Durations'!$R$23)+$W19*'3 - Phase Durations'!$R$24)/12 -> 0.67 | AK19: =($Q19*'3 - Phase Durations'!$S$16+$R19*'3 - Phase Durations'!$S$17+$S19*('3 - Phase Durations'!$S$18+'3 - Phase Durations'!$S$19)+$T19*'3 - Phase Durations'!$S$20+$U19*'3 - Phase Durations'!$S$21+$V19*('3 - Phase Durations'!$S$22+'3 - Phase Durations'!$S$23)+$W19*'3 - Phase Durations'!$S$24)/12 -> 0.67 | AL19: =($Q19*'3 - Phase Durations'!$T$16+$R19*'3 - Phase Durations'!$T$17+$S19*('3 - Phase Durations'!$T$18+'3 - Phase Durations'!$T$19)+$T19*'3 - Phase Durations'!$T$20+$U19*'3 - Phase Durations'!$T$21+$V19*('3 - Phase Durations'!$T$22+'3 - Phase Durations'!$T$23)+$W19*'3 - Phase Durations'!$T$24)/12 -> 0.67 | AM19: =($Q19*'3 - Phase Durations'!$U$16+$R19*'3 - Phase Durations'!$U$17+$S19*('3 - Phase Durations'!$U$18+'3 - Phase Durations'!$U$19)+$T19*'3 - Phase Durations'!$U$20+$U19*'3 - Phase Durations'!$U$21+$V19*('3 - Phase Durations'!$U$22+'3 - Phase Durations'!$U$23)+$W19*'3 - Phase Durations'!$U$24)/12 -> 0.67183562 | AN19: =($Q19*'3 - Phase Durations'!$V$16+$R19*'3 - Phase Durations'!$V$17+$S19*('3 - Phase Durations'!$V$18+'3 - Phase Durations'!$V$19)+$T19*'3 - Phase Durations'!$V$20+$U19*'3 - Phase Durations'!$V$21+$V19*('3 - Phase Durations'!$V$22+'3 - Phase Durations'!$V$23)+$W19*'3 - Phase Durations'!$V$24)/12 -> 0.75136986 | AO19: =($Q19*'3 - Phase Durations'!$W$16+$R19*'3 - Phase Durations'!$W$17+$S19*('3 - Phase Durations'!$W$18+'3 - Phase Durations'!$W$19)+$T19*'3 - Phase Durations'!$W$20+$U19*'3 - Phase Durations'!$W$21+$V19*('3 - Phase Durations'!$W$22+'3 - Phase Durations'!$W$23)+$W19*'3 - Phase Durations'!$W$24)/12 -> 1 | AP19: =($Q19*'3 - Phase Durations'!$X$16+$R19*'3 - Phase Durations'!$X$17+$S19*('3 - Phase Durations'!$X$18+'3 - Phase Durations'!$X$19)+$T19*'3 - Phase Durations'!$X$20+$U19*'3 - Phase Durations'!$X$21+$V19*('3 - Phase Durations'!$X$22+'3 - Phase Durations'!$X$23)+$W19*'3 - Phase Durations'!$X$24)/12 -> 1 | AQ19: =($Q19*'3 - Phase Durations'!$Y$16+$R19*'3 - Phase Durations'!$Y$17+$S19*('3 - Phase Durations'!$Y$18+'3 - Phase Durations'!$Y$19)+$T19*'3 - Phase Durations'!$Y$20+$U19*'3 - Phase Durations'!$Y$21+$V19*('3 - Phase Durations'!$Y$22+'3 - Phase Durations'!$Y$23)+$W19*'3 - Phase Durations'!$Y$24)/12 -> 1.0027397 | AR19: =($Q19*'3 - Phase Durations'!$Z$16+$R19*'3 - Phase Durations'!$Z$17+$S19*('3 - Phase Durations'!$Z$18+'3 - Phase Durations'!$Z$19)+$T19*'3 - Phase Durations'!$Z$20+$U19*'3 - Phase Durations'!$Z$21+$V19*('3 - Phase Durations'!$Z$22+'3 - Phase Durations'!$Z$23)+$W19*'3 - Phase Durations'!$Z$24)/12 -> 1 | AS19: =($Q19*'3 - Phase Durations'!$AA$16+$R19*'3 - Phase Durations'!$AA$17+$S19*('3 - Phase Durations'!$AA$18+'3 - Phase Durations'!$AA$19)+$T19*'3 - Phase Durations'!$AA$20+$U19*'3 - Phase Durations'!$AA$21+$V19*('3 - Phase Durations'!$AA$22+'3 - Phase Durations'!$AA$23)+$W19*'3 - Phase Durations'!$AA$24)/12 -> 1 | AT19: =($Q19*'3 - Phase Durations'!$AB$16+$R19*'3 - Phase Durations'!$AB$17+$S19*('3 - Phase Durations'!$AB$18+'3 - Phase Durations'!$AB$19)+$T19*'3 - Phase Durations'!$AB$20+$U19*'3 - Phase Durations'!$AB$21+$V19*('3 - Phase Durations'!$AB$22+'3 - Phase Durations'!$AB$23)+$W19*'3 - Phase Durations'!$AB$24)/12 -> 1 | AU19: =($Q19*'3 - Phase Durations'!$AC$16+$R19*'3 - Phase Durations'!$AC$17+$S19*('3 - Phase Durations'!$AC$18+'3 - Phase Durations'!$AC$19)+$T19*'3 - Phase Durations'!$AC$20+$U19*'3 - Phase Durations'!$AC$21+$V19*('3 - Phase Durations'!$AC$22+'3 - Phase Durations'!$AC$23)+$W19*'3 - Phase Durations'!$AC$24)/12 -> 1.0027397 | AV19: =($Q19*'3 - Phase Durations'!$AD$16+$R19*'3 - Phase Durations'!$AD$17+$S19*('3 - Phase Durations'!$AD$18+'3 - Phase Durations'!$AD$19)+$T19*'3 - Phase Durations'!$AD$20+$U19*'3 - Phase Durations'!$AD$21+$V19*('3 - Phase Durations'!$AD$22+'3 - Phase Durations'!$AD$23)+$W19*'3 - Phase Durations'!$AD$24)/12 -> 1 | AW19: =($Q19*'3 - Phase Durations'!$AE$16+$R19*'3 - Phase Durations'!$AE$17+$S19*('3 - Phase Durations'!$AE$18+'3 - Phase Durations'!$AE$19)+$T19*'3 - Phase Durations'!$AE$20+$U19*'3 - Phase Durations'!$AE$21+$V19*('3 - Phase Durations'!$AE$22+'3 - Phase Durations'!$AE$23)+$W19*'3 - Phase Durations'!$AE$24)/12 -> 1 | AX19: =($Q19*'3 - Phase Durations'!$AF$16+$R19*'3 - Phase Durations'!$AF$17+$S19*('3 - Phase Durations'!$AF$18+'3 - Phase Durations'!$AF$19)+$T19*'3 - Phase Durations'!$AF$20+$U19*'3 - Phase Durations'!$AF$21+$V19*('3 - Phase Durations'!$AF$22+'3 - Phase Durations'!$AF$23)+$W19*'3 - Phase Durations'!$AF$24)/12 -> 1 | AY19: =($Q19*'3 - Phase Durations'!$AG$16+$R19*'3 - Phase Durations'!$AG$17+$S19*('3 - Phase Durations'!$AG$18+'3 - Phase Durations'!$AG$19)+$T19*'3 - Phase Durations'!$AG$20+$U19*'3 - Phase Durations'!$AG$21+$V19*('3 - Phase Durations'!$AG$22+'3 - Phase Durations'!$AG$23)+$W19*'3 - Phase Durations'!$AG$24)/12 -> 1.0027397 | AZ19: =($Q19*'3 - Phase Durations'!$AH$16+$R19*'3 - Phase Durations'!$AH$17+$S19*('3 - Phase Durations'!$AH$18+'3 - Phase Durations'!$AH$19)+$T19*'3 - Phase Durations'!$AH$20+$U19*'3 - Phase Durations'!$AH$21+$V19*('3 - Phase Durations'!$AH$22+'3 - Phase Durations'!$AH$23)+$W19*'3 - Phase Durations'!$AH$24)/12 -> 1 | BA19: =($Q19*'3 - Phase Durations'!$AI$16+$R19*'3 - Phase Durations'!$AI$17+$S19*('3 - Phase Durations'!$AI$18+'3 - Phase Durations'!$AI$19)+$T19*'3 - Phase Durations'!$AI$20+$U19*'3 - Phase Durations'!$AI$21+$V19*('3 - Phase Durations'!$AI$22+'3 - Phase Durations'!$AI$23)+$W19*'3 - Phase Durations'!$AI$24)/12 -> 1 | BB19: =($Q19*'3 - Phase Durations'!$AJ$16+$R19*'3 - Phase Durations'!$AJ$17+$S19*('3 - Phase Durations'!$AJ$18+'3 - Phase Durations'!$AJ$19)+$T19*'3 - Phase Durations'!$AJ$20+$U19*'3 - Phase Durations'!$AJ$21+$V19*('3 - Phase Durations'!$AJ$22+'3 - Phase Durations'!$AJ$23)+$W19*'3 - Phase Durations'!$AJ$24)/12 -> 1 | BC19: =($Q19*'3 - Phase Durations'!$AK$16+$R19*'3 - Phase Durations'!$AK$17+$S19*('3 - Phase Durations'!$AK$18+'3 - Phase Durations'!$AK$19)+$T19*'3 - Phase Durations'!$AK$20+$U19*'3 - Phase Durations'!$AK$21+$V19*('3 - Phase Durations'!$AK$22+'3 - Phase Durations'!$AK$23)+$W19*'3 - Phase Durations'!$AK$24)/12 -> 1.0027397 | BD19: =($Q19*'3 - Phase Durations'!$AL$16+$R19*'3 - Phase Durations'!$AL$17+$S19*('3 - Phase Durations'!$AL$18+'3 - Phase Durations'!$AL$19)+$T19*'3 - Phase Durations'!$AL$20+$U19*'3 - Phase Durations'!$AL$21+$V19*('3 - Phase Durations'!$AL$22+'3 - Phase Durations'!$AL$23)+$W19*'3 - Phase Durations'!$AL$24)/12 -> 1 | BE19: =($Q19*'3 - Phase Durations'!$AM$16+$R19*'3 - Phase Durations'!$AM$17+$S19*('3 - Phase Durations'!$AM$18+'3 - Phase Durations'!$AM$19)+$T19*'3 - Phase Durations'!$AM$20+$U19*'3 - Phase Durations'!$AM$21+$V19*('3 - Phase Durations'!$AM$22+'3 - Phase Durations'!$AM$23)+$W19*'3 - Phase Durations'!$AM$24)/12 -> 1 | BF19: =($Q19*'3 - Phase Durations'!$AN$16+$R19*'3 - Phase Durations'!$AN$17+$S19*('3 - Phase Durations'!$AN$18+'3 - Phase Durations'!$AN$19)+$T19*'3 - Phase Durations'!$AN$20+$U19*'3 - Phase Durations'!$AN$21+$V19*('3 - Phase Durations'!$AN$22+'3 - Phase Durations'!$AN$23)+$W19*'3 - Phase Durations'!$AN$24)/12 -> 1 | BG19: =($Q19*'3 - Phase Durations'!$AO$16+$R19*'3 - Phase Durations'!$AO$17+$S19*('3 - Phase Durations'!$AO$18+'3 - Phase Durations'!$AO$19)+$T19*'3 - Phase Durations'!$AO$20+$U19*'3 - Phase Durations'!$AO$21+$V19*('3 - Phase Durations'!$AO$22+'3 - Phase Durations'!$AO$23)+$W19*'3 - Phase Durations'!$AO$24)/12 -> 0.24931507 | BH19: =SUM(Y19:BG19) -> 25.503534
A20: 3 | B20: CSA | C20: Project Team | D20: Scientific | E20: Mission Ops | F20: Mission Operations Scientist | G20: Science Segment | H20: Space Exploration | I20: Planetary Science | J20: Devon Okafor | K20: ORCA-SCI-001 | L20: New | M20: PC-3 | N20: Max Echelon | O20: Labour Rates | P20: FF-CSA | Q20: 0 | R20: 1 | S20: 1 | T20: 0 | U20: 0.73 | V20: 0 | W20: 0 | X20: =IFERROR(VLOOKUP($M20,'Labour Rates lookup'!$A:$B,2,FALSE()),0) -> 105000 | Y20: =($Q20*'3 - Phase Durations'!$G$16+$R20*'3 - Phase Durations'!$G$17+$S20*('3 - Phase Durations'!$G$18+'3 - Phase Durations'!$G$19)+$T20*'3 - Phase Durations'!$G$20+$U20*'3 - Phase Durations'!$G$21+$V20*('3 - Phase Durations'!$G$22+'3 - Phase Durations'!$G$23)+$W20*'3 - Phase Durations'!$G$24)/12 -> 0 | Z20: =($Q20*'3 - Phase Durations'!$H$16+$R20*'3 - Phase Durations'!$H$17+$S20*('3 - Phase Durations'!$H$18+'3 - Phase Durations'!$H$19)+$T20*'3 - Phase Durations'!$H$20+$U20*'3 - Phase Durations'!$H$21+$V20*('3 - Phase Durations'!$H$22+'3 - Phase Durations'!$H$23)+$W20*'3 - Phase Durations'!$H$24)/12 -> 0 | AA20: =($Q20*'3 - Phase Durations'!$I$16+$R20*'3 - Phase Durations'!$I$17+$S20*('3 - Phase Durations'!$I$18+'3 - Phase Durations'!$I$19)+$T20*'3 - Phase Durations'!$I$20+$U20*'3 - Phase Durations'!$I$21+$V20*('3 - Phase Durations'!$I$22+'3 - Phase Durations'!$I$23)+$W20*'3 - Phase Durations'!$I$24)/12 -> 0.24931507 | AB20: =($Q20*'3 - Phase Durations'!$J$16+$R20*'3 - Phase Durations'!$J$17+$S20*('3 - Phase Durations'!$J$18+'3 - Phase Durations'!$J$19)+$T20*'3 - Phase Durations'!$J$20+$U20*'3 - Phase Durations'!$J$21+$V20*('3 - Phase Durations'!$J$22+'3 - Phase Durations'!$J$23)+$W20*'3 - Phase Durations'!$J$24)/12 -> 1 | AC20: =($Q20*'3 - Phase Durations'!$K$16+$R20*'3 - Phase Durations'!$K$17+$S20*('3 - Phase Durations'!$K$18+'3 - Phase Durations'!$K$19)+$T20*'3 - Phase Durations'!$K$20+$U20*'3 - Phase Durations'!$K$21+$V20*('3 - Phase Durations'!$K$22+'3 - Phase Durations'!$K$23)+$W20*'3 - Phase Durations'!$K$24)/12 -> 1 | AD20: =($Q20*'3 - Phase Durations'!$L$16+$R20*'3 - Phase Durations'!$L$17+$S20*('3 - Phase Durations'!$L$18+'3 - Phase Durations'!$L$19)+$T20*'3 - Phase Durations'!$L$20+$U20*'3 - Phase Durations'!$L$21+$V20*('3 - Phase Durations'!$L$22+'3 - Phase Durations'!$L$23)+$W20*'3 - Phase Durations'!$L$24)/12 -> 1 | AE20: =($Q20*'3 - Phase Durations'!$M$16+$R20*'3 - Phase Durations'!$M$17+$S20*('3 - Phase Durations'!$M$18+'3 - Phase Durations'!$M$19)+$T20*'3 - Phase Durations'!$M$20+$U20*'3 - Phase Durations'!$M$21+$V20*('3 - Phase Durations'!$M$22+'3 - Phase Durations'!$M$23)+$W20*'3 - Phase Durations'!$M$24)/12 -> 0.75342466 | AF20: =($Q20*'3 - Phase Durations'!$N$16+$R20*'3 - Phase Durations'!$N$17+$S20*('3 - Phase Durations'!$N$18+'3 - Phase Durations'!$N$19)+$T20*'3 - Phase Durations'!$N$20+$U20*'3 - Phase Durations'!$N$21+$V20*('3 - Phase Durations'!$N$22+'3 - Phase Durations'!$N$23)+$W20*'3 - Phase Durations'!$N$24)/12 -> 0 | AG20: =($Q20*'3 - Phase Durations'!$O$16+$R20*'3 - Phase Durations'!$O$17+$S20*('3 - Phase Durations'!$O$18+'3 - Phase Durations'!$O$19)+$T20*'3 - Phase Durations'!$O$20+$U20*'3 - Phase Durations'!$O$21+$V20*('3 - Phase Durations'!$O$22+'3 - Phase Durations'!$O$23)+$W20*'3 - Phase Durations'!$O$24)/12 -> 0.18 | AH20: =($Q20*'3 - Phase Durations'!$P$16+$R20*'3 - Phase Durations'!$P$17+$S20*('3 - Phase Durations'!$P$18+'3 - Phase Durations'!$P$19)+$T20*'3 - Phase Durations'!$P$20+$U20*'3 - Phase Durations'!$P$21+$V20*('3 - Phase Durations'!$P$22+'3 - Phase Durations'!$P$23)+$W20*'3 - Phase Durations'!$P$24)/12 -> 0.73 | AI20: =($Q20*'3 - Phase Durations'!$Q$16+$R20*'3 - Phase Durations'!$Q$17+$S20*('3 - Phase Durations'!$Q$18+'3 - Phase Durations'!$Q$19)+$T20*'3 - Phase Durations'!$Q$20+$U20*'3 - Phase Durations'!$Q$21+$V20*('3 - Phase Durations'!$Q$22+'3 - Phase Durations'!$Q$23)+$W20*'3 - Phase Durations'!$Q$24)/12 -> 0.732 | AJ20: =($Q20*'3 - Phase Durations'!$R$16+$R20*'3 - Phase Durations'!$R$17+$S20*('3 - Phase Durations'!$R$18+'3 - Phase Durations'!$R$19)+$T20*'3 - Phase Durations'!$R$20+$U20*'3 - Phase Durations'!$R$21+$V20*('3 - Phase Durations'!$R$22+'3 - Phase Durations'!$R$23)+$W20*'3 - Phase Durations'!$R$24)/12 -> 0.73 | AK20: =($Q20*'3 - Phase Durations'!$S$16+$R20*'3 - Phase Durations'!$S$17+$S20*('3 - Phase Durations'!$S$18+'3 - Phase Durations'!$S$19)+$T20*'3 - Phase Durations'!$S$20+$U20*'3 - Phase Durations'!$S$21+$V20*('3 - Phase Durations'!$S$22+'3 - Phase Durations'!$S$23)+$W20*'3 - Phase Durations'!$S$24)/12 -> 0.73 | AL20: =($Q20*'3 - Phase Durations'!$T$16+$R20*'3 - Phase Durations'!$T$17+$S20*('3 - Phase Durations'!$T$18+'3 - Phase Durations'!$T$19)+$T20*'3 - Phase Durations'!$T$20+$U20*'3 - Phase Durations'!$T$21+$V20*('3 - Phase Durations'!$T$22+'3 - Phase Durations'!$T$23)+$W20*'3 - Phase Durations'!$T$24)/12 -> 0.73 | AM20: =($Q20*'3 - Phase Durations'!$U$16+$R20*'3 - Phase Durations'!$U$17+$S20*('3 - Phase Durations'!$U$18+'3 - Phase Durations'!$U$19)+$T20*'3 - Phase Durations'!$U$20+$U20*'3 - Phase Durations'!$U$21+$V20*('3 - Phase Durations'!$U$22+'3 - Phase Durations'!$U$23)+$W20*'3 - Phase Durations'!$U$24)/12 -> 0.732 | AN20: =($Q20*'3 - Phase Durations'!$V$16+$R20*'3 - Phase Durations'!$V$17+$S20*('3 - Phase Durations'!$V$18+'3 - Phase Durations'!$V$19)+$T20*'3 - Phase Durations'!$V$20+$U20*'3 - Phase Durations'!$V$21+$V20*('3 - Phase Durations'!$V$22+'3 - Phase Durations'!$V$23)+$W20*'3 - Phase Durations'!$V$24)/12 -> 0.55 | AO20: =($Q20*'3 - Phase Durations'!$W$16+$R20*'3 - Phase Durations'!$W$17+$S20*('3 - Phase Durations'!$W$18+'3 - Phase Durations'!$W$19)+$T20*'3 - Phase Durations'!$W$20+$U20*'3 - Phase Durations'!$W$21+$V20*('3 - Phase Durations'!$W$22+'3 - Phase Durations'!$W$23)+$W20*'3 - Phase Durations'!$W$24)/12 -> 0 | AP20: =($Q20*'3 - Phase Durations'!$X$16+$R20*'3 - Phase Durations'!$X$17+$S20*('3 - Phase Durations'!$X$18+'3 - Phase Durations'!$X$19)+$T20*'3 - Phase Durations'!$X$20+$U20*'3 - Phase Durations'!$X$21+$V20*('3 - Phase Durations'!$X$22+'3 - Phase Durations'!$X$23)+$W20*'3 - Phase Durations'!$X$24)/12 -> 0 | AQ20: =($Q20*'3 - Phase Durations'!$Y$16+$R20*'3 - Phase Durations'!$Y$17+$S20*('3 - Phase Durations'!$Y$18+'3 - Phase Durations'!$Y$19)+$T20*'3 - Phase Durations'!$Y$20+$U20*'3 - Phase Durations'!$Y$21+$V20*('3 - Phase Durations'!$Y$22+'3 - Phase Durations'!$Y$23)+$W20*'3 - Phase Durations'!$Y$24)/12 -> 0 | AR20: =($Q20*'3 - Phase Durations'!$Z$16+$R20*'3 - Phase Durations'!$Z$17+$S20*('3 - Phase Durations'!$Z$18+'3 - Phase Durations'!$Z$19)+$T20*'3 - Phase Durations'!$Z$20+$U20*'3 - Phase Durations'!$Z$21+$V20*('3 - Phase Durations'!$Z$22+'3 - Phase Durations'!$Z$23)+$W20*'3 - Phase Durations'!$Z$24)/12 -> 0 | AS20: =($Q20*'3 - Phase Durations'!$AA$16+$R20*'3 - Phase Durations'!$AA$17+$S20*('3 - Phase Durations'!$AA$18+'3 - Phase Durations'!$AA$19)+$T20*'3 - Phase Durations'!$AA$20+$U20*'3 - Phase Durations'!$AA$21+$V20*('3 - Phase Durations'!$AA$22+'3 - Phase Durations'!$AA$23)+$W20*'3 - Phase Durations'!$AA$24)/12 -> 0 | AT20: =($Q20*'3 - Phase Durations'!$AB$16+$R20*'3 - Phase Durations'!$AB$17+$S20*('3 - Phase Durations'!$AB$18+'3 - Phase Durations'!$AB$19)+$T20*'3 - Phase Durations'!$AB$20+$U20*'3 - Phase Durations'!$AB$21+$V20*('3 - Phase Durations'!$AB$22+'3 - Phase Durations'!$AB$23)+$W20*'3 - Phase Durations'!$AB$24)/12 -> 0 | AU20: =($Q20*'3 - Phase Durations'!$AC$16+$R20*'3 - Phase Durations'!$AC$17+$S20*('3 - Phase Durations'!$AC$18+'3 - Phase Durations'!$AC$19)+$T20*'3 - Phase Durations'!$AC$20+$U20*'3 - Phase Durations'!$AC$21+$V20*('3 - Phase Durations'!$AC$22+'3 - Phase Durations'!$AC$23)+$W20*'3 - Phase Durations'!$AC$24)/12 -> 0 | AV20: =($Q20*'3 - Phase Durations'!$AD$16+$R20*'3 - Phase Durations'!$AD$17+$S20*('3 - Phase Durations'!$AD$18+'3 - Phase Durations'!$AD$19)+$T20*'3 - Phase Durations'!$AD$20+$U20*'3 - Phase Durations'!$AD$21+$V20*('3 - Phase Durations'!$AD$22+'3 - Phase Durations'!$AD$23)+$W20*'3 - Phase Durations'!$AD$24)/12 -> 0 | AW20: =($Q20*'3 - Phase Durations'!$AE$16+$R20*'3 - Phase Durations'!$AE$17+$S20*('3 - Phase Durations'!$AE$18+'3 - Phase Durations'!$AE$19)+$T20*'3 - Phase Durations'!$AE$20+$U20*'3 - Phase Durations'!$AE$21+$V20*('3 - Phase Durations'!$AE$22+'3 - Phase Durations'!$AE$23)+$W20*'3 - Phase Durations'!$AE$24)/12 -> 0 | AX20: =($Q20*'3 - Phase Durations'!$AF$16+$R20*'3 - Phase Durations'!$AF$17+$S20*('3 - Phase Durations'!$AF$18+'3 - Phase Durations'!$AF$19)+$T20*'3 - Phase Durations'!$AF$20+$U20*'3 - Phase Durations'!$AF$21+$V20*('3 - Phase Durations'!$AF$22+'3 - Phase Durations'!$AF$23)+$W20*'3 - Phase Durations'!$AF$24)/12 -> 0 | AY20: =($Q20*'3 - Phase Durations'!$AG$16+$R20*'3 - Phase Durations'!$AG$17+$S20*('3 - Phase Durations'!$AG$18+'3 - Phase Durations'!$AG$19)+$T20*'3 - Phase Durations'!$AG$20+$U20*'3 - Phase Durations'!$AG$21+$V20*('3 - Phase Durations'!$AG$22+'3 - Phase Durations'!$AG$23)+$W20*'3 - Phase Durations'!$AG$24)/12 -> 0 | AZ20: =($Q20*'3 - Phase Durations'!$AH$16+$R20*'3 - Phase Durations'!$AH$17+$S20*('3 - Phase Durations'!$AH$18+'3 - Phase Durations'!$AH$19)+$T20*'3 - Phase Durations'!$AH$20+$U20*'3 - Phase Durations'!$AH$21+$V20*('3 - Phase Durations'!$AH$22+'3 - Phase Durations'!$AH$23)+$W20*'3 - Phase Durations'!$AH$24)/12 -> 0 | BA20: =($Q20*'3 - Phase Durations'!$AI$16+$R20*'3 - Phase Durations'!$AI$17+$S20*('3 - Phase Durations'!$AI$18+'3 - Phase Durations'!$AI$19)+$T20*'3 - Phase Durations'!$AI$20+$U20*'3 - Phase Durations'!$AI$21+$V20*('3 - Phase Durations'!$AI$22+'3 - Phase Durations'!$AI$23)+$W20*'3 - Phase Durations'!$AI$24)/12 -> 0 | BB20: =($Q20*'3 - Phase Durations'!$AJ$16+$R20*'3 - Phase Durations'!$AJ$17+$S20*('3 - Phase Durations'!$AJ$18+'3 - Phase Durations'!$AJ$19)+$T20*'3 - Phase Durations'!$AJ$20+$U20*'3 - Phase Durations'!$AJ$21+$V20*('3 - Phase Durations'!$AJ$22+'3 - Phase Durations'!$AJ$23)+$W20*'3 - Phase Durations'!$AJ$24)/12 -> 0 | BC20: =($Q20*'3 - Phase Durations'!$AK$16+$R20*'3 - Phase Durations'!$AK$17+$S20*('3 - Phase Durations'!$AK$18+'3 - Phase Durations'!$AK$19)+$T20*'3 - Phase Durations'!$AK$20+$U20*'3 - Phase Durations'!$AK$21+$V20*('3 - Phase Durations'!$AK$22+'3 - Phase Durations'!$AK$23)+$W20*'3 - Phase Durations'!$AK$24)/12 -> 0 | BD20: =($Q20*'3 - Phase Durations'!$AL$16+$R20*'3 - Phase Durations'!$AL$17+$S20*('3 - Phase Durations'!$AL$18+'3 - Phase Durations'!$AL$19)+$T20*'3 - Phase Durations'!$AL$20+$U20*'3 - Phase Durations'!$AL$21+$V20*('3 - Phase Durations'!$AL$22+'3 - Phase Durations'!$AL$23)+$W20*'3 - Phase Durations'!$AL$24)/12 -> 0 | BE20: =($Q20*'3 - Phase Durations'!$AM$16+$R20*'3 - Phase Durations'!$AM$17+$S20*('3 - Phase Durations'!$AM$18+'3 - Phase Durations'!$AM$19)+$T20*'3 - Phase Durations'!$AM$20+$U20*'3 - Phase Durations'!$AM$21+$V20*('3 - Phase Durations'!$AM$22+'3 - Phase Durations'!$AM$23)+$W20*'3 - Phase Durations'!$AM$24)/12 -> 0 | BF20: =($Q20*'3 - Phase Durations'!$AN$16+$R20*'3 - Phase Durations'!$AN$17+$S20*('3 - Phase Durations'!$AN$18+'3 - Phase Durations'!$AN$19)+$T20*'3 - Phase Durations'!$AN$20+$U20*'3 - Phase Durations'!$AN$21+$V20*('3 - Phase Durations'!$AN$22+'3 - Phase Durations'!$AN$23)+$W20*'3 - Phase Durations'!$AN$24)/12 -> 0 | BG20: =($Q20*'3 - Phase Durations'!$AO$16+$R20*'3 - Phase Durations'!$AO$17+$S20*('3 - Phase Durations'!$AO$18+'3 - Phase Durations'!$AO$19)+$T20*'3 - Phase Durations'!$AO$20+$U20*'3 - Phase Durations'!$AO$21+$V20*('3 - Phase Durations'!$AO$22+'3 - Phase Durations'!$AO$23)+$W20*'3 - Phase Durations'!$AO$24)/12 -> 0 | BH20: =SUM(Y20:BG20) -> 9.1167397
A21: 4 | B21: CSA | C21: Project Team | D21: Project Manager | E21: PM | F21: Lead Project Manager | G21: Program Office | H21: Space Exploration | I21: Program Management | J21: Priya Raman | K21: ORCA-PM-003 | L21: New | M21: EN-ENG-5 | N21: Max Echelon | O21: Labour Rates | P21: FF-CSA | Q21: 0 | R21: 1 | S21: 0.25 | T21: 0.25 | U21: 0.27 | V21: 1 | W21: 0 | X21: =IFERROR(VLOOKUP($M21,'Labour Rates lookup'!$A:$B,2,FALSE()),0) -> 145000 | Y21: =($Q21*'3 - Phase Durations'!$G$16+$R21*'3 - Phase Durations'!$G$17+$S21*('3 - Phase Durations'!$G$18+'3 - Phase Durations'!$G$19)+$T21*'3 - Phase Durations'!$G$20+$U21*'3 - Phase Durations'!$G$21+$V21*('3 - Phase Durations'!$G$22+'3 - Phase Durations'!$G$23)+$W21*'3 - Phase Durations'!$G$24)/12 -> 0 | Z21: =($Q21*'3 - Phase Durations'!$H$16+$R21*'3 - Phase Durations'!$H$17+$S21*('3 - Phase Durations'!$H$18+'3 - Phase Durations'!$H$19)+$T21*'3 - Phase Durations'!$H$20+$U21*'3 - Phase Durations'!$H$21+$V21*('3 - Phase Durations'!$H$22+'3 - Phase Durations'!$H$23)+$W21*'3 - Phase Durations'!$H$24)/12 -> 0 | AA21: =($Q21*'3 - Phase Durations'!$I$16+$R21*'3 - Phase Durations'!$I$17+$S21*('3 - Phase Durations'!$I$18+'3 - Phase Durations'!$I$19)+$T21*'3 - Phase Durations'!$I$20+$U21*'3 - Phase Durations'!$I$21+$V21*('3 - Phase Durations'!$I$22+'3 - Phase Durations'!$I$23)+$W21*'3 - Phase Durations'!$I$24)/12 -> 0.24931507 | AB21: =($Q21*'3 - Phase Durations'!$J$16+$R21*'3 - Phase Durations'!$J$17+$S21*('3 - Phase Durations'!$J$18+'3 - Phase Durations'!$J$19)+$T21*'3 - Phase Durations'!$J$20+$U21*'3 - Phase Durations'!$J$21+$V21*('3 - Phase Durations'!$J$22+'3 - Phase Durations'!$J$23)+$W21*'3 - Phase Durations'!$J$24)/12 -> 1 | AC21: =($Q21*'3 - Phase Durations'!$K$16+$R21*'3 - Phase Durations'!$K$17+$S21*('3 - Phase Durations'!$K$18+'3 - Phase Durations'!$K$19)+$T21*'3 - Phase Durations'!$K$20+$U21*'3 - Phase Durations'!$K$21+$V21*('3 - Phase Durations'!$K$22+'3 - Phase Durations'!$K$23)+$W21*'3 - Phase Durations'!$K$24)/12 -> 0.81506849 | AD21: =($Q21*'3 - Phase Durations'!$L$16+$R21*'3 - Phase Durations'!$L$17+$S21*('3 - Phase Durations'!$L$18+'3 - Phase Durations'!$L$19)+$T21*'3 - Phase Durations'!$L$20+$U21*'3 - Phase Durations'!$L$21+$V21*('3 - Phase Durations'!$L$22+'3 - Phase Durations'!$L$23)+$W21*'3 - Phase Durations'!$L$24)/12 -> 0.25 | AE21: =($Q21*'3 - Phase Durations'!$M$16+$R21*'3 - Phase Durations'!$M$17+$S21*('3 - Phase Durations'!$M$18+'3 - Phase Durations'!$M$19)+$T21*'3 - Phase Durations'!$M$20+$U21*'3 - Phase Durations'!$M$21+$V21*('3 - Phase Durations'!$M$22+'3 - Phase Durations'!$M$23)+$W21*'3 - Phase Durations'!$M$24)/12 -> 0.25068493 | AF21: =($Q21*'3 - Phase Durations'!$N$16+$R21*'3 - Phase Durations'!$N$17+$S21*('3 - Phase Durations'!$N$18+'3 - Phase Durations'!$N$19)+$T21*'3 - Phase Durations'!$N$20+$U21*'3 - Phase Durations'!$N$21+$V21*('3 - Phase Durations'!$N$22+'3 - Phase Durations'!$N$23)+$W21*'3 - Phase Durations'!$N$24)/12 -> 0.25 | AG21: =($Q21*'3 - Phase Durations'!$O$16+$R21*'3 - Phase Durations'!$O$17+$S21*('3 - Phase Durations'!$O$18+'3 - Phase Durations'!$O$19)+$T21*'3 - Phase Durations'!$O$20+$U21*'3 - Phase Durations'!$O$21+$V21*('3 - Phase Durations'!$O$22+'3 - Phase Durations'!$O$23)+$W21*'3 - Phase Durations'!$O$24)/12 -> 0.25493151 | AH21: =($Q21*'3 - Phase Durations'!$P$16+$R21*'3 - Phase Durations'!$P$17+$S21*('3 - Phase Durations'!$P$18+'3 - Phase Durations'!$P$19)+$T21*'3 - Phase Durations'!$P$20+$U21*'3 - Phase Durations'!$P$21+$V21*('3 - Phase Durations'!$P$22+'3 - Phase Durations'!$P$23)+$W21*'3 - Phase Durations'!$P$24)/12 -> 0.27 | AI21: =($Q21*'3 - Phase Durations'!$Q$16+$R21*'3 - Phase Durations'!$Q$17+$S21*('3 - Phase Durations'!$Q$18+'3 - Phase Durations'!$Q$19)+$T21*'3 - Phase Durations'!$Q$20+$U21*'3 - Phase Durations'!$Q$21+$V21*('3 - Phase Durations'!$Q$22+'3 - Phase Durations'!$Q$23)+$W21*'3 - Phase Durations'!$Q$24)/12 -> 0.27073973 | AJ21: =($Q21*'3 - Phase Durations'!$R$16+$R21*'3 - Phase Durations'!$R$17+$S21*('3 - Phase Durations'!$R$18+'3 - Phase Durations'!$R$19)+$T21*'3 - Phase Durations'!$R$20+$U21*'3 - Phase Durations'!$R$21+$V21*('3 - Phase Durations'!$R$22+'3 - Phase Durations'!$R$23)+$W21*'3 - Phase Durations'!$R$24)/12 -> 0.27 | AK21: =($Q21*'3 - Phase Durations'!$S$16+$R21*'3 - Phase Durations'!$S$17+$S21*('3 - Phase Durations'!$S$18+'3 - Phase Durations'!$S$19)+$T21*'3 - Phase Durations'!$S$20+$U21*'3 - Phase Durations'!$S$21+$V21*('3 - Phase Durations'!$S$22+'3 - Phase Durations'!$S$23)+$W21*'3 - Phase Durations'!$S$24)/12 -> 0.27 | AL21: =($Q21*'3 - Phase Durations'!$T$16+$R21*'3 - Phase Durations'!$T$17+$S21*('3 - Phase Durations'!$T$18+'3 - Phase Durations'!$T$19)+$T21*'3 - Phase Durations'!$T$20+$U21*'3 - Phase Durations'!$T$21+$V21*('3 - Phase Durations'!$T$22+'3 - Phase Durations'!$T$23)+$W21*'3 - Phase Durations'!$T$24)/12 -> 0.27 | AM21: =($Q21*'3 - Phase Durations'!$U$16+$R21*'3 - Phase Durations'!$U$17+$S21*('3 - Phase Durations'!$U$18+'3 - Phase Durations'!$U$19)+$T21*'3 - Phase Durations'!$U$20+$U21*'3 - Phase Durations'!$U$21+$V21*('3 - Phase Durations'!$U$22+'3 - Phase Durations'!$U$23)+$W21*'3 - Phase Durations'!$U$24)/12 -> 0.27073973 | AN21: =($Q21*'3 - Phase Durations'!$V$16+$R21*'3 - Phase Durations'!$V$17+$S21*('3 - Phase Durations'!$V$18+'3 - Phase Durations'!$V$19)+$T21*'3 - Phase Durations'!$V$20+$U21*'3 - Phase Durations'!$V$21+$V21*('3 - Phase Durations'!$V$22+'3 - Phase Durations'!$V$23)+$W21*'3 - Phase Durations'!$V$24)/12 -> 0.45 | AO21: =($Q21*'3 - Phase Durations'!$W$16+$R21*'3 - Phase Durations'!$W$17+$S21*('3 - Phase Durations'!$W$18+'3 - Phase Durations'!$W$19)+$T21*'3 - Phase Durations'!$W$20+$U21*'3 - Phase Durations'!$W$21+$V21*('3 - Phase Durations'!$W$22+'3 - Phase Durations'!$W$23)+$W21*'3 - Phase Durations'!$W$24)/12 -> 1 | AP21: =($Q21*'3 - Phase Durations'!$X$16+$R21*'3 - Phase Durations'!$X$17+$S21*('3 - Phase Durations'!$X$18+'3 - Phase Durations'!$X$19)+$T21*'3 - Phase Durations'!$X$20+$U21*'3 - Phase Durations'!$X$21+$V21*('3 - Phase Durations'!$X$22+'3 - Phase Durations'!$X$23)+$W21*'3 - Phase Durations'!$X$24)/12 -> 1 | AQ21: =($Q21*'3 - Phase Durations'!$Y$16+$R21*'3 - Phase Durations'!$Y$17+$S21*('3 - Phase Durations'!$Y$18+'3 - Phase Durations'!$Y$19)+$T21*'3 - Phase Durations'!$Y$20+$U21*'3 - Phase Durations'!$Y$21+$V21*('3 - Phase Durations'!$Y$22+'3 - Phase Durations'!$Y$23)+$W21*'3 - Phase Durations'!$Y$24)/12 -> 1.0027397 | AR21: =($Q21*'3 - Phase Durations'!$Z$16+$R21*'3 - Phase Durations'!$Z$17+$S21*('3 - Phase Durations'!$Z$18+'3 - Phase Durations'!$Z$19)+$T21*'3 - Phase Durations'!$Z$20+$U21*'3 - Phase Durations'!$Z$21+$V21*('3 - Phase Durations'!$Z$22+'3 - Phase Durations'!$Z$23)+$W21*'3 - Phase Durations'!$Z$24)/12 -> 1 | AS21: =($Q21*'3 - Phase Durations'!$AA$16+$R21*'3 - Phase Durations'!$AA$17+$S21*('3 - Phase Durations'!$AA$18+'3 - Phase Durations'!$AA$19)+$T21*'3 - Phase Durations'!$AA$20+$U21*'3 - Phase Durations'!$AA$21+$V21*('3 - Phase Durations'!$AA$22+'3 - Phase Durations'!$AA$23)+$W21*'3 - Phase Durations'!$AA$24)/12 -> 1 | AT21: =($Q21*'3 - Phase Durations'!$AB$16+$R21*'3 - Phase Durations'!$AB$17+$S21*('3 - Phase Durations'!$AB$18+'3 - Phase Durations'!$AB$19)+$T21*'3 - Phase Durations'!$AB$20+$U21*'3 - Phase Durations'!$AB$21+$V21*('3 - Phase Durations'!$AB$22+'3 - Phase Durations'!$AB$23)+$W21*'3 - Phase Durations'!$AB$24)/12 -> 1 | AU21: =($Q21*'3 - Phase Durations'!$AC$16+$R21*'3 - Phase Durations'!$AC$17+$S21*('3 - Phase Durations'!$AC$18+'3 - Phase Durations'!$AC$19)+$T21*'3 - Phase Durations'!$AC$20+$U21*'3 - Phase Durations'!$AC$21+$V21*('3 - Phase Durations'!$AC$22+'3 - Phase Durations'!$AC$23)+$W21*'3 - Phase Durations'!$AC$24)/12 -> 1.0027397 | AV21: =($Q21*'3 - Phase Durations'!$AD$16+$R21*'3 - Phase Durations'!$AD$17+$S21*('3 - Phase Durations'!$AD$18+'3 - Phase Durations'!$AD$19)+$T21*'3 - Phase Durations'!$AD$20+$U21*'3 - Phase Durations'!$AD$21+$V21*('3 - Phase Durations'!$AD$22+'3 - Phase Durations'!$AD$23)+$W21*'3 - Phase Durations'!$AD$24)/12 -> 1 | AW21: =($Q21*'3 - Phase Durations'!$AE$16+$R21*'3 - Phase Durations'!$AE$17+$S21*('3 - Phase Durations'!$AE$18+'3 - Phase Durations'!$AE$19)+$T21*'3 - Phase Durations'!$AE$20+$U21*'3 - Phase Durations'!$AE$21+$V21*('3 - Phase Durations'!$AE$22+'3 - Phase Durations'!$AE$23)+$W21*'3 - Phase Durations'!$AE$24)/12 -> 1 | AX21: =($Q21*'3 - Phase Durations'!$AF$16+$R21*'3 - Phase Durations'!$AF$17+$S21*('3 - Phase Durations'!$AF$18+'3 - Phase Durations'!$AF$19)+$T21*'3 - Phase Durations'!$AF$20+$U21*'3 - Phase Durations'!$AF$21+$V21*('3 - Phase Durations'!$AF$22+'3 - Phase Durations'!$AF$23)+$W21*'3 - Phase Durations'!$AF$24)/12 -> 1 | AY21: =($Q21*'3 - Phase Durations'!$AG$16+$R21*'3 - Phase Durations'!$AG$17+$S21*('3 - Phase Durations'!$AG$18+'3 - Phase Durations'!$AG$19)+$T21*'3 - Phase Durations'!$AG$20+$U21*'3 - Phase Durations'!$AG$21+$V21*('3 - Phase Durations'!$AG$22+'3 - Phase Durations'!$AG$23)+$W21*'3 - Phase Durations'!$AG$24)/12 -> 1.0027397 | AZ21: =($Q21*'3 - Phase Durations'!$AH$16+$R21*'3 - Phase Durations'!$AH$17+$S21*('3 - Phase Durations'!$AH$18+'3 - Phase Durations'!$AH$19)+$T21*'3 - Phase Durations'!$AH$20+$U21*'3 - Phase Durations'!$AH$21+$V21*('3 - Phase Durations'!$AH$22+'3 - Phase Durations'!$AH$23)+$W21*'3 - Phase Durations'!$AH$24)/12 -> 1 | BA21: =($Q21*'3 - Phase Durations'!$AI$16+$R21*'3 - Phase Durations'!$AI$17+$S21*('3 - Phase Durations'!$AI$18+'3 - Phase Durations'!$AI$19)+$T21*'3 - Phase Durations'!$AI$20+$U21*'3 - Phase Durations'!$AI$21+$V21*('3 - Phase Durations'!$AI$22+'3 - Phase Durations'!$AI$23)+$W21*'3 - Phase Durations'!$AI$24)/12 -> 1 | BB21: =($Q21*'3 - Phase Durations'!$AJ$16+$R21*'3 - Phase Durations'!$AJ$17+$S21*('3 - Phase Durations'!$AJ$18+'3 - Phase Durations'!$AJ$19)+$T21*'3 - Phase Durations'!$AJ$20+$U21*'3 - Phase Durations'!$AJ$21+$V21*('3 - Phase Durations'!$AJ$22+'3 - Phase Durations'!$AJ$23)+$W21*'3 - Phase Durations'!$AJ$24)/12 -> 1 | BC21: =($Q21*'3 - Phase Durations'!$AK$16+$R21*'3 - Phase Durations'!$AK$17+$S21*('3 - Phase Durations'!$AK$18+'3 - Phase Durations'!$AK$19)+$T21*'3 - Phase Durations'!$AK$20+$U21*'3 - Phase Durations'!$AK$21+$V21*('3 - Phase Durations'!$AK$22+'3 - Phase Durations'!$AK$23)+$W21*'3 - Phase Durations'!$AK$24)/12 -> 1.0027397 | BD21: =($Q21*'3 - Phase Durations'!$AL$16+$R21*'3 - Phase Durations'!$AL$17+$S21*('3 - Phase Durations'!$AL$18+'3 - Phase Durations'!$AL$19)+$T21*'3 - Phase Durations'!$AL$20+$U21*'3 - Phase Durations'!$AL$21+$V21*('3 - Phase Durations'!$AL$22+'3 - Phase Durations'!$AL$23)+$W21*'3 - Phase Durations'!$AL$24)/12 -> 1 | BE21: =($Q21*'3 - Phase Durations'!$AM$16+$R21*'3 - Phase Durations'!$AM$17+$S21*('3 - Phase Durations'!$AM$18+'3 - Phase Durations'!$AM$19)+$T21*'3 - Phase Durations'!$AM$20+$U21*'3 - Phase Durations'!$AM$21+$V21*('3 - Phase Durations'!$AM$22+'3 - Phase Durations'!$AM$23)+$W21*'3 - Phase Durations'!$AM$24)/12 -> 1 | BF21: =($Q21*'3 - Phase Durations'!$AN$16+$R21*'3 - Phase Durations'!$AN$17+$S21*('3 - Phase Durations'!$AN$18+'3 - Phase Durations'!$AN$19)+$T21*'3 - Phase Durations'!$AN$20+$U21*'3 - Phase Durations'!$AN$21+$V21*('3 - Phase Durations'!$AN$22+'3 - Phase Durations'!$AN$23)+$W21*'3 - Phase Durations'!$AN$24)/12 -> 1 | BG21: =($Q21*'3 - Phase Durations'!$AO$16+$R21*'3 - Phase Durations'!$AO$17+$S21*('3 - Phase Durations'!$AO$18+'3 - Phase Durations'!$AO$19)+$T21*'3 - Phase Durations'!$AO$20+$U21*'3 - Phase Durations'!$AO$21+$V21*('3 - Phase Durations'!$AO$22+'3 - Phase Durations'!$AO$23)+$W21*'3 - Phase Durations'!$AO$24)/12 -> 0.24931507 | BH21: =SUM(Y21:BG21) -> 23.401753
A22: 5 | B22: CSA | C22: Project Team | D22: Project Manager | E22: PM | F22: Deputy Project Manager | G22: Program Office | H22: Space Exploration | I22: Program Management | J22: Étienne Lacroix | K22: ORCA-PM-004 | L22: New | M22: EN-ENG-4 | N22: Max Echelon | O22: Labour Rates | P22: FF-CSA | Q22: 0 | R22: 0.15 | S22: 0 | T22: 0 | U22: 0.7 | V22: 0 | W22: 0 | X22: =IFERROR(VLOOKUP($M22,'Labour Rates lookup'!$A:$B,2,FALSE()),0) -> 128000 | Y22: =($Q22*'3 - Phase Durations'!$G$16+$R22*'3 - Phase Durations'!$G$17+$S22*('3 - Phase Durations'!$G$18+'3 - Phase Durations'!$G$19)+$T22*'3 - Phase Durations'!$G$20+$U22*'3 - Phase Durations'!$G$21+$V22*('3 - Phase Durations'!$G$22+'3 - Phase Durations'!$G$23)+$W22*'3 - Phase Durations'!$G$24)/12 -> 0 | Z22: =($Q22*'3 - Phase Durations'!$H$16+$R22*'3 - Phase Durations'!$H$17+$S22*('3 - Phase Durations'!$H$18+'3 - Phase Durations'!$H$19)+$T22*'3 - Phase Durations'!$H$20+$U22*'3 - Phase Durations'!$H$21+$V22*('3 - Phase Durations'!$H$22+'3 - Phase Durations'!$H$23)+$W22*'3 - Phase Durations'!$H$24)/12 -> 0 | AA22: =($Q22*'3 - Phase Durations'!$I$16+$R22*'3 - Phase Durations'!$I$17+$S22*('3 - Phase Durations'!$I$18+'3 - Phase Durations'!$I$19)+$T22*'3 - Phase Durations'!$I$20+$U22*'3 - Phase Durations'!$I$21+$V22*('3 - Phase Durations'!$I$22+'3 - Phase Durations'!$I$23)+$W22*'3 - Phase Durations'!$I$24)/12 -> 0.03739726 | AB22: =($Q22*'3 - Phase Durations'!$J$16+$R22*'3 - Phase Durations'!$J$17+$S22*('3 - Phase Durations'!$J$18+'3 - Phase Durations'!$J$19)+$T22*'3 - Phase Durations'!$J$20+$U22*'3 - Phase Durations'!$J$21+$V22*('3 - Phase Durations'!$J$22+'3 - Phase Durations'!$J$23)+$W22*'3 - Phase Durations'!$J$24)/12 -> 0.15 | AC22: =($Q22*'3 - Phase Durations'!$K$16+$R22*'3 - Phase Durations'!$K$17+$S22*('3 - Phase Durations'!$K$18+'3 - Phase Durations'!$K$19)+$T22*'3 - Phase Durations'!$K$20+$U22*'3 - Phase Durations'!$K$21+$V22*('3 - Phase Durations'!$K$22+'3 - Phase Durations'!$K$23)+$W22*'3 - Phase Durations'!$K$24)/12 -> 0.1130137 | AD22: =($Q22*'3 - Phase Durations'!$L$16+$R22*'3 - Phase Durations'!$L$17+$S22*('3 - Phase Durations'!$L$18+'3 - Phase Durations'!$L$19)+$T22*'3 - Phase Durations'!$L$20+$U22*'3 - Phase Durations'!$L$21+$V22*('3 - Phase Durations'!$L$22+'3 - Phase Durations'!$L$23)+$W22*'3 - Phase Durations'!$L$24)/12 -> 0 | AE22: =($Q22*'3 - Phase Durations'!$M$16+$R22*'3 - Phase Durations'!$M$17+$S22*('3 - Phase Durations'!$M$18+'3 - Phase Durations'!$M$19)+$T22*'3 - Phase Durations'!$M$20+$U22*'3 - Phase Durations'!$M$21+$V22*('3 - Phase Durations'!$M$22+'3 - Phase Durations'!$M$23)+$W22*'3 - Phase Durations'!$M$24)/12 -> 0 | AF22: =($Q22*'3 - Phase Durations'!$N$16+$R22*'3 - Phase Durations'!$N$17+$S22*('3 - Phase Durations'!$N$18+'3 - Phase Durations'!$N$19)+$T22*'3 - Phase Durations'!$N$20+$U22*'3 - Phase Durations'!$N$21+$V22*('3 - Phase Durations'!$N$22+'3 - Phase Durations'!$N$23)+$W22*'3 - Phase Durations'!$N$24)/12 -> 0 | AG22: =($Q22*'3 - Phase Durations'!$O$16+$R22*'3 - Phase Durations'!$O$17+$S22*('3 - Phase Durations'!$O$18+'3 - Phase Durations'!$O$19)+$T22*'3 - Phase Durations'!$O$20+$U22*'3 - Phase Durations'!$O$21+$V22*('3 - Phase Durations'!$O$22+'3 - Phase Durations'!$O$23)+$W22*'3 - Phase Durations'!$O$24)/12 -> 0.17260274 | AH22: =($Q22*'3 - Phase Durations'!$P$16+$R22*'3 - Phase Durations'!$P$17+$S22*('3 - Phase Durations'!$P$18+'3 - Phase Durations'!$P$19)+$T22*'3 - Phase Durations'!$P$20+$U22*'3 - Phase Durations'!$P$21+$V22*('3 - Phase Durations'!$P$22+'3 - Phase Durations'!$P$23)+$W22*'3 - Phase Durations'!$P$24)/12 -> 0.7 | AI22: =($Q22*'3 - Phase Durations'!$Q$16+$R22*'3 - Phase Durations'!$Q$17+$S22*('3 - Phase Durations'!$Q$18+'3 - Phase Durations'!$Q$19)+$T22*'3 - Phase Durations'!$Q$20+$U22*'3 - Phase Durations'!$Q$21+$V22*('3 - Phase Durations'!$Q$22+'3 - Phase Durations'!$Q$23)+$W22*'3 - Phase Durations'!$Q$24)/12 -> 0.70191781 | AJ22: =($Q22*'3 - Phase Durations'!$R$16+$R22*'3 - Phase Durations'!$R$17+$S22*('3 - Phase Durations'!$R$18+'3 - Phase Durations'!$R$19)+$T22*'3 - Phase Durations'!$R$20+$U22*'3 - Phase Durations'!$R$21+$V22*('3 - Phase Durations'!$R$22+'3 - Phase Durations'!$R$23)+$W22*'3 - Phase Durations'!$R$24)/12 -> 0.7 | AK22: =($Q22*'3 - Phase Durations'!$S$16+$R22*'3 - Phase Durations'!$S$17+$S22*('3 - Phase Durations'!$S$18+'3 - Phase Durations'!$S$19)+$T22*'3 - Phase Durations'!$S$20+$U22*'3 - Phase Durations'!$S$21+$V22*('3 - Phase Durations'!$S$22+'3 - Phase Durations'!$S$23)+$W22*'3 - Phase Durations'!$S$24)/12 -> 0.7 | AL22: =($Q22*'3 - Phase Durations'!$T$16+$R22*'3 - Phase Durations'!$T$17+$S22*('3 - Phase Durations'!$T$18+'3 - Phase Durations'!$T$19)+$T22*'3 - Phase Durations'!$T$20+$U22*'3 - Phase Durations'!$T$21+$V22*('3 - Phase Durations'!$T$22+'3 - Phase Durations'!$T$23)+$W22*'3 - Phase Durations'!$T$24)/12 -> 0.7 | AM22: =($Q22*'3 - Phase Durations'!$U$16+$R22*'3 - Phase Durations'!$U$17+$S22*('3 - Phase Durations'!$U$18+'3 - Phase Durations'!$U$19)+$T22*'3 - Phase Durations'!$U$20+$U22*'3 - Phase Durations'!$U$21+$V22*('3 - Phase Durations'!$U$22+'3 - Phase Durations'!$U$23)+$W22*'3 - Phase Durations'!$U$24)/12 -> 0.70191781 | AN22: =($Q22*'3 - Phase Durations'!$V$16+$R22*'3 - Phase Durations'!$V$17+$S22*('3 - Phase Durations'!$V$18+'3 - Phase Durations'!$V$19)+$T22*'3 - Phase Durations'!$V$20+$U22*'3 - Phase Durations'!$V$21+$V22*('3 - Phase Durations'!$V$22+'3 - Phase Durations'!$V$23)+$W22*'3 - Phase Durations'!$V$24)/12 -> 0.52739726 | AO22: =($Q22*'3 - Phase Durations'!$W$16+$R22*'3 - Phase Durations'!$W$17+$S22*('3 - Phase Durations'!$W$18+'3 - Phase Durations'!$W$19)+$T22*'3 - Phase Durations'!$W$20+$U22*'3 - Phase Durations'!$W$21+$V22*('3 - Phase Durations'!$W$22+'3 - Phase Durations'!$W$23)+$W22*'3 - Phase Durations'!$W$24)/12 -> 0 | AP22: =($Q22*'3 - Phase Durations'!$X$16+$R22*'3 - Phase Durations'!$X$17+$S22*('3 - Phase Durations'!$X$18+'3 - Phase Durations'!$X$19)+$T22*'3 - Phase Durations'!$X$20+$U22*'3 - Phase Durations'!$X$21+$V22*('3 - Phase Durations'!$X$22+'3 - Phase Durations'!$X$23)+$W22*'3 - Phase Durations'!$X$24)/12 -> 0 | AQ22: =($Q22*'3 - Phase Durations'!$Y$16+$R22*'3 - Phase Durations'!$Y$17+$S22*('3 - Phase Durations'!$Y$18+'3 - Phase Durations'!$Y$19)+$T22*'3 - Phase Durations'!$Y$20+$U22*'3 - Phase Durations'!$Y$21+$V22*('3 - Phase Durations'!$Y$22+'3 - Phase Durations'!$Y$23)+$W22*'3 - Phase Durations'!$Y$24)/12 -> 0 | AR22: =($Q22*'3 - Phase Durations'!$Z$16+$R22*'3 - Phase Durations'!$Z$17+$S22*('3 - Phase Durations'!$Z$18+'3 - Phase Durations'!$Z$19)+$T22*'3 - Phase Durations'!$Z$20+$U22*'3 - Phase Durations'!$Z$21+$V22*('3 - Phase Durations'!$Z$22+'3 - Phase Durations'!$Z$23)+$W22*'3 - Phase Durations'!$Z$24)/12 -> 0 | AS22: =($Q22*'3 - Phase Durations'!$AA$16+$R22*'3 - Phase Durations'!$AA$17+$S22*('3 - Phase Durations'!$AA$18+'3 - Phase Durations'!$AA$19)+$T22*'3 - Phase Durations'!$AA$20+$U22*'3 - Phase Durations'!$AA$21+$V22*('3 - Phase Durations'!$AA$22+'3 - Phase Durations'!$AA$23)+$W22*'3 - Phase Durations'!$AA$24)/12 -> 0 | AT22: =($Q22*'3 - Phase Durations'!$AB$16+$R22*'3 - Phase Durations'!$AB$17+$S22*('3 - Phase Durations'!$AB$18+'3 - Phase Durations'!$AB$19)+$T22*'3 - Phase Durations'!$AB$20+$U22*'3 - Phase Durations'!$AB$21+$V22*('3 - Phase Durations'!$AB$22+'3 - Phase Durations'!$AB$23)+$W22*'3 - Phase Durations'!$AB$24)/12 -> 0 | AU22: =($Q22*'3 - Phase Durations'!$AC$16+$R22*'3 - Phase Durations'!$AC$17+$S22*('3 - Phase Durations'!$AC$18+'3 - Phase Durations'!$AC$19)+$T22*'3 - Phase Durations'!$AC$20+$U22*'3 - Phase Durations'!$AC$21+$V22*('3 - Phase Durations'!$AC$22+'3 - Phase Durations'!$AC$23)+$W22*'3 - Phase Durations'!$AC$24)/12 -> 0 | AV22: =($Q22*'3 - Phase Durations'!$AD$16+$R22*'3 - Phase Durations'!$AD$17+$S22*('3 - Phase Durations'!$AD$18+'3 - Phase Durations'!$AD$19)+$T22*'3 - Phase Durations'!$AD$20+$U22*'3 - Phase Durations'!$AD$21+$V22*('3 - Phase Durations'!$AD$22+'3 - Phase Durations'!$AD$23)+$W22*'3 - Phase Durations'!$AD$24)/12 -> 0 | AW22: =($Q22*'3 - Phase Durations'!$AE$16+$R22*'3 - Phase Durations'!$AE$17+$S22*('3 - Phase Durations'!$AE$18+'3 - Phase Durations'!$AE$19)+$T22*'3 - Phase Durations'!$AE$20+$U22*'3 - Phase Durations'!$AE$21+$V22*('3 - Phase Durations'!$AE$22+'3 - Phase Durations'!$AE$23)+$W22*'3 - Phase Durations'!$AE$24)/12 -> 0 | AX22: =($Q22*'3 - Phase Durations'!$AF$16+$R22*'3 - Phase Durations'!$AF$17+$S22*('3 - Phase Durations'!$AF$18+'3 - Phase Durations'!$AF$19)+$T22*'3 - Phase Durations'!$AF$20+$U22*'3 - Phase Durations'!$AF$21+$V22*('3 - Phase Durations'!$AF$22+'3 - Phase Durations'!$AF$23)+$W22*'3 - Phase Durations'!$AF$24)/12 -> 0 | AY22: =($Q22*'3 - Phase Durations'!$AG$16+$R22*'3 - Phase Durations'!$AG$17+$S22*('3 - Phase Durations'!$AG$18+'3 - Phase Durations'!$AG$19)+$T22*'3 - Phase Durations'!$AG$20+$U22*'3 - Phase Durations'!$AG$21+$V22*('3 - Phase Durations'!$AG$22+'3 - Phase Durations'!$AG$23)+$W22*'3 - Phase Durations'!$AG$24)/12 -> 0 | AZ22: =($Q22*'3 - Phase Durations'!$AH$16+$R22*'3 - Phase Durations'!$AH$17+$S22*('3 - Phase Durations'!$AH$18+'3 - Phase Durations'!$AH$19)+$T22*'3 - Phase Durations'!$AH$20+$U22*'3 - Phase Durations'!$AH$21+$V22*('3 - Phase Durations'!$AH$22+'3 - Phase Durations'!$AH$23)+$W22*'3 - Phase Durations'!$AH$24)/12 -> 0 | BA22: =($Q22*'3 - Phase Durations'!$AI$16+$R22*'3 - Phase Durations'!$AI$17+$S22*('3 - Phase Durations'!$AI$18+'3 - Phase Durations'!$AI$19)+$T22*'3 - Phase Durations'!$AI$20+$U22*'3 - Phase Durations'!$AI$21+$V22*('3 - Phase Durations'!$AI$22+'3 - Phase Durations'!$AI$23)+$W22*'3 - Phase Durations'!$AI$24)/12 -> 0 | BB22: =($Q22*'3 - Phase Durations'!$AJ$16+$R22*'3 - Phase Durations'!$AJ$17+$S22*('3 - Phase Durations'!$AJ$18+'3 - Phase Durations'!$AJ$19)+$T22*'3 - Phase Durations'!$AJ$20+$U22*'3 - Phase Durations'!$AJ$21+$V22*('3 - Phase Durations'!$AJ$22+'3 - Phase Durations'!$AJ$23)+$W22*'3 - Phase Durations'!$AJ$24)/12 -> 0 | BC22: =($Q22*'3 - Phase Durations'!$AK$16+$R22*'3 - Phase Durations'!$AK$17+$S22*('3 - Phase Durations'!$AK$18+'3 - Phase Durations'!$AK$19)+$T22*'3 - Phase Durations'!$AK$20+$U22*'3 - Phase Durations'!$AK$21+$V22*('3 - Phase Durations'!$AK$22+'3 - Phase Durations'!$AK$23)+$W22*'3 - Phase Durations'!$AK$24)/12 -> 0 | BD22: =($Q22*'3 - Phase Durations'!$AL$16+$R22*'3 - Phase Durations'!$AL$17+$S22*('3 - Phase Durations'!$AL$18+'3 - Phase Durations'!$AL$19)+$T22*'3 - Phase Durations'!$AL$20+$U22*'3 - Phase Durations'!$AL$21+$V22*('3 - Phase Durations'!$AL$22+'3 - Phase Durations'!$AL$23)+$W22*'3 - Phase Durations'!$AL$24)/12 -> 0 | BE22: =($Q22*'3 - Phase Durations'!$AM$16+$R22*'3 - Phase Durations'!$AM$17+$S22*('3 - Phase Durations'!$AM$18+'3 - Phase Durations'!$AM$19)+$T22*'3 - Phase Durations'!$AM$20+$U22*'3 - Phase Durations'!$AM$21+$V22*('3 - Phase Durations'!$AM$22+'3 - Phase Durations'!$AM$23)+$W22*'3 - Phase Durations'!$AM$24)/12 -> 0 | BF22: =($Q22*'3 - Phase Durations'!$AN$16+$R22*'3 - Phase Durations'!$AN$17+$S22*('3 - Phase Durations'!$AN$18+'3 - Phase Durations'!$AN$19)+$T22*'3 - Phase Durations'!$AN$20+$U22*'3 - Phase Durations'!$AN$21+$V22*('3 - Phase Durations'!$AN$22+'3 - Phase Durations'!$AN$23)+$W22*'3 - Phase Durations'!$AN$24)/12 -> 0 | BG22: =($Q22*'3 - Phase Durations'!$AO$16+$R22*'3 - Phase Durations'!$AO$17+$S22*('3 - Phase Durations'!$AO$18+'3 - Phase Durations'!$AO$19)+$T22*'3 - Phase Durations'!$AO$20+$U22*'3 - Phase Durations'!$AO$21+$V22*('3 - Phase Durations'!$AO$22+'3 - Phase Durations'!$AO$23)+$W22*'3 - Phase Durations'!$AO$24)/12 -> 0 | BH22: =SUM(Y22:BG22) -> 5.2042466
A23: 6 | B23: CSA | C23: Project Team | D23: Project Manager | E23: Planning | F23: Project Management Engineer | G23: Program Office | H23: Space Exploration | I23: Program Management | J23: Grace Lindqvist | K23: ORCA-PM-005 | L23: New | M23: EN-ENG-4 | N23: Max Echelon | O23: Labour Rates | P23: FF-CSA | Q23: 0 | R23: 0.2 | S23: 0.1 | T23: 0 | U23: 0.48 | V23: 0.1 | W23: 0 | X23: =IFERROR(VLOOKUP($M23,'Labour Rates lookup'!$A:$B,2,FALSE()),0) -> 128000 | Y23: =($Q23*'3 - Phase Durations'!$G$16+$R23*'3 - Phase Durations'!$G$17+$S23*('3 - Phase Durations'!$G$18+'3 - Phase Durations'!$G$19)+$T23*'3 - Phase Durations'!$G$20+$U23*'3 - Phase Durations'!$G$21+$V23*('3 - Phase Durations'!$G$22+'3 - Phase Durations'!$G$23)+$W23*'3 - Phase Durations'!$G$24)/12 -> 0 | Z23: =($Q23*'3 - Phase Durations'!$H$16+$R23*'3 - Phase Durations'!$H$17+$S23*('3 - Phase Durations'!$H$18+'3 - Phase Durations'!$H$19)+$T23*'3 - Phase Durations'!$H$20+$U23*'3 - Phase Durations'!$H$21+$V23*('3 - Phase Durations'!$H$22+'3 - Phase Durations'!$H$23)+$W23*'3 - Phase Durations'!$H$24)/12 -> 0 | AA23: =($Q23*'3 - Phase Durations'!$I$16+$R23*'3 - Phase Durations'!$I$17+$S23*('3 - Phase Durations'!$I$18+'3 - Phase Durations'!$I$19)+$T23*'3 - Phase Durations'!$I$20+$U23*'3 - Phase Durations'!$I$21+$V23*('3 - Phase Durations'!$I$22+'3 - Phase Durations'!$I$23)+$W23*'3 - Phase Durations'!$I$24)/12 -> 0.049863014 | AB23: =($Q23*'3 - Phase Durations'!$J$16+$R23*'3 - Phase Durations'!$J$17+$S23*('3 - Phase Durations'!$J$18+'3 - Phase Durations'!$J$19)+$T23*'3 - Phase Durations'!$J$20+$U23*'3 - Phase Durations'!$J$21+$V23*('3 - Phase Durations'!$J$22+'3 - Phase Durations'!$J$23)+$W23*'3 - Phase Durations'!$J$24)/12 -> 0.2 | AC23: =($Q23*'3 - Phase Durations'!$K$16+$R23*'3 - Phase Durations'!$K$17+$S23*('3 - Phase Durations'!$K$18+'3 - Phase Durations'!$K$19)+$T23*'3 - Phase Durations'!$K$20+$U23*'3 - Phase Durations'!$K$21+$V23*('3 - Phase Durations'!$K$22+'3 - Phase Durations'!$K$23)+$W23*'3 - Phase Durations'!$K$24)/12 -> 0.17534247 | AD23: =($Q23*'3 - Phase Durations'!$L$16+$R23*'3 - Phase Durations'!$L$17+$S23*('3 - Phase Durations'!$L$18+'3 - Phase Durations'!$L$19)+$T23*'3 - Phase Durations'!$L$20+$U23*'3 - Phase Durations'!$L$21+$V23*('3 - Phase Durations'!$L$22+'3 - Phase Durations'!$L$23)+$W23*'3 - Phase Durations'!$L$24)/12 -> 0.1 | AE23: =($Q23*'3 - Phase Durations'!$M$16+$R23*'3 - Phase Durations'!$M$17+$S23*('3 - Phase Durations'!$M$18+'3 - Phase Durations'!$M$19)+$T23*'3 - Phase Durations'!$M$20+$U23*'3 - Phase Durations'!$M$21+$V23*('3 - Phase Durations'!$M$22+'3 - Phase Durations'!$M$23)+$W23*'3 - Phase Durations'!$M$24)/12 -> 0.075342466 | AF23: =($Q23*'3 - Phase Durations'!$N$16+$R23*'3 - Phase Durations'!$N$17+$S23*('3 - Phase Durations'!$N$18+'3 - Phase Durations'!$N$19)+$T23*'3 - Phase Durations'!$N$20+$U23*'3 - Phase Durations'!$N$21+$V23*('3 - Phase Durations'!$N$22+'3 - Phase Durations'!$N$23)+$W23*'3 - Phase Durations'!$N$24)/12 -> 0 | AG23: =($Q23*'3 - Phase Durations'!$O$16+$R23*'3 - Phase Durations'!$O$17+$S23*('3 - Phase Durations'!$O$18+'3 - Phase Durations'!$O$19)+$T23*'3 - Phase Durations'!$O$20+$U23*'3 - Phase Durations'!$O$21+$V23*('3 - Phase Durations'!$O$22+'3 - Phase Durations'!$O$23)+$W23*'3 - Phase Durations'!$O$24)/12 -> 0.11835616 | AH23: =($Q23*'3 - Phase Durations'!$P$16+$R23*'3 - Phase Durations'!$P$17+$S23*('3 - Phase Durations'!$P$18+'3 - Phase Durations'!$P$19)+$T23*'3 - Phase Durations'!$P$20+$U23*'3 - Phase Durations'!$P$21+$V23*('3 - Phase Durations'!$P$22+'3 - Phase Durations'!$P$23)+$W23*'3 - Phase Durations'!$P$24)/12 -> 0.48 | AI23: =($Q23*'3 - Phase Durations'!$Q$16+$R23*'3 - Phase Durations'!$Q$17+$S23*('3 - Phase Durations'!$Q$18+'3 - Phase Durations'!$Q$19)+$T23*'3 - Phase Durations'!$Q$20+$U23*'3 - Phase Durations'!$Q$21+$V23*('3 - Phase Durations'!$Q$22+'3 - Phase Durations'!$Q$23)+$W23*'3 - Phase Durations'!$Q$24)/12 -> 0.48131507 | AJ23: =($Q23*'3 - Phase Durations'!$R$16+$R23*'3 - Phase Durations'!$R$17+$S23*('3 - Phase Durations'!$R$18+'3 - Phase Durations'!$R$19)+$T23*'3 - Phase Durations'!$R$20+$U23*'3 - Phase Durations'!$R$21+$V23*('3 - Phase Durations'!$R$22+'3 - Phase Durations'!$R$23)+$W23*'3 - Phase Durations'!$R$24)/12 -> 0.48 | AK23: =($Q23*'3 - Phase Durations'!$S$16+$R23*'3 - Phase Durations'!$S$17+$S23*('3 - Phase Durations'!$S$18+'3 - Phase Durations'!$S$19)+$T23*'3 - Phase Durations'!$S$20+$U23*'3 - Phase Durations'!$S$21+$V23*('3 - Phase Durations'!$S$22+'3 - Phase Durations'!$S$23)+$W23*'3 - Phase Durations'!$S$24)/12 -> 0.48 | AL23: =($Q23*'3 - Phase Durations'!$T$16+$R23*'3 - Phase Durations'!$T$17+$S23*('3 - Phase Durations'!$T$18+'3 - Phase Durations'!$T$19)+$T23*'3 - Phase Durations'!$T$20+$U23*'3 - Phase Durations'!$T$21+$V23*('3 - Phase Durations'!$T$22+'3 - Phase Durations'!$T$23)+$W23*'3 - Phase Durations'!$T$24)/12 -> 0.48 | AM23: =($Q23*'3 - Phase Durations'!$U$16+$R23*'3 - Phase Durations'!$U$17+$S23*('3 - Phase Durations'!$U$18+'3 - Phase Durations'!$U$19)+$T23*'3 - Phase Durations'!$U$20+$U23*'3 - Phase Durations'!$U$21+$V23*('3 - Phase Durations'!$U$22+'3 - Phase Durations'!$U$23)+$W23*'3 - Phase Durations'!$U$24)/12 -> 0.48131507 | AN23: =($Q23*'3 - Phase Durations'!$V$16+$R23*'3 - Phase Durations'!$V$17+$S23*('3 - Phase Durations'!$V$18+'3 - Phase Durations'!$V$19)+$T23*'3 - Phase Durations'!$V$20+$U23*'3 - Phase Durations'!$V$21+$V23*('3 - Phase Durations'!$V$22+'3 - Phase Durations'!$V$23)+$W23*'3 - Phase Durations'!$V$24)/12 -> 0.38630137 | AO23: =($Q23*'3 - Phase Durations'!$W$16+$R23*'3 - Phase Durations'!$W$17+$S23*('3 - Phase Durations'!$W$18+'3 - Phase Durations'!$W$19)+$T23*'3 - Phase Durations'!$W$20+$U23*'3 - Phase Durations'!$W$21+$V23*('3 - Phase Durations'!$W$22+'3 - Phase Durations'!$W$23)+$W23*'3 - Phase Durations'!$W$24)/12 -> 0.1 | AP23: =($Q23*'3 - Phase Durations'!$X$16+$R23*'3 - Phase Durations'!$X$17+$S23*('3 - Phase Durations'!$X$18+'3 - Phase Durations'!$X$19)+$T23*'3 - Phase Durations'!$X$20+$U23*'3 - Phase Durations'!$X$21+$V23*('3 - Phase Durations'!$X$22+'3 - Phase Durations'!$X$23)+$W23*'3 - Phase Durations'!$X$24)/12 -> 0.1 | AQ23: =($Q23*'3 - Phase Durations'!$Y$16+$R23*'3 - Phase Durations'!$Y$17+$S23*('3 - Phase Durations'!$Y$18+'3 - Phase Durations'!$Y$19)+$T23*'3 - Phase Durations'!$Y$20+$U23*'3 - Phase Durations'!$Y$21+$V23*('3 - Phase Durations'!$Y$22+'3 - Phase Durations'!$Y$23)+$W23*'3 - Phase Durations'!$Y$24)/12 -> 0.10027397 | AR23: =($Q23*'3 - Phase Durations'!$Z$16+$R23*'3 - Phase Durations'!$Z$17+$S23*('3 - Phase Durations'!$Z$18+'3 - Phase Durations'!$Z$19)+$T23*'3 - Phase Durations'!$Z$20+$U23*'3 - Phase Durations'!$Z$21+$V23*('3 - Phase Durations'!$Z$22+'3 - Phase Durations'!$Z$23)+$W23*'3 - Phase Durations'!$Z$24)/12 -> 0.1 | AS23: =($Q23*'3 - Phase Durations'!$AA$16+$R23*'3 - Phase Durations'!$AA$17+$S23*('3 - Phase Durations'!$AA$18+'3 - Phase Durations'!$AA$19)+$T23*'3 - Phase Durations'!$AA$20+$U23*'3 - Phase Durations'!$AA$21+$V23*('3 - Phase Durations'!$AA$22+'3 - Phase Durations'!$AA$23)+$W23*'3 - Phase Durations'!$AA$24)/12 -> 0.1 | AT23: =($Q23*'3 - Phase Durations'!$AB$16+$R23*'3 - Phase Durations'!$AB$17+$S23*('3 - Phase Durations'!$AB$18+'3 - Phase Durations'!$AB$19)+$T23*'3 - Phase Durations'!$AB$20+$U23*'3 - Phase Durations'!$AB$21+$V23*('3 - Phase Durations'!$AB$22+'3 - Phase Durations'!$AB$23)+$W23*'3 - Phase Durations'!$AB$24)/12 -> 0.1 | AU23: =($Q23*'3 - Phase Durations'!$AC$16+$R23*'3 - Phase Durations'!$AC$17+$S23*('3 - Phase Durations'!$AC$18+'3 - Phase Durations'!$AC$19)+$T23*'3 - Phase Durations'!$AC$20+$U23*'3 - Phase Durations'!$AC$21+$V23*('3 - Phase Durations'!$AC$22+'3 - Phase Durations'!$AC$23)+$W23*'3 - Phase Durations'!$AC$24)/12 -> 0.10027397 | AV23: =($Q23*'3 - Phase Durations'!$AD$16+$R23*'3 - Phase Durations'!$AD$17+$S23*('3 - Phase Durations'!$AD$18+'3 - Phase Durations'!$AD$19)+$T23*'3 - Phase Durations'!$AD$20+$U23*'3 - Phase Durations'!$AD$21+$V23*('3 - Phase Durations'!$AD$22+'3 - Phase Durations'!$AD$23)+$W23*'3 - Phase Durations'!$AD$24)/12 -> 0.1 | AW23: =($Q23*'3 - Phase Durations'!$AE$16+$R23*'3 - Phase Durations'!$AE$17+$S23*('3 - Phase Durations'!$AE$18+'3 - Phase Durations'!$AE$19)+$T23*'3 - Phase Durations'!$AE$20+$U23*'3 - Phase Durations'!$AE$21+$V23*('3 - Phase Durations'!$AE$22+'3 - Phase Durations'!$AE$23)+$W23*'3 - Phase Durations'!$AE$24)/12 -> 0.1 | AX23: =($Q23*'3 - Phase Durations'!$AF$16+$R23*'3 - Phase Durations'!$AF$17+$S23*('3 - Phase Durations'!$AF$18+'3 - Phase Durations'!$AF$19)+$T23*'3 - Phase Durations'!$AF$20+$U23*'3 - Phase Durations'!$AF$21+$V23*('3 - Phase Durations'!$AF$22+'3 - Phase Durations'!$AF$23)+$W23*'3 - Phase Durations'!$AF$24)/12 -> 0.1 | AY23: =($Q23*'3 - Phase Durations'!$AG$16+$R23*'3 - Phase Durations'!$AG$17+$S23*('3 - Phase Durations'!$AG$18+'3 - Phase Durations'!$AG$19)+$T23*'3 - Phase Durations'!$AG$20+$U23*'3 - Phase Durations'!$AG$21+$V23*('3 - Phase Durations'!$AG$22+'3 - Phase Durations'!$AG$23)+$W23*'3 - Phase Durations'!$AG$24)/12 -> 0.10027397 | AZ23: =($Q23*'3 - Phase Durations'!$AH$16+$R23*'3 - Phase Durations'!$AH$17+$S23*('3 - Phase Durations'!$AH$18+'3 - Phase Durations'!$AH$19)+$T23*'3 - Phase Durations'!$AH$20+$U23*'3 - Phase Durations'!$AH$21+$V23*('3 - Phase Durations'!$AH$22+'3 - Phase Durations'!$AH$23)+$W23*'3 - Phase Durations'!$AH$24)/12 -> 0.1 | BA23: =($Q23*'3 - Phase Durations'!$AI$16+$R23*'3 - Phase Durations'!$AI$17+$S23*('3 - Phase Durations'!$AI$18+'3 - Phase Durations'!$AI$19)+$T23*'3 - Phase Durations'!$AI$20+$U23*'3 - Phase Durations'!$AI$21+$V23*('3 - Phase Durations'!$AI$22+'3 - Phase Durations'!$AI$23)+$W23*'3 - Phase Durations'!$AI$24)/12 -> 0.1 | BB23: =($Q23*'3 - Phase Durations'!$AJ$16+$R23*'3 - Phase Durations'!$AJ$17+$S23*('3 - Phase Durations'!$AJ$18+'3 - Phase Durations'!$AJ$19)+$T23*'3 - Phase Durations'!$AJ$20+$U23*'3 - Phase Durations'!$AJ$21+$V23*('3 - Phase Durations'!$AJ$22+'3 - Phase Durations'!$AJ$23)+$W23*'3 - Phase Durations'!$AJ$24)/12 -> 0.1 | BC23: =($Q23*'3 - Phase Durations'!$AK$16+$R23*'3 - Phase Durations'!$AK$17+$S23*('3 - Phase Durations'!$AK$18+'3 - Phase Durations'!$AK$19)+$T23*'3 - Phase Durations'!$AK$20+$U23*'3 - Phase Durations'!$AK$21+$V23*('3 - Phase Durations'!$AK$22+'3 - Phase Durations'!$AK$23)+$W23*'3 - Phase Durations'!$AK$24)/12 -> 0.10027397 | BD23: =($Q23*'3 - Phase Durations'!$AL$16+$R23*'3 - Phase Durations'!$AL$17+$S23*('3 - Phase Durations'!$AL$18+'3 - Phase Durations'!$AL$19)+$T23*'3 - Phase Durations'!$AL$20+$U23*'3 - Phase Durations'!$AL$21+$V23*('3 - Phase Durations'!$AL$22+'3 - Phase Durations'!$AL$23)+$W23*'3 - Phase Durations'!$AL$24)/12 -> 0.1 | BE23: =($Q23*'3 - Phase Durations'!$AM$16+$R23*'3 - Phase Durations'!$AM$17+$S23*('3 - Phase Durations'!$AM$18+'3 - Phase Durations'!$AM$19)+$T23*'3 - Phase Durations'!$AM$20+$U23*'3 - Phase Durations'!$AM$21+$V23*('3 - Phase Durations'!$AM$22+'3 - Phase Durations'!$AM$23)+$W23*'3 - Phase Durations'!$AM$24)/12 -> 0.1 | BF23: =($Q23*'3 - Phase Durations'!$AN$16+$R23*'3 - Phase Durations'!$AN$17+$S23*('3 - Phase Durations'!$AN$18+'3 - Phase Durations'!$AN$19)+$T23*'3 - Phase Durations'!$AN$20+$U23*'3 - Phase Durations'!$AN$21+$V23*('3 - Phase Durations'!$AN$22+'3 - Phase Durations'!$AN$23)+$W23*'3 - Phase Durations'!$AN$24)/12 -> 0.1 | BG23: =($Q23*'3 - Phase Durations'!$AO$16+$R23*'3 - Phase Durations'!$AO$17+$S23*('3 - Phase Durations'!$AO$18+'3 - Phase Durations'!$AO$19)+$T23*'3 - Phase Durations'!$AO$20+$U23*'3 - Phase Durations'!$AO$21+$V23*('3 - Phase Durations'!$AO$22+'3 - Phase Durations'!$AO$23)+$W23*'3 - Phase Durations'!$AO$24)/12 -> 0.024931507 | BH23: =SUM(Y23:BG23) -> 5.813863
A24: 7 | B24: CSA | C24: Project Team | D24: Project Manager | E24: Cost & Schedule | F24: Schedule and Cost Management Engineer | G24: Program Office | H24: Space Exploration | I24: Program Management | J24: Samuel Boucher | K24: ORCA-PM-006 | L24: New | M24: EN-ENG-4 | N24: Max Echelon | O24: Labour Rates | P24: FF-CSA | Q24: 0 | R24: 1 | S24: 0.1 | T24: 1 | U24: 0.45 | V24: 1 | W24: 0 | X24: =IFERROR(VLOOKUP($M24,'Labour Rates lookup'!$A:$B,2,FALSE()),0) -> 128000 | Y24: =($Q24*'3 - Phase Durations'!$G$16+$R24*'3 - Phase Durations'!$G$17+$S24*('3 - Phase Durations'!$G$18+'3 - Phase Durations'!$G$19)+$T24*'3 - Phase Durations'!$G$20+$U24*'3 - Phase Durations'!$G$21+$V24*('3 - Phase Durations'!$G$22+'3 - Phase Durations'!$G$23)+$W24*'3 - Phase Durations'!$G$24)/12 -> 0 | Z24: =($Q24*'3 - Phase Durations'!$H$16+$R24*'3 - Phase Durations'!$H$17+$S24*('3 - Phase Durations'!$H$18+'3 - Phase Durations'!$H$19)+$T24*'3 - Phase Durations'!$H$20+$U24*'3 - Phase Durations'!$H$21+$V24*('3 - Phase Durations'!$H$22+'3 - Phase Durations'!$H$23)+$W24*'3 - Phase Durations'!$H$24)/12 -> 0 | AA24: =($Q24*'3 - Phase Durations'!$I$16+$R24*'3 - Phase Durations'!$I$17+$S24*('3 - Phase Durations'!$I$18+'3 - Phase Durations'!$I$19)+$T24*'3 - Phase Durations'!$I$20+$U24*'3 - Phase Durations'!$I$21+$V24*('3 - Phase Durations'!$I$22+'3 - Phase Durations'!$I$23)+$W24*'3 - Phase Durations'!$I$24)/12 -> 0.24931507 | AB24: =($Q24*'3 - Phase Durations'!$J$16+$R24*'3 - Phase Durations'!$J$17+$S24*('3 - Phase Durations'!$J$18+'3 - Phase Durations'!$J$19)+$T24*'3 - Phase Durations'!$J$20+$U24*'3 - Phase Durations'!$J$21+$V24*('3 - Phase Durations'!$J$22+'3 - Phase Durations'!$J$23)+$W24*'3 - Phase Durations'!$J$24)/12 -> 1 | AC24: =($Q24*'3 - Phase Durations'!$K$16+$R24*'3 - Phase Durations'!$K$17+$S24*('3 - Phase Durations'!$K$18+'3 - Phase Durations'!$K$19)+$T24*'3 - Phase Durations'!$K$20+$U24*'3 - Phase Durations'!$K$21+$V24*('3 - Phase Durations'!$K$22+'3 - Phase Durations'!$K$23)+$W24*'3 - Phase Durations'!$K$24)/12 -> 0.77808219 | AD24: =($Q24*'3 - Phase Durations'!$L$16+$R24*'3 - Phase Durations'!$L$17+$S24*('3 - Phase Durations'!$L$18+'3 - Phase Durations'!$L$19)+$T24*'3 - Phase Durations'!$L$20+$U24*'3 - Phase Durations'!$L$21+$V24*('3 - Phase Durations'!$L$22+'3 - Phase Durations'!$L$23)+$W24*'3 - Phase Durations'!$L$24)/12 -> 0.1 | AE24: =($Q24*'3 - Phase Durations'!$M$16+$R24*'3 - Phase Durations'!$M$17+$S24*('3 - Phase Durations'!$M$18+'3 - Phase Durations'!$M$19)+$T24*'3 - Phase Durations'!$M$20+$U24*'3 - Phase Durations'!$M$21+$V24*('3 - Phase Durations'!$M$22+'3 - Phase Durations'!$M$23)+$W24*'3 - Phase Durations'!$M$24)/12 -> 0.32465753 | AF24: =($Q24*'3 - Phase Durations'!$N$16+$R24*'3 - Phase Durations'!$N$17+$S24*('3 - Phase Durations'!$N$18+'3 - Phase Durations'!$N$19)+$T24*'3 - Phase Durations'!$N$20+$U24*'3 - Phase Durations'!$N$21+$V24*('3 - Phase Durations'!$N$22+'3 - Phase Durations'!$N$23)+$W24*'3 - Phase Durations'!$N$24)/12 -> 1 | AG24: =($Q24*'3 - Phase Durations'!$O$16+$R24*'3 - Phase Durations'!$O$17+$S24*('3 - Phase Durations'!$O$18+'3 - Phase Durations'!$O$19)+$T24*'3 - Phase Durations'!$O$20+$U24*'3 - Phase Durations'!$O$21+$V24*('3 - Phase Durations'!$O$22+'3 - Phase Durations'!$O$23)+$W24*'3 - Phase Durations'!$O$24)/12 -> 0.86438356 | AH24: =($Q24*'3 - Phase Durations'!$P$16+$R24*'3 - Phase Durations'!$P$17+$S24*('3 - Phase Durations'!$P$18+'3 - Phase Durations'!$P$19)+$T24*'3 - Phase Durations'!$P$20+$U24*'3 - Phase Durations'!$P$21+$V24*('3 - Phase Durations'!$P$22+'3 - Phase Durations'!$P$23)+$W24*'3 - Phase Durations'!$P$24)/12 -> 0.45 | AI24: =($Q24*'3 - Phase Durations'!$Q$16+$R24*'3 - Phase Durations'!$Q$17+$S24*('3 - Phase Durations'!$Q$18+'3 - Phase Durations'!$Q$19)+$T24*'3 - Phase Durations'!$Q$20+$U24*'3 - Phase Durations'!$Q$21+$V24*('3 - Phase Durations'!$Q$22+'3 - Phase Durations'!$Q$23)+$W24*'3 - Phase Durations'!$Q$24)/12 -> 0.45123288 | AJ24: =($Q24*'3 - Phase Durations'!$R$16+$R24*'3 - Phase Durations'!$R$17+$S24*('3 - Phase Durations'!$R$18+'3 - Phase Durations'!$R$19)+$T24*'3 - Phase Durations'!$R$20+$U24*'3 - Phase Durations'!$R$21+$V24*('3 - Phase Durations'!$R$22+'3 - Phase Durations'!$R$23)+$W24*'3 - Phase Durations'!$R$24)/12 -> 0.45 | AK24: =($Q24*'3 - Phase Durations'!$S$16+$R24*'3 - Phase Durations'!$S$17+$S24*('3 - Phase Durations'!$S$18+'3 - Phase Durations'!$S$19)+$T24*'3 - Phase Durations'!$S$20+$U24*'3 - Phase Durations'!$S$21+$V24*('3 - Phase Durations'!$S$22+'3 - Phase Durations'!$S$23)+$W24*'3 - Phase Durations'!$S$24)/12 -> 0.45 | AL24: =($Q24*'3 - Phase Durations'!$T$16+$R24*'3 - Phase Durations'!$T$17+$S24*('3 - Phase Durations'!$T$18+'3 - Phase Durations'!$T$19)+$T24*'3 - Phase Durations'!$T$20+$U24*'3 - Phase Durations'!$T$21+$V24*('3 - Phase Durations'!$T$22+'3 - Phase Durations'!$T$23)+$W24*'3 - Phase Durations'!$T$24)/12 -> 0.45 | AM24: =($Q24*'3 - Phase Durations'!$U$16+$R24*'3 - Phase Durations'!$U$17+$S24*('3 - Phase Durations'!$U$18+'3 - Phase Durations'!$U$19)+$T24*'3 - Phase Durations'!$U$20+$U24*'3 - Phase Durations'!$U$21+$V24*('3 - Phase Durations'!$U$22+'3 - Phase Durations'!$U$23)+$W24*'3 - Phase Durations'!$U$24)/12 -> 0.45123288 | AN24: =($Q24*'3 - Phase Durations'!$V$16+$R24*'3 - Phase Durations'!$V$17+$S24*('3 - Phase Durations'!$V$18+'3 - Phase Durations'!$V$19)+$T24*'3 - Phase Durations'!$V$20+$U24*'3 - Phase Durations'!$V$21+$V24*('3 - Phase Durations'!$V$22+'3 - Phase Durations'!$V$23)+$W24*'3 - Phase Durations'!$V$24)/12 -> 0.58561644 | AO24: =($Q24*'3 - Phase Durations'!$W$16+$R24*'3 - Phase Durations'!$W$17+$S24*('3 - Phase Durations'!$W$18+'3 - Phase Durations'!$W$19)+$T24*'3 - Phase Durations'!$W$20+$U24*'3 - Phase Durations'!$W$21+$V24*('3 - Phase Durations'!$W$22+'3 - Phase Durations'!$W$23)+$W24*'3 - Phase Durations'!$W$24)/12 -> 1 | AP24: =($Q24*'3 - Phase Durations'!$X$16+$R24*'3 - Phase Durations'!$X$17+$S24*('3 - Phase Durations'!$X$18+'3 - Phase Durations'!$X$19)+$T24*'3 - Phase Durations'!$X$20+$U24*'3 - Phase Durations'!$X$21+$V24*('3 - Phase Durations'!$X$22+'3 - Phase Durations'!$X$23)+$W24*'3 - Phase Durations'!$X$24)/12 -> 1 | AQ24: =($Q24*'3 - Phase Durations'!$Y$16+$R24*'3 - Phase Durations'!$Y$17+$S24*('3 - Phase Durations'!$Y$18+'3 - Phase Durations'!$Y$19)+$T24*'3 - Phase Durations'!$Y$20+$U24*'3 - Phase Durations'!$Y$21+$V24*('3 - Phase Durations'!$Y$22+'3 - Phase Durations'!$Y$23)+$W24*'3 - Phase Durations'!$Y$24)/12 -> 1.0027397 | AR24: =($Q24*'3 - Phase Durations'!$Z$16+$R24*'3 - Phase Durations'!$Z$17+$S24*('3 - Phase Durations'!$Z$18+'3 - Phase Durations'!$Z$19)+$T24*'3 - Phase Durations'!$Z$20+$U24*'3 - Phase Durations'!$Z$21+$V24*('3 - Phase Durations'!$Z$22+'3 - Phase Durations'!$Z$23)+$W24*'3 - Phase Durations'!$Z$24)/12 -> 1 | AS24: =($Q24*'3 - Phase Durations'!$AA$16+$R24*'3 - Phase Durations'!$AA$17+$S24*('3 - Phase Durations'!$AA$18+'3 - Phase Durations'!$AA$19)+$T24*'3 - Phase Durations'!$AA$20+$U24*'3 - Phase Durations'!$AA$21+$V24*('3 - Phase Durations'!$AA$22+'3 - Phase Durations'!$AA$23)+$W24*'3 - Phase Durations'!$AA$24)/12 -> 1 | AT24: =($Q24*'3 - Phase Durations'!$AB$16+$R24*'3 - Phase Durations'!$AB$17+$S24*('3 - Phase Durations'!$AB$18+'3 - Phase Durations'!$AB$19)+$T24*'3 - Phase Durations'!$AB$20+$U24*'3 - Phase Durations'!$AB$21+$V24*('3 - Phase Durations'!$AB$22+'3 - Phase Durations'!$AB$23)+$W24*'3 - Phase Durations'!$AB$24)/12 -> 1 | AU24: =($Q24*'3 - Phase Durations'!$AC$16+$R24*'3 - Phase Durations'!$AC$17+$S24*('3 - Phase Durations'!$AC$18+'3 - Phase Durations'!$AC$19)+$T24*'3 - Phase Durations'!$AC$20+$U24*'3 - Phase Durations'!$AC$21+$V24*('3 - Phase Durations'!$AC$22+'3 - Phase Durations'!$AC$23)+$W24*'3 - Phase Durations'!$AC$24)/12 -> 1.0027397 | AV24: =($Q24*'3 - Phase Durations'!$AD$16+$R24*'3 - Phase Durations'!$AD$17+$S24*('3 - Phase Durations'!$AD$18+'3 - Phase Durations'!$AD$19)+$T24*'3 - Phase Durations'!$AD$20+$U24*'3 - Phase Durations'!$AD$21+$V24*('3 - Phase Durations'!$AD$22+'3 - Phase Durations'!$AD$23)+$W24*'3 - Phase Durations'!$AD$24)/12 -> 1 | AW24: =($Q24*'3 - Phase Durations'!$AE$16+$R24*'3 - Phase Durations'!$AE$17+$S24*('3 - Phase Durations'!$AE$18+'3 - Phase Durations'!$AE$19)+$T24*'3 - Phase Durations'!$AE$20+$U24*'3 - Phase Durations'!$AE$21+$V24*('3 - Phase Durations'!$AE$22+'3 - Phase Durations'!$AE$23)+$W24*'3 - Phase Durations'!$AE$24)/12 -> 1 | AX24: =($Q24*'3 - Phase Durations'!$AF$16+$R24*'3 - Phase Durations'!$AF$17+$S24*('3 - Phase Durations'!$AF$18+'3 - Phase Durations'!$AF$19)+$T24*'3 - Phase Durations'!$AF$20+$U24*'3 - Phase Durations'!$AF$21+$V24*('3 - Phase Durations'!$AF$22+'3 - Phase Durations'!$AF$23)+$W24*'3 - Phase Durations'!$AF$24)/12 -> 1 | AY24: =($Q24*'3 - Phase Durations'!$AG$16+$R24*'3 - Phase Durations'!$AG$17+$S24*('3 - Phase Durations'!$AG$18+'3 - Phase Durations'!$AG$19)+$T24*'3 - Phase Durations'!$AG$20+$U24*'3 - Phase Durations'!$AG$21+$V24*('3 - Phase Durations'!$AG$22+'3 - Phase Durations'!$AG$23)+$W24*'3 - Phase Durations'!$AG$24)/12 -> 1.0027397 | AZ24: =($Q24*'3 - Phase Durations'!$AH$16+$R24*'3 - Phase Durations'!$AH$17+$S24*('3 - Phase Durations'!$AH$18+'3 - Phase Durations'!$AH$19)+$T24*'3 - Phase Durations'!$AH$20+$U24*'3 - Phase Durations'!$AH$21+$V24*('3 - Phase Durations'!$AH$22+'3 - Phase Durations'!$AH$23)+$W24*'3 - Phase Durations'!$AH$24)/12 -> 1 | BA24: =($Q24*'3 - Phase Durations'!$AI$16+$R24*'3 - Phase Durations'!$AI$17+$S24*('3 - Phase Durations'!$AI$18+'3 - Phase Durations'!$AI$19)+$T24*'3 - Phase Durations'!$AI$20+$U24*'3 - Phase Durations'!$AI$21+$V24*('3 - Phase Durations'!$AI$22+'3 - Phase Durations'!$AI$23)+$W24*'3 - Phase Durations'!$AI$24)/12 -> 1 | BB24: =($Q24*'3 - Phase Durations'!$AJ$16+$R24*'3 - Phase Durations'!$AJ$17+$S24*('3 - Phase Durations'!$AJ$18+'3 - Phase Durations'!$AJ$19)+$T24*'3 - Phase Durations'!$AJ$20+$U24*'3 - Phase Durations'!$AJ$21+$V24*('3 - Phase Durations'!$AJ$22+'3 - Phase Durations'!$AJ$23)+$W24*'3 - Phase Durations'!$AJ$24)/12 -> 1 | BC24: =($Q24*'3 - Phase Durations'!$AK$16+$R24*'3 - Phase Durations'!$AK$17+$S24*('3 - Phase Durations'!$AK$18+'3 - Phase Durations'!$AK$19)+$T24*'3 - Phase Durations'!$AK$20+$U24*'3 - Phase Durations'!$AK$21+$V24*('3 - Phase Durations'!$AK$22+'3 - Phase Durations'!$AK$23)+$W24*'3 - Phase Durations'!$AK$24)/12 -> 1.0027397 | BD24: =($Q24*'3 - Phase Durations'!$AL$16+$R24*'3 - Phase Durations'!$AL$17+$S24*('3 - Phase Durations'!$AL$18+'3 - Phase Durations'!$AL$19)+$T24*'3 - Phase Durations'!$AL$20+$U24*'3 - Phase Durations'!$AL$21+$V24*('3 - Phase Durations'!$AL$22+'3 - Phase Durations'!$AL$23)+$W24*'3 - Phase Durations'!$AL$24)/12 -> 1 | BE24: =($Q24*'3 - Phase Durations'!$AM$16+$R24*'3 - Phase Durations'!$AM$17+$S24*('3 - Phase Durations'!$AM$18+'3 - Phase Durations'!$AM$19)+$T24*'3 - Phase Durations'!$AM$20+$U24*'3 - Phase Durations'!$AM$21+$V24*('3 - Phase Durations'!$AM$22+'3 - Phase Durations'!$AM$23)+$W24*'3 - Phase Durations'!$AM$24)/12 -> 1 | BF24: =($Q24*'3 - Phase Durations'!$AN$16+$R24*'3 - Phase Durations'!$AN$17+$S24*('3 - Phase Durations'!$AN$18+'3 - Phase Durations'!$AN$19)+$T24*'3 - Phase Durations'!$AN$20+$U24*'3 - Phase Durations'!$AN$21+$V24*('3 - Phase Durations'!$AN$22+'3 - Phase Durations'!$AN$23)+$W24*'3 - Phase Durations'!$AN$24)/12 -> 1 | BG24: =($Q24*'3 - Phase Durations'!$AO$16+$R24*'3 - Phase Durations'!$AO$17+$S24*('3 - Phase Durations'!$AO$18+'3 - Phase Durations'!$AO$19)+$T24*'3 - Phase Durations'!$AO$20+$U24*'3 - Phase Durations'!$AO$21+$V24*('3 - Phase Durations'!$AO$22+'3 - Phase Durations'!$AO$23)+$W24*'3 - Phase Durations'!$AO$24)/12 -> 0.24931507 | BH24: =SUM(Y24:BG24) -> 25.864795
A25: 8 | B25: CSA | C25: Project Team | D25: Systems | E25: Systems Engineering | F25: Lead Spacecraft Systems Engineer | G25: Instrument Suite | H25: Space Exploration | I25: Engineering | J25: Naomi Fitzgerald | K25: ORCA-SE-001 | L25: New | M25: EN-ENG-5 | N25: Max Echelon | O25: Labour Rates | P25: FF-CSA | Q25: 0 | R25: 0.3 | S25: 0 | T25: 0.25 | U25: 0.37 | V25: 0.05 | W25: 0 | X25: =IFERROR(VLOOKUP($M25,'Labour Rates lookup'!$A:$B,2,FALSE()),0) -> 145000 | Y25: =($Q25*'3 - Phase Durations'!$G$16+$R25*'3 - Phase Durations'!$G$17+$S25*('3 - Phase Durations'!$G$18+'3 - Phase Durations'!$G$19)+$T25*'3 - Phase Durations'!$G$20+$U25*'3 - Phase Durations'!$G$21+$V25*('3 - Phase Durations'!$G$22+'3 - Phase Durations'!$G$23)+$W25*'3 - Phase Durations'!$G$24)/12 -> 0 | Z25: =($Q25*'3 - Phase Durations'!$H$16+$R25*'3 - Phase Durations'!$H$17+$S25*('3 - Phase Durations'!$H$18+'3 - Phase Durations'!$H$19)+$T25*'3 - Phase Durations'!$H$20+$U25*'3 - Phase Durations'!$H$21+$V25*('3 - Phase Durations'!$H$22+'3 - Phase Durations'!$H$23)+$W25*'3 - Phase Durations'!$H$24)/12 -> 0 | AA25: =($Q25*'3 - Phase Durations'!$I$16+$R25*'3 - Phase Durations'!$I$17+$S25*('3 - Phase Durations'!$I$18+'3 - Phase Durations'!$I$19)+$T25*'3 - Phase Durations'!$I$20+$U25*'3 - Phase Durations'!$I$21+$V25*('3 - Phase Durations'!$I$22+'3 - Phase Durations'!$I$23)+$W25*'3 - Phase Durations'!$I$24)/12 -> 0.074794521 | AB25: =($Q25*'3 - Phase Durations'!$J$16+$R25*'3 - Phase Durations'!$J$17+$S25*('3 - Phase Durations'!$J$18+'3 - Phase Durations'!$J$19)+$T25*'3 - Phase Durations'!$J$20+$U25*'3 - Phase Durations'!$J$21+$V25*('3 - Phase Durations'!$J$22+'3 - Phase Durations'!$J$23)+$W25*'3 - Phase Durations'!$J$24)/12 -> 0.3 | AC25: =($Q25*'3 - Phase Durations'!$K$16+$R25*'3 - Phase Durations'!$K$17+$S25*('3 - Phase Durations'!$K$18+'3 - Phase Durations'!$K$19)+$T25*'3 - Phase Durations'!$K$20+$U25*'3 - Phase Durations'!$K$21+$V25*('3 - Phase Durations'!$K$22+'3 - Phase Durations'!$K$23)+$W25*'3 - Phase Durations'!$K$24)/12 -> 0.2260274 | AD25: =($Q25*'3 - Phase Durations'!$L$16+$R25*'3 - Phase Durations'!$L$17+$S25*('3 - Phase Durations'!$L$18+'3 - Phase Durations'!$L$19)+$T25*'3 - Phase Durations'!$L$20+$U25*'3 - Phase Durations'!$L$21+$V25*('3 - Phase Durations'!$L$22+'3 - Phase Durations'!$L$23)+$W25*'3 - Phase Durations'!$L$24)/12 -> 0 | AE25: =($Q25*'3 - Phase Durations'!$M$16+$R25*'3 - Phase Durations'!$M$17+$S25*('3 - Phase Durations'!$M$18+'3 - Phase Durations'!$M$19)+$T25*'3 - Phase Durations'!$M$20+$U25*'3 - Phase Durations'!$M$21+$V25*('3 - Phase Durations'!$M$22+'3 - Phase Durations'!$M$23)+$W25*'3 - Phase Durations'!$M$24)/12 -> 0.062328767 | AF25: =($Q25*'3 - Phase Durations'!$N$16+$R25*'3 - Phase Durations'!$N$17+$S25*('3 - Phase Durations'!$N$18+'3 - Phase Durations'!$N$19)+$T25*'3 - Phase Durations'!$N$20+$U25*'3 - Phase Durations'!$N$21+$V25*('3 - Phase Durations'!$N$22+'3 - Phase Durations'!$N$23)+$W25*'3 - Phase Durations'!$N$24)/12 -> 0.25 | AG25: =($Q25*'3 - Phase Durations'!$O$16+$R25*'3 - Phase Durations'!$O$17+$S25*('3 - Phase Durations'!$O$18+'3 - Phase Durations'!$O$19)+$T25*'3 - Phase Durations'!$O$20+$U25*'3 - Phase Durations'!$O$21+$V25*('3 - Phase Durations'!$O$22+'3 - Phase Durations'!$O$23)+$W25*'3 - Phase Durations'!$O$24)/12 -> 0.27958904 | AH25: =($Q25*'3 - Phase Durations'!$P$16+$R25*'3 - Phase Durations'!$P$17+$S25*('3 - Phase Durations'!$P$18+'3 - Phase Durations'!$P$19)+$T25*'3 - Phase Durations'!$P$20+$U25*'3 - Phase Durations'!$P$21+$V25*('3 - Phase Durations'!$P$22+'3 - Phase Durations'!$P$23)+$W25*'3 - Phase Durations'!$P$24)/12 -> 0.37 | AI25: =($Q25*'3 - Phase Durations'!$Q$16+$R25*'3 - Phase Durations'!$Q$17+$S25*('3 - Phase Durations'!$Q$18+'3 - Phase Durations'!$Q$19)+$T25*'3 - Phase Durations'!$Q$20+$U25*'3 - Phase Durations'!$Q$21+$V25*('3 - Phase Durations'!$Q$22+'3 - Phase Durations'!$Q$23)+$W25*'3 - Phase Durations'!$Q$24)/12 -> 0.3710137 | AJ25: =($Q25*'3 - Phase Durations'!$R$16+$R25*'3 - Phase Durations'!$R$17+$S25*('3 - Phase Durations'!$R$18+'3 - Phase Durations'!$R$19)+$T25*'3 - Phase Durations'!$R$20+$U25*'3 - Phase Durations'!$R$21+$V25*('3 - Phase Durations'!$R$22+'3 - Phase Durations'!$R$23)+$W25*'3 - Phase Durations'!$R$24)/12 -> 0.37 | AK25: =($Q25*'3 - Phase Durations'!$S$16+$R25*'3 - Phase Durations'!$S$17+$S25*('3 - Phase Durations'!$S$18+'3 - Phase Durations'!$S$19)+$T25*'3 - Phase Durations'!$S$20+$U25*'3 - Phase Durations'!$S$21+$V25*('3 - Phase Durations'!$S$22+'3 - Phase Durations'!$S$23)+$W25*'3 - Phase Durations'!$S$24)/12 -> 0.37 | AL25: =($Q25*'3 - Phase Durations'!$T$16+$R25*'3 - Phase Durations'!$T$17+$S25*('3 - Phase Durations'!$T$18+'3 - Phase Durations'!$T$19)+$T25*'3 - Phase Durations'!$T$20+$U25*'3 - Phase Durations'!$T$21+$V25*('3 - Phase Durations'!$T$22+'3 - Phase Durations'!$T$23)+$W25*'3 - Phase Durations'!$T$24)/12 -> 0.37 | AM25: =($Q25*'3 - Phase Durations'!$U$16+$R25*'3 - Phase Durations'!$U$17+$S25*('3 - Phase Durations'!$U$18+'3 - Phase Durations'!$U$19)+$T25*'3 - Phase Durations'!$U$20+$U25*'3 - Phase Durations'!$U$21+$V25*('3 - Phase Durations'!$U$22+'3 - Phase Durations'!$U$23)+$W25*'3 - Phase Durations'!$U$24)/12 -> 0.3710137 | AN25: =($Q25*'3 - Phase Durations'!$V$16+$R25*'3 - Phase Durations'!$V$17+$S25*('3 - Phase Durations'!$V$18+'3 - Phase Durations'!$V$19)+$T25*'3 - Phase Durations'!$V$20+$U25*'3 - Phase Durations'!$V$21+$V25*('3 - Phase Durations'!$V$22+'3 - Phase Durations'!$V$23)+$W25*'3 - Phase Durations'!$V$24)/12 -> 0.29109589 | AO25: =($Q25*'3 - Phase Durations'!$W$16+$R25*'3 - Phase Durations'!$W$17+$S25*('3 - Phase Durations'!$W$18+'3 - Phase Durations'!$W$19)+$T25*'3 - Phase Durations'!$W$20+$U25*'3 - Phase Durations'!$W$21+$V25*('3 - Phase Durations'!$W$22+'3 - Phase Durations'!$W$23)+$W25*'3 - Phase Durations'!$W$24)/12 -> 0.05 | AP25: =($Q25*'3 - Phase Durations'!$X$16+$R25*'3 - Phase Durations'!$X$17+$S25*('3 - Phase Durations'!$X$18+'3 - Phase Durations'!$X$19)+$T25*'3 - Phase Durations'!$X$20+$U25*'3 - Phase Durations'!$X$21+$V25*('3 - Phase Durations'!$X$22+'3 - Phase Durations'!$X$23)+$W25*'3 - Phase Durations'!$X$24)/12 -> 0.05 | AQ25: =($Q25*'3 - Phase Durations'!$Y$16+$R25*'3 - Phase Durations'!$Y$17+$S25*('3 - Phase Durations'!$Y$18+'3 - Phase Durations'!$Y$19)+$T25*'3 - Phase Durations'!$Y$20+$U25*'3 - Phase Durations'!$Y$21+$V25*('3 - Phase Durations'!$Y$22+'3 - Phase Durations'!$Y$23)+$W25*'3 - Phase Durations'!$Y$24)/12 -> 0.050136986 | AR25: =($Q25*'3 - Phase Durations'!$Z$16+$R25*'3 - Phase Durations'!$Z$17+$S25*('3 - Phase Durations'!$Z$18+'3 - Phase Durations'!$Z$19)+$T25*'3 - Phase Durations'!$Z$20+$U25*'3 - Phase Durations'!$Z$21+$V25*('3 - Phase Durations'!$Z$22+'3 - Phase Durations'!$Z$23)+$W25*'3 - Phase Durations'!$Z$24)/12 -> 0.05 | AS25: =($Q25*'3 - Phase Durations'!$AA$16+$R25*'3 - Phase Durations'!$AA$17+$S25*('3 - Phase Durations'!$AA$18+'3 - Phase Durations'!$AA$19)+$T25*'3 - Phase Durations'!$AA$20+$U25*'3 - Phase Durations'!$AA$21+$V25*('3 - Phase Durations'!$AA$22+'3 - Phase Durations'!$AA$23)+$W25*'3 - Phase Durations'!$AA$24)/12 -> 0.05 | AT25: =($Q25*'3 - Phase Durations'!$AB$16+$R25*'3 - Phase Durations'!$AB$17+$S25*('3 - Phase Durations'!$AB$18+'3 - Phase Durations'!$AB$19)+$T25*'3 - Phase Durations'!$AB$20+$U25*'3 - Phase Durations'!$AB$21+$V25*('3 - Phase Durations'!$AB$22+'3 - Phase Durations'!$AB$23)+$W25*'3 - Phase Durations'!$AB$24)/12 -> 0.05 | AU25: =($Q25*'3 - Phase Durations'!$AC$16+$R25*'3 - Phase Durations'!$AC$17+$S25*('3 - Phase Durations'!$AC$18+'3 - Phase Durations'!$AC$19)+$T25*'3 - Phase Durations'!$AC$20+$U25*'3 - Phase Durations'!$AC$21+$V25*('3 - Phase Durations'!$AC$22+'3 - Phase Durations'!$AC$23)+$W25*'3 - Phase Durations'!$AC$24)/12 -> 0.050136986 | AV25: =($Q25*'3 - Phase Durations'!$AD$16+$R25*'3 - Phase Durations'!$AD$17+$S25*('3 - Phase Durations'!$AD$18+'3 - Phase Durations'!$AD$19)+$T25*'3 - Phase Durations'!$AD$20+$U25*'3 - Phase Durations'!$AD$21+$V25*('3 - Phase Durations'!$AD$22+'3 - Phase Durations'!$AD$23)+$W25*'3 - Phase Durations'!$AD$24)/12 -> 0.05 | AW25: =($Q25*'3 - Phase Durations'!$AE$16+$R25*'3 - Phase Durations'!$AE$17+$S25*('3 - Phase Durations'!$AE$18+'3 - Phase Durations'!$AE$19)+$T25*'3 - Phase Durations'!$AE$20+$U25*'3 - Phase Durations'!$AE$21+$V25*('3 - Phase Durations'!$AE$22+'3 - Phase Durations'!$AE$23)+$W25*'3 - Phase Durations'!$AE$24)/12 -> 0.05 | AX25: =($Q25*'3 - Phase Durations'!$AF$16+$R25*'3 - Phase Durations'!$AF$17+$S25*('3 - Phase Durations'!$AF$18+'3 - Phase Durations'!$AF$19)+$T25*'3 - Phase Durations'!$AF$20+$U25*'3 - Phase Durations'!$AF$21+$V25*('3 - Phase Durations'!$AF$22+'3 - Phase Durations'!$AF$23)+$W25*'3 - Phase Durations'!$AF$24)/12 -> 0.05 | AY25: =($Q25*'3 - Phase Durations'!$AG$16+$R25*'3 - Phase Durations'!$AG$17+$S25*('3 - Phase Durations'!$AG$18+'3 - Phase Durations'!$AG$19)+$T25*'3 - Phase Durations'!$AG$20+$U25*'3 - Phase Durations'!$AG$21+$V25*('3 - Phase Durations'!$AG$22+'3 - Phase Durations'!$AG$23)+$W25*'3 - Phase Durations'!$AG$24)/12 -> 0.050136986 | AZ25: =($Q25*'3 - Phase Durations'!$AH$16+$R25*'3 - Phase Durations'!$AH$17+$S25*('3 - Phase Durations'!$AH$18+'3 - Phase Durations'!$AH$19)+$T25*'3 - Phase Durations'!$AH$20+$U25*'3 - Phase Durations'!$AH$21+$V25*('3 - Phase Durations'!$AH$22+'3 - Phase Durations'!$AH$23)+$W25*'3 - Phase Durations'!$AH$24)/12 -> 0.05 | BA25: =($Q25*'3 - Phase Durations'!$AI$16+$R25*'3 - Phase Durations'!$AI$17+$S25*('3 - Phase Durations'!$AI$18+'3 - Phase Durations'!$AI$19)+$T25*'3 - Phase Durations'!$AI$20+$U25*'3 - Phase Durations'!$AI$21+$V25*('3 - Phase Durations'!$AI$22+'3 - Phase Durations'!$AI$23)+$W25*'3 - Phase Durations'!$AI$24)/12 -> 0.05 | BB25: =($Q25*'3 - Phase Durations'!$AJ$16+$R25*'3 - Phase Durations'!$AJ$17+$S25*('3 - Phase Durations'!$AJ$18+'3 - Phase Durations'!$AJ$19)+$T25*'3 - Phase Durations'!$AJ$20+$U25*'3 - Phase Durations'!$AJ$21+$V25*('3 - Phase Durations'!$AJ$22+'3 - Phase Durations'!$AJ$23)+$W25*'3 - Phase Durations'!$AJ$24)/12 -> 0.05 | BC25: =($Q25*'3 - Phase Durations'!$AK$16+$R25*'3 - Phase Durations'!$AK$17+$S25*('3 - Phase Durations'!$AK$18+'3 - Phase Durations'!$AK$19)+$T25*'3 - Phase Durations'!$AK$20+$U25*'3 - Phase Durations'!$AK$21+$V25*('3 - Phase Durations'!$AK$22+'3 - Phase Durations'!$AK$23)+$W25*'3 - Phase Durations'!$AK$24)/12 -> 0.050136986 | BD25: =($Q25*'3 - Phase Durations'!$AL$16+$R25*'3 - Phase Durations'!$AL$17+$S25*('3 - Phase Durations'!$AL$18+'3 - Phase Durations'!$AL$19)+$T25*'3 - Phase Durations'!$AL$20+$U25*'3 - Phase Durations'!$AL$21+$V25*('3 - Phase Durations'!$AL$22+'3 - Phase Durations'!$AL$23)+$W25*'3 - Phase Durations'!$AL$24)/12 -> 0.05 | BE25: =($Q25*'3 - Phase Durations'!$AM$16+$R25*'3 - Phase Durations'!$AM$17+$S25*('3 - Phase Durations'!$AM$18+'3 - Phase Durations'!$AM$19)+$T25*'3 - Phase Durations'!$AM$20+$U25*'3 - Phase Durations'!$AM$21+$V25*('3 - Phase Durations'!$AM$22+'3 - Phase Durations'!$AM$23)+$W25*'3 - Phase Durations'!$AM$24)/12 -> 0.05 | BF25: =($Q25*'3 - Phase Durations'!$AN$16+$R25*'3 - Phase Durations'!$AN$17+$S25*('3 - Phase Durations'!$AN$18+'3 - Phase Durations'!$AN$19)+$T25*'3 - Phase Durations'!$AN$20+$U25*'3 - Phase Durations'!$AN$21+$V25*('3 - Phase Durations'!$AN$22+'3 - Phase Durations'!$AN$23)+$W25*'3 - Phase Durations'!$AN$24)/12 -> 0.05 | BG25: =($Q25*'3 - Phase Durations'!$AO$16+$R25*'3 - Phase Durations'!$AO$17+$S25*('3 - Phase Durations'!$AO$18+'3 - Phase Durations'!$AO$19)+$T25*'3 - Phase Durations'!$AO$20+$U25*'3 - Phase Durations'!$AO$21+$V25*('3 - Phase Durations'!$AO$22+'3 - Phase Durations'!$AO$23)+$W25*'3 - Phase Durations'!$AO$24)/12 -> 0.012465753 | BH25: =SUM(Y25:BG25) -> 4.6188767
A26: 9 | B26: CSA | C26: Project Team | D26: Systems | E26: Systems Engineering | F26: Spacecraft Systems Engineer | G26: Instrument Suite | H26: Space Exploration | I26: Engineering | J26: Kevin Anand | K26: ORCA-SE-002 | L26: New | M26: EN-ENG-4 | N26: Max Echelon | O26: Labour Rates | P26: FF-CSA | Q26: 0 | R26: 0.1 | S26: 0.05 | T26: 1 | U26: 0.05 | V26: 0.21 | W26: 0 | X26: =IFERROR(VLOOKUP($M26,'Labour Rates lookup'!$A:$B,2,FALSE()),0) -> 128000 | Y26: =($Q26*'3 - Phase Durations'!$G$16+$R26*'3 - Phase Durations'!$G$17+$S26*('3 - Phase Durations'!$G$18+'3 - Phase Durations'!$G$19)+$T26*'3 - Phase Durations'!$G$20+$U26*'3 - Phase Durations'!$G$21+$V26*('3 - Phase Durations'!$G$22+'3 - Phase Durations'!$G$23)+$W26*'3 - Phase Durations'!$G$24)/12 -> 0 | Z26: =($Q26*'3 - Phase Durations'!$H$16+$R26*'3 - Phase Durations'!$H$17+$S26*('3 - Phase Durations'!$H$18+'3 - Phase Durations'!$H$19)+$T26*'3 - Phase Durations'!$H$20+$U26*'3 - Phase Durations'!$H$21+$V26*('3 - Phase Durations'!$H$22+'3 - Phase Durations'!$H$23)+$W26*'3 - Phase Durations'!$H$24)/12 -> 0 | AA26: =($Q26*'3 - Phase Durations'!$I$16+$R26*'3 - Phase Durations'!$I$17+$S26*('3 - Phase Durations'!$I$18+'3 - Phase Durations'!$I$19)+$T26*'3 - Phase Durations'!$I$20+$U26*'3 - Phase Durations'!$I$21+$V26*('3 - Phase Durations'!$I$22+'3 - Phase Durations'!$I$23)+$W26*'3 - Phase Durations'!$I$24)/12 -> 0.024931507 | AB26: =($Q26*'3 - Phase Durations'!$J$16+$R26*'3 - Phase Durations'!$J$17+$S26*('3 - Phase Durations'!$J$18+'3 - Phase Durations'!$J$19)+$T26*'3 - Phase Durations'!$J$20+$U26*'3 - Phase Durations'!$J$21+$V26*('3 - Phase Durations'!$J$22+'3 - Phase Durations'!$J$23)+$W26*'3 - Phase Durations'!$J$24)/12 -> 0.1 | AC26: =($Q26*'3 - Phase Durations'!$K$16+$R26*'3 - Phase Durations'!$K$17+$S26*('3 - Phase Durations'!$K$18+'3 - Phase Durations'!$K$19)+$T26*'3 - Phase Durations'!$K$20+$U26*'3 - Phase Durations'!$K$21+$V26*('3 - Phase Durations'!$K$22+'3 - Phase Durations'!$K$23)+$W26*'3 - Phase Durations'!$K$24)/12 -> 0.087671233 | AD26: =($Q26*'3 - Phase Durations'!$L$16+$R26*'3 - Phase Durations'!$L$17+$S26*('3 - Phase Durations'!$L$18+'3 - Phase Durations'!$L$19)+$T26*'3 - Phase Durations'!$L$20+$U26*'3 - Phase Durations'!$L$21+$V26*('3 - Phase Durations'!$L$22+'3 - Phase Durations'!$L$23)+$W26*'3 - Phase Durations'!$L$24)/12 -> 0.05 | AE26: =($Q26*'3 - Phase Durations'!$M$16+$R26*'3 - Phase Durations'!$M$17+$S26*('3 - Phase Durations'!$M$18+'3 - Phase Durations'!$M$19)+$T26*'3 - Phase Durations'!$M$20+$U26*'3 - Phase Durations'!$M$21+$V26*('3 - Phase Durations'!$M$22+'3 - Phase Durations'!$M$23)+$W26*'3 - Phase Durations'!$M$24)/12 -> 0.2869863 | AF26: =($Q26*'3 - Phase Durations'!$N$16+$R26*'3 - Phase Durations'!$N$17+$S26*('3 - Phase Durations'!$N$18+'3 - Phase Durations'!$N$19)+$T26*'3 - Phase Durations'!$N$20+$U26*'3 - Phase Durations'!$N$21+$V26*('3 - Phase Durations'!$N$22+'3 - Phase Durations'!$N$23)+$W26*'3 - Phase Durations'!$N$24)/12 -> 1 | AG26: =($Q26*'3 - Phase Durations'!$O$16+$R26*'3 - Phase Durations'!$O$17+$S26*('3 - Phase Durations'!$O$18+'3 - Phase Durations'!$O$19)+$T26*'3 - Phase Durations'!$O$20+$U26*'3 - Phase Durations'!$O$21+$V26*('3 - Phase Durations'!$O$22+'3 - Phase Durations'!$O$23)+$W26*'3 - Phase Durations'!$O$24)/12 -> 0.76575342 | AH26: =($Q26*'3 - Phase Durations'!$P$16+$R26*'3 - Phase Durations'!$P$17+$S26*('3 - Phase Durations'!$P$18+'3 - Phase Durations'!$P$19)+$T26*'3 - Phase Durations'!$P$20+$U26*'3 - Phase Durations'!$P$21+$V26*('3 - Phase Durations'!$P$22+'3 - Phase Durations'!$P$23)+$W26*'3 - Phase Durations'!$P$24)/12 -> 0.05 | AI26: =($Q26*'3 - Phase Durations'!$Q$16+$R26*'3 - Phase Durations'!$Q$17+$S26*('3 - Phase Durations'!$Q$18+'3 - Phase Durations'!$Q$19)+$T26*'3 - Phase Durations'!$Q$20+$U26*'3 - Phase Durations'!$Q$21+$V26*('3 - Phase Durations'!$Q$22+'3 - Phase Durations'!$Q$23)+$W26*'3 - Phase Durations'!$Q$24)/12 -> 0.050136986 | AJ26: =($Q26*'3 - Phase Durations'!$R$16+$R26*'3 - Phase Durations'!$R$17+$S26*('3 - Phase Durations'!$R$18+'3 - Phase Durations'!$R$19)+$T26*'3 - Phase Durations'!$R$20+$U26*'3 - Phase Durations'!$R$21+$V26*('3 - Phase Durations'!$R$22+'3 - Phase Durations'!$R$23)+$W26*'3 - Phase Durations'!$R$24)/12 -> 0.05 | AK26: =($Q26*'3 - Phase Durations'!$S$16+$R26*'3 - Phase Durations'!$S$17+$S26*('3 - Phase Durations'!$S$18+'3 - Phase Durations'!$S$19)+$T26*'3 - Phase Durations'!$S$20+$U26*'3 - Phase Durations'!$S$21+$V26*('3 - Phase Durations'!$S$22+'3 - Phase Durations'!$S$23)+$W26*'3 - Phase Durations'!$S$24)/12 -> 0.05 | AL26: =($Q26*'3 - Phase Durations'!$T$16+$R26*'3 - Phase Durations'!$T$17+$S26*('3 - Phase Durations'!$T$18+'3 - Phase Durations'!$T$19)+$T26*'3 - Phase Durations'!$T$20+$U26*'3 - Phase Durations'!$T$21+$V26*('3 - Phase Durations'!$T$22+'3 - Phase Durations'!$T$23)+$W26*'3 - Phase Durations'!$T$24)/12 -> 0.05 | AM26: =($Q26*'3 - Phase Durations'!$U$16+$R26*'3 - Phase Durations'!$U$17+$S26*('3 - Phase Durations'!$U$18+'3 - Phase Durations'!$U$19)+$T26*'3 - Phase Durations'!$U$20+$U26*'3 - Phase Durations'!$U$21+$V26*('3 - Phase Durations'!$U$22+'3 - Phase Durations'!$U$23)+$W26*'3 - Phase Durations'!$U$24)/12 -> 0.050136986 | AN26: =($Q26*'3 - Phase Durations'!$V$16+$R26*'3 - Phase Durations'!$V$17+$S26*('3 - Phase Durations'!$V$18+'3 - Phase Durations'!$V$19)+$T26*'3 - Phase Durations'!$V$20+$U26*'3 - Phase Durations'!$V$21+$V26*('3 - Phase Durations'!$V$22+'3 - Phase Durations'!$V$23)+$W26*'3 - Phase Durations'!$V$24)/12 -> 0.089452055 | AO26: =($Q26*'3 - Phase Durations'!$W$16+$R26*'3 - Phase Durations'!$W$17+$S26*('3 - Phase Durations'!$W$18+'3 - Phase Durations'!$W$19)+$T26*'3 - Phase Durations'!$W$20+$U26*'3 - Phase Durations'!$W$21+$V26*('3 - Phase Durations'!$W$22+'3 - Phase Durations'!$W$23)+$W26*'3 - Phase Durations'!$W$24)/12 -> 0.21 | AP26: =($Q26*'3 - Phase Durations'!$X$16+$R26*'3 - Phase Durations'!$X$17+$S26*('3 - Phase Durations'!$X$18+'3 - Phase Durations'!$X$19)+$T26*'3 - Phase Durations'!$X$20+$U26*'3 - Phase Durations'!$X$21+$V26*('3 - Phase Durations'!$X$22+'3 - Phase Durations'!$X$23)+$W26*'3 - Phase Durations'!$X$24)/12 -> 0.21 | AQ26: =($Q26*'3 - Phase Durations'!$Y$16+$R26*'3 - Phase Durations'!$Y$17+$S26*('3 - Phase Durations'!$Y$18+'3 - Phase Durations'!$Y$19)+$T26*'3 - Phase Durations'!$Y$20+$U26*'3 - Phase Durations'!$Y$21+$V26*('3 - Phase Durations'!$Y$22+'3 - Phase Durations'!$Y$23)+$W26*'3 - Phase Durations'!$Y$24)/12 -> 0.21057534 | AR26: =($Q26*'3 - Phase Durations'!$Z$16+$R26*'3 - Phase Durations'!$Z$17+$S26*('3 - Phase Durations'!$Z$18+'3 - Phase Durations'!$Z$19)+$T26*'3 - Phase Durations'!$Z$20+$U26*'3 - Phase Durations'!$Z$21+$V26*('3 - Phase Durations'!$Z$22+'3 - Phase Durations'!$Z$23)+$W26*'3 - Phase Durations'!$Z$24)/12 -> 0.21 | AS26: =($Q26*'3 - Phase Durations'!$AA$16+$R26*'3 - Phase Durations'!$AA$17+$S26*('3 - Phase Durations'!$AA$18+'3 - Phase Durations'!$AA$19)+$T26*'3 - Phase Durations'!$AA$20+$U26*'3 - Phase Durations'!$AA$21+$V26*('3 - Phase Durations'!$AA$22+'3 - Phase Durations'!$AA$23)+$W26*'3 - Phase Durations'!$AA$24)/12 -> 0.21 | AT26: =($Q26*'3 - Phase Durations'!$AB$16+$R26*'3 - Phase Durations'!$AB$17+$S26*('3 - Phase Durations'!$AB$18+'3 - Phase Durations'!$AB$19)+$T26*'3 - Phase Durations'!$AB$20+$U26*'3 - Phase Durations'!$AB$21+$V26*('3 - Phase Durations'!$AB$22+'3 - Phase Durations'!$AB$23)+$W26*'3 - Phase Durations'!$AB$24)/12 -> 0.21 | AU26: =($Q26*'3 - Phase Durations'!$AC$16+$R26*'3 - Phase Durations'!$AC$17+$S26*('3 - Phase Durations'!$AC$18+'3 - Phase Durations'!$AC$19)+$T26*'3 - Phase Durations'!$AC$20+$U26*'3 - Phase Durations'!$AC$21+$V26*('3 - Phase Durations'!$AC$22+'3 - Phase Durations'!$AC$23)+$W26*'3 - Phase Durations'!$AC$24)/12 -> 0.21057534 | AV26: =($Q26*'3 - Phase Durations'!$AD$16+$R26*'3 - Phase Durations'!$AD$17+$S26*('3 - Phase Durations'!$AD$18+'3 - Phase Durations'!$AD$19)+$T26*'3 - Phase Durations'!$AD$20+$U26*'3 - Phase Durations'!$AD$21+$V26*('3 - Phase Durations'!$AD$22+'3 - Phase Durations'!$AD$23)+$W26*'3 - Phase Durations'!$AD$24)/12 -> 0.21 | AW26: =($Q26*'3 - Phase Durations'!$AE$16+$R26*'3 - Phase Durations'!$AE$17+$S26*('3 - Phase Durations'!$AE$18+'3 - Phase Durations'!$AE$19)+$T26*'3 - Phase Durations'!$AE$20+$U26*'3 - Phase Durations'!$AE$21+$V26*('3 - Phase Durations'!$AE$22+'3 - Phase Durations'!$AE$23)+$W26*'3 - Phase Durations'!$AE$24)/12 -> 0.21 | AX26: =($Q26*'3 - Phase Durations'!$AF$16+$R26*'3 - Phase Durations'!$AF$17+$S26*('3 - Phase Durations'!$AF$18+'3 - Phase Durations'!$AF$19)+$T26*'3 - Phase Durations'!$AF$20+$U26*'3 - Phase Durations'!$AF$21+$V26*('3 - Phase Durations'!$AF$22+'3 - Phase Durations'!$AF$23)+$W26*'3 - Phase Durations'!$AF$24)/12 -> 0.21 | AY26: =($Q26*'3 - Phase Durations'!$AG$16+$R26*'3 - Phase Durations'!$AG$17+$S26*('3 - Phase Durations'!$AG$18+'3 - Phase Durations'!$AG$19)+$T26*'3 - Phase Durations'!$AG$20+$U26*'3 - Phase Durations'!$AG$21+$V26*('3 - Phase Durations'!$AG$22+'3 - Phase Durations'!$AG$23)+$W26*'3 - Phase Durations'!$AG$24)/12 -> 0.21057534 | AZ26: =($Q26*'3 - Phase Durations'!$AH$16+$R26*'3 - Phase Durations'!$AH$17+$S26*('3 - Phase Durations'!$AH$18+'3 - Phase Durations'!$AH$19)+$T26*'3 - Phase Durations'!$AH$20+$U26*'3 - Phase Durations'!$AH$21+$V26*('3 - Phase Durations'!$AH$22+'3 - Phase Durations'!$AH$23)+$W26*'3 - Phase Durations'!$AH$24)/12 -> 0.21 | BA26: =($Q26*'3 - Phase Durations'!$AI$16+$R26*'3 - Phase Durations'!$AI$17+$S26*('3 - Phase Durations'!$AI$18+'3 - Phase Durations'!$AI$19)+$T26*'3 - Phase Durations'!$AI$20+$U26*'3 - Phase Durations'!$AI$21+$V26*('3 - Phase Durations'!$AI$22+'3 - Phase Durations'!$AI$23)+$W26*'3 - Phase Durations'!$AI$24)/12 -> 0.21 | BB26: =($Q26*'3 - Phase Durations'!$AJ$16+$R26*'3 - Phase Durations'!$AJ$17+$S26*('3 - Phase Durations'!$AJ$18+'3 - Phase Durations'!$AJ$19)+$T26*'3 - Phase Durations'!$AJ$20+$U26*'3 - Phase Durations'!$AJ$21+$V26*('3 - Phase Durations'!$AJ$22+'3 - Phase Durations'!$AJ$23)+$W26*'3 - Phase Durations'!$AJ$24)/12 -> 0.21 | BC26: =($Q26*'3 - Phase Durations'!$AK$16+$R26*'3 - Phase Durations'!$AK$17+$S26*('3 - Phase Durations'!$AK$18+'3 - Phase Durations'!$AK$19)+$T26*'3 - Phase Durations'!$AK$20+$U26*'3 - Phase Durations'!$AK$21+$V26*('3 - Phase Durations'!$AK$22+'3 - Phase Durations'!$AK$23)+$W26*'3 - Phase Durations'!$AK$24)/12 -> 0.21057534 | BD26: =($Q26*'3 - Phase Durations'!$AL$16+$R26*'3 - Phase Durations'!$AL$17+$S26*('3 - Phase Durations'!$AL$18+'3 - Phase Durations'!$AL$19)+$T26*'3 - Phase Durations'!$AL$20+$U26*'3 - Phase Durations'!$AL$21+$V26*('3 - Phase Durations'!$AL$22+'3 - Phase Durations'!$AL$23)+$W26*'3 - Phase Durations'!$AL$24)/12 -> 0.21 | BE26: =($Q26*'3 - Phase Durations'!$AM$16+$R26*'3 - Phase Durations'!$AM$17+$S26*('3 - Phase Durations'!$AM$18+'3 - Phase Durations'!$AM$19)+$T26*'3 - Phase Durations'!$AM$20+$U26*'3 - Phase Durations'!$AM$21+$V26*('3 - Phase Durations'!$AM$22+'3 - Phase Durations'!$AM$23)+$W26*'3 - Phase Durations'!$AM$24)/12 -> 0.21 | BF26: =($Q26*'3 - Phase Durations'!$AN$16+$R26*'3 - Phase Durations'!$AN$17+$S26*('3 - Phase Durations'!$AN$18+'3 - Phase Durations'!$AN$19)+$T26*'3 - Phase Durations'!$AN$20+$U26*'3 - Phase Durations'!$AN$21+$V26*('3 - Phase Durations'!$AN$22+'3 - Phase Durations'!$AN$23)+$W26*'3 - Phase Durations'!$AN$24)/12 -> 0.21 | BG26: =($Q26*'3 - Phase Durations'!$AO$16+$R26*'3 - Phase Durations'!$AO$17+$S26*('3 - Phase Durations'!$AO$18+'3 - Phase Durations'!$AO$19)+$T26*'3 - Phase Durations'!$AO$20+$U26*'3 - Phase Durations'!$AO$21+$V26*('3 - Phase Durations'!$AO$22+'3 - Phase Durations'!$AO$23)+$W26*'3 - Phase Durations'!$AO$24)/12 -> 0.052356164 | BH26: =SUM(Y26:BG26) -> 6.539726
